Workbook
Name b0: NSS!$C$248
Name b0: '[1]Nelson Siegel Model'!$B$16
Name b1_: NSS!$C$249
Name b1_: '[1]Nelson Siegel Model'!$B$17
Name b2_: NSS!$C$250
Name b2_: '[1]Nelson Siegel Model'!$B$18
Name b3_: '[2]Nelson Siegel Svensson Model'!$C$39
Name b3_: NSS!$C$251
Name b3_: '[2]Nelson Siegel Svensson Model'!$C$39
Name b3_: #REF!
Name tau1_: NSS!$C$252
Name tau1_: '[1]Nelson Siegel Model'!$B$19
Name tau2_: '[2]Nelson Siegel Svensson Model'!$C$41
Name tau2_: NSS!$C$253
Name tau2_: '[2]Nelson Siegel Svensson Model'!$C$41
Name tau2_: #REF!

Sheet Bloomberg (Online)
A1: Instrument | B1: Name | C1: Ticker | D1: Country/Region | E1: Currency | F1: Maturity | G1: Coupon Type | H1: Coupon Frequency | I1: Coupon | J1: Ask Yield to Maturity | K1: Bid Yield to Maturity | L1: Ask Price | M1: Bid Price | N1: Identifier | O1: ISIN | P1: Bloomberg Composite Rating | Q1: Announce | R1: Next Coupon Settle Date | S1: Time
A2: YL396238 Corp | B2: {=_xll.BDP("YL396238 Corp","DS520")} -> #NAME? | C2: {=_xll.BDP("YL396238 Corp","DS001")} -> #NAME? | D2: {=_xll.BDP("YL396238 Corp","DS458")} -> #NAME? | E2: {=_xll.BDP("YL396238 Corp","DS004")} -> #NAME? | F2: {=_xll.BDP("YL396238 Corp","DS035")} -> #NAME? | G2: {=_xll.BDP(A2,"DS086")} -> #NAME? | H2: {=_xll.BDP(A2,"DS034")} -> #NAME? | I2: {=_xll.BDP("YL396238 Corp","DS033")} -> #NAME? | J2: {=_xll.BDP(A2,"YL018")} -> #NAME? | K2: {=_xll.BDP("YL396238 Corp","YL016")} -> #NAME? | L2: {=_xll.BDP("YL396238 Corp","PR004")} -> #NAME? | M2: {=_xll.BDP(A2,"PR002")} -> #NAME? | N2: {=_xll.BDP(A2,"ID028")} -> #NAME? | O2: {=_xll.BDP("YL396238 Corp","ID005")} -> #NAME? | P2: {=_xll.BDP("YL396238 Corp","RA007")} -> #NAME? | Q2: {=_xll.BDP("YL396238 Corp","DS219")} -> #NAME? | R2: {=_xll.BDP(A2,"DS040")} -> #NAME? | S2: =(F2-TODAY())/365.25 -> #NAME? | T2: {=_xll.BDP(C2,"HS022")} -> #NAME?
A3: ZI885852 Corp | B3: {=_xll.BDP("ZI885852 Corp","DS520")} -> #NAME? | C3: {=_xll.BDP("ZI885852 Corp","DS001")} -> #NAME? | D3: {=_xll.BDP("ZI885852 Corp","DS458")} -> #NAME? | E3: {=_xll.BDP("ZI885852 Corp","DS004")} -> #NAME? | F3: {=_xll.BDP("ZI885852 Corp","DS035")} -> #NAME? | G3: {=_xll.BDP(A3,"DS086")} -> #NAME? | H3: {=_xll.BDP(A3,"DS034")} -> #NAME? | I3: {=_xll.BDP("ZI885852 Corp","DS033")} -> #NAME? | J3: {=_xll.BDP(A3,"YL018")} -> #NAME? | K3: {=_xll.BDP("ZI885852 Corp","YL016")} -> #NAME? | L3: {=_xll.BDP("ZI885852 Corp","PR004")} -> #NAME? | M3: {=_xll.BDP(A3,"PR002")} -> #NAME? | N3: {=_xll.BDP(A3,"ID028")} -> #NAME? | O3: {=_xll.BDP("ZI885852 Corp","ID005")} -> #NAME? | P3: {=_xll.BDP("ZI885852 Corp","RA007")} -> #NAME? | Q3: {=_xll.BDP("ZI885852 Corp","DS219")} -> #NAME? | R3: {=_xll.BDP(A3,"DS040")} -> #NAME? | S3: =(F3-TODAY())/365.25 -> #NAME?
A4: LW169500 Corp | B4: {=_xll.BDP("LW169500 Corp","DS520")} -> #NAME? | C4: {=_xll.BDP("LW169500 Corp","DS001")} -> #NAME? | D4: {=_xll.BDP("LW169500 Corp","DS458")} -> #NAME? | E4: {=_xll.BDP("LW169500 Corp","DS004")} -> #NAME? | F4: {=_xll.BDP("LW169500 Corp","DS035")} -> #NAME? | G4: {=_xll.BDP(A4,"DS086")} -> #NAME? | H4: {=_xll.BDP(A4,"DS034")} -> #NAME? | I4: {=_xll.BDP("LW169500 Corp","DS033")} -> #NAME? | J4: {=_xll.BDP(A4,"YL018")} -> #NAME? | K4: {=_xll.BDP("LW169500 Corp","YL016")} -> #NAME? | L4: {=_xll.BDP("LW169500 Corp","PR004")} -> #NAME? | M4: {=_xll.BDP(A4,"PR002")} -> #NAME? | N4: {=_xll.BDP(A4,"ID028")} -> #NAME? | O4: {=_xll.BDP("LW169500 Corp","ID005")} -> #NAME? | P4: {=_xll.BDP("LW169500 Corp","RA007")} -> #NAME? | Q4: {=_xll.BDP("LW169500 Corp","DS219")} -> #NAME? | R4: {=_xll.BDP(A4,"DS040")} -> #NAME? | S4: =(F4-TODAY())/365.25 -> #NAME?
A5: AN666227 Corp | B5: {=_xll.BDP("AN666227 Corp","DS520")} -> #NAME? | C5: {=_xll.BDP("AN666227 Corp","DS001")} -> #NAME? | D5: {=_xll.BDP("AN666227 Corp","DS458")} -> #NAME? | E5: {=_xll.BDP("AN666227 Corp","DS004")} -> #NAME? | F5: {=_xll.BDP("AN666227 Corp","DS035")} -> #NAME? | G5: {=_xll.BDP(A5,"DS086")} -> #NAME? | H5: {=_xll.BDP(A5,"DS034")} -> #NAME? | I5: {=_xll.BDP("AN666227 Corp","DS033")} -> #NAME? | J5: {=_xll.BDP(A5,"YL018")} -> #NAME? | K5: {=_xll.BDP("AN666227 Corp","YL016")} -> #NAME? | L5: {=_xll.BDP("AN666227 Corp","PR004")} -> #NAME? | M5: {=_xll.BDP(A5,"PR002")} -> #NAME? | N5: {=_xll.BDP(A5,"ID028")} -> #NAME? | O5: {=_xll.BDP("AN666227 Corp","ID005")} -> #NAME? | P5: {=_xll.BDP("AN666227 Corp","RA007")} -> #NAME? | Q5: {=_xll.BDP("AN666227 Corp","DS219")} -> #NAME? | R5: {=_xll.BDP(A5,"DS040")} -> #NAME? | S5: =(F5-TODAY())/365.25 -> #NAME?
A6: BO356983 Corp | B6: {=_xll.BDP("BO356983 Corp","DS520")} -> #NAME? | C6: {=_xll.BDP("BO356983 Corp","DS001")} -> #NAME? | D6: {=_xll.BDP("BO356983 Corp","DS458")} -> #NAME? | E6: {=_xll.BDP("BO356983 Corp","DS004")} -> #NAME? | F6: {=_xll.BDP("BO356983 Corp","DS035")} -> #NAME? | G6: {=_xll.BDP(A6,"DS086")} -> #NAME? | H6: {=_xll.BDP(A6,"DS034")} -> #NAME? | I6: {=_xll.BDP("BO356983 Corp","DS033")} -> #NAME? | J6: {=_xll.BDP(A6,"YL018")} -> #NAME? | K6: {=_xll.BDP("BO356983 Corp","YL016")} -> #NAME? | L6: {=_xll.BDP("BO356983 Corp","PR004")} -> #NAME? | M6: {=_xll.BDP(A6,"PR002")} -> #NAME? | N6: {=_xll.BDP(A6,"ID028")} -> #NAME? | O6: {=_xll.BDP("BO356983 Corp","ID005")} -> #NAME? | P6: {=_xll.BDP("BO356983 Corp","RA007")} -> #NAME? | Q6: {=_xll.BDP("BO356983 Corp","DS219")} -> #NAME? | R6: {=_xll.BDP(A6,"DS040")} -> #NAME? | S6: =(F6-TODAY())/365.25 -> #NAME?
A7: BO356985 Corp | B7: {=_xll.BDP("BO356985 Corp","DS520")} -> #NAME? | C7: {=_xll.BDP("BO356985 Corp","DS001")} -> #NAME? | D7: {=_xll.BDP("BO356985 Corp","DS458")} -> #NAME? | E7: {=_xll.BDP("BO356985 Corp","DS004")} -> #NAME? | F7: {=_xll.BDP("BO356985 Corp","DS035")} -> #NAME? | G7: {=_xll.BDP(A7,"DS086")} -> #NAME? | H7: {=_xll.BDP(A7,"DS034")} -> #NAME? | I7: {=_xll.BDP("BO356985 Corp","DS033")} -> #NAME? | J7: {=_xll.BDP(A7,"YL018")} -> #NAME? | K7: {=_xll.BDP("BO356985 Corp","YL016")} -> #NAME? | L7: {=_xll.BDP("BO356985 Corp","PR004")} -> #NAME? | M7: {=_xll.BDP(A7,"PR002")} -> #NAME? | N7: {=_xll.BDP(A7,"ID028")} -> #NAME? | O7: {=_xll.BDP("BO356985 Corp","ID005")} -> #NAME? | P7: {=_xll.BDP("BO356985 Corp","RA007")} -> #NAME? | Q7: {=_xll.BDP("BO356985 Corp","DS219")} -> #NAME? | R7: {=_xll.BDP(A7,"DS040")} -> #NAME? | S7: =(F7-TODAY())/365.25 -> #NAME?
A8: BO356982 Corp | B8: {=_xll.BDP("BO356982 Corp","DS520")} -> #NAME? | C8: {=_xll.BDP("BO356982 Corp","DS001")} -> #NAME? | D8: {=_xll.BDP("BO356982 Corp","DS458")} -> #NAME? | E8: {=_xll.BDP("BO356982 Corp","DS004")} -> #NAME? | F8: {=_xll.BDP("BO356982 Corp","DS035")} -> #NAME? | G8: {=_xll.BDP(A8,"DS086")} -> #NAME? | H8: {=_xll.BDP(A8,"DS034")} -> #NAME? | I8: {=_xll.BDP("BO356982 Corp","DS033")} -> #NAME? | J8: {=_xll.BDP(A8,"YL018")} -> #NAME? | K8: {=_xll.BDP("BO356982 Corp","YL016")} -> #NAME? | L8: {=_xll.BDP("BO356982 Corp","PR004")} -> #NAME? | M8: {=_xll.BDP(A8,"PR002")} -> #NAME? | N8: {=_xll.BDP(A8,"ID028")} -> #NAME? | O8: {=_xll.BDP("BO356982 Corp","ID005")} -> #NAME? | P8: {=_xll.BDP("BO356982 Corp","RA007")} -> #NAME? | Q8: {=_xll.BDP("BO356982 Corp","DS219")} -> #NAME? | R8: {=_xll.BDP(A8,"DS040")} -> #NAME? | S8: =(F8-TODAY())/365.25 -> #NAME?
A9: DA928584 Corp | B9: {=_xll.BDP("DA928584 Corp","DS520")} -> #NAME? | C9: {=_xll.BDP("DA928584 Corp","DS001")} -> #NAME? | D9: {=_xll.BDP("DA928584 Corp","DS458")} -> #NAME? | E9: {=_xll.BDP("DA928584 Corp","DS004")} -> #NAME? | F9: {=_xll.BDP("DA928584 Corp","DS035")} -> #NAME? | G9: {=_xll.BDP(A9,"DS086")} -> #NAME? | H9: {=_xll.BDP(A9,"DS034")} -> #NAME? | I9: {=_xll.BDP("DA928584 Corp","DS033")} -> #NAME? | J9: {=_xll.BDP(A9,"YL018")} -> #NAME? | K9: {=_xll.BDP("DA928584 Corp","YL016")} -> #NAME? | L9: {=_xll.BDP("DA928584 Corp","PR004")} -> #NAME? | M9: {=_xll.BDP(A9,"PR002")} -> #NAME? | N9: {=_xll.BDP(A9,"ID028")} -> #NAME? | O9: {=_xll.BDP("DA928584 Corp","ID005")} -> #NAME? | P9: {=_xll.BDP("DA928584 Corp","RA007")} -> #NAME? | Q9: {=_xll.BDP("DA928584 Corp","DS219")} -> #NAME? | R9: {=_xll.BDP(A9,"DS040")} -> #NAME? | S9: =(F9-TODAY())/365.25 -> #NAME?
A10: YL396232 Corp | B10: {=_xll.BDP("YL396232 Corp","DS520")} -> #NAME? | C10: {=_xll.BDP("YL396232 Corp","DS001")} -> #NAME? | D10: {=_xll.BDP("YL396232 Corp","DS458")} -> #NAME? | E10: {=_xll.BDP("YL396232 Corp","DS004")} -> #NAME? | F10: {=_xll.BDP("YL396232 Corp","DS035")} -> #NAME? | G10: {=_xll.BDP(A10,"DS086")} -> #NAME? | H10: {=_xll.BDP(A10,"DS034")} -> #NAME? | I10: {=_xll.BDP("YL396232 Corp","DS033")} -> #NAME? | J10: {=_xll.BDP(A10,"YL018")} -> #NAME? | K10: {=_xll.BDP("YL396232 Corp","YL016")} -> #NAME? | L10: {=_xll.BDP("YL396232 Corp","PR004")} -> #NAME? | M10: {=_xll.BDP(A10,"PR002")} -> #NAME? | N10: {=_xll.BDP(A10,"ID028")} -> #NAME? | O10: {=_xll.BDP("YL396232 Corp","ID005")} -> #NAME? | P10: {=_xll.BDP("YL396232 Corp","RA007")} -> #NAME? | Q10: {=_xll.BDP("YL396232 Corp","DS219")} -> #NAME? | R10: {=_xll.BDP(A10,"DS040")} -> #NAME? | S10: =(F10-TODAY())/365.25 -> #NAME?
A11: YK173563 Corp | B11: {=_xll.BDP("YK173563 Corp","DS520")} -> #NAME? | C11: {=_xll.BDP("YK173563 Corp","DS001")} -> #NAME? | D11: {=_xll.BDP("YK173563 Corp","DS458")} -> #NAME? | E11: {=_xll.BDP("YK173563 Corp","DS004")} -> #NAME? | F11: {=_xll.BDP("YK173563 Corp","DS035")} -> #NAME? | G11: {=_xll.BDP(A11,"DS086")} -> #NAME? | H11: {=_xll.BDP(A11,"DS034")} -> #NAME? | I11: {=_xll.BDP("YK173563 Corp","DS033")} -> #NAME? | J11: {=_xll.BDP(A11,"YL018")} -> #NAME? | K11: {=_xll.BDP("YK173563 Corp","YL016")} -> #NAME? | L11: {=_xll.BDP("YK173563 Corp","PR004")} -> #NAME? | M11: {=_xll.BDP(A11,"PR002")} -> #NAME? | N11: {=_xll.BDP(A11,"ID028")} -> #NAME? | O11: {=_xll.BDP("YK173563 Corp","ID005")} -> #NAME? | P11: {=_xll.BDP("YK173563 Corp","RA007")} -> #NAME? | Q11: {=_xll.BDP("YK173563 Corp","DS219")} -> #NAME? | R11: {=_xll.BDP(A11,"DS040")} -> #NAME? | S11: =(F11-TODAY())/365.25 -> #NAME?
A12: YN599739 Corp | B12: {=_xll.BDP("YN599739 Corp","DS520")} -> #NAME? | C12: {=_xll.BDP("YN599739 Corp","DS001")} -> #NAME? | D12: {=_xll.BDP("YN599739 Corp","DS458")} -> #NAME? | E12: {=_xll.BDP("YN599739 Corp","DS004")} -> #NAME? | F12: {=_xll.BDP("YN599739 Corp","DS035")} -> #NAME? | G12: {=_xll.BDP(A12,"DS086")} -> #NAME? | H12: {=_xll.BDP(A12,"DS034")} -> #NAME? | I12: {=_xll.BDP("YN599739 Corp","DS033")} -> #NAME? | J12: {=_xll.BDP(A12,"YL018")} -> #NAME? | K12: {=_xll.BDP("YN599739 Corp","YL016")} -> #NAME? | L12: {=_xll.BDP("YN599739 Corp","PR004")} -> #NAME? | M12: {=_xll.BDP(A12,"PR002")} -> #NAME? | N12: {=_xll.BDP(A12,"ID028")} -> #NAME? | O12: {=_xll.BDP("YN599739 Corp","ID005")} -> #NAME? | P12: {=_xll.BDP("YN599739 Corp","RA007")} -> #NAME? | Q12: {=_xll.BDP("YN599739 Corp","DS219")} -> #NAME? | R12: {=_xll.BDP(A12,"DS040")} -> #NAME? | S12: =(F12-TODAY())/365.25 -> #NAME?
A13: YN599935 Corp | B13: {=_xll.BDP("YN599935 Corp","DS520")} -> #NAME? | C13: {=_xll.BDP("YN599935 Corp","DS001")} -> #NAME? | D13: {=_xll.BDP("YN599935 Corp","DS458")} -> #NAME? | E13: {=_xll.BDP("YN599935 Corp","DS004")} -> #NAME? | F13: {=_xll.BDP("YN599935 Corp","DS035")} -> #NAME? | G13: {=_xll.BDP(A13,"DS086")} -> #NAME? | H13: {=_xll.BDP(A13,"DS034")} -> #NAME? | I13: {=_xll.BDP("YN599935 Corp","DS033")} -> #NAME? | J13: {=_xll.BDP(A13,"YL018")} -> #NAME? | K13: {=_xll.BDP("YN599935 Corp","YL016")} -> #NAME? | L13: {=_xll.BDP("YN599935 Corp","PR004")} -> #NAME? | M13: {=_xll.BDP(A13,"PR002")} -> #NAME? | N13: {=_xll.BDP(A13,"ID028")} -> #NAME? | O13: {=_xll.BDP("YN599935 Corp","ID005")} -> #NAME? | P13: {=_xll.BDP("YN599935 Corp","RA007")} -> #NAME? | Q13: {=_xll.BDP("YN599935 Corp","DS219")} -> #NAME? | R13: {=_xll.BDP(A13,"DS040")} -> #NAME? | S13: =(F13-TODAY())/365.25 -> #NAME?
A14: YN600126 Corp | B14: {=_xll.BDP("YN600126 Corp","DS520")} -> #NAME? | C14: {=_xll.BDP("YN600126 Corp","DS001")} -> #NAME? | D14: {=_xll.BDP("YN600126 Corp","DS458")} -> #NAME? | E14: {=_xll.BDP("YN600126 Corp","DS004")} -> #NAME? | F14: {=_xll.BDP("YN600126 Corp","DS035")} -> #NAME? | G14: {=_xll.BDP(A14,"DS086")} -> #NAME? | H14: {=_xll.BDP(A14,"DS034")} -> #NAME? | I14: {=_xll.BDP("YN600126 Corp","DS033")} -> #NAME? | J14: {=_xll.BDP(A14,"YL018")} -> #NAME? | K14: {=_xll.BDP("YN600126 Corp","YL016")} -> #NAME? | L14: {=_xll.BDP("YN600126 Corp","PR004")} -> #NAME? | M14: {=_xll.BDP(A14,"PR002")} -> #NAME? | N14: {=_xll.BDP(A14,"ID028")} -> #NAME? | O14: {=_xll.BDP("YN600126 Corp","ID005")} -> #NAME? | P14: {=_xll.BDP("YN600126 Corp","RA007")} -> #NAME? | Q14: {=_xll.BDP("YN600126 Corp","DS219")} -> #NAME? | R14: {=_xll.BDP(A14,"DS040")} -> #NAME? | S14: =(F14-TODAY())/365.25 -> #NAME?
A15: ZD637375 Corp | B15: {=_xll.BDP("ZD637375 Corp","DS520")} -> #NAME? | C15: {=_xll.BDP("ZD637375 Corp","DS001")} -> #NAME? | D15: {=_xll.BDP("ZD637375 Corp","DS458")} -> #NAME? | E15: {=_xll.BDP("ZD637375 Corp","DS004")} -> #NAME? | F15: {=_xll.BDP("ZD637375 Corp","DS035")} -> #NAME? | G15: {=_xll.BDP(A15,"DS086")} -> #NAME? | H15: {=_xll.BDP(A15,"DS034")} -> #NAME? | I15: {=_xll.BDP("ZD637375 Corp","DS033")} -> #NAME? | J15: {=_xll.BDP(A15,"YL018")} -> #NAME? | K15: {=_xll.BDP("ZD637375 Corp","YL016")} -> #NAME? | L15: {=_xll.BDP("ZD637375 Corp","PR004")} -> #NAME? | M15: {=_xll.BDP(A15,"PR002")} -> #NAME? | N15: {=_xll.BDP(A15,"ID028")} -> #NAME? | O15: {=_xll.BDP("ZD637375 Corp","ID005")} -> #NAME? | P15: {=_xll.BDP("ZD637375 Corp","RA007")} -> #NAME? | Q15: {=_xll.BDP("ZD637375 Corp","DS219")} -> #NAME? | R15: {=_xll.BDP(A15,"DS040")} -> #NAME? | S15: =(F15-TODAY())/365.25 -> #NAME?
A16: AN666209 Corp | B16: {=_xll.BDP("AN666209 Corp","DS520")} -> #NAME? | C16: {=_xll.BDP("AN666209 Corp","DS001")} -> #NAME? | D16: {=_xll.BDP("AN666209 Corp","DS458")} -> #NAME? | E16: {=_xll.BDP("AN666209 Corp","DS004")} -> #NAME? | F16: {=_xll.BDP("AN666209 Corp","DS035")} -> #NAME? | G16: {=_xll.BDP(A16,"DS086")} -> #NAME? | H16: {=_xll.BDP(A16,"DS034")} -> #NAME? | I16: {=_xll.BDP("AN666209 Corp","DS033")} -> #NAME? | J16: {=_xll.BDP(A16,"YL018")} -> #NAME? | K16: {=_xll.BDP("AN666209 Corp","YL016")} -> #NAME? | L16: {=_xll.BDP("AN666209 Corp","PR004")} -> #NAME? | M16: {=_xll.BDP(A16,"PR002")} -> #NAME? | N16: {=_xll.BDP(A16,"ID028")} -> #NAME? | O16: {=_xll.BDP("AN666209 Corp","ID005")} -> #NAME? | P16: {=_xll.BDP("AN666209 Corp","RA007")} -> #NAME? | Q16: {=_xll.BDP("AN666209 Corp","DS219")} -> #NAME? | R16: {=_xll.BDP(A16,"DS040")} -> #NAME? | S16: =(F16-TODAY())/365.25 -> #NAME?
A17: YS631917 Corp | B17: {=_xll.BDP("YS631917 Corp","DS520")} -> #NAME? | C17: {=_xll.BDP("YS631917 Corp","DS001")} -> #NAME? | D17: {=_xll.BDP("YS631917 Corp","DS458")} -> #NAME? | E17: {=_xll.BDP("YS631917 Corp","DS004")} -> #NAME? | F17: {=_xll.BDP("YS631917 Corp","DS035")} -> #NAME? | G17: {=_xll.BDP(A17,"DS086")} -> #NAME? | H17: {=_xll.BDP(A17,"DS034")} -> #NAME? | I17: {=_xll.BDP("YS631917 Corp","DS033")} -> #NAME? | J17: {=_xll.BDP(A17,"YL018")} -> #NAME? | K17: {=_xll.BDP("YS631917 Corp","YL016")} -> #NAME? | L17: {=_xll.BDP("YS631917 Corp","PR004")} -> #NAME? | M17: {=_xll.BDP(A17,"PR002")} -> #NAME? | N17: {=_xll.BDP(A17,"ID028")} -> #NAME? | O17: {=_xll.BDP("YS631917 Corp","ID005")} -> #NAME? | P17: {=_xll.BDP("YS631917 Corp","RA007")} -> #NAME? | Q17: {=_xll.BDP("YS631917 Corp","DS219")} -> #NAME? | R17: {=_xll.BDP(A17,"DS040")} -> #NAME? | S17: =(F17-TODAY())/365.25 -> #NAME?
A18: BW601183 Corp | B18: {=_xll.BDP("BW601183 Corp","DS520")} -> #NAME? | C18: {=_xll.BDP("BW601183 Corp","DS001")} -> #NAME? | D18: {=_xll.BDP("BW601183 Corp","DS458")} -> #NAME? | E18: {=_xll.BDP("BW601183 Corp","DS004")} -> #NAME? | F18: {=_xll.BDP("BW601183 Corp","DS035")} -> #NAME? | G18: {=_xll.BDP(A18,"DS086")} -> #NAME? | H18: {=_xll.BDP(A18,"DS034")} -> #NAME? | I18: {=_xll.BDP("BW601183 Corp","DS033")} -> #NAME? | J18: {=_xll.BDP(A18,"YL018")} -> #NAME? | K18: {=_xll.BDP("BW601183 Corp","YL016")} -> #NAME? | L18: {=_xll.BDP("BW601183 Corp","PR004")} -> #NAME? | M18: {=_xll.BDP(A18,"PR002")} -> #NAME? | N18: {=_xll.BDP(A18,"ID028")} -> #NAME? | O18: {=_xll.BDP("BW601183 Corp","ID005")} -> #NAME? | P18: {=_xll.BDP("BW601183 Corp","RA007")} -> #NAME? | Q18: {=_xll.BDP("BW601183 Corp","DS219")} -> #NAME? | R18: {=_xll.BDP(A18,"DS040")} -> #NAME? | S18: =(F18-TODAY())/365.25 -> #NAME?
A19: YT821868 Corp | B19: {=_xll.BDP("YT821868 Corp","DS520")} -> #NAME? | C19: {=_xll.BDP("YT821868 Corp","DS001")} -> #NAME? | D19: {=_xll.BDP("YT821868 Corp","DS458")} -> #NAME? | E19: {=_xll.BDP("YT821868 Corp","DS004")} -> #NAME? | F19: {=_xll.BDP("YT821868 Corp","DS035")} -> #NAME? | G19: {=_xll.BDP(A19,"DS086")} -> #NAME? | H19: {=_xll.BDP(A19,"DS034")} -> #NAME? | I19: {=_xll.BDP("YT821868 Corp","DS033")} -> #NAME? | J19: {=_xll.BDP(A19,"YL018")} -> #NAME? | K19: {=_xll.BDP("YT821868 Corp","YL016")} -> #NAME? | L19: {=_xll.BDP("YT821868 Corp","PR004")} -> #NAME? | M19: {=_xll.BDP(A19,"PR002")} -> #NAME? | N19: {=_xll.BDP(A19,"ID028")} -> #NAME? | O19: {=_xll.BDP("YT821868 Corp","ID005")} -> #NAME? | P19: {=_xll.BDP("YT821868 Corp","RA007")} -> #NAME? | Q19: {=_xll.BDP("YT821868 Corp","DS219")} -> #NAME? | R19: {=_xll.BDP(A19,"DS040")} -> #NAME? | S19: =(F19-TODAY())/365.25 -> #NAME?
A20: YT968038 Corp | B20: {=_xll.BDP("YT968038 Corp","DS520")} -> #NAME? | C20: {=_xll.BDP("YT968038 Corp","DS001")} -> #NAME? | D20: {=_xll.BDP("YT968038 Corp","DS458")} -> #NAME? | E20: {=_xll.BDP("YT968038 Corp","DS004")} -> #NAME? | F20: {=_xll.BDP("YT968038 Corp","DS035")} -> #NAME? | G20: {=_xll.BDP(A20,"DS086")} -> #NAME? | H20: {=_xll.BDP(A20,"DS034")} -> #NAME? | I20: {=_xll.BDP("YT968038 Corp","DS033")} -> #NAME? | J20: {=_xll.BDP(A20,"YL018")} -> #NAME? | K20: {=_xll.BDP("YT968038 Corp","YL016")} -> #NAME? | L20: {=_xll.BDP("YT968038 Corp","PR004")} -> #NAME? | M20: {=_xll.BDP(A20,"PR002")} -> #NAME? | N20: {=_xll.BDP(A20,"ID028")} -> #NAME? | O20: {=_xll.BDP("YT968038 Corp","ID005")} -> #NAME? | P20: {=_xll.BDP("YT968038 Corp","RA007")} -> #NAME? | Q20: {=_xll.BDP("YT968038 Corp","DS219")} -> #NAME? | R20: {=_xll.BDP(A20,"DS040")} -> #NAME? | S20: =(F20-TODAY())/365.25 -> #NAME?
A21: AP577034 Corp | B21: {=_xll.BDP("AP577034 Corp","DS520")} -> #NAME? | C21: {=_xll.BDP("AP577034 Corp","DS001")} -> #NAME? | D21: {=_xll.BDP("AP577034 Corp","DS458")} -> #NAME? | E21: {=_xll.BDP("AP577034 Corp","DS004")} -> #NAME? | F21: {=_xll.BDP("AP577034 Corp","DS035")} -> #NAME? | G21: {=_xll.BDP(A21,"DS086")} -> #NAME? | H21: {=_xll.BDP(A21,"DS034")} -> #NAME? | I21: {=_xll.BDP("AP577034 Corp","DS033")} -> #NAME? | J21: {=_xll.BDP(A21,"YL018")} -> #NAME? | K21: {=_xll.BDP("AP577034 Corp","YL016")} -> #NAME? | L21: {=_xll.BDP("AP577034 Corp","PR004")} -> #NAME? | M21: {=_xll.BDP(A21,"PR002")} -> #NAME? | N21: {=_xll.BDP(A21,"ID028")} -> #NAME? | O21: {=_xll.BDP("AP577034 Corp","ID005")} -> #NAME? | P21: {=_xll.BDP("AP577034 Corp","RA007")} -> #NAME? | Q21: {=_xll.BDP("AP577034 Corp","DS219")} -> #NAME? | R21: {=_xll.BDP(A21,"DS040")} -> #NAME? | S21: =(F21-TODAY())/365.25 -> #NAME?
A22: LW169503 Corp | B22: {=_xll.BDP("LW169503 Corp","DS520")} -> #NAME? | C22: {=_xll.BDP("LW169503 Corp","DS001")} -> #NAME? | D22: {=_xll.BDP("LW169503 Corp","DS458")} -> #NAME? | E22: {=_xll.BDP("LW169503 Corp","DS004")} -> #NAME? | F22: {=_xll.BDP("LW169503 Corp","DS035")} -> #NAME? | G22: {=_xll.BDP(A22,"DS086")} -> #NAME? | H22: {=_xll.BDP(A22,"DS034")} -> #NAME? | I22: {=_xll.BDP("LW169503 Corp","DS033")} -> #NAME? | J22: {=_xll.BDP(A22,"YL018")} -> #NAME? | K22: {=_xll.BDP("LW169503 Corp","YL016")} -> #NAME? | L22: {=_xll.BDP("LW169503 Corp","PR004")} -> #NAME? | M22: {=_xll.BDP(A22,"PR002")} -> #NAME? | N22: {=_xll.BDP(A22,"ID028")} -> #NAME? | O22: {=_xll.BDP("LW169503 Corp","ID005")} -> #NAME? | P22: {=_xll.BDP("LW169503 Corp","RA007")} -> #NAME? | Q22: {=_xll.BDP("LW169503 Corp","DS219")} -> #NAME? | R22: {=_xll.BDP(A22,"DS040")} -> #NAME? | S22: =(F22-TODAY())/365.25 -> #NAME?
A23: YK943560 Corp | B23: {=_xll.BDP("YK943560 Corp","DS520")} -> #NAME? | C23: {=_xll.BDP("YK943560 Corp","DS001")} -> #NAME? | D23: {=_xll.BDP("YK943560 Corp","DS458")} -> #NAME? | E23: {=_xll.BDP("YK943560 Corp","DS004")} -> #NAME? | F23: {=_xll.BDP("YK943560 Corp","DS035")} -> #NAME? | G23: {=_xll.BDP(A23,"DS086")} -> #NAME? | H23: {=_xll.BDP(A23,"DS034")} -> #NAME? | I23: {=_xll.BDP("YK943560 Corp","DS033")} -> #NAME? | J23: {=_xll.BDP(A23,"YL018")} -> #NAME? | K23: {=_xll.BDP("YK943560 Corp","YL016")} -> #NAME? | L23: {=_xll.BDP("YK943560 Corp","PR004")} -> #NAME? | M23: {=_xll.BDP(A23,"PR002")} -> #NAME? | N23: {=_xll.BDP(A23,"ID028")} -> #NAME? | O23: {=_xll.BDP("YK943560 Corp","ID005")} -> #NAME? | P23: {=_xll.BDP("YK943560 Corp","RA007")} -> #NAME? | Q23: {=_xll.BDP("YK943560 Corp","DS219")} -> #NAME? | R23: {=_xll.BDP(A23,"DS040")} -> #NAME? | S23: =(F23-TODAY())/365.25 -> #NAME?
A24: YT967931 Corp | B24: {=_xll.BDP("YT967931 Corp","DS520")} -> #NAME? | C24: {=_xll.BDP("YT967931 Corp","DS001")} -> #NAME? | D24: {=_xll.BDP("YT967931 Corp","DS458")} -> #NAME? | E24: {=_xll.BDP("YT967931 Corp","DS004")} -> #NAME? | F24: {=_xll.BDP("YT967931 Corp","DS035")} -> #NAME? | G24: {=_xll.BDP(A24,"DS086")} -> #NAME? | H24: {=_xll.BDP(A24,"DS034")} -> #NAME? | I24: {=_xll.BDP("YT967931 Corp","DS033")} -> #NAME? | J24: {=_xll.BDP(A24,"YL018")} -> #NAME? | K24: {=_xll.BDP("YT967931 Corp","YL016")} -> #NAME? | L24: {=_xll.BDP("YT967931 Corp","PR004")} -> #NAME? | M24: {=_xll.BDP(A24,"PR002")} -> #NAME? | N24: {=_xll.BDP(A24,"ID028")} -> #NAME? | O24: {=_xll.BDP("YT967931 Corp","ID005")} -> #NAME? | P24: {=_xll.BDP("YT967931 Corp","RA007")} -> #NAME? | Q24: {=_xll.BDP("YT967931 Corp","DS219")} -> #NAME? | R24: {=_xll.BDP(A24,"DS040")} -> #NAME? | S24: =(F24-TODAY())/365.25 -> #NAME?
A25: YV792963 Corp | B25: {=_xll.BDP("YV792963 Corp","DS520")} -> #NAME? | C25: {=_xll.BDP("YV792963 Corp","DS001")} -> #NAME? | D25: {=_xll.BDP("YV792963 Corp","DS458")} -> #NAME? | E25: {=_xll.BDP("YV792963 Corp","DS004")} -> #NAME? | F25: {=_xll.BDP("YV792963 Corp","DS035")} -> #NAME? | G25: {=_xll.BDP(A25,"DS086")} -> #NAME? | H25: {=_xll.BDP(A25,"DS034")} -> #NAME? | I25: {=_xll.BDP("YV792963 Corp","DS033")} -> #NAME? | J25: {=_xll.BDP(A25,"YL018")} -> #NAME? | K25: {=_xll.BDP("YV792963 Corp","YL016")} -> #NAME? | L25: {=_xll.BDP("YV792963 Corp","PR004")} -> #NAME? | M25: {=_xll.BDP(A25,"PR002")} -> #NAME? | N25: {=_xll.BDP(A25,"ID028")} -> #NAME? | O25: {=_xll.BDP("YV792963 Corp","ID005")} -> #NAME? | P25: {=_xll.BDP("YV792963 Corp","RA007")} -> #NAME? | Q25: {=_xll.BDP("YV792963 Corp","DS219")} -> #NAME? | R25: {=_xll.BDP(A25,"DS040")} -> #NAME? | S25: =(F25-TODAY())/365.25 -> #NAME?
A26: YV793180 Corp | B26: {=_xll.BDP("YV793180 Corp","DS520")} -> #NAME? | C26: {=_xll.BDP("YV793180 Corp","DS001")} -> #NAME? | D26: {=_xll.BDP("YV793180 Corp","DS458")} -> #NAME? | E26: {=_xll.BDP("YV793180 Corp","DS004")} -> #NAME? | F26: {=_xll.BDP("YV793180 Corp","DS035")} -> #NAME? | G26: {=_xll.BDP(A26,"DS086")} -> #NAME? | H26: {=_xll.BDP(A26,"DS034")} -> #NAME? | I26: {=_xll.BDP("YV793180 Corp","DS033")} -> #NAME? | J26: {=_xll.BDP(A26,"YL018")} -> #NAME? | K26: {=_xll.BDP("YV793180 Corp","YL016")} -> #NAME? | L26: {=_xll.BDP("YV793180 Corp","PR004")} -> #NAME? | M26: {=_xll.BDP(A26,"PR002")} -> #NAME? | N26: {=_xll.BDP(A26,"ID028")} -> #NAME? | O26: {=_xll.BDP("YV793180 Corp","ID005")} -> #NAME? | P26: {=_xll.BDP("YV793180 Corp","RA007")} -> #NAME? | Q26: {=_xll.BDP("YV793180 Corp","DS219")} -> #NAME? | R26: {=_xll.BDP(A26,"DS040")} -> #NAME? | S26: =(F26-TODAY())/365.25 -> #NAME?
A27: ZD637368 Corp | B27: {=_xll.BDP("ZD637368 Corp","DS520")} -> #NAME? | C27: {=_xll.BDP("ZD637368 Corp","DS001")} -> #NAME? | D27: {=_xll.BDP("ZD637368 Corp","DS458")} -> #NAME? | E27: {=_xll.BDP("ZD637368 Corp","DS004")} -> #NAME? | F27: {=_xll.BDP("ZD637368 Corp","DS035")} -> #NAME? | G27: {=_xll.BDP(A27,"DS086")} -> #NAME? | H27: {=_xll.BDP(A27,"DS034")} -> #NAME? | I27: {=_xll.BDP("ZD637368 Corp","DS033")} -> #NAME? | J27: {=_xll.BDP(A27,"YL018")} -> #NAME? | K27: {=_xll.BDP("ZD637368 Corp","YL016")} -> #NAME? | L27: {=_xll.BDP("ZD637368 Corp","PR004")} -> #NAME? | M27: {=_xll.BDP(A27,"PR002")} -> #NAME? | N27: {=_xll.BDP(A27,"ID028")} -> #NAME? | O27: {=_xll.BDP("ZD637368 Corp","ID005")} -> #NAME? | P27: {=_xll.BDP("ZD637368 Corp","RA007")} -> #NAME? | Q27: {=_xll.BDP("ZD637368 Corp","DS219")} -> #NAME? | R27: {=_xll.BDP(A27,"DS040")} -> #NAME? | S27: =(F27-TODAY())/365.25 -> #NAME?
A28: ZK701516 Corp | B28: {=_xll.BDP("ZK701516 Corp","DS520")} -> #NAME? | C28: {=_xll.BDP("ZK701516 Corp","DS001")} -> #NAME? | D28: {=_xll.BDP("ZK701516 Corp","DS458")} -> #NAME? | E28: {=_xll.BDP("ZK701516 Corp","DS004")} -> #NAME? | F28: {=_xll.BDP("ZK701516 Corp","DS035")} -> #NAME? | G28: {=_xll.BDP(A28,"DS086")} -> #NAME? | H28: {=_xll.BDP(A28,"DS034")} -> #NAME? | I28: {=_xll.BDP("ZK701516 Corp","DS033")} -> #NAME? | J28: {=_xll.BDP(A28,"YL018")} -> #NAME? | K28: {=_xll.BDP("ZK701516 Corp","YL016")} -> #NAME? | L28: {=_xll.BDP("ZK701516 Corp","PR004")} -> #NAME? | M28: {=_xll.BDP(A28,"PR002")} -> #NAME? | N28: {=_xll.BDP(A28,"ID028")} -> #NAME? | O28: {=_xll.BDP("ZK701516 Corp","ID005")} -> #NAME? | P28: {=_xll.BDP("ZK701516 Corp","RA007")} -> #NAME? | Q28: {=_xll.BDP("ZK701516 Corp","DS219")} -> #NAME? | R28: {=_xll.BDP(A28,"DS040")} -> #NAME? | S28: =(F28-TODAY())/365.25 -> #NAME?
A29: ZK701649 Corp | B29: {=_xll.BDP("ZK701649 Corp","DS520")} -> #NAME? | C29: {=_xll.BDP("ZK701649 Corp","DS001")} -> #NAME? | D29: {=_xll.BDP("ZK701649 Corp","DS458")} -> #NAME? | E29: {=_xll.BDP("ZK701649 Corp","DS004")} -> #NAME? | F29: {=_xll.BDP("ZK701649 Corp","DS035")} -> #NAME? | G29: {=_xll.BDP(A29,"DS086")} -> #NAME? | H29: {=_xll.BDP(A29,"DS034")} -> #NAME? | I29: {=_xll.BDP("ZK701649 Corp","DS033")} -> #NAME? | J29: {=_xll.BDP(A29,"YL018")} -> #NAME? | K29: {=_xll.BDP("ZK701649 Corp","YL016")} -> #NAME? | L29: {=_xll.BDP("ZK701649 Corp","PR004")} -> #NAME? | M29: {=_xll.BDP(A29,"PR002")} -> #NAME? | N29: {=_xll.BDP(A29,"ID028")} -> #NAME? | O29: {=_xll.BDP("ZK701649 Corp","ID005")} -> #NAME? | P29: {=_xll.BDP("ZK701649 Corp","RA007")} -> #NAME? | Q29: {=_xll.BDP("ZK701649 Corp","DS219")} -> #NAME? | R29: {=_xll.BDP(A29,"DS040")} -> #NAME? | S29: =(F29-TODAY())/365.25 -> #NAME?
A30: AO295977 Corp | B30: {=_xll.BDP("AO295977 Corp","DS520")} -> #NAME? | C30: {=_xll.BDP("AO295977 Corp","DS001")} -> #NAME? | D30: {=_xll.BDP("AO295977 Corp","DS458")} -> #NAME? | E30: {=_xll.BDP("AO295977 Corp","DS004")} -> #NAME? | F30: {=_xll.BDP("AO295977 Corp","DS035")} -> #NAME? | G30: {=_xll.BDP(A30,"DS086")} -> #NAME? | H30: {=_xll.BDP(A30,"DS034")} -> #NAME? | I30: {=_xll.BDP("AO295977 Corp","DS033")} -> #NAME? | J30: {=_xll.BDP(A30,"YL018")} -> #NAME? | K30: {=_xll.BDP("AO295977 Corp","YL016")} -> #NAME? | L30: {=_xll.BDP("AO295977 Corp","PR004")} -> #NAME? | M30: {=_xll.BDP(A30,"PR002")} -> #NAME? | N30: {=_xll.BDP(A30,"ID028")} -> #NAME? | O30: {=_xll.BDP("AO295977 Corp","ID005")} -> #NAME? | P30: {=_xll.BDP("AO295977 Corp","RA007")} -> #NAME? | Q30: {=_xll.BDP("AO295977 Corp","DS219")} -> #NAME? | R30: {=_xll.BDP(A30,"DS040")} -> #NAME? | S30: =(F30-TODAY())/365.25 -> #NAME?
A31: AU925890 Corp | B31: {=_xll.BDP("AU925890 Corp","DS520")} -> #NAME? | C31: {=_xll.BDP("AU925890 Corp","DS001")} -> #NAME? | D31: {=_xll.BDP("AU925890 Corp","DS458")} -> #NAME? | E31: {=_xll.BDP("AU925890 Corp","DS004")} -> #NAME? | F31: {=_xll.BDP("AU925890 Corp","DS035")} -> #NAME? | G31: {=_xll.BDP(A31,"DS086")} -> #NAME? | H31: {=_xll.BDP(A31,"DS034")} -> #NAME? | I31: {=_xll.BDP("AU925890 Corp","DS033")} -> #NAME? | J31: {=_xll.BDP(A31,"YL018")} -> #NAME? | K31: {=_xll.BDP("AU925890 Corp","YL016")} -> #NAME? | L31: {=_xll.BDP("AU925890 Corp","PR004")} -> #NAME? | M31: {=_xll.BDP(A31,"PR002")} -> #NAME? | N31: {=_xll.BDP(A31,"ID028")} -> #NAME? | O31: {=_xll.BDP("AU925890 Corp","ID005")} -> #NAME? | P31: {=_xll.BDP("AU925890 Corp","RA007")} -> #NAME? | Q31: {=_xll.BDP("AU925890 Corp","DS219")} -> #NAME? | R31: {=_xll.BDP(A31,"DS040")} -> #NAME? | S31: =(F31-TODAY())/365.25 -> #NAME?
A32: BO579315 Corp | B32: {=_xll.BDP("BO579315 Corp","DS520")} -> #NAME? | C32: {=_xll.BDP("BO579315 Corp","DS001")} -> #NAME? | D32: {=_xll.BDP("BO579315 Corp","DS458")} -> #NAME? | E32: {=_xll.BDP("BO579315 Corp","DS004")} -> #NAME? | F32: {=_xll.BDP("BO579315 Corp","DS035")} -> #NAME? | G32: {=_xll.BDP(A32,"DS086")} -> #NAME? | H32: {=_xll.BDP(A32,"DS034")} -> #NAME? | I32: {=_xll.BDP("BO579315 Corp","DS033")} -> #NAME? | J32: {=_xll.BDP(A32,"YL018")} -> #NAME? | K32: {=_xll.BDP("BO579315 Corp","YL016")} -> #NAME? | L32: {=_xll.BDP("BO579315 Corp","PR004")} -> #NAME? | M32: {=_xll.BDP(A32,"PR002")} -> #NAME? | N32: {=_xll.BDP(A32,"ID028")} -> #NAME? | O32: {=_xll.BDP("BO579315 Corp","ID005")} -> #NAME? | P32: {=_xll.BDP("BO579315 Corp","RA007")} -> #NAME? | Q32: {=_xll.BDP("BO579315 Corp","DS219")} -> #NAME? | R32: {=_xll.BDP(A32,"DS040")} -> #NAME? | S32: =(F32-TODAY())/365.25 -> #NAME?
A33: BW601098 Corp | B33: {=_xll.BDP("BW601098 Corp","DS520")} -> #NAME? | C33: {=_xll.BDP("BW601098 Corp","DS001")} -> #NAME? | D33: {=_xll.BDP("BW601098 Corp","DS458")} -> #NAME? | E33: {=_xll.BDP("BW601098 Corp","DS004")} -> #NAME? | F33: {=_xll.BDP("BW601098 Corp","DS035")} -> #NAME? | G33: {=_xll.BDP(A33,"DS086")} -> #NAME? | H33: {=_xll.BDP(A33,"DS034")} -> #NAME? | I33: {=_xll.BDP("BW601098 Corp","DS033")} -> #NAME? | J33: {=_xll.BDP(A33,"YL018")} -> #NAME? | K33: {=_xll.BDP("BW601098 Corp","YL016")} -> #NAME? | L33: {=_xll.BDP("BW601098 Corp","PR004")} -> #NAME? | M33: {=_xll.BDP(A33,"PR002")} -> #NAME? | N33: {=_xll.BDP(A33,"ID028")} -> #NAME? | O33: {=_xll.BDP("BW601098 Corp","ID005")} -> #NAME? | P33: {=_xll.BDP("BW601098 Corp","RA007")} -> #NAME? | Q33: {=_xll.BDP("BW601098 Corp","DS219")} -> #NAME? | R33: {=_xll.BDP(A33,"DS040")} -> #NAME? | S33: =(F33-TODAY())/365.25 -> #NAME?
A34: YK173548 Corp | B34: {=_xll.BDP("YK173548 Corp","DS520")} -> #NAME? | C34: {=_xll.BDP("YK173548 Corp","DS001")} -> #NAME? | D34: {=_xll.BDP("YK173548 Corp","DS458")} -> #NAME? | E34: {=_xll.BDP("YK173548 Corp","DS004")} -> #NAME? | F34: {=_xll.BDP("YK173548 Corp","DS035")} -> #NAME? | G34: {=_xll.BDP(A34,"DS086")} -> #NAME? | H34: {=_xll.BDP(A34,"DS034")} -> #NAME? | I34: {=_xll.BDP("YK173548 Corp","DS033")} -> #NAME? | J34: {=_xll.BDP(A34,"YL018")} -> #NAME? | K34: {=_xll.BDP("YK173548 Corp","YL016")} -> #NAME? | L34: {=_xll.BDP("YK173548 Corp","PR004")} -> #NAME? | M34: {=_xll.BDP(A34,"PR002")} -> #NAME? | N34: {=_xll.BDP(A34,"ID028")} -> #NAME? | O34: {=_xll.BDP("YK173548 Corp","ID005")} -> #NAME? | P34: {=_xll.BDP("YK173548 Corp","RA007")} -> #NAME? | Q34: {=_xll.BDP("YK173548 Corp","DS219")} -> #NAME? | R34: {=_xll.BDP(A34,"DS040")} -> #NAME? | S34: =(F34-TODAY())/365.25 -> #NAME?
A35: ZI885869 Corp | B35: {=_xll.BDP("ZI885869 Corp","DS520")} -> #NAME? | C35: {=_xll.BDP("ZI885869 Corp","DS001")} -> #NAME? | D35: {=_xll.BDP("ZI885869 Corp","DS458")} -> #NAME? | E35: {=_xll.BDP("ZI885869 Corp","DS004")} -> #NAME? | F35: {=_xll.BDP("ZI885869 Corp","DS035")} -> #NAME? | G35: {=_xll.BDP(A35,"DS086")} -> #NAME? | H35: {=_xll.BDP(A35,"DS034")} -> #NAME? | I35: {=_xll.BDP("ZI885869 Corp","DS033")} -> #NAME? | J35: {=_xll.BDP(A35,"YL018")} -> #NAME? | K35: {=_xll.BDP("ZI885869 Corp","YL016")} -> #NAME? | L35: {=_xll.BDP("ZI885869 Corp","PR004")} -> #NAME? | M35: {=_xll.BDP(A35,"PR002")} -> #NAME? | N35: {=_xll.BDP(A35,"ID028")} -> #NAME? | O35: {=_xll.BDP("ZI885869 Corp","ID005")} -> #NAME? | P35: {=_xll.BDP("ZI885869 Corp","RA007")} -> #NAME? | Q35: {=_xll.BDP("ZI885869 Corp","DS219")} -> #NAME? | R35: {=_xll.BDP(A35,"DS040")} -> #NAME? | S35: =(F35-TODAY())/365.25 -> #NAME?
A36: ZS613802 Corp | B36: {=_xll.BDP("ZS613802 Corp","DS520")} -> #NAME? | C36: {=_xll.BDP("ZS613802 Corp","DS001")} -> #NAME? | D36: {=_xll.BDP("ZS613802 Corp","DS458")} -> #NAME? | E36: {=_xll.BDP("ZS613802 Corp","DS004")} -> #NAME? | F36: {=_xll.BDP("ZS613802 Corp","DS035")} -> #NAME? | G36: {=_xll.BDP(A36,"DS086")} -> #NAME? | H36: {=_xll.BDP(A36,"DS034")} -> #NAME? | I36: {=_xll.BDP("ZS613802 Corp","DS033")} -> #NAME? | J36: {=_xll.BDP(A36,"YL018")} -> #NAME? | K36: {=_xll.BDP("ZS613802 Corp","YL016")} -> #NAME? | L36: {=_xll.BDP("ZS613802 Corp","PR004")} -> #NAME? | M36: {=_xll.BDP(A36,"PR002")} -> #NAME? | N36: {=_xll.BDP(A36,"ID028")} -> #NAME? | O36: {=_xll.BDP("ZS613802 Corp","ID005")} -> #NAME? | P36: {=_xll.BDP("ZS613802 Corp","RA007")} -> #NAME? | Q36: {=_xll.BDP("ZS613802 Corp","DS219")} -> #NAME? | R36: {=_xll.BDP(A36,"DS040")} -> #NAME? | S36: =(F36-TODAY())/365.25 -> #NAME?
A37: BZ742454 Corp | B37: {=_xll.BDP("BZ742454 Corp","DS520")} -> #NAME? | C37: {=_xll.BDP("BZ742454 Corp","DS001")} -> #NAME? | D37: {=_xll.BDP("BZ742454 Corp","DS458")} -> #NAME? | E37: {=_xll.BDP("BZ742454 Corp","DS004")} -> #NAME? | F37: {=_xll.BDP("BZ742454 Corp","DS035")} -> #NAME? | G37: {=_xll.BDP(A37,"DS086")} -> #NAME? | H37: {=_xll.BDP(A37,"DS034")} -> #NAME? | I37: {=_xll.BDP("BZ742454 Corp","DS033")} -> #NAME? | J37: {=_xll.BDP(A37,"YL018")} -> #NAME? | K37: {=_xll.BDP("BZ742454 Corp","YL016")} -> #NAME? | L37: {=_xll.BDP("BZ742454 Corp","PR004")} -> #NAME? | M37: {=_xll.BDP(A37,"PR002")} -> #NAME? | N37: {=_xll.BDP(A37,"ID028")} -> #NAME? | O37: {=_xll.BDP("BZ742454 Corp","ID005")} -> #NAME? | P37: {=_xll.BDP("BZ742454 Corp","RA007")} -> #NAME? | Q37: {=_xll.BDP("BZ742454 Corp","DS219")} -> #NAME? | R37: {=_xll.BDP(A37,"DS040")} -> #NAME? | S37: =(F37-TODAY())/365.25 -> #NAME?
A38: YK172992 Corp | B38: {=_xll.BDP("YK172992 Corp","DS520")} -> #NAME? | C38: {=_xll.BDP("YK172992 Corp","DS001")} -> #NAME? | D38: {=_xll.BDP("YK172992 Corp","DS458")} -> #NAME? | E38: {=_xll.BDP("YK172992 Corp","DS004")} -> #NAME? | F38: {=_xll.BDP("YK172992 Corp","DS035")} -> #NAME? | G38: {=_xll.BDP(A38,"DS086")} -> #NAME? | H38: {=_xll.BDP(A38,"DS034")} -> #NAME? | I38: {=_xll.BDP("YK172992 Corp","DS033")} -> #NAME? | J38: {=_xll.BDP(A38,"YL018")} -> #NAME? | K38: {=_xll.BDP("YK172992 Corp","YL016")} -> #NAME? | L38: {=_xll.BDP("YK172992 Corp","PR004")} -> #NAME? | M38: {=_xll.BDP(A38,"PR002")} -> #NAME? | N38: {=_xll.BDP(A38,"ID028")} -> #NAME? | O38: {=_xll.BDP("YK172992 Corp","ID005")} -> #NAME? | P38: {=_xll.BDP("YK172992 Corp","RA007")} -> #NAME? | Q38: {=_xll.BDP("YK172992 Corp","DS219")} -> #NAME? | R38: {=_xll.BDP(A38,"DS040")} -> #NAME? | S38: =(F38-TODAY())/365.25 -> #NAME?

Sheet Offline
A1: Instrument | B1: Name | C1: Ticker | D1: Country/Region | E1: Currency | F1: Maturity | G1: Coupon Type | H1: Coupon Frequency | I1: Coupon | J1: Ask Yield to Maturity | K1: Bid Yield to Maturity | L1: Ask Price | M1: Bid Price | N1: Identifier | O1: ISIN | P1: Bloomberg Composite Rating | Q1: Announce | R1: Next Coupon Settle Date | S1: Time | T1: AVG Price | U1: ID | V1: TIMEish | W1: years ago | X1: Accrued Interest | Y1: Clean price | Z1: AVG yield
A2: YL396238 Corp | B2: Toyota Motor Corp | C2: TOYOTA | D2: JP | E2: JPY | F2: 04/09/2035 | G2: FIXED | H2: 2 | I2: 1.793 | J2: 2.507 | K2: 2.507 | L2: 94.531 | M2: 94.531 | N2: YL3962385 | O2: JP363340AR99 | P2: A+ | Q2: 29/08/2025 | R2: 04/09/2026 | S2: =(F2-TODAY())/365.25 -> 9.431896 | T2: =+AVERAGE(L2:M2) -> 94.531 | U2: {=_xlfn.SEQUENCE(COUNT(H:H))} -> 1 | V2: =ROUNDDOWN(S2,0)+IF(S2-ROUNDDOWN(S2,0)>0.5,0.5,0) -> 9 | W2: =YEAR(TODAY())-YEAR(Q2) -> 1 | X2: =(TODAY()-DATE(YEAR(R2),MONTH(R2)-6,DAY(R2)))/182*(I2) -> 0.25614286 | Y2: =T2-X2 -> 94.274857 | Z2: =AVERAGE(J2:K2) -> 2.507
A3: ZI885852 Corp | B3: Toyota Finance Corp | C3: TOYOTA | D3: JP | E3: JPY | F3: 13/10/2026 | G3: FIXED | H3: 2 | I3: 0.37 | J3: 1.163 | K3: 1.163 | L3: 99.538 | M3: 99.538 | N3: ZI8858527 | O3: JP363360APA1 | P3: A+ | Q3: 06/10/2023 | R3: 13/04/2026 | S3: =(F3-TODAY())/365.25 -> 0.53935661 | T3: =+AVERAGE(L3:M3) -> 99.538 | U3: 2 | V3: =ROUNDDOWN(S3,0)+IF(S3-ROUNDDOWN(S3,0)>0.5,0.5,0) -> 0.5 | W3: =YEAR(TODAY())-YEAR(Q3) -> 3 | X3: =(TODAY()-DATE(YEAR(R3),MONTH(R3)-6,DAY(R3)))/182*(I3) -> 0.34153846 | Y3: =T3-X3 -> 99.196462 | Z3: =AVERAGE(J3:K3) -> 1.163
A4: LW169500 Corp | B4: Toyota Motor Corp | C4: TOYOTA | D4: JP | E4: JPY | F4: 03/06/2026 | G4: FIXED | H4: 2 | I4: 0.09 | J4: 0.864 | K4: 1.134 | L4: 99.826 | M4: 99.766 | N4: LW1695003 | O4: JP363340AG68 | P4: A+ | Q4: 27/05/2016 | R4: 03/06/2026 | S4: =(F4-TODAY())/365.25 -> 0.1779603 | T4: =+AVERAGE(L4:M4) -> 99.796 | U4: 3 | V4: =ROUNDDOWN(S4,0)+IF(S4-ROUNDDOWN(S4,0)>0.5,0.5,0) -> 0 | W4: =YEAR(TODAY())-YEAR(Q4) -> 10 | X4: =(TODAY()-DATE(YEAR(R4),MONTH(R4)-6,DAY(R4)))/182*(I4) -> 0.057857143 | Y4: =T4-X4 -> 99.738143 | Z4: =AVERAGE(J4:K4) -> 0.999
A5: AN666227 Corp | B5: Toyota Motor Corp | C5: TOYOTA | D5: JP | E5: JPY | F5: 02/06/2037 | G5: FIXED | H5: 2 | I5: 0.651 | J5: 2.962 | K5: 2.962 | L5: 80.535 | M5: 80.535 | N5: AN6662273 | O5: JP363340DH64 | P5: A+ | Q5: 26/05/2017 | R5: 02/06/2026 | S5: =(F5-TODAY())/365.25 -> 11.175907 | T5: =+AVERAGE(L5:M5) -> 80.535 | U5: 4 | V5: =ROUNDDOWN(S5,0)+IF(S5-ROUNDDOWN(S5,0)>0.5,0.5,0) -> 11 | W5: =YEAR(TODAY())-YEAR(Q5) -> 9 | X5: =(TODAY()-DATE(YEAR(R5),MONTH(R5)-6,DAY(R5)))/182*(I5) -> 0.42207692 | Y5: =T5-X5 -> 80.112923 | Z5: =AVERAGE(J5:K5) -> 2.962
A6: BO356983 Corp | B6: Toyota Motor Corp | C6: TOYOTA | D6: JP | E6: JPY | F6: 18/03/2031 | G6: FIXED | H6: 2 | I6: 0.219 | J6: 1.982 | K6: 1.982 | L6: 91.959 | M6: 91.959 | N6: BO3569833 | O6: JP363340CM35 | P6: A+ | Q6: 12/03/2021 | R6: 18/03/2026 | S6: =(F6-TODAY())/365.25 -> 4.9664613 | T6: =+AVERAGE(L6:M6) -> 91.959 | U6: 5 | V6: =ROUNDDOWN(S6,0)+IF(S6-ROUNDDOWN(S6,0)>0.5,0.5,0) -> 4.5 | W6: =YEAR(TODAY())-YEAR(Q6) -> 5 | X6: =(TODAY()-DATE(YEAR(R6),MONTH(R6)-6,DAY(R6)))/182*(I6) -> 0.23223626 | Y6: =T6-X6 -> 91.726764 | Z6: =AVERAGE(J6:K6) -> 1.982
A7: BO356985 Corp | B7: Toyota Motor Corp | C7: TOYOTA | D7: JP | E7: JPY | F7: 27/03/2026 | G7: FIXED | H7: 2 | I7: 0.1 | J7: 1.173 | K7: 1.176 | L7: 99.958 | M7: 99.958 | N7: BO3569858 | O7: JP363340AM37 | P7: #N/A N/A | Q7: 12/03/2021 | R7: 27/03/2026 | S7: =(F7-TODAY())/365.25 -> -0.0082135524 | T7: =+AVERAGE(L7:M7) -> 99.958 | U7: 6 | V7: =ROUNDDOWN(S7,0)+IF(S7-ROUNDDOWN(S7,0)>0.5,0.5,0) -> 0 | W7: =YEAR(TODAY())-YEAR(Q7) -> 5 | X7: =(TODAY()-DATE(YEAR(R7),MONTH(R7)-6,DAY(R7)))/182*(I7) -> 0.1010989 | Y7: =T7-X7 -> 99.856901 | Z7: =AVERAGE(J7:K7) -> 1.1745
A8: BO356982 Corp | B8: Toyota Motor Corp | C8: TOYOTA | D8: JP | E8: JPY | F8: 18/03/2026 | G8: FIXED | H8: 2 | I8: 0.05 | J8: 1.477 | K8: 1.483 | L8: 99.98 | M8: 99.98 | N8: BO3569825 | O8: JP363340BM36 | P8: A+ | Q8: 12/03/2021 | R8: 18/03/2026 | S8: =(F8-TODAY())/365.25 -> -0.032854209 | T8: =+AVERAGE(L8:M8) -> 99.98 | U8: 7 | V8: =ROUNDDOWN(S8,0)+IF(S8-ROUNDDOWN(S8,0)>0.5,0.5,0) -> 0 | W8: =YEAR(TODAY())-YEAR(Q8) -> 5 | X8: =(TODAY()-DATE(YEAR(R8),MONTH(R8)-6,DAY(R8)))/182*(I8) -> 0.053021978 | Y8: =T8-X8 -> 99.926978 | Z8: =AVERAGE(J8:K8) -> 1.48
A9: DA928584 Corp | B9: Toyota Finance Corp | C9: TOYOTA | D9: JP | E9: JPY | F9: 01/12/2028 | G9: FIXED | H9: 2 | I9: 1.35 | J9: 1.407 | K9: 1.607 | L9: 99.849 | M9: 99.328 | N9: DA9285846 | O9: JP363360ARQ3 | P9: #N/A N/A | Q9: 27/11/2025 | R9: 03/06/2026 | S9: =(F9-TODAY())/365.25 -> 2.6748802 | T9: =+AVERAGE(L9:M9) -> 99.5885 | U9: 8 | V9: =ROUNDDOWN(S9,0)+IF(S9-ROUNDDOWN(S9,0)>0.5,0.5,0) -> 2.5 | W9: =YEAR(TODAY())-YEAR(Q9) -> 1 | X9: =(TODAY()-DATE(YEAR(R9),MONTH(R9)-6,DAY(R9)))/182*(I9) -> 0.86785714 | Y9: =T9-X9 -> 98.720643 | Z9: =AVERAGE(J9:K9) -> 1.507
A10: YL396232 Corp | B10: Toyota Motor Corp | C10: TOYOTA | D10: JP | E10: JPY | F10: 04/09/2030 | G10: FIXED | H10: 2 | I10: 1.296 | J10: 1.838 | K10: 1.838 | L10: 97.756 | M10: 97.756 | N10: YL3962328 | O10: JP363340BR98 | P10: A+ | Q10: 29/08/2025 | R10: 04/09/2026 | S10: =(F10-TODAY())/365.25 -> 4.4325804 | T10: =+AVERAGE(L10:M10) -> 97.756 | U10: 9 | V10: =ROUNDDOWN(S10,0)+IF(S10-ROUNDDOWN(S10,0)>0.5,0.5,0) -> 4 | W10: =YEAR(TODAY())-YEAR(Q10) -> 1 | X10: =(TODAY()-DATE(YEAR(R10),MONTH(R10)-6,DAY(R10)))/182*(I10) -> 0.18514286 | Y10: =T10-X10 -> 97.570857 | Z10: =AVERAGE(J10:K10) -> 1.838
A11: YK173563 Corp | B11: Toyota Finance Corp | C11: TOYOTA | D11: JP | E11: JPY | F11: 17/10/2030 | G11: FIXED | H11: 2 | I11: 1.493 | J11: 1.888 | K11: 1.888 | L11: 98.329 | M11: 98.329 | N11: YK1735637 | O11: JP363360ARA7 | P11: A+ | Q11: 10/10/2025 | R11: 17/04/2026 | S11: =(F11-TODAY())/365.25 -> 4.550308 | T11: =+AVERAGE(L11:M11) -> 98.329 | U11: 10 | V11: =ROUNDDOWN(S11,0)+IF(S11-ROUNDDOWN(S11,0)>0.5,0.5,0) -> 4.5 | W11: =YEAR(TODAY())-YEAR(Q11) -> 1 | X11: =(TODAY()-DATE(YEAR(R11),MONTH(R11)-6,DAY(R11)))/182*(I11) -> 1.3453407 | Y11: =T11-X11 -> 96.983659 | Z11: =AVERAGE(J11:K11) -> 1.888
A12: YN599739 Corp | B12: Toyota Finance Corp | C12: TOYOTA | D12: JP | E12: JPY | F12: 22/07/2027 | G12: FIXED | H12: 2 | I12: 0.966 | J12: 1.34 | K12: 1.354 | L12: 99.5 | M12: 99.482 | N12: YN5997393 | O12: JP363360AR78 | P12: A+ | Q12: 15/07/2025 | R12: 22/07/2026 | S12: =(F12-TODAY())/365.25 -> 1.3114305 | T12: =+AVERAGE(L12:M12) -> 99.491 | U12: 11 | V12: =ROUNDDOWN(S12,0)+IF(S12-ROUNDDOWN(S12,0)>0.5,0.5,0) -> 1 | W12: =YEAR(TODAY())-YEAR(Q12) -> 1 | X12: =(TODAY()-DATE(YEAR(R12),MONTH(R12)-6,DAY(R12)))/182*(I12) -> 0.35561538 | Y12: =T12-X12 -> 99.135385 | Z12: =AVERAGE(J12:K12) -> 1.347
A13: YN599935 Corp | B13: Toyota Finance Corp | C13: TOYOTA | D13: JP | E13: JPY | F13: 21/07/2028 | G13: FIXED | H13: 2 | I13: 1.082 | J13: 1.468 | K13: 1.521 | L13: 99.12 | M13: 98.999 | N13: YN5999357 | O13: JP363360BR77 | P13: A+ | Q13: 15/07/2025 | R13: 22/07/2026 | S13: =(F13-TODAY())/365.25 -> 2.3107461 | T13: =+AVERAGE(L13:M13) -> 99.0595 | U13: 12 | V13: =ROUNDDOWN(S13,0)+IF(S13-ROUNDDOWN(S13,0)>0.5,0.5,0) -> 2 | W13: =YEAR(TODAY())-YEAR(Q13) -> 1 | X13: =(TODAY()-DATE(YEAR(R13),MONTH(R13)-6,DAY(R13)))/182*(I13) -> 0.39831868 | Y13: =T13-X13 -> 98.661181 | Z13: =AVERAGE(J13:K13) -> 1.4945
A14: YN600126 Corp | B14: Toyota Finance Corp | C14: TOYOTA | D14: JP | E14: JPY | F14: 22/07/2030 | G14: FIXED | H14: 2 | I14: 1.326 | J14: 1.821 | K14: 1.85 | L14: 98.001 | M14: 97.886 | N14: YN6001260 | O14: JP363360CR76 | P14: A+ | Q14: 15/07/2025 | R14: 22/07/2026 | S14: =(F14-TODAY())/365.25 -> 4.312115 | T14: =+AVERAGE(L14:M14) -> 97.9435 | U14: 13 | V14: =ROUNDDOWN(S14,0)+IF(S14-ROUNDDOWN(S14,0)>0.5,0.5,0) -> 4 | W14: =YEAR(TODAY())-YEAR(Q14) -> 1 | X14: =(TODAY()-DATE(YEAR(R14),MONTH(R14)-6,DAY(R14)))/182*(I14) -> 0.48814286 | Y14: =T14-X14 -> 97.455357 | Z14: =AVERAGE(J14:K14) -> 1.8355
... A38: YK172992 Corp | B38: Toyota Finance Corp | C38: TOYOTA | D38: JP | E38: JPY | F38: 15/10/2027 | G38: FIXED | H38: 2 | I38: 1.089 | J38: 1.396 | K38: 1.411 | L38: 99.521 | M38: 99.498 | N38: YK1729929 | O38: JP363360CRA3 | P38: A+ | Q38: 10/10/2025 | R38: 17/04/2026 | S38: =(F38-TODAY())/365.25 -> 1.5441478 | T38: =+AVERAGE(L38:M38) -> 99.5095 | U38: 37 | V38: =ROUNDDOWN(S38,0)+IF(S38-ROUNDDOWN(S38,0)>0.5,0.5,0) -> 1.5 | W38: =YEAR(TODAY())-YEAR(Q38) -> 1 | X38: =(TODAY()-DATE(YEAR(R38),MONTH(R38)-6,DAY(R38)))/182*(I38) -> 0.9812967 | Y38: =T38-X38 -> 98.528203 | Z38: =AVERAGE(J38:K38) -> 1.4035

Sheet SORT
A1: {=+OFFSET(Offline!A1,,,1,COUNTA(Offline!1:1))} -> Instrument | B1: Name | C1: Ticker | D1: Country/Region | E1: Currency | F1: Maturity | G1: Coupon Type | H1: Coupon Frequency | I1: Coupon | J1: Ask Yield to Maturity | K1: Bid Yield to Maturity | L1: Ask Price | M1: Bid Price | N1: Identifier | O1: ISIN | P1: Bloomberg Composite Rating | Q1: Announce | R1: Next Coupon Settle Date | S1: Time | T1: AVG Price | U1: ID | V1: TIMEish | W1: years ago | X1: Accrued Interest | Y1: Clean price | Z1: AVG yield
A2: {=_xlfn._xlws.SORT(OFFSET(Offline!A2,,,COUNTA(Offline!A:A)-1,COUNTA(Offline!1:1)),COLUMN(Offline!S1))} -> BO356982 Corp | B2: Toyota Motor Corp | C2: TOYOTA | D2: JP | E2: JPY | F2: 18/03/2026 | G2: FIXED | H2: 2 | I2: 0.05 | J2: 1.477 | K2: 1.483 | L2: 99.98 | M2: 99.98 | N2: BO3569825 | O2: JP363340BM36 | P2: A+ | Q2: 12/03/2021 | R2: 18/03/2026 | S2: -0.032854209 | T2: 99.98 | U2: 7 | V2: 0 | W2: 5 | X2: 0.053021978 | Y2: 99.926978 | Z2: 1.48
A3: BO356985 Corp | B3: Toyota Motor Corp | C3: TOYOTA | D3: JP | E3: JPY | F3: 27/03/2026 | G3: FIXED | H3: 2 | I3: 0.1 | J3: 1.173 | K3: 1.176 | L3: 99.958 | M3: 99.958 | N3: BO3569858 | O3: JP363340AM37 | P3: #N/A N/A | Q3: 12/03/2021 | R3: 27/03/2026 | S3: -0.0082135524 | T3: 99.958 | U3: 6 | V3: 0 | W3: 5 | X3: 0.1010989 | Y3: 99.856901 | Z3: 1.1745
A4: BO579315 Corp | B4: Toyota Finance Corp | C4: TOYOTA | D4: JP | E4: JPY | F4: 15/04/2026 | G4: FIXED | H4: 2 | I4: 0.06 | J4: 1.099 | K4: 1.1 | L4: 99.906 | M4: 99.906 | N4: BO5793159 | O4: JP363360BM49 | P4: A+ | Q4: 09/04/2021 | R4: 15/04/2026 | S4: 0.043805613 | T4: 99.906 | U4: 31 | V4: 0 | W4: 5 | X4: 0.054725275 | Y4: 99.851275 | Z4: 1.0995
A5: LW169500 Corp | B5: Toyota Motor Corp | C5: TOYOTA | D5: JP | E5: JPY | F5: 03/06/2026 | G5: FIXED | H5: 2 | I5: 0.09 | J5: 0.864 | K5: 1.134 | L5: 99.826 | M5: 99.766 | N5: LW1695003 | O5: JP363340AG68 | P5: A+ | Q5: 27/05/2016 | R5: 03/06/2026 | S5: 0.1779603 | T5: 99.796 | U5: 3 | V5: 0 | W5: 10 | X5: 0.057857143 | Y5: 99.738143 | Z5: 0.999
A6: ZI885852 Corp | B6: Toyota Finance Corp | C6: TOYOTA | D6: JP | E6: JPY | F6: 13/10/2026 | G6: FIXED | H6: 2 | I6: 0.37 | J6: 1.163 | K6: 1.163 | L6: 99.538 | M6: 99.538 | N6: ZI8858527 | O6: JP363360APA1 | P6: A+ | Q6: 06/10/2023 | R6: 13/04/2026 | S6: 0.53935661 | T6: 99.538 | U6: 2 | V6: 0.5 | W6: 3 | X6: 0.34153846 | Y6: 99.196462 | Z6: 1.163
A7: YT821868 Corp | B7: Toyota Finance Corp | C7: TOYOTA | D7: JP | E7: JPY | F7: 11/12/2026 | G7: FIXED | H7: 2 | I7: 0.773 | J7: 1.014 | K7: 1.214 | L7: 99.821 | M7: 99.673 | N7: YT8218687 | O7: JP363360AQQ5 | P7: #N/A N/A | Q7: 06/12/2024 | R7: 12/06/2026 | S7: 0.7008898 | T7: 99.747 | U7: 18 | V7: 0.5 | W7: 2 | X7: 0.4587033 | Y7: 99.288297 | Z7: 1.114
A8: ZD637368 Corp | B8: Toyota Finance Corp | C8: TOYOTA | D8: JP | E8: JPY | F8: 09/04/2027 | G8: FIXED | H8: 2 | I8: 0.414 | J8: 1.259 | K8: 1.281 | L8: 99.104 | M8: 99.081 | N8: ZD6373686 | O8: JP363360AQ46 | P8: A+ | Q8: 05/04/2024 | R8: 10/04/2026 | S8: 1.026694 | T8: 99.0925 | U8: 26 | V8: 1 | W8: 2 | X8: 0.38897802 | Y8: 98.703522 | Z8: 1.27
A9: AN666209 Corp | B9: Toyota Motor Corp | C9: TOYOTA | D9: JP | E9: JPY | F9: 02/06/2027 | G9: FIXED | H9: 2 | I9: 0.22 | J9: 1.274 | K9: 1.292 | L9: 98.73 | M9: 98.709 | N9: AN6662091 | O9: JP363340CH65 | P9: A+ | Q9: 26/05/2017 | R9: 02/06/2026 | S9: 1.174538 | T9: 98.7195 | U9: 15 | V9: 1 | W9: 9 | X9: 0.14263736 | Y9: 98.576863 | Z9: 1.283
A10: BW601098 Corp | B10: Toyota Motor Corp | C10: TOYOTA | D10: JP | E10: JPY | F10: 02/06/2027 | G10: FIXED | H10: 2 | I10: 0.11 | J10: 1.273 | K10: 1.291 | L10: 98.599 | M10: 98.578 | N10: BW6010985 | O10: JP363340AN69 | P10: A+ | Q10: 27/05/2022 | R10: 02/06/2026 | S10: 1.174538 | T10: 98.5885 | U10: 32 | V10: 1 | W10: 4 | X10: 0.071318681 | Y10: 98.517181 | Z10: 1.282
A11: YN599739 Corp | B11: Toyota Finance Corp | C11: TOYOTA | D11: JP | E11: JPY | F11: 22/07/2027 | G11: FIXED | H11: 2 | I11: 0.966 | J11: 1.34 | K11: 1.354 | L11: 99.5 | M11: 99.482 | N11: YN5997393 | O11: JP363360AR78 | P11: A+ | Q11: 15/07/2025 | R11: 22/07/2026 | S11: 1.3114305 | T11: 99.491 | U11: 11 | V11: 1 | W11: 1 | X11: 0.35561538 | Y11: 99.135385 | Z11: 1.347
A12: AO295977 Corp | B12: Toyota Finance Corp | C12: TOYOTA | D12: JP | E12: JPY | F12: 23/07/2027 | G12: FIXED | H12: 2 | I12: 0.265 | J12: 1.346 | K12: 1.36 | L12: 98.553 | M12: 98.534 | N12: AO2959770 | O12: JP363360CH78 | P12: A+ | Q12: 14/07/2017 | R12: 24/07/2026 | S12: 1.3141684 | T12: 98.5435 | U12: 29 | V12: 1 | W12: 9 | X12: 0.094642857 | Y12: 98.448857 | Z12: 1.353
A13: YV792963 Corp | B13: Toyota Finance Corp | C13: TOYOTA | D13: JP | E13: JPY | F13: 08/10/2027 | G13: FIXED | H13: 2 | I13: 0.573 | J13: 1.406 | K13: 1.421 | L13: 98.716 | M13: 98.694 | N13: YV7929636 | O13: JP363360AQA9 | P13: A+ | Q13: 04/10/2024 | R13: 10/04/2026 | S13: 1.5249829 | T13: 98.705 | U13: 24 | V13: 1.5 | W13: 2 | X13: 0.53836813 | Y13: 98.166632 | Z13: 1.4135
A14: YK172992 Corp | B14: Toyota Finance Corp | C14: TOYOTA | D14: JP | E14: JPY | F14: 15/10/2027 | G14: FIXED | H14: 2 | I14: 1.089 | J14: 1.396 | K14: 1.411 | L14: 99.521 | M14: 99.498 | N14: YK1729929 | O14: JP363360CRA3 | P14: A+ | Q14: 10/10/2025 | R14: 17/04/2026 | S14: 1.5441478 | T14: 99.5095 | U14: 37 | V14: 1.5 | W14: 1 | X14: 0.9812967 | Y14: 98.528203 | Z14: 1.4035
... A38: AN666227 Corp | B38: Toyota Motor Corp | C38: TOYOTA | D38: JP | E38: JPY | F38: 02/06/2037 | G38: FIXED | H38: 2 | I38: 0.651 | J38: 2.962 | K38: 2.962 | L38: 80.535 | M38: 80.535 | N38: AN6662273 | O38: JP363340DH64 | P38: A+ | Q38: 26/05/2017 | R38: 02/06/2026 | S38: 11.175907 | T38: 80.535 | U38: 4 | V38: 11 | W38: 9 | X38: 0.42207692 | Y38: 80.112923 | Z38: 2.962

Sheet ID filter
A1: ID | B1: {=_xlfn.ANCHORARRAY(SORT!A1)} -> Instrument | C1: Name | D1: Ticker | E1: Country/Region | F1: Currency | G1: Maturity | H1: Coupon Type | I1: Coupon Frequency | J1: Coupon | K1: Ask Yield to Maturity | L1: Bid Yield to Maturity | M1: Ask Price | N1: Bid Price | O1: Identifier | P1: ISIN | Q1: Bloomberg Composite Rating | R1: Announce | S1: Next Coupon Settle Date | T1: Time | U1: AVG Price | V1: ID | W1: TIMEish | X1: years ago | Y1: Accrued Interest | Z1: Clean price | AA1: AVG yield
A2: 3 | B2: {=_xlfn.XLOOKUP(A2,SORT!$U$2:$U$38,_xlfn.ANCHORARRAY(SORT!$A$2),,0)} -> LW169500 Corp | C2: Toyota Motor Corp | D2: TOYOTA | E2: JP | F2: JPY | G2: 03/06/2026 | H2: FIXED | I2: 2 | J2: 0.09 | K2: 0.864 | L2: 1.134 | M2: 99.826 | N2: 99.766 | O2: LW1695003 | P2: JP363340AG68 | Q2: A+ | R2: 27/05/2016 | S2: 03/06/2026 | T2: 0.1779603 | U2: 99.796 | V2: 3 | W2: 0 | X2: 10 | Y2: 0.057857143 | Z2: 99.738143 | AA2: 0.999
A3: 18 | B3: {=_xlfn.XLOOKUP(A3,SORT!$U$2:$U$38,_xlfn.ANCHORARRAY(SORT!$A$2),,0)} -> YT821868 Corp | C3: Toyota Finance Corp | D3: TOYOTA | E3: JP | F3: JPY | G3: 11/12/2026 | H3: FIXED | I3: 2 | J3: 0.773 | K3: 1.014 | L3: 1.214 | M3: 99.821 | N3: 99.673 | O3: YT8218687 | P3: JP363360AQQ5 | Q3: #N/A N/A | R3: 06/12/2024 | S3: 12/06/2026 | T3: 0.7008898 | U3: 99.747 | V3: 18 | W3: 0.5 | X3: 2 | Y3: 0.4587033 | Z3: 99.288297 | AA3: 1.114
A4: 29 | B4: {=_xlfn.XLOOKUP(A4,SORT!$U$2:$U$38,_xlfn.ANCHORARRAY(SORT!$A$2),,0)} -> AO295977 Corp | C4: Toyota Finance Corp | D4: TOYOTA | E4: JP | F4: JPY | G4: 23/07/2027 | H4: FIXED | I4: 2 | J4: 0.265 | K4: 1.346 | L4: 1.36 | M4: 98.553 | N4: 98.534 | O4: AO2959770 | P4: JP363360CH78 | Q4: A+ | R4: 14/07/2017 | S4: 24/07/2026 | T4: 1.3141684 | U4: 98.5435 | V4: 29 | W4: 1 | X4: 9 | Y4: 0.094642857 | Z4: 98.448857 | AA4: 1.353
A5: 23 | B5: {=_xlfn.XLOOKUP(A5,SORT!$U$2:$U$38,_xlfn.ANCHORARRAY(SORT!$A$2),,0)} -> YT967931 Corp | C5: Toyota Finance Corp | D5: TOYOTA | E5: JP | F5: JPY | G5: 21/01/2028 | H5: FIXED | I5: 2 | J5: 0.9 | K5: 1.452 | L5: 1.464 | M5: 99 | N5: 98.978 | O5: YT9679317 | P5: JP363360AR11 | Q5: A+ | R5: 17/01/2025 | S5: 23/07/2026 | T5: 1.8124572 | U5: 98.989 | V5: 23 | W5: 1.5 | X5: 1 | Y5: 0.32637363 | Z5: 98.662626 | AA5: 1.458
A6: 12 | B6: {=_xlfn.XLOOKUP(A6,SORT!$U$2:$U$38,_xlfn.ANCHORARRAY(SORT!$A$2),,0)} -> YN599935 Corp | C6: Toyota Finance Corp | D6: TOYOTA | E6: JP | F6: JPY | G6: 21/07/2028 | H6: FIXED | I6: 2 | J6: 1.082 | K6: 1.468 | L6: 1.521 | M6: 99.12 | N6: 98.999 | O6: YN5999357 | P6: JP363360BR77 | Q6: A+ | R6: 15/07/2025 | S6: 22/07/2026 | T6: 2.3107461 | U6: 99.0595 | V6: 12 | W6: 2 | X6: 1 | Y6: 0.39831868 | Z6: 98.661181 | AA6: 1.4945
A7: 35 | B7: {=_xlfn.XLOOKUP(A7,SORT!$U$2:$U$38,_xlfn.ANCHORARRAY(SORT!$A$2),,0)} -> ZS613802 Corp | C7: Toyota Motor Corp | D7: TOYOTA | E7: JP | F7: JPY | G7: 24/05/2029 | H7: FIXED | I7: 2 | J7: 0.15 | K7: 1.653 | L7: 1.665 | M7: 95.435 | N7: 95.4 | O7: ZS6138029 | P7: JP363340BK53 | Q7: A+ | R7: 17/05/2019 | S7: 22/05/2026 | T7: 3.1512663 | U7: 95.4175 | V7: 35 | W7: 3 | X7: 7 | Y7: 0.10549451 | Z7: 95.312005 | AA7: 1.659
A8: 25 | B8: {=_xlfn.XLOOKUP(A8,SORT!$U$2:$U$38,_xlfn.ANCHORARRAY(SORT!$A$2),,0)} -> YV793180 Corp | C8: Toyota Finance Corp | D8: TOYOTA | E8: JP | F8: JPY | G8: 10/10/2029 | H8: FIXED | I8: 2 | J8: 0.71 | K8: 1.77 | L8: 1.77 | M8: 96.433 | N8: 96.433 | O8: YV7931806 | P8: JP363360BQA7 | Q8: A+ | R8: 04/10/2024 | S8: 10/04/2026 | T8: 3.5318275 | U8: 96.433 | V8: 25 | W8: 3.5 | X8: 2 | Y8: 0.66708791 | Z8: 95.765912 | AA8: 1.77
A9: 19 | B9: {=_xlfn.XLOOKUP(A9,SORT!$U$2:$U$38,_xlfn.ANCHORARRAY(SORT!$A$2),,0)} -> YT968038 Corp | C9: Toyota Finance Corp | D9: TOYOTA | E9: JP | F9: JPY | G9: 23/01/2030 | H9: FIXED | I9: 2 | J9: 1.051 | K9: 1.809 | L9: 1.809 | M9: 97.261 | N9: 97.261 | O9: YT9680380 | P9: JP363360BR10 | Q9: A+ | R9: 17/01/2025 | S9: 23/07/2026 | T9: 3.8193018 | U9: 97.261 | V9: 19 | W9: 3.5 | X9: 1 | Y9: 0.38113187 | Z9: 96.879868 | AA9: 1.809
A10: 9 | B10: {=_xlfn.XLOOKUP(A10,SORT!$U$2:$U$38,_xlfn.ANCHORARRAY(SORT!$A$2),,0)} -> YL396232 Corp | C10: Toyota Motor Corp | D10: TOYOTA | E10: JP | F10: JPY | G10: 04/09/2030 | H10: FIXED | I10: 2 | J10: 1.296 | K10: 1.838 | L10: 1.838 | M10: 97.756 | N10: 97.756 | O10: YL3962328 | P10: JP363340BR98 | Q10: A+ | R10: 29/08/2025 | S10: 04/09/2026 | T10: 4.4325804 | U10: 97.756 | V10: 9 | W10: 4 | X10: 1 | Y10: 0.18514286 | Z10: 97.570857 | AA10: 1.838
A11: 10 | B11: {=_xlfn.XLOOKUP(A11,SORT!$U$2:$U$38,_xlfn.ANCHORARRAY(SORT!$A$2),,0)} -> YK173563 Corp | C11: Toyota Finance Corp | D11: TOYOTA | E11: JP | F11: JPY | G11: 17/10/2030 | H11: FIXED | I11: 2 | J11: 1.493 | K11: 1.888 | L11: 1.888 | M11: 98.329 | N11: 98.329 | O11: YK1735637 | P11: JP363360ARA7 | Q11: A+ | R11: 10/10/2025 | S11: 17/04/2026 | T11: 4.550308 | U11: 98.329 | V11: 10 | W11: 4.5 | X11: 1 | Y11: 1.3453407 | Z11: 96.983659 | AA11: 1.888
A12: 5 | B12: {=_xlfn.XLOOKUP(A12,SORT!$U$2:$U$38,_xlfn.ANCHORARRAY(SORT!$A$2),,0)} -> BO356983 Corp | C12: Toyota Motor Corp | D12: TOYOTA | E12: JP | F12: JPY | G12: 18/03/2031 | H12: FIXED | I12: 2 | J12: 0.219 | K12: 1.982 | L12: 1.982 | M12: 91.959 | N12: 91.959 | O12: BO3569833 | P12: JP363340CM35 | Q12: A+ | R12: 12/03/2021 | S12: 18/03/2026 | T12: 4.9664613 | U12: 91.959 | V12: 5 | W12: 4.5 | X12: 5 | Y12: 0.23223626 | Z12: 91.726764 | AA12: 1.982
A13: 16 | B13: {=_xlfn.XLOOKUP(A13,SORT!$U$2:$U$38,_xlfn.ANCHORARRAY(SORT!$A$2),,0)} -> YS631917 Corp | C13: Toyota Finance Corp | D13: TOYOTA | E13: JP | F13: JPY | G13: 23/01/2032 | H13: FIXED | I13: 2 | J13: 1.18 | K13: 2.088 | L13: 2.088 | M13: 95.255 | N13: 95.255 | O13: YS6319174 | P13: JP363360CR19 | Q13: A+ | R13: 17/01/2025 | S13: 23/07/2026 | T13: 5.8179329 | U13: 95.255 | V13: 16 | W13: 5.5 | X13: 1 | Y13: 0.42791209 | Z13: 94.827088 | AA13: 2.088
... A19: 4 | B19: {=_xlfn.XLOOKUP(A19,SORT!$U$2:$U$38,_xlfn.ANCHORARRAY(SORT!$A$2),,0)} -> AN666227 Corp | C19: Toyota Motor Corp | D19: TOYOTA | E19: JP | F19: JPY | G19: 02/06/2037 | H19: FIXED | I19: 2 | J19: 0.651 | K19: 2.962 | L19: 2.962 | M19: 80.535 | N19: 80.535 | O19: AN6662273 | P19: JP363340DH64 | Q19: A+ | R19: 26/05/2017 | S19: 02/06/2026 | T19: 11.175907 | U19: 80.535 | V19: 4 | W19: 11 | X19: 9 | Y19: 0.42207692 | Z19: 80.112923 | AA19: 2.962

Sheet F coupon<0.5
A1: ID | B1: {=_xlfn.ANCHORARRAY(SORT!A1)} -> Instrument | C1: Name | D1: Ticker | E1: Country/Region | F1: Currency | G1: Maturity | H1: Coupon Type | I1: Coupon Frequency | J1: Coupon | K1: Ask Yield to Maturity | L1: Bid Yield to Maturity | M1: Ask Price | N1: Bid Price | O1: Identifier | P1: ISIN | Q1: Bloomberg Composite Rating | R1: Announce | S1: Next Coupon Settle Date | T1: Time | U1: AVG Price | V1: ID | W1: TIMEish | X1: years ago | Y1: Accrued Interest | Z1: Clean price | AA1: AVG yield | AE1: {=_xlfn.ANCHORARRAY(B1)} -> Instrument | AF1: Name | AG1: Ticker | AH1: Country/Region | AI1: Currency | AJ1: Maturity | AK1: Coupon Type | AL1: Coupon Frequency | AM1: Coupon | AN1: Ask Yield to Maturity | AO1: Bid Yield to Maturity | AP1: Ask Price | AQ1: Bid Price | AR1: Identifier | AS1: ISIN | AT1: Bloomberg Composite Rating | AU1: Announce | AV1: Next Coupon Settle Date | AW1: Time | AX1: AVG Price | AY1: ID | AZ1: TIMEish | BA1: years ago | BB1: Accrued Interest | BC1: Clean price | BD1: AVG yield
B2: {=_xlfn._xlws.FILTER(_xlfn.ANCHORARRAY(AE2),OFFSET(AZ1,1,,COUNT(AZ:AZ))>0)} -> ZI885852 Corp | C2: Toyota Finance Corp | D2: TOYOTA | E2: JP | F2: JPY | G2: 13/10/2026 | H2: FIXED | I2: 2 | J2: 0.37 | K2: 1.163 | L2: 1.163 | M2: 99.538 | N2: 99.538 | O2: ZI8858527 | P2: JP363360APA1 | Q2: A+ | R2: 06/10/2023 | S2: 13/04/2026 | T2: 0.53935661 | U2: 99.538 | V2: 2 | W2: 0.5 | X2: 3 | Y2: 0.34153846 | Z2: 99.196462 | AA2: 1.163 | AE2: {=_xlfn._xlws.FILTER(_xlfn.ANCHORARRAY(SORT!A2),SORT!I2:I38<0.5)} -> BO356982 Corp | AF2: Toyota Motor Corp | AG2: TOYOTA | AH2: JP | AI2: JPY | AJ2: 18/03/2026 | AK2: FIXED | AL2: 2 | AM2: 0.05 | AN2: 1.477 | AO2: 1.483 | AP2: 99.98 | AQ2: 99.98 | AR2: BO3569825 | AS2: JP363340BM36 | AT2: A+ | AU2: 12/03/2021 | AV2: 18/03/2026 | AW2: -0.032854209 | AX2: 99.98 | AY2: 7 | AZ2: 0 | BA2: 5 | BB2: 0.053021978 | BC2: 99.926978 | BD2: 1.48
B3: ZD637368 Corp | C3: Toyota Finance Corp | D3: TOYOTA | E3: JP | F3: JPY | G3: 09/04/2027 | H3: FIXED | I3: 2 | J3: 0.414 | K3: 1.259 | L3: 1.281 | M3: 99.104 | N3: 99.081 | O3: ZD6373686 | P3: JP363360AQ46 | Q3: A+ | R3: 05/04/2024 | S3: 10/04/2026 | T3: 1.026694 | U3: 99.0925 | V3: 26 | W3: 1 | X3: 2 | Y3: 0.38897802 | Z3: 98.703522 | AA3: 1.27 | AE3: BO356985 Corp | AF3: Toyota Motor Corp | AG3: TOYOTA | AH3: JP | AI3: JPY | AJ3: 27/03/2026 | AK3: FIXED | AL3: 2 | AM3: 0.1 | AN3: 1.173 | AO3: 1.176 | AP3: 99.958 | AQ3: 99.958 | AR3: BO3569858 | AS3: JP363340AM37 | AT3: #N/A N/A | AU3: 12/03/2021 | AV3: 27/03/2026 | AW3: -0.0082135524 | AX3: 99.958 | AY3: 6 | AZ3: 0 | BA3: 5 | BB3: 0.1010989 | BC3: 99.856901 | BD3: 1.1745
B4: AN666209 Corp | C4: Toyota Motor Corp | D4: TOYOTA | E4: JP | F4: JPY | G4: 02/06/2027 | H4: FIXED | I4: 2 | J4: 0.22 | K4: 1.274 | L4: 1.292 | M4: 98.73 | N4: 98.709 | O4: AN6662091 | P4: JP363340CH65 | Q4: A+ | R4: 26/05/2017 | S4: 02/06/2026 | T4: 1.174538 | U4: 98.7195 | V4: 15 | W4: 1 | X4: 9 | Y4: 0.14263736 | Z4: 98.576863 | AA4: 1.283 | AE4: BO579315 Corp | AF4: Toyota Finance Corp | AG4: TOYOTA | AH4: JP | AI4: JPY | AJ4: 15/04/2026 | AK4: FIXED | AL4: 2 | AM4: 0.06 | AN4: 1.099 | AO4: 1.1 | AP4: 99.906 | AQ4: 99.906 | AR4: BO5793159 | AS4: JP363360BM49 | AT4: A+ | AU4: 09/04/2021 | AV4: 15/04/2026 | AW4: 0.043805613 | AX4: 99.906 | AY4: 31 | AZ4: 0 | BA4: 5 | BB4: 0.054725275 | BC4: 99.851275 | BD4: 1.0995
B5: BW601098 Corp | C5: Toyota Motor Corp | D5: TOYOTA | E5: JP | F5: JPY | G5: 02/06/2027 | H5: FIXED | I5: 2 | J5: 0.11 | K5: 1.273 | L5: 1.291 | M5: 98.599 | N5: 98.578 | O5: BW6010985 | P5: JP363340AN69 | Q5: A+ | R5: 27/05/2022 | S5: 02/06/2026 | T5: 1.174538 | U5: 98.5885 | V5: 32 | W5: 1 | X5: 4 | Y5: 0.071318681 | Z5: 98.517181 | AA5: 1.282 | AE5: LW169500 Corp | AF5: Toyota Motor Corp | AG5: TOYOTA | AH5: JP | AI5: JPY | AJ5: 03/06/2026 | AK5: FIXED | AL5: 2 | AM5: 0.09 | AN5: 0.864 | AO5: 1.134 | AP5: 99.826 | AQ5: 99.766 | AR5: LW1695003 | AS5: JP363340AG68 | AT5: A+ | AU5: 27/05/2016 | AV5: 03/06/2026 | AW5: 0.1779603 | AX5: 99.796 | AY5: 3 | AZ5: 0 | BA5: 10 | BB5: 0.057857143 | BC5: 99.738143 | BD5: 0.999
B6: AO295977 Corp | C6: Toyota Finance Corp | D6: TOYOTA | E6: JP | F6: JPY | G6: 23/07/2027 | H6: FIXED | I6: 2 | J6: 0.265 | K6: 1.346 | L6: 1.36 | M6: 98.553 | N6: 98.534 | O6: AO2959770 | P6: JP363360CH78 | Q6: A+ | R6: 14/07/2017 | S6: 24/07/2026 | T6: 1.3141684 | U6: 98.5435 | V6: 29 | W6: 1 | X6: 9 | Y6: 0.094642857 | Z6: 98.448857 | AA6: 1.353 | AE6: ZI885852 Corp | AF6: Toyota Finance Corp | AG6: TOYOTA | AH6: JP | AI6: JPY | AJ6: 13/10/2026 | AK6: FIXED | AL6: 2 | AM6: 0.37 | AN6: 1.163 | AO6: 1.163 | AP6: 99.538 | AQ6: 99.538 | AR6: ZI8858527 | AS6: JP363360APA1 | AT6: A+ | AU6: 06/10/2023 | AV6: 13/04/2026 | AW6: 0.53935661 | AX6: 99.538 | AY6: 2 | AZ6: 0.5 | BA6: 3 | BB6: 0.34153846 | BC6: 99.196462 | BD6: 1.163
B7: BZ742454 Corp | C7: Toyota Finance Corp | D7: TOYOTA | E7: JP | F7: JPY | G7: 21/10/2027 | H7: FIXED | I7: 2 | J7: 0.385 | K7: 1.419 | L7: 1.434 | M7: 98.374 | N7: 98.351 | O7: BZ7424543 | P7: JP363360BNA4 | Q7: A+ | R7: 14/10/2022 | S7: 21/04/2026 | T7: 1.5605749 | U7: 98.3625 | V7: 36 | W7: 1.5 | X7: 4 | Y7: 0.33846154 | Z7: 98.024038 | AA7: 1.4265 | AE7: ZD637368 Corp | AF7: Toyota Finance Corp | AG7: TOYOTA | AH7: JP | AI7: JPY | AJ7: 09/04/2027 | AK7: FIXED | AL7: 2 | AM7: 0.414 | AN7: 1.259 | AO7: 1.281 | AP7: 99.104 | AQ7: 99.081 | AR7: ZD6373686 | AS7: JP363360AQ46 | AT7: A+ | AU7: 05/04/2024 | AV7: 10/04/2026 | AW7: 1.026694 | AX7: 99.0925 | AY7: 26 | AZ7: 1 | BA7: 2 | BB7: 0.38897802 | BC7: 98.703522 | BD7: 1.27
B8: AP577034 Corp | C8: Toyota Finance Corp | D8: TOYOTA | E8: JP | F8: JPY | G8: 22/10/2027 | H8: FIXED | I8: 2 | J8: 0.265 | K8: 1.418 | L8: 1.433 | M8: 98.184 | N8: 98.16 | O8: AP5770346 | P8: JP363360CHA4 | Q8: A+ | R8: 13/10/2017 | S8: 24/04/2026 | T8: 1.5633128 | U8: 98.172 | V8: 20 | W8: 1.5 | X8: 9 | Y8: 0.2285989 | Z8: 97.943401 | AA8: 1.4255 | AE8: AN666209 Corp | AF8: Toyota Motor Corp | AG8: TOYOTA | AH8: JP | AI8: JPY | AJ8: 02/06/2027 | AK8: FIXED | AL8: 2 | AM8: 0.22 | AN8: 1.274 | AO8: 1.292 | AP8: 98.73 | AQ8: 98.709 | AR8: AN6662091 | AS8: JP363340CH65 | AT8: A+ | AU8: 26/05/2017 | AV8: 02/06/2026 | AW8: 1.174538 | AX8: 98.7195 | AY8: 15 | AZ8: 1 | BA8: 9 | BB8: 0.14263736 | BC8: 98.576863 | BD8: 1.283
B9: ZK701649 Corp | C9: Toyota Motor Corp | D9: TOYOTA | E9: JP | F9: JPY | G9: 01/06/2028 | H9: FIXED | I9: 2 | J9: 0.33 | K9: 1.487 | L9: 1.487 | M9: 97.514 | N9: 97.514 | O9: ZK7016494 | P9: JP363340AP67 | Q9: A+ | R9: 26/05/2023 | S9: 01/06/2026 | T9: 2.1738535 | U9: 97.514 | V9: 28 | W9: 2 | X9: 3 | Y9: 0.21576923 | Z9: 97.298231 | AA9: 1.487 | AE9: BW601098 Corp | AF9: Toyota Motor Corp | AG9: TOYOTA | AH9: JP | AI9: JPY | AJ9: 02/06/2027 | AK9: FIXED | AL9: 2 | AM9: 0.11 | AN9: 1.273 | AO9: 1.291 | AP9: 98.599 | AQ9: 98.578 | AR9: BW6010985 | AS9: JP363340AN69 | AT9: A+ | AU9: 27/05/2022 | AV9: 02/06/2026 | AW9: 1.174538 | AX9: 98.5885 | AY9: 32 | AZ9: 1 | BA9: 4 | BB9: 0.071318681 | BC9: 98.517181 | BD9: 1.282
B10: AU925890 Corp | C10: Toyota Finance Corp | D10: TOYOTA | E10: JP | F10: JPY | G10: 23/10/2028 | H10: FIXED | I10: 2 | J10: 0.319 | K10: 1.565 | L10: 1.579 | M10: 96.871 | N10: 96.837 | O10: AU9258909 | P10: JP363360CJA0 | Q10: A+ | R10: 10/10/2018 | S10: 23/04/2026 | T10: 2.568104 | U10: 96.854 | V10: 30 | W10: 2.5 | X10: 8 | Y10: 0.27693407 | Z10: 96.577066 | AA10: 1.572 | AE10: AO295977 Corp | AF10: Toyota Finance Corp | AG10: TOYOTA | AH10: JP | AI10: JPY | AJ10: 23/07/2027 | AK10: FIXED | AL10: 2 | AM10: 0.265 | AN10: 1.346 | AO10: 1.36 | AP10: 98.553 | AQ10: 98.534 | AR10: AO2959770 | AS10: JP363360CH78 | AT10: A+ | AU10: 14/07/2017 | AV10: 24/07/2026 | AW10: 1.3141684 | AX10: 98.5435 | AY10: 29 | AZ10: 1 | BA10: 9 | BB10: 0.094642857 | BC10: 98.448857 | BD10: 1.353
B11: ZS613802 Corp | C11: Toyota Motor Corp | D11: TOYOTA | E11: JP | F11: JPY | G11: 24/05/2029 | H11: FIXED | I11: 2 | J11: 0.15 | K11: 1.653 | L11: 1.665 | M11: 95.435 | N11: 95.4 | O11: ZS6138029 | P11: JP363340BK53 | Q11: A+ | R11: 17/05/2019 | S11: 22/05/2026 | T11: 3.1512663 | U11: 95.4175 | V11: 35 | W11: 3 | X11: 7 | Y11: 0.10549451 | Z11: 95.312005 | AA11: 1.659 | AE11: BZ742454 Corp | AF11: Toyota Finance Corp | AG11: TOYOTA | AH11: JP | AI11: JPY | AJ11: 21/10/2027 | AK11: FIXED | AL11: 2 | AM11: 0.385 | AN11: 1.419 | AO11: 1.434 | AP11: 98.374 | AQ11: 98.351 | AR11: BZ7424543 | AS11: JP363360BNA4 | AT11: A+ | AU11: 14/10/2022 | AV11: 21/04/2026 | AW11: 1.5605749 | AX11: 98.3625 | AY11: 36 | AZ11: 1.5 | BA11: 4 | BB11: 0.33846154 | BC11: 98.024038 | BD11: 1.4265
B12: BO356983 Corp | C12: Toyota Motor Corp | D12: TOYOTA | E12: JP | F12: JPY | G12: 18/03/2031 | H12: FIXED | I12: 2 | J12: 0.219 | K12: 1.982 | L12: 1.982 | M12: 91.959 | N12: 91.959 | O12: BO3569833 | P12: JP363340CM35 | Q12: A+ | R12: 12/03/2021 | S12: 18/03/2026 | T12: 4.9664613 | U12: 91.959 | V12: 5 | W12: 4.5 | X12: 5 | Y12: 0.23223626 | Z12: 91.726764 | AA12: 1.982 | AE12: AP577034 Corp | AF12: Toyota Finance Corp | AG12: TOYOTA | AH12: JP | AI12: JPY | AJ12: 22/10/2027 | AK12: FIXED | AL12: 2 | AM12: 0.265 | AN12: 1.418 | AO12: 1.433 | AP12: 98.184 | AQ12: 98.16 | AR12: AP5770346 | AS12: JP363360CHA4 | AT12: A+ | AU12: 13/10/2017 | AV12: 24/04/2026 | AW12: 1.5633128 | AX12: 98.172 | AY12: 20 | AZ12: 1.5 | BA12: 9 | BB12: 0.2285989 | BC12: 97.943401 | BD12: 1.4255
B13: BW601183 Corp | C13: Toyota Motor Corp | D13: TOYOTA | E13: JP | F13: JPY | G13: 02/06/2032 | H13: FIXED | I13: 2 | J13: 0.324 | K13: 2.155 | L13: 2.155 | M13: 89.954 | N13: 89.954 | O13: BW6011835 | P13: JP363340BN68 | Q13: A+ | R13: 27/05/2022 | S13: 02/06/2026 | T13: 6.1765914 | U13: 89.954 | V13: 17 | W13: 6 | X13: 4 | Y13: 0.21006593 | Z13: 89.743934 | AA13: 2.155 | AE13: ZK701649 Corp | AF13: Toyota Motor Corp | AG13: TOYOTA | AH13: JP | AI13: JPY | AJ13: 01/06/2028 | AK13: FIXED | AL13: 2 | AM13: 0.33 | AN13: 1.487 | AO13: 1.487 | AP13: 97.514 | AQ13: 97.514 | AR13: ZK7016494 | AS13: JP363340AP67 | AT13: A+ | AU13: 26/05/2023 | AV13: 01/06/2026 | AW13: 2.1738535 | AX13: 97.514 | AY13: 28 | AZ13: 2 | BA13: 3 | BB13: 0.21576923 | BC13: 97.298231 | BD13: 1.487
B14: LW169503 Corp | C14: Toyota Motor Corp | D14: TOYOTA | E14: JP | F14: JPY | G14: 03/06/2036 | H14: FIXED | I14: 2 | J14: 0.343 | K14: 2.839 | L14: 2.839 | M14: 80.22 | N14: 80.22 | O14: LW1695037 | P14: JP363340BG67 | Q14: A+ | R14: 27/05/2016 | S14: 03/06/2026 | T14: 10.179329 | U14: 80.22 | V14: 21 | W14: 10 | X14: 10 | Y14: 0.2205 | Z14: 79.9995 | AA14: 2.839 | AE14: AU925890 Corp | AF14: Toyota Finance Corp | AG14: TOYOTA | AH14: JP | AI14: JPY | AJ14: 23/10/2028 | AK14: FIXED | AL14: 2 | AM14: 0.319 | AN14: 1.565 | AO14: 1.579 | AP14: 96.871 | AQ14: 96.837 | AR14: AU9258909 | AS14: JP363360CJA0 | AT14: A+ | AU14: 10/10/2018 | AV14: 23/04/2026 | AW14: 2.568104 | AX14: 96.854 | AY14: 30 | AZ14: 2.5 | BA14: 8 | BB14: 0.27693407 | BC14: 96.577066 | BD14: 1.572
AE15: ZS613802 Corp | AF15: Toyota Motor Corp | AG15: TOYOTA | AH15: JP | AI15: JPY | AJ15: 24/05/2029 | AK15: FIXED | AL15: 2 | AM15: 0.15 | AN15: 1.653 | AO15: 1.665 | AP15: 95.435 | AQ15: 95.4 | AR15: ZS6138029 | AS15: JP363340BK53 | AT15: A+ | AU15: 17/05/2019 | AV15: 22/05/2026 | AW15: 3.1512663 | AX15: 95.4175 | AY15: 35 | AZ15: 3 | BA15: 7 | BB15: 0.10549451 | BC15: 95.312005 | BD15: 1.659
AE16: BO356983 Corp | AF16: Toyota Motor Corp | AG16: TOYOTA | AH16: JP | AI16: JPY | AJ16: 18/03/2031 | AK16: FIXED | AL16: 2 | AM16: 0.219 | AN16: 1.982 | AO16: 1.982 | AP16: 91.959 | AQ16: 91.959 | AR16: BO3569833 | AS16: JP363340CM35 | AT16: A+ | AU16: 12/03/2021 | AV16: 18/03/2026 | AW16: 4.9664613 | AX16: 91.959 | AY16: 5 | AZ16: 4.5 | BA16: 5 | BB16: 0.23223626 | BC16: 91.726764 | BD16: 1.982
AE17: BW601183 Corp | AF17: Toyota Motor Corp | AG17: TOYOTA | AH17: JP | AI17: JPY | AJ17: 02/06/2032 | AK17: FIXED | AL17: 2 | AM17: 0.324 | AN17: 2.155 | AO17: 2.155 | AP17: 89.954 | AQ17: 89.954 | AR17: BW6011835 | AS17: JP363340BN68 | AT17: A+ | AU17: 27/05/2022 | AV17: 02/06/2026 | AW17: 6.1765914 | AX17: 89.954 | AY17: 17 | AZ17: 6 | BA17: 4 | BB17: 0.21006593 | BC17: 89.743934 | BD17: 2.155
AE18: LW169503 Corp | AF18: Toyota Motor Corp | AG18: TOYOTA | AH18: JP | AI18: JPY | AJ18: 03/06/2036 | AK18: FIXED | AL18: 2 | AM18: 0.343 | AN18: 2.839 | AO18: 2.839 | AP18: 80.22 | AQ18: 80.22 | AR18: LW1695037 | AS18: JP363340BG67 | AT18: A+ | AU18: 27/05/2016 | AV18: 03/06/2026 | AW18: 10.179329 | AX18: 80.22 | AY18: 21 | AZ18: 10 | BA18: 10 | BB18: 0.2205 | BC18: 79.9995 | BD18: 2.839

Sheet F date<=1
A1: ID | B1: {=_xlfn.ANCHORARRAY(SORT!A1)} -> Instrument | C1: Name | D1: Ticker | E1: Country/Region | F1: Currency | G1: Maturity | H1: Coupon Type | I1: Coupon Frequency | J1: Coupon | K1: Ask Yield to Maturity | L1: Bid Yield to Maturity | M1: Ask Price | N1: Bid Price | O1: Identifier | P1: ISIN | Q1: Bloomberg Composite Rating | R1: Announce | S1: Next Coupon Settle Date | T1: Time | U1: AVG Price | V1: ID | W1: TIMEish | X1: years ago | Y1: Accrued Interest | Z1: Clean price | AA1: AVG yield | AD1: {=_xlfn.ANCHORARRAY(B1)} -> Instrument | AE1: Name | AF1: Ticker | AG1: Country/Region | AH1: Currency | AI1: Maturity | AJ1: Coupon Type | AK1: Coupon Frequency | AL1: Coupon | AM1: Ask Yield to Maturity | AN1: Bid Yield to Maturity | AO1: Ask Price | AP1: Bid Price | AQ1: Identifier | AR1: ISIN | AS1: Bloomberg Composite Rating | AT1: Announce | AU1: Next Coupon Settle Date | AV1: Time | AW1: AVG Price | AX1: ID | AY1: TIMEish | AZ1: years ago | BA1: Accrued Interest | BB1: Clean price | BC1: AVG yield
B2: {=_xlfn._xlws.FILTER(_xlfn.ANCHORARRAY(AD2),OFFSET(AY1,1,,COUNT(AY:AY))>0)} -> YN599739 Corp | C2: Toyota Finance Corp | D2: TOYOTA | E2: JP | F2: JPY | G2: 22/07/2027 | H2: FIXED | I2: 2 | J2: 0.966 | K2: 1.34 | L2: 1.354 | M2: 99.5 | N2: 99.482 | O2: YN5997393 | P2: JP363360AR78 | Q2: A+ | R2: 15/07/2025 | S2: 22/07/2026 | T2: 1.3114305 | U2: 99.491 | V2: 11 | W2: 1 | X2: 1 | Y2: 0.35561538 | Z2: 99.135385 | AA2: 1.347 | AD2: {=_xlfn._xlws.FILTER(_xlfn.ANCHORARRAY(SORT!A2),SORT!W2:W38<=1)} -> YN599739 Corp | AE2: Toyota Finance Corp | AF2: TOYOTA | AG2: JP | AH2: JPY | AI2: 22/07/2027 | AJ2: FIXED | AK2: 2 | AL2: 0.966 | AM2: 1.34 | AN2: 1.354 | AO2: 99.5 | AP2: 99.482 | AQ2: YN5997393 | AR2: JP363360AR78 | AS2: A+ | AT2: 15/07/2025 | AU2: 22/07/2026 | AV2: 1.3114305 | AW2: 99.491 | AX2: 11 | AY2: 1 | AZ2: 1 | BA2: 0.35561538 | BB2: 99.135385 | BC2: 1.347
B3: YK172992 Corp | C3: Toyota Finance Corp | D3: TOYOTA | E3: JP | F3: JPY | G3: 15/10/2027 | H3: FIXED | I3: 2 | J3: 1.089 | K3: 1.396 | L3: 1.411 | M3: 99.521 | N3: 99.498 | O3: YK1729929 | P3: JP363360CRA3 | Q3: A+ | R3: 10/10/2025 | S3: 17/04/2026 | T3: 1.5441478 | U3: 99.5095 | V3: 37 | W3: 1.5 | X3: 1 | Y3: 0.9812967 | Z3: 98.528203 | AA3: 1.4035 | AD3: YK172992 Corp | AE3: Toyota Finance Corp | AF3: TOYOTA | AG3: JP | AH3: JPY | AI3: 15/10/2027 | AJ3: FIXED | AK3: 2 | AL3: 1.089 | AM3: 1.396 | AN3: 1.411 | AO3: 99.521 | AP3: 99.498 | AQ3: YK1729929 | AR3: JP363360CRA3 | AS3: A+ | AT3: 10/10/2025 | AU3: 17/04/2026 | AV3: 1.5441478 | AW3: 99.5095 | AX3: 37 | AY3: 1.5 | AZ3: 1 | BA3: 0.9812967 | BB3: 98.528203 | BC3: 1.4035
B4: YT967931 Corp | C4: Toyota Finance Corp | D4: TOYOTA | E4: JP | F4: JPY | G4: 21/01/2028 | H4: FIXED | I4: 2 | J4: 0.9 | K4: 1.452 | L4: 1.464 | M4: 99 | N4: 98.978 | O4: YT9679317 | P4: JP363360AR11 | Q4: A+ | R4: 17/01/2025 | S4: 23/07/2026 | T4: 1.8124572 | U4: 98.989 | V4: 23 | W4: 1.5 | X4: 1 | Y4: 0.32637363 | Z4: 98.662626 | AA4: 1.458 | AD4: YT967931 Corp | AE4: Toyota Finance Corp | AF4: TOYOTA | AG4: JP | AH4: JPY | AI4: 21/01/2028 | AJ4: FIXED | AK4: 2 | AL4: 0.9 | AM4: 1.452 | AN4: 1.464 | AO4: 99 | AP4: 98.978 | AQ4: YT9679317 | AR4: JP363360AR11 | AS4: A+ | AT4: 17/01/2025 | AU4: 23/07/2026 | AV4: 1.8124572 | AW4: 98.989 | AX4: 23 | AY4: 1.5 | AZ4: 1 | BA4: 0.32637363 | BB4: 98.662626 | BC4: 1.458
B5: YN599935 Corp | C5: Toyota Finance Corp | D5: TOYOTA | E5: JP | F5: JPY | G5: 21/07/2028 | H5: FIXED | I5: 2 | J5: 1.082 | K5: 1.468 | L5: 1.521 | M5: 99.12 | N5: 98.999 | O5: YN5999357 | P5: JP363360BR77 | Q5: A+ | R5: 15/07/2025 | S5: 22/07/2026 | T5: 2.3107461 | U5: 99.0595 | V5: 12 | W5: 2 | X5: 1 | Y5: 0.39831868 | Z5: 98.661181 | AA5: 1.4945 | AD5: YN599935 Corp | AE5: Toyota Finance Corp | AF5: TOYOTA | AG5: JP | AH5: JPY | AI5: 21/07/2028 | AJ5: FIXED | AK5: 2 | AL5: 1.082 | AM5: 1.468 | AN5: 1.521 | AO5: 99.12 | AP5: 98.999 | AQ5: YN5999357 | AR5: JP363360BR77 | AS5: A+ | AT5: 15/07/2025 | AU5: 22/07/2026 | AV5: 2.3107461 | AW5: 99.0595 | AX5: 12 | AY5: 2 | AZ5: 1 | BA5: 0.39831868 | BB5: 98.661181 | BC5: 1.4945
B6: YK173548 Corp | C6: Toyota Finance Corp | D6: TOYOTA | E6: JP | F6: JPY | G6: 17/10/2028 | H6: FIXED | I6: 2 | J6: 1.234 | K6: 1.542 | L6: 1.554 | M6: 99.23 | N6: 99.198 | O6: YK1735488 | P6: JP363360DRA1 | Q6: A+ | R6: 10/10/2025 | S6: 17/04/2026 | T6: 2.5516769 | U6: 99.214 | V6: 33 | W6: 2.5 | X6: 1 | Y6: 1.111956 | Z6: 98.102044 | AA6: 1.548 | AD6: YK173548 Corp | AE6: Toyota Finance Corp | AF6: TOYOTA | AG6: JP | AH6: JPY | AI6: 17/10/2028 | AJ6: FIXED | AK6: 2 | AL6: 1.234 | AM6: 1.542 | AN6: 1.554 | AO6: 99.23 | AP6: 99.198 | AQ6: YK1735488 | AR6: JP363360DRA1 | AS6: A+ | AT6: 10/10/2025 | AU6: 17/04/2026 | AV6: 2.5516769 | AW6: 99.214 | AX6: 33 | AY6: 2.5 | AZ6: 1 | BA6: 1.111956 | BB6: 98.102044 | BC6: 1.548
B7: DA928584 Corp | C7: Toyota Finance Corp | D7: TOYOTA | E7: JP | F7: JPY | G7: 01/12/2028 | H7: FIXED | I7: 2 | J7: 1.35 | K7: 1.407 | L7: 1.607 | M7: 99.849 | N7: 99.328 | O7: DA9285846 | P7: JP363360ARQ3 | Q7: #N/A N/A | R7: 27/11/2025 | S7: 03/06/2026 | T7: 2.6748802 | U7: 99.5885 | V7: 8 | W7: 2.5 | X7: 1 | Y7: 0.86785714 | Z7: 98.720643 | AA7: 1.507 | AD7: DA928584 Corp | AE7: Toyota Finance Corp | AF7: TOYOTA | AG7: JP | AH7: JPY | AI7: 01/12/2028 | AJ7: FIXED | AK7: 2 | AL7: 1.35 | AM7: 1.407 | AN7: 1.607 | AO7: 99.849 | AP7: 99.328 | AQ7: DA9285846 | AR7: JP363360ARQ3 | AS7: #N/A N/A | AT7: 27/11/2025 | AU7: 03/06/2026 | AV7: 2.6748802 | AW7: 99.5885 | AX7: 8 | AY7: 2.5 | AZ7: 1 | BA7: 0.86785714 | BB7: 98.720643 | BC7: 1.507
B8: YT968038 Corp | C8: Toyota Finance Corp | D8: TOYOTA | E8: JP | F8: JPY | G8: 23/01/2030 | H8: FIXED | I8: 2 | J8: 1.051 | K8: 1.809 | L8: 1.809 | M8: 97.261 | N8: 97.261 | O8: YT9680380 | P8: JP363360BR10 | Q8: A+ | R8: 17/01/2025 | S8: 23/07/2026 | T8: 3.8193018 | U8: 97.261 | V8: 19 | W8: 3.5 | X8: 1 | Y8: 0.38113187 | Z8: 96.879868 | AA8: 1.809 | AD8: YT968038 Corp | AE8: Toyota Finance Corp | AF8: TOYOTA | AG8: JP | AH8: JPY | AI8: 23/01/2030 | AJ8: FIXED | AK8: 2 | AL8: 1.051 | AM8: 1.809 | AN8: 1.809 | AO8: 97.261 | AP8: 97.261 | AQ8: YT9680380 | AR8: JP363360BR10 | AS8: A+ | AT8: 17/01/2025 | AU8: 23/07/2026 | AV8: 3.8193018 | AW8: 97.261 | AX8: 19 | AY8: 3.5 | AZ8: 1 | BA8: 0.38113187 | BB8: 96.879868 | BC8: 1.809
B9: YN600126 Corp | C9: Toyota Finance Corp | D9: TOYOTA | E9: JP | F9: JPY | G9: 22/07/2030 | H9: FIXED | I9: 2 | J9: 1.326 | K9: 1.821 | L9: 1.85 | M9: 98.001 | N9: 97.886 | O9: YN6001260 | P9: JP363360CR76 | Q9: A+ | R9: 15/07/2025 | S9: 22/07/2026 | T9: 4.312115 | U9: 97.9435 | V9: 13 | W9: 4 | X9: 1 | Y9: 0.48814286 | Z9: 97.455357 | AA9: 1.8355 | AD9: YN600126 Corp | AE9: Toyota Finance Corp | AF9: TOYOTA | AG9: JP | AH9: JPY | AI9: 22/07/2030 | AJ9: FIXED | AK9: 2 | AL9: 1.326 | AM9: 1.821 | AN9: 1.85 | AO9: 98.001 | AP9: 97.886 | AQ9: YN6001260 | AR9: JP363360CR76 | AS9: A+ | AT9: 15/07/2025 | AU9: 22/07/2026 | AV9: 4.312115 | AW9: 97.9435 | AX9: 13 | AY9: 4 | AZ9: 1 | BA9: 0.48814286 | BB9: 97.455357 | BC9: 1.8355
B10: YL396232 Corp | C10: Toyota Motor Corp | D10: TOYOTA | E10: JP | F10: JPY | G10: 04/09/2030 | H10: FIXED | I10: 2 | J10: 1.296 | K10: 1.838 | L10: 1.838 | M10: 97.756 | N10: 97.756 | O10: YL3962328 | P10: JP363340BR98 | Q10: A+ | R10: 29/08/2025 | S10: 04/09/2026 | T10: 4.4325804 | U10: 97.756 | V10: 9 | W10: 4 | X10: 1 | Y10: 0.18514286 | Z10: 97.570857 | AA10: 1.838 | AD10: YL396232 Corp | AE10: Toyota Motor Corp | AF10: TOYOTA | AG10: JP | AH10: JPY | AI10: 04/09/2030 | AJ10: FIXED | AK10: 2 | AL10: 1.296 | AM10: 1.838 | AN10: 1.838 | AO10: 97.756 | AP10: 97.756 | AQ10: YL3962328 | AR10: JP363340BR98 | AS10: A+ | AT10: 29/08/2025 | AU10: 04/09/2026 | AV10: 4.4325804 | AW10: 97.756 | AX10: 9 | AY10: 4 | AZ10: 1 | BA10: 0.18514286 | BB10: 97.570857 | BC10: 1.838
B11: YK173563 Corp | C11: Toyota Finance Corp | D11: TOYOTA | E11: JP | F11: JPY | G11: 17/10/2030 | H11: FIXED | I11: 2 | J11: 1.493 | K11: 1.888 | L11: 1.888 | M11: 98.329 | N11: 98.329 | O11: YK1735637 | P11: JP363360ARA7 | Q11: A+ | R11: 10/10/2025 | S11: 17/04/2026 | T11: 4.550308 | U11: 98.329 | V11: 10 | W11: 4.5 | X11: 1 | Y11: 1.3453407 | Z11: 96.983659 | AA11: 1.888 | AD11: YK173563 Corp | AE11: Toyota Finance Corp | AF11: TOYOTA | AG11: JP | AH11: JPY | AI11: 17/10/2030 | AJ11: FIXED | AK11: 2 | AL11: 1.493 | AM11: 1.888 | AN11: 1.888 | AO11: 98.329 | AP11: 98.329 | AQ11: YK1735637 | AR11: JP363360ARA7 | AS11: A+ | AT11: 10/10/2025 | AU11: 17/04/2026 | AV11: 4.550308 | AW11: 98.329 | AX11: 10 | AY11: 4.5 | AZ11: 1 | BA11: 1.3453407 | BB11: 96.983659 | BC11: 1.888
B12: YS631917 Corp | C12: Toyota Finance Corp | D12: TOYOTA | E12: JP | F12: JPY | G12: 23/01/2032 | H12: FIXED | I12: 2 | J12: 1.18 | K12: 2.088 | L12: 2.088 | M12: 95.255 | N12: 95.255 | O12: YS6319174 | P12: JP363360CR19 | Q12: A+ | R12: 17/01/2025 | S12: 23/07/2026 | T12: 5.8179329 | U12: 95.255 | V12: 16 | W12: 5.5 | X12: 1 | Y12: 0.42791209 | Z12: 94.827088 | AA12: 2.088 | AD12: YS631917 Corp | AE12: Toyota Finance Corp | AF12: TOYOTA | AG12: JP | AH12: JPY | AI12: 23/01/2032 | AJ12: FIXED | AK12: 2 | AL12: 1.18 | AM12: 2.088 | AN12: 2.088 | AO12: 95.255 | AP12: 95.255 | AQ12: YS6319174 | AR12: JP363360CR19 | AS12: A+ | AT12: 17/01/2025 | AU12: 23/07/2026 | AV12: 5.8179329 | AW12: 95.255 | AX12: 16 | AY12: 5.5 | AZ12: 1 | BA12: 0.42791209 | BB12: 94.827088 | BC12: 2.088
B13: YK943560 Corp | C13: Toyota Finance Corp | D13: TOYOTA | E13: JP | F13: JPY | G13: 15/10/2032 | H13: FIXED | I13: 2 | J13: 1.708 | K13: 2.147 | L13: 2.147 | M13: 97.464 | N13: 97.464 | O13: YK9435602 | P13: JP363360BRA5 | Q13: A+ | R13: 10/10/2025 | S13: 17/04/2026 | T13: 6.5462012 | U13: 97.464 | V13: 22 | W13: 6.5 | X13: 1 | Y13: 1.5390769 | Z13: 95.924923 | AA13: 2.147 | AD13: YK943560 Corp | AE13: Toyota Finance Corp | AF13: TOYOTA | AG13: JP | AH13: JPY | AI13: 15/10/2032 | AJ13: FIXED | AK13: 2 | AL13: 1.708 | AM13: 2.147 | AN13: 2.147 | AO13: 97.464 | AP13: 97.464 | AQ13: YK9435602 | AR13: JP363360BRA5 | AS13: A+ | AT13: 10/10/2025 | AU13: 17/04/2026 | AV13: 6.5462012 | AW13: 97.464 | AX13: 22 | AY13: 6.5 | AZ13: 1 | BA13: 1.5390769 | BB13: 95.924923 | BC13: 2.147
B14: YL396238 Corp | C14: Toyota Motor Corp | D14: TOYOTA | E14: JP | F14: JPY | G14: 04/09/2035 | H14: FIXED | I14: 2 | J14: 1.793 | K14: 2.507 | L14: 2.507 | M14: 94.531 | N14: 94.531 | O14: YL3962385 | P14: JP363340AR99 | Q14: A+ | R14: 29/08/2025 | S14: 04/09/2026 | T14: 9.431896 | U14: 94.531 | V14: 1 | W14: 9 | X14: 1 | Y14: 0.25614286 | Z14: 94.274857 | AA14: 2.507 | AD14: YL396238 Corp | AE14: Toyota Motor Corp | AF14: TOYOTA | AG14: JP | AH14: JPY | AI14: 04/09/2035 | AJ14: FIXED | AK14: 2 | AL14: 1.793 | AM14: 2.507 | AN14: 2.507 | AO14: 94.531 | AP14: 94.531 | AQ14: YL3962385 | AR14: JP363340AR99 | AS14: A+ | AT14: 29/08/2025 | AU14: 04/09/2026 | AV14: 9.431896 | AW14: 94.531 | AX14: 1 | AY14: 9 | AZ14: 1 | BA14: 0.25614286 | BB14: 94.274857 | BC14: 2.507

Sheet NSS
A1: F coupon<0.5 | C1: Price | E1: =IF(COUNT(H:H)>=COUNT(INDIRECT("'"&A1&"'!W:W")),"YAY ENOUGH ROWS","NEEDS MORE ROWS") -> YAY ENOUGH ROWS | K1: Cash flows | CN1: FITTED VISUALISATION | EC1: AVG yield | ED1: ask yield | EE1: bid yield
A2: Maturity | B2: Coupon | C2: Market | D2: Model | E2: Error | F2: Abs Error | G2: Yield | H2: Yield Model | I2: Yield Error | J2: - prices | K2: {=_xlfn.SEQUENCE(1,79,0,0.5)} -> 0 | L2: 0.5 | M2: 1 | N2: 1.5 | O2: 2 | P2: 2.5 | Q2: 3 | R2: 3.5 | S2: 4 | T2: 4.5 | U2: 5 | V2: 5.5 | W2: 6 | X2: 6.5 | Y2: 7 | Z2: 7.5 | AA2: 8 | AB2: 8.5 | AC2: 9 | AD2: 9.5 | AE2: 10 | AF2: 10.5 | AG2: 11 | AH2: 11.5 | AI2: 12 | AJ2: 12.5 | AK2: 13 | AL2: 13.5 | AM2: 14 | AN2: 14.5 | AO2: 15 | AP2: 15.5 | AQ2: 16 | AR2: 16.5 | AS2: 17 | AT2: 17.5 | AU2: 18 | AV2: 18.5 | AW2: 19 | AX2: 19.5 | AY2: 20 | AZ2: 20.5 | BA2: 21 | BB2: 21.5 | BC2: 22 | BD2: 22.5 | BE2: 23 | BF2: 23.5 | BG2: 24 | BH2: 24.5 | BI2: 25 | BJ2: 25.5 | BK2: 26 | BL2: 26.5 | BM2: 27 | BN2: 27.5 | BO2: 28 | BP2: 28.5 | BQ2: 29 | BR2: 29.5 | BS2: 30 | BT2: 30.5 | BU2: 31 | BV2: 31.5 | BW2: 32 | BX2: 32.5 | BY2: 33 | BZ2: 33.5 | CA2: 34 | CB2: 34.5 | CC2: 35 | CD2: 35.5 | CE2: 36 | CF2: 36.5 | CG2: 37 | CH2: 37.5 | CI2: 38 | CJ2: 38.5 | CK2: 39 | CN2: Time discretization | CO2: Long term spot | CP2: Time decay | CQ2: First hump | CR2: Second hump | CS2: Total | EC2: {=OFFSET(INDIRECT(ADDRESS(1,27,,,A1)),1,,COUNT(INDIRECT("'"&A1&"'!U:U")))/100} -> 0.01163 | ED2: {=OFFSET(INDIRECT(ADDRESS(1,11,,,A1)),1,,COUNT(INDIRECT("'"&A1&"'!U:U")))/100} -> 0.01163 | EE2: {=OFFSET(INDIRECT(ADDRESS(1,12,,,A1)),1,,COUNT(INDIRECT("'"&A1&"'!U:U")))/100} -> 0.01163
A3: {=OFFSET(INDIRECT(ADDRESS(1,23,,,A1)),1,,COUNT(INDIRECT("'"&A1&"'!W:W")))} -> 0.5 | B3: {=OFFSET(INDIRECT(ADDRESS(1,10,,,A1)),1,,COUNT(INDIRECT("'"&A1&"'!J:J")))/100} -> 0.0037 | C3: {=OFFSET(INDIRECT(ADDRESS(1,21,,,A1)),1,,COUNT(INDIRECT("'"&A1&"'!U:U")))} -> 99.538 | D3: =SUMPRODUCT(L3:CK3,$L$249:$CK$249) -> 99.537994 | E3: =+D3-C3 -> -5.9927328e-06 | F3: =ABS(C3-D3) -> 5.9927328e-06 | G3: =+IFERROR(IRR(K3:CK3,0),0) -> 0.0083586168 | H3: =IFERROR(IRR((J3,L3:CK3),0),0) -> 0.0083586775 | I3: =IFERROR(H3-G3,0) -> 6.0708715e-08 | J3: =-D3 -> -99.537994 | K3: =-C3 -> -99.538 | L3: =$B3*100*(L$2<$A3)+100*(1+$B3)*(L$2=$A3) -> 100.37 | M3: =$B3*100*(M$2<$A3)+100*(1+$B3)*(M$2=$A3) -> 0 | N3: =$B3*100*(N$2<$A3)+100*(1+$B3)*(N$2=$A3) -> 0 | O3: =$B3*100*(O$2<$A3)+100*(1+$B3)*(O$2=$A3) -> 0 | P3: =$B3*100*(P$2<$A3)+100*(1+$B3)*(P$2=$A3) -> 0 | Q3: =$B3*100*(Q$2<$A3)+100*(1+$B3)*(Q$2=$A3) -> 0 | R3: =$B3*100*(R$2<$A3)+100*(1+$B3)*(R$2=$A3) -> 0 | S3: =$B3*100*(S$2<$A3)+100*(1+$B3)*(S$2=$A3) -> 0 | ... CK3: =$B3*100*(CK$2<$A3)+100*(1+$B3)*(CK$2=$A3) -> 0 | CN3: 1e-06 | CO3: =$B$248 -> 0.05 | CP3: =b1_*(1-EXP(-CN3/tau1_))/(CN3/tau1_) -> -0.021912017 | CQ3: =b2_*((1-EXP(-CN3/tau1_))/(CN3/tau1_)-EXP(-CN3/tau1_)) -> 1.4819519e-09 | CR3: =+b3_*((1-EXP(-CN3/tau2_))/(CN3/tau2_)-EXP(-CN3/tau2_)) -> 2.0944027e-09 | CS3: =SUM(CO3:CR3) -> 0.028087987 | EC3: 0.0127 | ED3: 0.01259 | EE3: 0.01281
A4: 1 | B4: 0.00414 | C4: 99.0925 | D4: =SUMPRODUCT(L4:CK4,$L$249:$CK$249) -> 99.155932 | E4: =+D4-C4 -> 0.06343152 | F4: =ABS(C4-D4) -> 0.06343152 | G4: =+IFERROR(IRR(K4:CK4,0),0) -> 0.0087370528 | H4: =IFERROR(IRR((J4,L4:CK4),0),0) -> 0.0084136797 | I4: =IFERROR(H4-G4,0) -> -0.00032337309 | J4: =-D4 -> -99.155932 | K4: =-C4 -> -99.0925 | L4: =$B4*100*(L$2<$A4)+100*(1+$B4)*(L$2=$A4) -> 0.414 | M4: =$B4*100*(M$2<$A4)+100*(1+$B4)*(M$2=$A4) -> 100.414 | N4: =$B4*100*(N$2<$A4)+100*(1+$B4)*(N$2=$A4) -> 0 | O4: =$B4*100*(O$2<$A4)+100*(1+$B4)*(O$2=$A4) -> 0 | P4: =$B4*100*(P$2<$A4)+100*(1+$B4)*(P$2=$A4) -> 0 | Q4: =$B4*100*(Q$2<$A4)+100*(1+$B4)*(Q$2=$A4) -> 0 | R4: =$B4*100*(R$2<$A4)+100*(1+$B4)*(R$2=$A4) -> 0 | S4: =$B4*100*(S$2<$A4)+100*(1+$B4)*(S$2=$A4) -> 0 | ... CK4: =$B4*100*(CK$2<$A4)+100*(1+$B4)*(CK$2=$A4) -> 0 | CN4: {=_xlfn.SEQUENCE(500,,0.5,0.5)} -> 0.5 | CO4: {=_xlfn.ANCHORARRAY(CN4)-_xlfn.ANCHORARRAY(CN4)+$B$248} -> 0.05 | CP4: {=b1_*(1-EXP(-_xlfn.ANCHORARRAY(CN4)/tau1_))/(_xlfn.ANCHORARRAY(CN4)/tau1_)} -> -0.021606522 | CQ4: {=b2_*((1-EXP(-_xlfn.ANCHORARRAY(CN4)/tau1_))/(_xlfn.ANCHORARRAY(CN4)/tau1_)-EXP(-_xlfn.ANCHORARRAY(CN4)/tau1_))} -> 0.0007259782 | CR4: {=+b3_*((1-EXP(-_xlfn.ANCHORARRAY(CN4)/tau2_))/(_xlfn.ANCHORARRAY(CN4)/tau2_)-EXP(-_xlfn.ANCHORARRAY(CN4)/tau2_))} -> 0.00088775393 | CS4: =SUM(CO4:CR4) -> 0.03000721 | EC4: 0.01283 | ED4: 0.01274 | EE4: 0.01292
A5: 1 | B5: 0.0022 | C5: 98.7195 | D5: =SUMPRODUCT(L5:CK5,$L$249:$CK$249) -> 98.772763 | E5: =+D5-C5 -> 0.05326347 | F5: =ABS(C5-D5) -> 0.05326347 | G5: =+IFERROR(IRR(K5:CK5,0),0) -> 0.0086860388 | H5: =IFERROR(IRR((J5,L5:CK5),0),0) -> 0.0084137331 | I5: =IFERROR(H5-G5,0) -> -0.00027230569 | J5: =-D5 -> -98.772763 | K5: =-C5 -> -98.7195 | L5: =$B5*100*(L$2<$A5)+100*(1+$B5)*(L$2=$A5) -> 0.22 | M5: =$B5*100*(M$2<$A5)+100*(1+$B5)*(M$2=$A5) -> 100.22 | N5: =$B5*100*(N$2<$A5)+100*(1+$B5)*(N$2=$A5) -> 0 | O5: =$B5*100*(O$2<$A5)+100*(1+$B5)*(O$2=$A5) -> 0 | P5: =$B5*100*(P$2<$A5)+100*(1+$B5)*(P$2=$A5) -> 0 | Q5: =$B5*100*(Q$2<$A5)+100*(1+$B5)*(Q$2=$A5) -> 0 | R5: =$B5*100*(R$2<$A5)+100*(1+$B5)*(R$2=$A5) -> 0 | S5: =$B5*100*(S$2<$A5)+100*(1+$B5)*(S$2=$A5) -> 0 | ... CK5: =$B5*100*(CK$2<$A5)+100*(1+$B5)*(CK$2=$A5) -> 0 | CN5: 1 | CO5: 0.05 | CP5: -0.021306693 | CQ5: 0.0014250602 | CR5: 0.0017609214 | CS5: =SUM(CO5:CR5) -> 0.031879289 | EC5: 0.01282 | ED5: 0.01273 | EE5: 0.01291
A6: 1 | B6: 0.0011 | C6: 98.5885 | D6: =SUMPRODUCT(L6:CK6,$L$249:$CK$249) -> 98.555503 | E6: =+D6-C6 -> -0.032996764 | F6: =ABS(C6-D6) -> 0.032996764 | G6: =+IFERROR(IRR(K6:CK6,0),0) -> 0.008244902 | H6: =IFERROR(IRR((J6,L6:CK6),0),0) -> 0.0084137635 | I6: =IFERROR(H6-G6,0) -> 0.00016886147 | J6: =-D6 -> -98.555503 | K6: =-C6 -> -98.5885 | L6: =$B6*100*(L$2<$A6)+100*(1+$B6)*(L$2=$A6) -> 0.11 | M6: =$B6*100*(M$2<$A6)+100*(1+$B6)*(M$2=$A6) -> 100.11 | N6: =$B6*100*(N$2<$A6)+100*(1+$B6)*(N$2=$A6) -> 0 | O6: =$B6*100*(O$2<$A6)+100*(1+$B6)*(O$2=$A6) -> 0 | P6: =$B6*100*(P$2<$A6)+100*(1+$B6)*(P$2=$A6) -> 0 | Q6: =$B6*100*(Q$2<$A6)+100*(1+$B6)*(Q$2=$A6) -> 0 | R6: =$B6*100*(R$2<$A6)+100*(1+$B6)*(R$2=$A6) -> 0 | S6: =$B6*100*(S$2<$A6)+100*(1+$B6)*(S$2=$A6) -> 0 | ... CK6: =$B6*100*(CK$2<$A6)+100*(1+$B6)*(CK$2=$A6) -> 0 | CN6: 1.5 | CO6: 0.05 | CP6: -0.021012411 | CQ6: 0.0020980865 | CR6: 0.0026197045 | CS6: =SUM(CO6:CR6) -> 0.03370538 | EC6: 0.01353 | ED6: 0.01346 | EE6: 0.0136
A7: 1 | B7: 0.00265 | C7: 98.5435 | D7: =SUMPRODUCT(L7:CK7,$L$249:$CK$249) -> 98.861643 | E7: =+D7-C7 -> 0.31814266 | F7: =ABS(C7-D7) -> 0.31814266 | G7: =+IFERROR(IRR(K7:CK7,0),0) -> 0.010042383 | H7: =IFERROR(IRR((J7,L7:CK7),0),0) -> 0.0084137207 | I7: =IFERROR(H7-G7,0) -> -0.0016286625 | J7: =-D7 -> -98.861643 | K7: =-C7 -> -98.5435 | L7: =$B7*100*(L$2<$A7)+100*(1+$B7)*(L$2=$A7) -> 0.265 | M7: =$B7*100*(M$2<$A7)+100*(1+$B7)*(M$2=$A7) -> 100.265 | N7: =$B7*100*(N$2<$A7)+100*(1+$B7)*(N$2=$A7) -> 0 | O7: =$B7*100*(O$2<$A7)+100*(1+$B7)*(O$2=$A7) -> 0 | P7: =$B7*100*(P$2<$A7)+100*(1+$B7)*(P$2=$A7) -> 0 | Q7: =$B7*100*(Q$2<$A7)+100*(1+$B7)*(Q$2=$A7) -> 0 | R7: =$B7*100*(R$2<$A7)+100*(1+$B7)*(R$2=$A7) -> 0 | S7: =$B7*100*(S$2<$A7)+100*(1+$B7)*(S$2=$A7) -> 0 | ... CK7: =$B7*100*(CK$2<$A7)+100*(1+$B7)*(CK$2=$A7) -> 0 | CN7: 2 | CO7: 0.05 | CP7: -0.020723561 | CQ7: 0.0027458725 | CR7: 0.0034643028 | CS7: =SUM(CO7:CR7) -> 0.035486614 | EC7: 0.014265 | ED7: 0.01419 | EE7: 0.01434
A8: 1.5 | B8: 0.00385 | C8: 98.3625 | D8: =SUMPRODUCT(L8:CK8,$L$249:$CK$249) -> 98.51409 | E8: =+D8-C8 -> 0.15158984 | F8: =ABS(C8-D8) -> 0.15158984 | G8: =+IFERROR(IRR(K8:CK8,0),0) -> 0.0094113952 | H8: =IFERROR(IRR((J8,L8:CK8),0),0) -> 0.0088913723 | I8: =IFERROR(H8-G8,0) -> -0.00052002291 | J8: =-D8 -> -98.51409 | K8: =-C8 -> -98.3625 | L8: =$B8*100*(L$2<$A8)+100*(1+$B8)*(L$2=$A8) -> 0.385 | M8: =$B8*100*(M$2<$A8)+100*(1+$B8)*(M$2=$A8) -> 0.385 | N8: =$B8*100*(N$2<$A8)+100*(1+$B8)*(N$2=$A8) -> 100.385 | O8: =$B8*100*(O$2<$A8)+100*(1+$B8)*(O$2=$A8) -> 0 | P8: =$B8*100*(P$2<$A8)+100*(1+$B8)*(P$2=$A8) -> 0 | Q8: =$B8*100*(Q$2<$A8)+100*(1+$B8)*(Q$2=$A8) -> 0 | R8: =$B8*100*(R$2<$A8)+100*(1+$B8)*(R$2=$A8) -> 0 | S8: =$B8*100*(S$2<$A8)+100*(1+$B8)*(S$2=$A8) -> 0 | ... CK8: =$B8*100*(CK$2<$A8)+100*(1+$B8)*(CK$2=$A8) -> 0 | CN8: 2.5 | CO8: 0.05 | CP8: -0.020440031 | CQ8: 0.0033692094 | CR8: 0.0042949132 | CS8: =SUM(CO8:CR8) -> 0.037224092 | EC8: 0.014255 | ED8: 0.01418 | EE8: 0.01433
A9: 1.5 | B9: 0.00265 | C9: 98.172 | D9: =SUMPRODUCT(L9:CK9,$L$249:$CK$249) -> 98.160224 | E9: =+D9-C9 -> -0.01177585 | F9: =ABS(C9-D9) -> 0.01177585 | G9: =+IFERROR(IRR(K9:CK9,0),0) -> 0.0088515207 | H9: =IFERROR(IRR((J9,L9:CK9),0),0) -> 0.0088919695 | I9: =IFERROR(H9-G9,0) -> 4.0448795e-05 | J9: =-D9 -> -98.160224 | K9: =-C9 -> -98.172 | L9: =$B9*100*(L$2<$A9)+100*(1+$B9)*(L$2=$A9) -> 0.265 | M9: =$B9*100*(M$2<$A9)+100*(1+$B9)*(M$2=$A9) -> 0.265 | N9: =$B9*100*(N$2<$A9)+100*(1+$B9)*(N$2=$A9) -> 100.265 | O9: =$B9*100*(O$2<$A9)+100*(1+$B9)*(O$2=$A9) -> 0 | P9: =$B9*100*(P$2<$A9)+100*(1+$B9)*(P$2=$A9) -> 0 | Q9: =$B9*100*(Q$2<$A9)+100*(1+$B9)*(Q$2=$A9) -> 0 | R9: =$B9*100*(R$2<$A9)+100*(1+$B9)*(R$2=$A9) -> 0 | S9: =$B9*100*(S$2<$A9)+100*(1+$B9)*(S$2=$A9) -> 0 | ... CK9: =$B9*100*(CK$2<$A9)+100*(1+$B9)*(CK$2=$A9) -> 0 | CN9: 3 | CO9: 0.05 | CP9: -0.020161709 | CQ9: 0.0039688652 | CR9: 0.0051117301 | CS9: =SUM(CO9:CR9) -> 0.038918886 | EC9: 0.01487 | ED9: 0.01487 | EE9: 0.01487
A10: 2 | B10: 0.0033 | C10: 97.514 | D10: =SUMPRODUCT(L10:CK10,$L$249:$CK$249) -> 97.634058 | E10: =+D10-C10 -> 0.12005826 | F10: =ABS(C10-D10) -> 0.12005826 | G10: =+IFERROR(IRR(K10:CK10,0),0) -> 0.0096659063 | H10: =IFERROR(IRR((J10,L10:CK10),0),0) -> 0.0093538143 | I10: =IFERROR(H10-G10,0) -> -0.000312092 | J10: =-D10 -> -97.634058 | K10: =-C10 -> -97.514 | L10: =$B10*100*(L$2<$A10)+100*(1+$B10)*(L$2=$A10) -> 0.33 | M10: =$B10*100*(M$2<$A10)+100*(1+$B10)*(M$2=$A10) -> 0.33 | N10: =$B10*100*(N$2<$A10)+100*(1+$B10)*(N$2=$A10) -> 0.33 | O10: =$B10*100*(O$2<$A10)+100*(1+$B10)*(O$2=$A10) -> 100.33 | P10: =$B10*100*(P$2<$A10)+100*(1+$B10)*(P$2=$A10) -> 0 | Q10: =$B10*100*(Q$2<$A10)+100*(1+$B10)*(Q$2=$A10) -> 0 | R10: =$B10*100*(R$2<$A10)+100*(1+$B10)*(R$2=$A10) -> 0 | S10: =$B10*100*(S$2<$A10)+100*(1+$B10)*(S$2=$A10) -> 0 | ... CK10: =$B10*100*(CK$2<$A10)+100*(1+$B10)*(CK$2=$A10) -> 0 | CN10: 3.5 | CO10: 0.05 | CP10: -0.019888488 | CQ10: 0.0045455848 | CR10: 0.0059149451 | CS10: =SUM(CO10:CR10) -> 0.040572042 | EC10: 0.01572 | ED10: 0.01565 | EE10: 0.01579
A11: 2.5 | B11: 0.00319 | C11: 96.854 | D11: =SUMPRODUCT(L11:CK11,$L$249:$CK$249) -> 96.789594 | E11: =+D11-C11 -> -0.064405934 | F11: =ABS(C11-D11) -> 0.064405934 | G11: =+IFERROR(IRR(K11:CK11,0),0) -> 0.0096656182 | H11: =IFERROR(IRR((J11,L11:CK11),0),0) -> 0.0098008271 | I11: =IFERROR(H11-G11,0) -> 0.00013520897 | J11: =-D11 -> -96.789594 | K11: =-C11 -> -96.854 | L11: =$B11*100*(L$2<$A11)+100*(1+$B11)*(L$2=$A11) -> 0.319 | M11: =$B11*100*(M$2<$A11)+100*(1+$B11)*(M$2=$A11) -> 0.319 | N11: =$B11*100*(N$2<$A11)+100*(1+$B11)*(N$2=$A11) -> 0.319 | O11: =$B11*100*(O$2<$A11)+100*(1+$B11)*(O$2=$A11) -> 0.319 | P11: =$B11*100*(P$2<$A11)+100*(1+$B11)*(P$2=$A11) -> 100.319 | Q11: =$B11*100*(Q$2<$A11)+100*(1+$B11)*(Q$2=$A11) -> 0 | R11: =$B11*100*(R$2<$A11)+100*(1+$B11)*(R$2=$A11) -> 0 | S11: =$B11*100*(S$2<$A11)+100*(1+$B11)*(S$2=$A11) -> 0 | ... CK11: =$B11*100*(CK$2<$A11)+100*(1+$B11)*(CK$2=$A11) -> 0 | CN11: 4 | CO11: 0.05 | CP11: -0.019620263 | CQ11: 0.0051000912 | CR11: 0.0067047475 | CS11: =SUM(CO11:CR11) -> 0.042184576 | EC11: 0.01659 | ED11: 0.01653 | EE11: 0.01665
A12: 3 | B12: 0.0015 | C12: 95.4175 | D12: =SUMPRODUCT(L12:CK12,$L$249:$CK$249) -> 94.940492 | E12: =+D12-C12 -> -0.47700753 | F12: =ABS(C12-D12) -> 0.47700753 | G12: =+IFERROR(IRR(K12:CK12,0),0) -> 0.0093904742 | H12: =IFERROR(IRR((J12,L12:CK12),0),0) -> 0.010237216 | I12: =IFERROR(H12-G12,0) -> 0.00084674176 | J12: =-D12 -> -94.940492 | K12: =-C12 -> -95.4175 | L12: =$B12*100*(L$2<$A12)+100*(1+$B12)*(L$2=$A12) -> 0.15 | M12: =$B12*100*(M$2<$A12)+100*(1+$B12)*(M$2=$A12) -> 0.15 | N12: =$B12*100*(N$2<$A12)+100*(1+$B12)*(N$2=$A12) -> 0.15 | O12: =$B12*100*(O$2<$A12)+100*(1+$B12)*(O$2=$A12) -> 0.15 | P12: =$B12*100*(P$2<$A12)+100*(1+$B12)*(P$2=$A12) -> 0.15 | Q12: =$B12*100*(Q$2<$A12)+100*(1+$B12)*(Q$2=$A12) -> 100.15 | R12: =$B12*100*(R$2<$A12)+100*(1+$B12)*(R$2=$A12) -> 0 | S12: =$B12*100*(S$2<$A12)+100*(1+$B12)*(S$2=$A12) -> 0 | ... CK12: =$B12*100*(CK$2<$A12)+100*(1+$B12)*(CK$2=$A12) -> 0 | CN12: 4.5 | CO12: 0.05 | CP12: -0.019356929 | CQ12: 0.0056330858 | CR12: 0.007481324 | CS12: =SUM(CO12:CR12) -> 0.043757481 | EC12: 0.01982 | ED12: 0.01982 | EE12: 0.01982
A13: 4.5 | B13: 0.00219 | C13: 91.959 | D13: =SUMPRODUCT(L13:CK13,$L$249:$CK$249) -> 92.123966 | E13: =+D13-C13 -> 0.16496619 | F13: =ABS(C13-D13) -> 0.16496619 | G13: =+IFERROR(IRR(K13:CK13,0),0) -> 0.011653052 | H13: =IFERROR(IRR((J13,L13:CK13),0),0) -> 0.011449744 | I13: =IFERROR(H13-G13,0) -> -0.00020330796 | J13: =-D13 -> -92.123966 | K13: =-C13 -> -91.959 | L13: =$B13*100*(L$2<$A13)+100*(1+$B13)*(L$2=$A13) -> 0.219 | M13: =$B13*100*(M$2<$A13)+100*(1+$B13)*(M$2=$A13) -> 0.219 | N13: =$B13*100*(N$2<$A13)+100*(1+$B13)*(N$2=$A13) -> 0.219 | O13: =$B13*100*(O$2<$A13)+100*(1+$B13)*(O$2=$A13) -> 0.219 | P13: =$B13*100*(P$2<$A13)+100*(1+$B13)*(P$2=$A13) -> 0.219 | Q13: =$B13*100*(Q$2<$A13)+100*(1+$B13)*(Q$2=$A13) -> 0.219 | R13: =$B13*100*(R$2<$A13)+100*(1+$B13)*(R$2=$A13) -> 0.219 | S13: =$B13*100*(S$2<$A13)+100*(1+$B13)*(S$2=$A13) -> 0.219 | ... CK13: =$B13*100*(CK$2<$A13)+100*(1+$B13)*(CK$2=$A13) -> 0 | CN13: 5 | CO13: 0.05 | CP13: -0.019098386 | CQ13: 0.0061452492 | CR13: 0.008244859 | CS13: =SUM(CO13:CR13) -> 0.045291722 | EC13: 0.02155 | ED13: 0.02155 | EE13: 0.02155
A14: 6 | B14: 0.00324 | C14: 89.954 | D14: =SUMPRODUCT(L14:CK14,$L$249:$CK$249) -> 89.702502 | E14: =+D14-C14 -> -0.25149772 | F14: =ABS(C14-D14) -> 0.25149772 | G14: =+IFERROR(IRR(K14:CK14,0),0) -> 0.012295735 | H14: =IFERROR(IRR((J14,L14:CK14),0),0) -> 0.012536475 | I14: =IFERROR(H14-G14,0) -> 0.00024074008 | J14: =-D14 -> -89.702502 | K14: =-C14 -> -89.954 | L14: =$B14*100*(L$2<$A14)+100*(1+$B14)*(L$2=$A14) -> 0.324 | M14: =$B14*100*(M$2<$A14)+100*(1+$B14)*(M$2=$A14) -> 0.324 | N14: =$B14*100*(N$2<$A14)+100*(1+$B14)*(N$2=$A14) -> 0.324 | O14: =$B14*100*(O$2<$A14)+100*(1+$B14)*(O$2=$A14) -> 0.324 | P14: =$B14*100*(P$2<$A14)+100*(1+$B14)*(P$2=$A14) -> 0.324 | Q14: =$B14*100*(Q$2<$A14)+100*(1+$B14)*(Q$2=$A14) -> 0.324 | R14: =$B14*100*(R$2<$A14)+100*(1+$B14)*(R$2=$A14) -> 0.324 | S14: =$B14*100*(S$2<$A14)+100*(1+$B14)*(S$2=$A14) -> 0.324 | ... CK14: =$B14*100*(CK$2<$A14)+100*(1+$B14)*(CK$2=$A14) -> 0 | CN14: 5.5 | CO14: 0.05 | CP14: -0.018844536 | CQ14: 0.0066372416 | CR14: 0.0089955342 | CS14: =SUM(CO14:CR14) -> 0.04678824 | EC14: 0.02839 | ED14: 0.02839 | EE14: 0.02839
A15: 10 | B15: 0.00343 | C15: 80.22 | D15: =SUMPRODUCT(L15:CK15,$L$249:$CK$249) -> 80.220009 | E15: =+D15-C15 -> 9.2599972e-06 | F15: =ABS(C15-D15) -> 9.2599972e-06 | G15: =+IFERROR(IRR(K15:CK15,0),0) -> 0.01494473 | H15: =IFERROR(IRR((J15,L15:CK15),0),0) -> 0.014944724 | I15: =IFERROR(H15-G15,0) -> -6.0810363e-09 | J15: =-D15 -> -80.220009 | K15: =-C15 -> -80.22 | L15: =$B15*100*(L$2<$A15)+100*(1+$B15)*(L$2=$A15) -> 0.343 | M15: =$B15*100*(M$2<$A15)+100*(1+$B15)*(M$2=$A15) -> 0.343 | N15: =$B15*100*(N$2<$A15)+100*(1+$B15)*(N$2=$A15) -> 0.343 | O15: =$B15*100*(O$2<$A15)+100*(1+$B15)*(O$2=$A15) -> 0.343 | P15: =$B15*100*(P$2<$A15)+100*(1+$B15)*(P$2=$A15) -> 0.343 | Q15: =$B15*100*(Q$2<$A15)+100*(1+$B15)*(Q$2=$A15) -> 0.343 | R15: =$B15*100*(R$2<$A15)+100*(1+$B15)*(R$2=$A15) -> 0.343 | S15: =$B15*100*(S$2<$A15)+100*(1+$B15)*(S$2=$A15) -> 0.343 | ... CK15: =$B15*100*(CK$2<$A15)+100*(1+$B15)*(CK$2=$A15) -> 0 | CN15: 6 | CO15: 0.05 | CP15: -0.018595281 | CQ15: 0.0071097037 | CR15: 0.0097335292 | CS15: =SUM(CO15:CR15) -> 0.048247951
D16: =SUMPRODUCT(L16:CK16,$L$249:$CK$249) -> 0 | E16: =+D16-C16 -> 0 | F16: =ABS(C16-D16) -> 0 | G16: =+IFERROR(IRR(K16:CK16,0),0) -> 0 | H16: =IFERROR(IRR((J16,L16:CK16),0),0) -> 0 | I16: =IFERROR(H16-G16,0) -> 0 | J16: =-D16 -> 0 | K16: =-C16 -> 0 | L16: =$B16*100*(L$2<$A16)+100*(1+$B16)*(L$2=$A16) -> 0 | M16: =$B16*100*(M$2<$A16)+100*(1+$B16)*(M$2=$A16) -> 0 | N16: =$B16*100*(N$2<$A16)+100*(1+$B16)*(N$2=$A16) -> 0 | O16: =$B16*100*(O$2<$A16)+100*(1+$B16)*(O$2=$A16) -> 0 | P16: =$B16*100*(P$2<$A16)+100*(1+$B16)*(P$2=$A16) -> 0 | Q16: =$B16*100*(Q$2<$A16)+100*(1+$B16)*(Q$2=$A16) -> 0 | R16: =$B16*100*(R$2<$A16)+100*(1+$B16)*(R$2=$A16) -> 0 | S16: =$B16*100*(S$2<$A16)+100*(1+$B16)*(S$2=$A16) -> 0 | ... CK16: =$B16*100*(CK$2<$A16)+100*(1+$B16)*(CK$2=$A16) -> 0 | CN16: 6.5 | CO16: 0.05 | CP16: -0.018350528 | CQ16: 0.007563257 | CR16: 0.010459021 | CS16: =SUM(CO16:CR16) -> 0.04967175
D17: =SUMPRODUCT(L17:CK17,$L$249:$CK$249) -> 0 | E17: =+D17-C17 -> 0 | F17: =ABS(C17-D17) -> 0 | G17: =+IFERROR(IRR(K17:CK17,0),0) -> 0 | H17: =IFERROR(IRR((J17,L17:CK17),0),0) -> 0 | I17: =IFERROR(H17-G17,0) -> 0 | J17: =-D17 -> 0 | K17: =-C17 -> 0 | L17: =$B17*100*(L$2<$A17)+100*(1+$B17)*(L$2=$A17) -> 0 | M17: =$B17*100*(M$2<$A17)+100*(1+$B17)*(M$2=$A17) -> 0 | N17: =$B17*100*(N$2<$A17)+100*(1+$B17)*(N$2=$A17) -> 0 | O17: =$B17*100*(O$2<$A17)+100*(1+$B17)*(O$2=$A17) -> 0 | P17: =$B17*100*(P$2<$A17)+100*(1+$B17)*(P$2=$A17) -> 0 | Q17: =$B17*100*(Q$2<$A17)+100*(1+$B17)*(Q$2=$A17) -> 0 | R17: =$B17*100*(R$2<$A17)+100*(1+$B17)*(R$2=$A17) -> 0 | S17: =$B17*100*(S$2<$A17)+100*(1+$B17)*(S$2=$A17) -> 0 | ... CK17: =$B17*100*(CK$2<$A17)+100*(1+$B17)*(CK$2=$A17) -> 0 | CN17: 7 | CO17: 0.05 | CP17: -0.018110184 | CQ17: 0.0079985043 | CR17: 0.011172184 | CS17: =SUM(CO17:CR17) -> 0.051060504
D18: =SUMPRODUCT(L18:CK18,$L$249:$CK$249) -> 0 | E18: =+D18-C18 -> 0 | F18: =ABS(C18-D18) -> 0 | G18: =+IFERROR(IRR(K18:CK18,0),0) -> 0 | H18: =IFERROR(IRR((J18,L18:CK18),0),0) -> 0 | I18: =IFERROR(H18-G18,0) -> 0 | J18: =-D18 -> 0 | K18: =-C18 -> 0 | L18: =$B18*100*(L$2<$A18)+100*(1+$B18)*(L$2=$A18) -> 0 | M18: =$B18*100*(M$2<$A18)+100*(1+$B18)*(M$2=$A18) -> 0 | N18: =$B18*100*(N$2<$A18)+100*(1+$B18)*(N$2=$A18) -> 0 | O18: =$B18*100*(O$2<$A18)+100*(1+$B18)*(O$2=$A18) -> 0 | P18: =$B18*100*(P$2<$A18)+100*(1+$B18)*(P$2=$A18) -> 0 | Q18: =$B18*100*(Q$2<$A18)+100*(1+$B18)*(Q$2=$A18) -> 0 | R18: =$B18*100*(R$2<$A18)+100*(1+$B18)*(R$2=$A18) -> 0 | S18: =$B18*100*(S$2<$A18)+100*(1+$B18)*(S$2=$A18) -> 0 | ... CK18: =$B18*100*(CK$2<$A18)+100*(1+$B18)*(CK$2=$A18) -> 0 | CN18: 7.5 | CO18: 0.05 | CP18: -0.017874159 | CQ18: 0.0084160308 | CR18: 0.011873192 | CS18: =SUM(CO18:CR18) -> 0.052415064
D19: =SUMPRODUCT(L19:CK19,$L$249:$CK$249) -> 0 | E19: =+D19-C19 -> 0 | F19: =ABS(C19-D19) -> 0 | G19: =+IFERROR(IRR(K19:CK19,0),0) -> 0 | H19: =IFERROR(IRR((J19,L19:CK19),0),0) -> 0 | I19: =IFERROR(H19-G19,0) -> 0 | J19: =-D19 -> 0 | K19: =-C19 -> 0 | L19: =$B19*100*(L$2<$A19)+100*(1+$B19)*(L$2=$A19) -> 0 | M19: =$B19*100*(M$2<$A19)+100*(1+$B19)*(M$2=$A19) -> 0 | N19: =$B19*100*(N$2<$A19)+100*(1+$B19)*(N$2=$A19) -> 0 | O19: =$B19*100*(O$2<$A19)+100*(1+$B19)*(O$2=$A19) -> 0 | P19: =$B19*100*(P$2<$A19)+100*(1+$B19)*(P$2=$A19) -> 0 | Q19: =$B19*100*(Q$2<$A19)+100*(1+$B19)*(Q$2=$A19) -> 0 | R19: =$B19*100*(R$2<$A19)+100*(1+$B19)*(R$2=$A19) -> 0 | S19: =$B19*100*(S$2<$A19)+100*(1+$B19)*(S$2=$A19) -> 0 | ... CK19: =$B19*100*(CK$2<$A19)+100*(1+$B19)*(CK$2=$A19) -> 0 | CN19: 8 | CO19: 0.05 | CP19: -0.017642364 | CQ19: 0.0088164038 | CR19: 0.012562213 | CS19: =SUM(CO19:CR19) -> 0.053736253
D20: =SUMPRODUCT(L20:CK20,$L$249:$CK$249) -> 0 | E20: =+D20-C20 -> 0 | F20: =ABS(C20-D20) -> 0 | G20: =+IFERROR(IRR(K20:CK20,0),0) -> 0 | H20: =IFERROR(IRR((J20,L20:CK20),0),0) -> 0 | I20: =IFERROR(H20-G20,0) -> 0 | J20: =-D20 -> 0 | K20: =-C20 -> 0 | L20: =$B20*100*(L$2<$A20)+100*(1+$B20)*(L$2=$A20) -> 0 | M20: =$B20*100*(M$2<$A20)+100*(1+$B20)*(M$2=$A20) -> 0 | N20: =$B20*100*(N$2<$A20)+100*(1+$B20)*(N$2=$A20) -> 0 | O20: =$B20*100*(O$2<$A20)+100*(1+$B20)*(O$2=$A20) -> 0 | P20: =$B20*100*(P$2<$A20)+100*(1+$B20)*(P$2=$A20) -> 0 | Q20: =$B20*100*(Q$2<$A20)+100*(1+$B20)*(Q$2=$A20) -> 0 | R20: =$B20*100*(R$2<$A20)+100*(1+$B20)*(R$2=$A20) -> 0 | S20: =$B20*100*(S$2<$A20)+100*(1+$B20)*(S$2=$A20) -> 0 | ... CK20: =$B20*100*(CK$2<$A20)+100*(1+$B20)*(CK$2=$A20) -> 0 | CN20: 8.5 | CO20: 0.05 | CP20: -0.017414713 | CQ20: 0.0092001738 | CR20: 0.013239417 | CS20: =SUM(CO20:CR20) -> 0.055024878
D21: =SUMPRODUCT(L21:CK21,$L$249:$CK$249) -> 0 | E21: =+D21-C21 -> 0 | F21: =ABS(C21-D21) -> 0 | G21: =+IFERROR(IRR(K21:CK21,0),0) -> 0 | H21: =IFERROR(IRR((J21,L21:CK21),0),0) -> 0 | I21: =IFERROR(H21-G21,0) -> 0 | J21: =-D21 -> 0 | K21: =-C21 -> 0 | L21: =$B21*100*(L$2<$A21)+100*(1+$B21)*(L$2=$A21) -> 0 | M21: =$B21*100*(M$2<$A21)+100*(1+$B21)*(M$2=$A21) -> 0 | N21: =$B21*100*(N$2<$A21)+100*(1+$B21)*(N$2=$A21) -> 0 | O21: =$B21*100*(O$2<$A21)+100*(1+$B21)*(O$2=$A21) -> 0 | P21: =$B21*100*(P$2<$A21)+100*(1+$B21)*(P$2=$A21) -> 0 | Q21: =$B21*100*(Q$2<$A21)+100*(1+$B21)*(Q$2=$A21) -> 0 | R21: =$B21*100*(R$2<$A21)+100*(1+$B21)*(R$2=$A21) -> 0 | S21: =$B21*100*(S$2<$A21)+100*(1+$B21)*(S$2=$A21) -> 0 | ... CK21: =$B21*100*(CK$2<$A21)+100*(1+$B21)*(CK$2=$A21) -> 0 | CN21: 9 | CO21: 0.05 | CP21: -0.017191121 | CQ21: 0.0095678748 | CR21: 0.013904969 | CS21: =SUM(CO21:CR21) -> 0.056281722
D22: =SUMPRODUCT(L22:CK22,$L$249:$CK$249) -> 0 | E22: =+D22-C22 -> 0 | F22: =ABS(C22-D22) -> 0 | G22: =+IFERROR(IRR(K22:CK22,0),0) -> 0 | H22: =IFERROR(IRR((J22,L22:CK22),0),0) -> 0 | I22: =IFERROR(H22-G22,0) -> 0 | J22: =-D22 -> 0 | K22: =-C22 -> 0 | L22: =$B22*100*(L$2<$A22)+100*(1+$B22)*(L$2=$A22) -> 0 | M22: =$B22*100*(M$2<$A22)+100*(1+$B22)*(M$2=$A22) -> 0 | N22: =$B22*100*(N$2<$A22)+100*(1+$B22)*(N$2=$A22) -> 0 | O22: =$B22*100*(O$2<$A22)+100*(1+$B22)*(O$2=$A22) -> 0 | P22: =$B22*100*(P$2<$A22)+100*(1+$B22)*(P$2=$A22) -> 0 | Q22: =$B22*100*(Q$2<$A22)+100*(1+$B22)*(Q$2=$A22) -> 0 | R22: =$B22*100*(R$2<$A22)+100*(1+$B22)*(R$2=$A22) -> 0 | S22: =$B22*100*(S$2<$A22)+100*(1+$B22)*(S$2=$A22) -> 0 | ... CK22: =$B22*100*(CK$2<$A22)+100*(1+$B22)*(CK$2=$A22) -> 0 | CN22: 9.5 | CO22: 0.05 | CP22: -0.016971507 | CQ22: 0.0099200248 | CR22: 0.014559032 | CS22: =SUM(CO22:CR22) -> 0.05750755
D23: =SUMPRODUCT(L23:CK23,$L$249:$CK$249) -> 0 | E23: =+D23-C23 -> 0 | F23: =ABS(C23-D23) -> 0 | G23: =+IFERROR(IRR(K23:CK23,0),0) -> 0 | H23: =IFERROR(IRR((J23,L23:CK23),0),0) -> 0 | I23: =IFERROR(H23-G23,0) -> 0 | J23: =-D23 -> 0 | K23: =-C23 -> 0 | L23: =$B23*100*(L$2<$A23)+100*(1+$B23)*(L$2=$A23) -> 0 | M23: =$B23*100*(M$2<$A23)+100*(1+$B23)*(M$2=$A23) -> 0 | N23: =$B23*100*(N$2<$A23)+100*(1+$B23)*(N$2=$A23) -> 0 | O23: =$B23*100*(O$2<$A23)+100*(1+$B23)*(O$2=$A23) -> 0 | P23: =$B23*100*(P$2<$A23)+100*(1+$B23)*(P$2=$A23) -> 0 | Q23: =$B23*100*(Q$2<$A23)+100*(1+$B23)*(Q$2=$A23) -> 0 | R23: =$B23*100*(R$2<$A23)+100*(1+$B23)*(R$2=$A23) -> 0 | S23: =$B23*100*(S$2<$A23)+100*(1+$B23)*(S$2=$A23) -> 0 | ... CK23: =$B23*100*(CK$2<$A23)+100*(1+$B23)*(CK$2=$A23) -> 0 | CN23: 10 | CO23: 0.05 | CP23: -0.016755788 | CQ23: 0.010257126 | CR23: 0.015201768 | CS23: =SUM(CO23:CR23) -> 0.058703106
D24: =SUMPRODUCT(L24:CK24,$L$249:$CK$249) -> 0 | E24: =+D24-C24 -> 0 | F24: =ABS(C24-D24) -> 0 | G24: =+IFERROR(IRR(K24:CK24,0),0) -> 0 | H24: =IFERROR(IRR((J24,L24:CK24),0),0) -> 0 | I24: =IFERROR(H24-G24,0) -> 0 | J24: =-D24 -> 0 | K24: =-C24 -> 0 | L24: =$B24*100*(L$2<$A24)+100*(1+$B24)*(L$2=$A24) -> 0 | M24: =$B24*100*(M$2<$A24)+100*(1+$B24)*(M$2=$A24) -> 0 | N24: =$B24*100*(N$2<$A24)+100*(1+$B24)*(N$2=$A24) -> 0 | O24: =$B24*100*(O$2<$A24)+100*(1+$B24)*(O$2=$A24) -> 0 | P24: =$B24*100*(P$2<$A24)+100*(1+$B24)*(P$2=$A24) -> 0 | Q24: =$B24*100*(Q$2<$A24)+100*(1+$B24)*(Q$2=$A24) -> 0 | R24: =$B24*100*(R$2<$A24)+100*(1+$B24)*(R$2=$A24) -> 0 | S24: =$B24*100*(S$2<$A24)+100*(1+$B24)*(S$2=$A24) -> 0 | ... CK24: =$B24*100*(CK$2<$A24)+100*(1+$B24)*(CK$2=$A24) -> 0 | CN24: 10.5 | CO24: 0.05 | CP24: -0.016543887 | CQ24: 0.010579667 | CR24: 0.015833336 | CS24: =SUM(CO24:CR24) -> 0.059869115
D25: =SUMPRODUCT(L25:CK25,$L$249:$CK$249) -> 0 | E25: =+D25-C25 -> 0 | F25: =ABS(C25-D25) -> 0 | G25: =+IFERROR(IRR(K25:CK25,0),0) -> 0 | H25: =IFERROR(IRR((J25,L25:CK25),0),0) -> 0 | I25: =IFERROR(H25-G25,0) -> 0 | J25: =-D25 -> 0 | K25: =-C25 -> 0 | L25: =$B25*100*(L$2<$A25)+100*(1+$B25)*(L$2=$A25) -> 0 | M25: =$B25*100*(M$2<$A25)+100*(1+$B25)*(M$2=$A25) -> 0 | N25: =$B25*100*(N$2<$A25)+100*(1+$B25)*(N$2=$A25) -> 0 | O25: =$B25*100*(O$2<$A25)+100*(1+$B25)*(O$2=$A25) -> 0 | P25: =$B25*100*(P$2<$A25)+100*(1+$B25)*(P$2=$A25) -> 0 | Q25: =$B25*100*(Q$2<$A25)+100*(1+$B25)*(Q$2=$A25) -> 0 | R25: =$B25*100*(R$2<$A25)+100*(1+$B25)*(R$2=$A25) -> 0 | S25: =$B25*100*(S$2<$A25)+100*(1+$B25)*(S$2=$A25) -> 0 | ... CK25: =$B25*100*(CK$2<$A25)+100*(1+$B25)*(CK$2=$A25) -> 0 | CN25: 11 | CO25: 0.05 | CP25: -0.016335725 | CQ25: 0.010888118 | CR25: 0.016453892 | CS25: =SUM(CO25:CR25) -> 0.061006286
D26: =SUMPRODUCT(L26:CK26,$L$249:$CK$249) -> 0 | E26: =+D26-C26 -> 0 | F26: =ABS(C26-D26) -> 0 | G26: =+IFERROR(IRR(K26:CK26,0),0) -> 0 | H26: =IFERROR(IRR((J26,L26:CK26),0),0) -> 0 | I26: =IFERROR(H26-G26,0) -> 0 | J26: =-D26 -> 0 | K26: =-C26 -> 0 | L26: =$B26*100*(L$2<$A26)+100*(1+$B26)*(L$2=$A26) -> 0 | M26: =$B26*100*(M$2<$A26)+100*(1+$B26)*(M$2=$A26) -> 0 | N26: =$B26*100*(N$2<$A26)+100*(1+$B26)*(N$2=$A26) -> 0 | O26: =$B26*100*(O$2<$A26)+100*(1+$B26)*(O$2=$A26) -> 0 | P26: =$B26*100*(P$2<$A26)+100*(1+$B26)*(P$2=$A26) -> 0 | Q26: =$B26*100*(Q$2<$A26)+100*(1+$B26)*(Q$2=$A26) -> 0 | R26: =$B26*100*(R$2<$A26)+100*(1+$B26)*(R$2=$A26) -> 0 | S26: =$B26*100*(S$2<$A26)+100*(1+$B26)*(S$2=$A26) -> 0 | ... CK26: =$B26*100*(CK$2<$A26)+100*(1+$B26)*(CK$2=$A26) -> 0 | CN26: 11.5 | CO26: 0.05 | CP26: -0.016131227 | CQ26: 0.01118294 | CR26: 0.017063594 | CS26: =SUM(CO26:CR26) -> 0.062115307
D27: =SUMPRODUCT(L27:CK27,$L$249:$CK$249) -> 0 | E27: =+D27-C27 -> 0 | F27: =ABS(C27-D27) -> 0 | G27: =+IFERROR(IRR(K27:CK27,0),0) -> 0 | H27: =IFERROR(IRR((J27,L27:CK27),0),0) -> 0 | I27: =IFERROR(H27-G27,0) -> 0 | J27: =-D27 -> 0 | K27: =-C27 -> 0 | L27: =$B27*100*(L$2<$A27)+100*(1+$B27)*(L$2=$A27) -> 0 | M27: =$B27*100*(M$2<$A27)+100*(1+$B27)*(M$2=$A27) -> 0 | N27: =$B27*100*(N$2<$A27)+100*(1+$B27)*(N$2=$A27) -> 0 | O27: =$B27*100*(O$2<$A27)+100*(1+$B27)*(O$2=$A27) -> 0 | P27: =$B27*100*(P$2<$A27)+100*(1+$B27)*(P$2=$A27) -> 0 | Q27: =$B27*100*(Q$2<$A27)+100*(1+$B27)*(Q$2=$A27) -> 0 | R27: =$B27*100*(R$2<$A27)+100*(1+$B27)*(R$2=$A27) -> 0 | S27: =$B27*100*(S$2<$A27)+100*(1+$B27)*(S$2=$A27) -> 0 | ... CK27: =$B27*100*(CK$2<$A27)+100*(1+$B27)*(CK$2=$A27) -> 0 | CN27: 12 | CO27: 0.05 | CP27: -0.015930319 | CQ27: 0.011464577 | CR27: 0.017662592 | CS27: =SUM(CO27:CR27) -> 0.06319685
... D66: =SUMPRODUCT(L66:CK66,$L$249:$CK$249) -> 0 | E66: =+D66-C66 -> 0 | F66: =ABS(C66-D66) -> 0 | G66: =+IFERROR(IRR(K66:CK66,0),0) -> 0 | H66: =IFERROR(IRR((J66,L66:CK66),0),0) -> 0 | I66: =IFERROR(H66-G66,0) -> 0 | J66: =-D66 -> 0 | K66: =-C66 -> 0 | L66: =$B66*100*(L$2<$A66)+100*(1+$B66)*(L$2=$A66) -> 0 | M66: =$B66*100*(M$2<$A66)+100*(1+$B66)*(M$2=$A66) -> 0 | N66: =$B66*100*(N$2<$A66)+100*(1+$B66)*(N$2=$A66) -> 0 | O66: =$B66*100*(O$2<$A66)+100*(1+$B66)*(O$2=$A66) -> 0 | P66: =$B66*100*(P$2<$A66)+100*(1+$B66)*(P$2=$A66) -> 0 | Q66: =$B66*100*(Q$2<$A66)+100*(1+$B66)*(Q$2=$A66) -> 0 | R66: =$B66*100*(R$2<$A66)+100*(1+$B66)*(R$2=$A66) -> 0 | S66: =$B66*100*(S$2<$A66)+100*(1+$B66)*(S$2=$A66) -> 0 | ... CK66: =$B66*100*(CK$2<$A66)+100*(1+$B66)*(CK$2=$A66) -> 0 | CN66: 31.5 | CO66: 0.05 | CP66: -0.0102592 | CQ66: 0.01568522 | CR66: 0.034100266 | CS66: =SUM(CO66:CR66) -> 0.089526287
CN67: 32 | CO67: 0.05 | CP67: -0.010156221 | CQ67: 0.015685882 | CR67: 0.034376028 | CS67: =SUM(CO67:CR67) -> 0.08990569
CN68: 32.5 | CO68: 0.05 | CP68: -0.010054844 | CQ68: 0.015683514 | CR68: 0.034645883 | CS68: =SUM(CO68:CR68) -> 0.090274552
CN69: 33 | CO69: 0.05 | CP69: -0.0099550397 | CQ69: 0.015678234 | CR69: 0.034909917 | CS69: =SUM(CO69:CR69) -> 0.09063311
CN70: 33.5 | CO70: 0.05 | CP70: -0.0098567779 | CQ70: 0.015670156 | CR70: 0.035168216 | CS70: =SUM(CO70:CR70) -> 0.090981594
CN71: 34 | CO71: 0.05 | CP71: -0.0097600302 | CQ71: 0.015659392 | CR71: 0.035420866 | CS71: =SUM(CO71:CR71) -> 0.091320228
CN72: 34.5 | CO72: 0.05 | CP72: -0.0096647683 | CQ72: 0.015646051 | CR72: 0.035667949 | CS72: =SUM(CO72:CR72) -> 0.091649232
CN73: 35 | CO73: 0.05 | CP73: -0.0095709646 | CQ73: 0.015630235 | CR73: 0.035909549 | CS73: =SUM(CO73:CR73) -> 0.09196882
CN74: 35.5 | CO74: 0.05 | CP74: -0.009478592 | CQ74: 0.015612047 | CR74: 0.036145746 | CS74: =SUM(CO74:CR74) -> 0.092279201
CN75: 36 | CO75: 0.05 | CP75: -0.0093876242 | CQ75: 0.015591583 | CR75: 0.036376621 | CS75: =SUM(CO75:CR75) -> 0.09258058
CN76: 36.5 | CO76: 0.05 | CP76: -0.009298035 | CQ76: 0.015568938 | CR76: 0.036602253 | CS76: =SUM(CO76:CR76) -> 0.092873156
CN77: 37 | CO77: 0.05 | CP77: -0.0092097992 | CQ77: 0.015544204 | CR77: 0.03682272 | CS77: =SUM(CO77:CR77) -> 0.093157125
CN78: 37.5 | CO78: 0.05 | CP78: -0.0091228919 | CQ78: 0.015517468 | CR78: 0.037038099 | CS78: =SUM(CO78:CR78) -> 0.093432676
... CN241: 119 | CO241: 0.05 | CP241: -0.0032670295 | CQ241: 0.0077721684 | CR241: 0.038845764 | CS241: =SUM(CO241:CR241) -> 0.093350903
E242: =_xlfn.CONCAT("Value = c(",ROUND(C248,5),",",ROUND(C249,5),",",ROUND(C250,5),",",ROUND(C251,5),",",ROUND(C252,5),",",ROUND(C253,5),"),") -> Value = c(0.03678,-0.02191,0.05256,0.14445,17.76451,40.34467), | CN242: 119.5 | CO242: 0.05 | CP242: -0.0032534713 | CQ242: 0.007741443 | CR242: 0.038776195 | CS242: =SUM(CO242:CR242) -> 0.093264166
E243: =_xlfn.CONCAT("Value = c(""",ROUND(E249,2),""",""",ROUND(E255,0),""",""",ROUND(E251,2),""",""",ROUND(E253,0),"""),") -> Value = c("0.03","361","0.09","252"), | CN243: 120 | CO243: 0.05 | CP243: -0.0032400231 | CQ243: 0.0077109313 | CR243: 0.038706448 | CS243: =SUM(CO243:CR243) -> 0.093177357
CN244: 120.5 | CO244: 0.05 | CP244: -0.0032266835 | CQ244: 0.0076806317 | CR244: 0.038636532 | CS244: =SUM(CO244:CR244) -> 0.09309048
CN245: 121 | CO245: 0.05 | CP245: -0.0032134512 | CQ245: 0.0076505424 | CR245: 0.038566451 | CS245: =SUM(CO245:CR245) -> 0.093003543
CN246: 121.5 | CO246: 0.05 | CP246: -0.003200325 | CQ246: 0.0076206618 | CR246: 0.038496214 | CS246: =SUM(CO246:CR246) -> 0.092916551
B247: INITIAL VALUES | C247: SOLVER VALUES | D247: INITIAL RESULTS | E247: SOLVER RESULTS | CN247: 122 | CO247: 0.05 | CP247: -0.0031873037 | CQ247: 0.0075909883 | CR247: 0.038425826 | CS247: =SUM(CO247:CR247) -> 0.09282951
A248: b0 | B248: 0.05 | C248: 0.036780013 | D248: Mean abs error | E248: MAE (Price) | I248: r(t) | J248: FITTED | K248: Spot | L248: =+b0+b1_*((1-EXP(-L2/tau1_))*tau1_/L2)+b2_*((1-EXP(-L2/tau1_))*tau1_/L2-EXP(-L2/tau1_))+b3_*((1-EXP(-L2/tau2_))*tau2_/L2-EXP(-L2/tau2_)) -> 0.016787223 | M248: =+b0+b1_*((1-EXP(-M2/tau1_))*tau1_/M2)+b2_*((1-EXP(-M2/tau1_))*tau1_/M2-EXP(-M2/tau1_)) -> 0.01689838 | N248: =+b0+b1_*((1-EXP(-N2/tau1_))*tau1_/N2)+b2_*((1-EXP(-N2/tau1_))*tau1_/N2-EXP(-N2/tau1_)) -> 0.017865688 | O248: =+b0+b1_*((1-EXP(-O2/tau1_))*tau1_/O2)+b2_*((1-EXP(-O2/tau1_))*tau1_/O2-EXP(-O2/tau1_)) -> 0.018802324 | P248: =+b0+b1_*((1-EXP(-P2/tau1_))*tau1_/P2)+b2_*((1-EXP(-P2/tau1_))*tau1_/P2-EXP(-P2/tau1_)) -> 0.019709191 | Q248: =+b0+b1_*((1-EXP(-Q2/tau1_))*tau1_/Q2)+b2_*((1-EXP(-Q2/tau1_))*tau1_/Q2-EXP(-Q2/tau1_)) -> 0.020587169 | R248: =+b0+b1_*((1-EXP(-R2/tau1_))*tau1_/R2)+b2_*((1-EXP(-R2/tau1_))*tau1_/R2-EXP(-R2/tau1_)) -> 0.021437109 | S248: =+b0+b1_*((1-EXP(-S2/tau1_))*tau1_/S2)+b2_*((1-EXP(-S2/tau1_))*tau1_/S2-EXP(-S2/tau1_)) -> 0.022259841 | T248: =+b0+b1_*((1-EXP(-T2/tau1_))*tau1_/T2)+b2_*((1-EXP(-T2/tau1_))*tau1_/T2-EXP(-T2/tau1_)) -> 0.02305617 | ... CK248: =+b0+b1_*((1-EXP(-CK2/tau1_))*tau1_/CK2)+b2_*((1-EXP(-CK2/tau1_))*tau1_/CK2-EXP(-CK2/tau1_)) -> 0.043336209 | CN248: 122.5 | CO248: 0.05 | CP248: -0.0031743861 | CQ248: 0.0075615201 | CR248: 0.038355293 | CS248: =SUM(CO248:CR248) -> 0.092742427
A249: b1 | B249: -0.04 | C249: -0.021912017 | D249: 6.6983366 | E249: =AVERAGE(F3:F231) -> 0.026705484 | I249: d(t) | J249: Discount factor | L249: =+(1+L248)^(-L2) -> 0.99171061 | M249: =+(1+M248)^(-M2) -> 0.98338243 | N249: =+(1+N248)^(-N2) -> 0.97378771 | O249: =+(1+O248)^(-O2) -> 0.96342996 | P249: =+(1+P248)^(-P2) -> 0.95237759 | Q249: =+(1+Q248)^(-Q2) -> 0.94069685 | R249: =+(1+R248)^(-R2) -> 0.92845164 | S249: =+(1+S248)^(-S2) -> 0.91570334 | ... CK249: =+(1+CK248)^(-CK2) -> 0.19118468 | CN249: 123 | CO249: 0.05 | CP249: -0.003161571 | CQ249: 0.0075322556 | CR249: 0.038284623 | CS249: =SUM(CO249:CR249) -> 0.092655307
A250: b2 | B250: 0.05 | C250: 0.052562539 | D250: RMSE (Price) | E250: RMSE (Price) | I250: f(t) | J250: Forward | N250: =L249/N249-1 -> 0.01840535 | O250: =M249/O249-1 -> 0.020709832 | P250: =N249/P249-1 -> 0.022480708 | Q250: =O249/Q249-1 -> 0.024166245 | R250: =P249/R249-1 -> 0.025769725 | S250: =Q249/S249-1 -> 0.027294326 | T250: =R249/T249-1 -> 0.028743118 | U250: =S249/U249-1 -> 0.030119071 | ... CK250: =CI249/CK249-1 -> 0.047321382 | CN250: 123.5 | CO250: 0.05 | CP250: -0.0031488572 | CQ250: 0.0075031931 | CR250: 0.03821382 | CS250: =SUM(CO250:CR250) -> 0.092568156
A251: b3 | B251: -0.05 | C251: 0.14445251 | D251: 8.3914837 | E251: =SQRT(SUMSQ(E3:E231)/COUNT(E3:E231)) -> 0.085590366 | J251: Forward credit spread | N251: =N250-[3]NSS!N250 -> 0.0038507626 | O251: =O250-[3]NSS!O250 -> 0.0050934519 | P251: =P250-[3]NSS!P250 -> 0.0058554488 | Q251: =Q250-[3]NSS!Q250 -> 0.006272059 | R251: =R250-[3]NSS!R250 -> 0.0064152642 | S251: =S250-[3]NSS!S250 -> 0.0063450579 | T251: =T250-[3]NSS!T250 -> 0.0061112423 | U251: =U250-[3]NSS!U250 -> 0.0057549624 | ... CK251: =CK250-[3]NSS!CK250 -> -0.0082685261 | CN251: 124 | CO251: 0.05 | CP251: -0.0031362435 | CQ251: 0.007474331 | CR251: 0.038142892 | CS251: =SUM(CO251:CR251) -> 0.09248098
A252: t1 | B252: 5 | C252: 17.76451 | D252: RMSE (Yield) | E252: RMSE (Yield) | CN252: 124.5 | CO252: 0.05 | CP252: -0.0031237289 | CQ252: 0.0074456677 | CR252: 0.038071844 | CS252: =SUM(CO252:CR252) -> 0.092393783
A253: t2 | B253: 10 | C253: 40.344667 | D253: 6334.9423 | E253: =SQRT(SUMSQ(I3:I236)/COUNT(I3:I236))*1000000 -> 251.98526 | CN253: 125 | CO253: 0.05 | CP253: -0.0031113121 | CQ253: 0.0074172016 | CR253: 0.038000682 | CS253: =SUM(CO253:CR253) -> 0.092306571
E254: MAE (yield) | CN254: 125.5 | CO254: 0.05 | CP254: -0.0030989922 | CQ254: 0.007388931 | CR254: 0.037929411 | CS254: =SUM(CO254:CR254) -> 0.09221935
E255: {=AVERAGE(ABS(G3:G15-H3:H15))*1000000} -> 360.91015 | CN255: 126 | CO255: 0.05 | CP255: -0.0030867679 | CQ255: 0.0073608543 | CR255: 0.037858038 | CS255: =SUM(CO255:CR255) -> 0.092132125
CN256: 126.5 | CO256: 0.05 | CP256: -0.0030746382 | CQ256: 0.00733297 | CR256: 0.037786568 | CS256: =SUM(CO256:CR256) -> 0.0920449
BC257: =_xlfn.CONCAT(AZ257:AZ334) -> (, 0) (, 0) (, 0) (, 0) (, 0) (, 0) (, 0) (, 0) (, 0) (, 0) (, 0) (, 0) (, 0) (, 0) (, 0) (, 0) (, 0) (, 0) (, 0) (, 0) (, 0) (, 0) (, 0) (, 0) (, 0) (, 0) (, 0) (, 0) (, 0) (, 0) (, 0) (, 0) (, 0) (, 0) (, 0) (, 0) (, 0) (, 0) (, 0) (, 0) (, 0) (, 0) (, 0) (, 0) (, 0) (, 0) (, 0) (, 0) (, 0) (, 0) (, 0) (, 0) (, 0) (, 0) (, 0) (, 0) (, 0) (, 0) (, 0) (, 0) (, 0) (, 0) (, 0) (, 0) (, 0) (, 0) (, 0) (, 0) (, 0) (, 0) (, 0) (, 0) (, 0) (, 0) (, 0) (, 0) | CN257: 127 | CO257: 0.05 | CP257: -0.003062602 | CQ257: 0.0073052764 | CR257: 0.037715006 | CS257: =SUM(CO257:CR257) -> 0.091957681
BC258: =_xlfn.CONCAT(AX257:AX334) -> (, 0) (, 0) (, 0) (, 0) (, 0) (, 0) (, 0) (, 0) (, 0) (, 0) (, 0) (, 0) (, 0) (, 0) (, 0) (, 0) (, 0) (, 0) (, 0) (, 0) (, 0) (, 0) (, 0) (, 0) (, 0) (, 0) (, 0) (, 0) (, 0) (, 0) (, 0) (, 0) (, 0) (, 0) (, 0) (, 0) (, 0) (, 0) (, 0) (, 0) (, 0) (, 0) (, 0) (, 0) (, 0) (, 0) (, 0) (, 0) (, 0) (, 0) (, 0) (, 0) (, 0) (, 0) (, 0) (, 0) (, 0) (, 0) (, 0) (, 0) (, 0) (, 0) (, 0) (, 0) (, 0) (, 0) (, 0) (, 0) (, 0) (, 0) (, 0) (, 0) (, 0) (, 0) (, 0) (, 0) | CN258: 127.5 | CO258: 0.05 | CP258: -0.0030506584 | CQ258: 0.0072777721 | CR258: 0.037643358 | CS258: =SUM(CO258:CR258) -> 0.091870472
AX259: ="("&AV259&", "&ROUND(AW259*100,2)&") " -> (, 0) | AZ259: ="("&AV259&", "&ROUND(AY259*100,2)&") " -> (, 0) | CN259: 128 | CO259: 0.05 | CP259: -0.0030388062 | CQ259: 0.0072504553 | CR259: 0.037571629 | CS259: =SUM(CO259:CR259) -> 0.091783278
AX260: ="("&AV260&", "&ROUND(AW260*100,2)&") " -> (, 0) | AZ260: ="("&AV260&", "&ROUND(AY260*100,2)&") " -> (, 0) | CN260: 128.5 | CO260: 0.05 | CP260: -0.0030270445 | CQ260: 0.0072233245 | CR260: 0.037499824 | CS260: =SUM(CO260:CR260) -> 0.091696104
AX261: ="("&AV261&", "&ROUND(AW261*100,2)&") " -> (, 0) | AZ261: ="("&AV261&", "&ROUND(AY261*100,2)&") " -> (, 0) | CN261: 129 | CO261: 0.05 | CP261: -0.0030153722 | CQ261: 0.0071963783 | CR261: 0.037427948 | CS261: =SUM(CO261:CR261) -> 0.091608954
AX262: ="("&AV262&", "&ROUND(AW262*100,2)&") " -> (, 0) | AZ262: ="("&AV262&", "&ROUND(AY262*100,2)&") " -> (, 0) | CN262: 129.5 | CO262: 0.05 | CP262: -0.0030037884 | CQ262: 0.0071696151 | CR262: 0.037356007 | CS262: =SUM(CO262:CR262) -> 0.091521833
AX263: ="("&AV263&", "&ROUND(AW263*100,2)&") " -> (, 0) | AZ263: ="("&AV263&", "&ROUND(AY263*100,2)&") " -> (, 0) | CN263: 130 | CO263: 0.05 | CP263: -0.0029922921 | CQ263: 0.0071430333 | CR263: 0.037284004 | CS263: =SUM(CO263:CR263) -> 0.091434746
AX264: ="("&AV264&", "&ROUND(AW264*100,2)&") " -> (, 0) | AZ264: ="("&AV264&", "&ROUND(AY264*100,2)&") " -> (, 0) | CN264: 130.5 | CO264: 0.05 | CP264: -0.0029808823 | CQ264: 0.0071166314 | CR264: 0.037211946 | CS264: =SUM(CO264:CR264) -> 0.091347695
AX265: ="("&AV265&", "&ROUND(AW265*100,2)&") " -> (, 0) | AZ265: ="("&AV265&", "&ROUND(AY265*100,2)&") " -> (, 0) | CN265: 131 | CO265: 0.05 | CP265: -0.0029695581 | CQ265: 0.0070904079 | CR265: 0.037139837 | CS265: =SUM(CO265:CR265) -> 0.091260687
AX266: ="("&AV266&", "&ROUND(AW266*100,2)&") " -> (, 0) | AZ266: ="("&AV266&", "&ROUND(AY266*100,2)&") " -> (, 0) | CN266: 131.5 | CO266: 0.05 | CP266: -0.0029583185 | CQ266: 0.0070643614 | CR266: 0.037067681 | CS266: =SUM(CO266:CR266) -> 0.091173724
AX267: ="("&AV267&", "&ROUND(AW267*100,2)&") " -> (, 0) | AZ267: ="("&AV267&", "&ROUND(AY267*100,2)&") " -> (, 0) | CN267: 132 | CO267: 0.05 | CP267: -0.0029471627 | CQ267: 0.0070384903 | CR267: 0.036995484 | CS267: =SUM(CO267:CR267) -> 0.091086811
AX268: ="("&AV268&", "&ROUND(AW268*100,2)&") " -> (, 0) | AZ268: ="("&AV268&", "&ROUND(AY268*100,2)&") " -> (, 0) | CN268: 132.5 | CO268: 0.05 | CP268: -0.0029360897 | CQ268: 0.0070127932 | CR268: 0.036923249 | CS268: =SUM(CO268:CR268) -> 0.090999952
AX269: ="("&AV269&", "&ROUND(AW269*100,2)&") " -> (, 0) | AZ269: ="("&AV269&", "&ROUND(AY269*100,2)&") " -> (, 0) | CN269: 133 | CO269: 0.05 | CP269: -0.0029250985 | CQ269: 0.0069872686 | CR269: 0.036850981 | CS269: =SUM(CO269:CR269) -> 0.090913151
AX270: ="("&AV270&", "&ROUND(AW270*100,2)&") " -> (, 0) | AZ270: ="("&AV270&", "&ROUND(AY270*100,2)&") " -> (, 0) | CN270: 133.5 | CO270: 0.05 | CP270: -0.0029141885 | CQ270: 0.0069619151 | CR270: 0.036778684 | CS270: =SUM(CO270:CR270) -> 0.090826411
... AX315: ="("&AV315&", "&ROUND(AW315*100,2)&") " -> (, 0) | AZ315: ="("&AV315&", "&ROUND(AY315*100,2)&") " -> (, 0) | CN315: 156 | CO315: 0.05 | CP315: -0.0024948493 | CQ315: 0.0059765731 | CR315: 0.033553379 | CS315: =SUM(CO315:CR315) -> 0.087035103
C316: MAE | D316: RMSE (Price) | E316: RMSE (Yield) | AX316: ="("&AV316&", "&ROUND(AW316*100,2)&") " -> (, 0) | AZ316: ="("&AV316&", "&ROUND(AY316*100,2)&") " -> (, 0) | CN316: 156.5 | CO316: 0.05 | CP316: -0.0024868891 | CQ316: 0.0059577022 | CR316: 0.033483354 | CS316: =SUM(CO316:CR316) -> 0.086954167
C317: Mean abs error | D317: Mean abs error | E317: Mean abs error | AX317: ="("&AV317&", "&ROUND(AW317*100,2)&") " -> (, 0) | AZ317: ="("&AV317&", "&ROUND(AY317*100,2)&") " -> (, 0) | CN317: 157 | CO317: 0.05 | CP317: -0.0024789793 | CQ317: 0.0059389461 | CR317: 0.033413436 | CS317: =SUM(CO317:CR317) -> 0.086873403
C318: 0.32473064 | D318: 0.32935859 | E318: 0.35668648 | AX318: ="("&AV318&", "&ROUND(AW318*100,2)&") " -> (, 0) | AZ318: ="("&AV318&", "&ROUND(AY318*100,2)&") " -> (, 0) | CN318: 157.5 | CO318: 0.05 | CP318: -0.0024711195 | CQ318: 0.0059203037 | CR318: 0.033343627 | CS318: =SUM(CO318:CR318) -> 0.086792811
C319: RMSE (Price) | D319: RMSE (Price) | E319: RMSE (Price) | AX319: ="("&AV319&", "&ROUND(AW319*100,2)&") " -> (, 0) | AZ319: ="("&AV319&", "&ROUND(AY319*100,2)&") " -> (, 0) | CN319: 158 | CO319: 0.05 | CP319: -0.0024633092 | CQ319: 0.005901774 | CR319: 0.033273927 | CS319: =SUM(CO319:CR319) -> 0.086712392
C320: 0.43391835 | D320: 0.42494575 | E320: 0.46006885 | AX320: ="("&AV320&", "&ROUND(AW320*100,2)&") " -> (, 0) | AZ320: ="("&AV320&", "&ROUND(AY320*100,2)&") " -> (, 0) | CN320: 158.5 | CO320: 0.05 | CP320: -0.0024555478 | CQ320: 0.0058833563 | CR320: 0.033204339 | CS320: =SUM(CO320:CR320) -> 0.086632148
C321: RMSE (Yield) | D321: RMSE (Yield) | E321: RMSE (Yield) | AX321: ="("&AV321&", "&ROUND(AW321*100,2)&") " -> (, 0) | AZ321: ="("&AV321&", "&ROUND(AY321*100,2)&") " -> (, 0) | CN321: 159 | CO321: 0.05 | CP321: -0.002447835 | CQ321: 0.0058650494 | CR321: 0.033134865 | CS321: =SUM(CO321:CR321) -> 0.08655208
C322: 759.64246 | D322: 781.5237 | E322: 719.14995 | AX322: ="("&AV322&", "&ROUND(AW322*100,2)&") " -> (, 0) | AZ322: ="("&AV322&", "&ROUND(AY322*100,2)&") " -> (, 0) | CN322: 159.5 | CO322: 0.05 | CP322: -0.0024401704 | CQ322: 0.0058468526 | CR322: 0.033065506 | CS322: =SUM(CO322:CR322) -> 0.086472188
AX323: ="("&AV323&", "&ROUND(AW323*100,2)&") " -> (, 0) | AZ323: ="("&AV323&", "&ROUND(AY323*100,2)&") " -> (, 0) | CN323: 160 | CO323: 0.05 | CP323: -0.0024325533 | CQ323: 0.0058287648 | CR323: 0.032996263 | CS323: =SUM(CO323:CR323) -> 0.086392474
C324: SOLVER VALUES | D324: SOLVER VALUES | E324: SOLVER VALUES | AX324: ="("&AV324&", "&ROUND(AW324*100,2)&") " -> (, 0) | AZ324: ="("&AV324&", "&ROUND(AY324*100,2)&") " -> (, 0) | CN324: 160.5 | CO324: 0.05 | CP324: -0.0024249835 | CQ324: 0.0058107852 | CR324: 0.032927138 | CS324: =SUM(CO324:CR324) -> 0.086312939
C325: 0.055063635 | D325: 0.055088041 | AX325: ="("&AV325&", "&ROUND(AW325*100,2)&") " -> (, 0) | AZ325: ="("&AV325&", "&ROUND(AY325*100,2)&") " -> (, 0) | CN325: 161 | CO325: 0.05 | CP325: -0.0024174605 | CQ325: 0.0057929129 | CR325: 0.032858132 | CS325: =SUM(CO325:CR325) -> 0.086233584
C326: -0.039758626 | D326: -0.039544817 | AX326: ="("&AV326&", "&ROUND(AW326*100,2)&") " -> (, 0) | AZ326: ="("&AV326&", "&ROUND(AY326*100,2)&") " -> (, 0) | CN326: 161.5 | CO326: 0.05 | CP326: -0.0024099839 | CQ326: 0.0057751469 | CR326: 0.032789247 | CS326: =SUM(CO326:CR326) -> 0.08615441
C327: -0.047746762 | D327: -0.047994342 | AX327: ="("&AV327&", "&ROUND(AW327*100,2)&") " -> (, 0) | AZ327: ="("&AV327&", "&ROUND(AY327*100,2)&") " -> (, 0) | CN327: 162 | CO327: 0.05 | CP327: -0.0024025532 | CQ327: 0.0057574865 | CR327: 0.032720485 | CS327: =SUM(CO327:CR327) -> 0.086075418
C328: -0.0076015895 | D328: -0.011113521 | AX328: ="("&AV328&", "&ROUND(AW328*100,2)&") " -> (, 0) | AZ328: ="("&AV328&", "&ROUND(AY328*100,2)&") " -> (, 0) | CN328: 162.5 | CO328: 0.05 | CP328: -0.002395168 | CQ328: 0.0057399307 | CR328: 0.032651846 | CS328: =SUM(CO328:CR328) -> 0.085996608
C329: 4.1283731 | D329: 4.1660306 | AX329: ="("&AV329&", "&ROUND(AW329*100,2)&") " -> (, 0) | AZ329: ="("&AV329&", "&ROUND(AY329*100,2)&") " -> (, 0) | CN329: 163 | CO329: 0.05 | CP329: -0.0023878279 | CQ329: 0.0057224786 | CR329: 0.032583331 | CS329: =SUM(CO329:CR329) -> 0.085917982
C330: 0.90200125 | D330: 0.76837732 | AX330: ="("&AV330&", "&ROUND(AW330*100,2)&") " -> (, 0) | AZ330: ="("&AV330&", "&ROUND(AY330*100,2)&") " -> (, 0) | CN330: 163.5 | CO330: 0.05 | CP330: -0.0023805325 | CQ330: 0.0057051295 | CR330: 0.032514944 | CS330: =SUM(CO330:CR330) -> 0.085839541
AX331: ="("&AV331&", "&ROUND(AW331*100,2)&") " -> (, 0) | AZ331: ="("&AV331&", "&ROUND(AY331*100,2)&") " -> (, 0) | CN331: 164 | CO331: 0.05 | CP331: -0.0023732814 | CQ331: 0.0056878824 | CR331: 0.032446683 | CS331: =SUM(CO331:CR331) -> 0.085761284
AX332: ="("&AV332&", "&ROUND(AW332*100,2)&") " -> (, 0) | AZ332: ="("&AV332&", "&ROUND(AY332*100,2)&") " -> (, 0) | CN332: 164.5 | CO332: 0.05 | CP332: -0.0023660742 | CQ332: 0.0056707366 | CR332: 0.032378551 | CS332: =SUM(CO332:CR332) -> 0.085683214
AX333: ="("&AV333&", "&ROUND(AW333*100,2)&") " -> (, 0) | AZ333: ="("&AV333&", "&ROUND(AY333*100,2)&") " -> (, 0) | CN333: 165 | CO333: 0.05 | CP333: -0.0023589105 | CQ333: 0.0056536911 | CR333: 0.03231055 | CS333: =SUM(CO333:CR333) -> 0.08560533
AX334: ="("&AV334&", "&ROUND(AW334*100,2)&") " -> (, 0) | AZ334: ="("&AV334&", "&ROUND(AY334*100,2)&") " -> (, 0) | CN334: 165.5 | CO334: 0.05 | CP334: -0.00235179 | CQ334: 0.0056367453 | CR334: 0.032242679 | CS334: =SUM(CO334:CR334) -> 0.085527634
CN335: 166 | CO335: 0.05 | CP335: -0.0023447121 | CQ335: 0.0056198981 | CR335: 0.03217494 | CS335: =SUM(CO335:CR335) -> 0.085450126
CN336: 166.5 | CO336: 0.05 | CP336: -0.0023376766 | CQ336: 0.0056031489 | CR336: 0.032107335 | CS336: =SUM(CO336:CR336) -> 0.085372807
CN337: 167 | CO337: 0.05 | CP337: -0.0023306831 | CQ337: 0.0055864969 | CR337: 0.032039864 | CS337: =SUM(CO337:CR337) -> 0.085295678
CN338: 167.5 | CO338: 0.05 | CP338: -0.0023237311 | CQ338: 0.0055699412 | CR338: 0.031972529 | CS338: =SUM(CO338:CR338) -> 0.085218739
CN339: 168 | CO339: 0.05 | CP339: -0.0023168204 | CQ339: 0.005553481 | CR339: 0.031905331 | CS339: =SUM(CO339:CR339) -> 0.085141991
CN340: 168.5 | CO340: 0.05 | CP340: -0.0023099506 | CQ340: 0.0055371157 | CR340: 0.031838269 | CS340: =SUM(CO340:CR340) -> 0.085065434
CN341: 169 | CO341: 0.05 | CP341: -0.0023031213 | CQ341: 0.0055208443 | CR341: 0.031771347 | CS341: =SUM(CO341:CR341) -> 0.08498907
CN342: 169.5 | CO342: 0.05 | CP342: -0.0022963321 | CQ342: 0.0055046662 | CR342: 0.031704564 | CS342: =SUM(CO342:CR342) -> 0.084912898
CN343: 170 | CO343: 0.05 | CP343: -0.0022895828 | CQ343: 0.0054885806 | CR343: 0.031637921 | CS343: =SUM(CO343:CR343) -> 0.084836919
CN344: 170.5 | CO344: 0.05 | CP344: -0.0022828729 | CQ344: 0.0054725868 | CR344: 0.03157142 | CS344: =SUM(CO344:CR344) -> 0.084761133
...

Sheet MANUAL FILTER
A1: min | B1: 1.2 | G1: {=_xlfn.ANCHORARRAY(SORT!A1)} -> Instrument | H1: Name | I1: Ticker | J1: Country/Region | K1: Currency | L1: Maturity | M1: Coupon Type | N1: Coupon Frequency | O1: Coupon | P1: Ask Yield to Maturity | Q1: Bid Yield to Maturity | R1: Ask Price | S1: Bid Price | T1: Identifier | U1: ISIN | V1: Bloomberg Composite Rating | W1: Announce | X1: Next Coupon Settle Date | Y1: Time | Z1: AVG Price | AA1: ID | AB1: TIMEish | AC1: years ago | AD1: Accrued Interest | AE1: Clean price | AF1: AVG yield
A2: max | B2: =B1+0.6 -> 1.8 | C2: {=(SORT!S2:S38>'MANUAL FILTER'!B1)} -> FALSE | D2: {=(SORT!S2:S38<'MANUAL FILTER'!B2)} -> TRUE | E2: =AND(C2:D2) -> FALSE | G2: {=_xlfn._xlws.FILTER(_xlfn.ANCHORARRAY(SORT!A2),E2:E38)} -> YN599739 Corp | H2: Toyota Finance Corp | I2: TOYOTA | J2: JP | K2: JPY | L2: 22/07/2027 | M2: FIXED | N2: 2 | O2: 0.966 | P2: 1.34 | Q2: 1.354 | R2: 99.5 | S2: 99.482 | T2: YN5997393 | U2: JP363360AR78 | V2: A+ | W2: 15/07/2025 | X2: 22/07/2026 | Y2: 1.3114305 | Z2: 99.491 | AA2: 11 | AB2: 1 | AC2: 1 | AD2: 0.35561538 | AE2: 99.135385 | AF2: 1.347
C3: FALSE | D3: TRUE | E3: =AND(C3:D3) -> FALSE | G3: AO295977 Corp | H3: Toyota Finance Corp | I3: TOYOTA | J3: JP | K3: JPY | L3: 23/07/2027 | M3: FIXED | N3: 2 | O3: 0.265 | P3: 1.346 | Q3: 1.36 | R3: 98.553 | S3: 98.534 | T3: AO2959770 | U3: JP363360CH78 | V3: A+ | W3: 14/07/2017 | X3: 24/07/2026 | Y3: 1.3141684 | Z3: 98.5435 | AA3: 29 | AB3: 1 | AC3: 9 | AD3: 0.094642857 | AE3: 98.448857 | AF3: 1.353
C4: FALSE | D4: TRUE | E4: =AND(C4:D4) -> FALSE | G4: YV792963 Corp | H4: Toyota Finance Corp | I4: TOYOTA | J4: JP | K4: JPY | L4: 08/10/2027 | M4: FIXED | N4: 2 | O4: 0.573 | P4: 1.406 | Q4: 1.421 | R4: 98.716 | S4: 98.694 | T4: YV7929636 | U4: JP363360AQA9 | V4: A+ | W4: 04/10/2024 | X4: 10/04/2026 | Y4: 1.5249829 | Z4: 98.705 | AA4: 24 | AB4: 1.5 | AC4: 2 | AD4: 0.53836813 | AE4: 98.166632 | AF4: 1.4135
C5: FALSE | D5: TRUE | E5: =AND(C5:D5) -> FALSE | G5: YK172992 Corp | H5: Toyota Finance Corp | I5: TOYOTA | J5: JP | K5: JPY | L5: 15/10/2027 | M5: FIXED | N5: 2 | O5: 1.089 | P5: 1.396 | Q5: 1.411 | R5: 99.521 | S5: 99.498 | T5: YK1729929 | U5: JP363360CRA3 | V5: A+ | W5: 10/10/2025 | X5: 17/04/2026 | Y5: 1.5441478 | Z5: 99.5095 | AA5: 37 | AB5: 1.5 | AC5: 1 | AD5: 0.9812967 | AE5: 98.528203 | AF5: 1.4035
C6: FALSE | D6: TRUE | E6: =AND(C6:D6) -> FALSE | G6: BZ742454 Corp | H6: Toyota Finance Corp | I6: TOYOTA | J6: JP | K6: JPY | L6: 21/10/2027 | M6: FIXED | N6: 2 | O6: 0.385 | P6: 1.419 | Q6: 1.434 | R6: 98.374 | S6: 98.351 | T6: BZ7424543 | U6: JP363360BNA4 | V6: A+ | W6: 14/10/2022 | X6: 21/04/2026 | Y6: 1.5605749 | Z6: 98.3625 | AA6: 36 | AB6: 1.5 | AC6: 4 | AD6: 0.33846154 | AE6: 98.024038 | AF6: 1.4265
C7: FALSE | D7: TRUE | E7: =AND(C7:D7) -> FALSE | G7: AP577034 Corp | H7: Toyota Finance Corp | I7: TOYOTA | J7: JP | K7: JPY | L7: 22/10/2027 | M7: FIXED | N7: 2 | O7: 0.265 | P7: 1.418 | Q7: 1.433 | R7: 98.184 | S7: 98.16 | T7: AP5770346 | U7: JP363360CHA4 | V7: A+ | W7: 13/10/2017 | X7: 24/04/2026 | Y7: 1.5633128 | Z7: 98.172 | AA7: 20 | AB7: 1.5 | AC7: 9 | AD7: 0.2285989 | AE7: 97.943401 | AF7: 1.4255
C8: FALSE | D8: TRUE | E8: =AND(C8:D8) -> FALSE
C9: FALSE | D9: TRUE | E9: =AND(C9:D9) -> FALSE
C10: FALSE | D10: TRUE | E10: =AND(C10:D10) -> FALSE
C11: TRUE | D11: TRUE | E11: =AND(C11:D11) -> TRUE
C12: TRUE | D12: TRUE | E12: =AND(C12:D12) -> TRUE
C13: TRUE | D13: TRUE | E13: =AND(C13:D13) -> TRUE
C14: TRUE | D14: TRUE | E14: =AND(C14:D14) -> TRUE
C15: TRUE | D15: TRUE | E15: =AND(C15:D15) -> TRUE
C16: TRUE | D16: TRUE | E16: =AND(C16:D16) -> TRUE
C17: TRUE | D17: FALSE | E17: =AND(C17:D17) -> FALSE
C18: TRUE | D18: FALSE | E18: =AND(C18:D18) -> FALSE
C19: TRUE | D19: FALSE | E19: =AND(C19:D19) -> FALSE
... C38: TRUE | D38: FALSE | E38: =AND(C38:D38) -> FALSE
