Workbook
Name b0: NSS!$C$248
Name b0: '[1]Nelson Siegel Model'!$B$16
Name b1_: NSS!$C$249
Name b1_: '[1]Nelson Siegel Model'!$B$17
Name b2_: NSS!$C$250
Name b2_: '[1]Nelson Siegel Model'!$B$18
Name b3_: NSS!$C$251
Name b3_: #REF!
Name tau1_: NSS!$C$252
Name tau1_: '[1]Nelson Siegel Model'!$B$19
Name tau2_: NSS!$C$253
Name tau2_: #REF!

Sheet Bloomberg (Online)
A1: Instrument | B1: Name | C1: Ticker | D1: Country/Region | E1: Currency | F1: Maturity | G1: Coupon Type | H1: Coupon Frequency | I1: Coupon | J1: Ask Yield to Maturity | K1: Bid Yield to Maturity | L1: Ask Price | M1: Bid Price | N1: Identifier | O1: ISIN | P1: Bloomberg Composite Rating | Q1: Announce | R1: Next Coupon Settle Date | S1: Time
A2: AL516835 Corp | B2: {=_xll.BDP("AL516835 Corp","DS520")} -> #NAME? | C2: {=_xll.BDP("AL516835 Corp","DS001")} -> #NAME? | D2: {=_xll.BDP("AL516835 Corp","DS458")} -> #NAME? | E2: {=_xll.BDP("AL516835 Corp","DS004")} -> #NAME? | F2: {=_xll.BDP("AL516835 Corp","DS035")} -> #NAME? | G2: {=_xll.BDP("AL516835 Corp","DS086")} -> #NAME? | H2: {=_xll.BDP("AL516835 Corp","DS034")} -> #NAME? | I2: {=_xll.BDP("AL516835 Corp","DS033")} -> #NAME? | J2: {=_xll.BDP("AL516835 Corp","YL018")} -> #NAME? | K2: {=_xll.BDP("AL516835 Corp","YL016")} -> #NAME? | L2: {=_xll.BDP("AL516835 Corp","PR004")} -> #NAME? | M2: {=_xll.BDP("AL516835 Corp","PR002")} -> #NAME? | N2: {=_xll.BDP("AL516835 Corp","ID028")} -> #NAME? | O2: {=_xll.BDP("AL516835 Corp","ID005")} -> #NAME? | P2: {=_xll.BDP(A2,"RA007")} -> #NAME? | Q2: {=_xll.BDP(A2,"DS219")} -> #NAME? | R2: {=_xll.BDP(A2,"DS040")} -> #NAME? | S2: =(F2-TODAY())/365.25 -> #NAME? | T2: =S2-ROUNDDOWN(S2,0) -> #NAME? | U2: =DATE(2026,MONTH(TODAY()),DAY(F2))>DATEVALUE(R2) -> #NAME?
A3: AL662876 Corp | B3: {=_xll.BDP("AL662876 Corp","DS520")} -> #NAME? | C3: {=_xll.BDP("AL662876 Corp","DS001")} -> #NAME? | D3: {=_xll.BDP("AL662876 Corp","DS458")} -> #NAME? | E3: {=_xll.BDP("AL662876 Corp","DS004")} -> #NAME? | F3: {=_xll.BDP("AL662876 Corp","DS035")} -> #NAME? | G3: {=_xll.BDP("AL662876 Corp","DS086")} -> #NAME? | H3: {=_xll.BDP("AL662876 Corp","DS034")} -> #NAME? | I3: {=_xll.BDP("AL662876 Corp","DS033")} -> #NAME? | J3: {=_xll.BDP("AL662876 Corp","YL018")} -> #NAME? | K3: {=_xll.BDP("AL662876 Corp","YL016")} -> #NAME? | L3: {=_xll.BDP("AL662876 Corp","PR004")} -> #NAME? | M3: {=_xll.BDP("AL662876 Corp","PR002")} -> #NAME? | N3: {=_xll.BDP("AL662876 Corp","ID028")} -> #NAME? | O3: {=_xll.BDP("AL662876 Corp","ID005")} -> #NAME? | P3: {=_xll.BDP(A3,"RA007")} -> #NAME? | Q3: {=_xll.BDP(A3,"DS219")} -> #NAME? | R3: {=_xll.BDP(A3,"DS040")} -> #NAME? | S3: =(F3-TODAY())/365.25 -> #NAME? | T3: =S3-ROUNDDOWN(S3,0) -> #NAME? | U3: =DATE(2026,MONTH(TODAY()),DAY(F3))>DATEVALUE(R3) -> #NAME?
A4: AL797512 Corp | B4: {=_xll.BDP("AL797512 Corp","DS520")} -> #NAME? | C4: {=_xll.BDP("AL797512 Corp","DS001")} -> #NAME? | D4: {=_xll.BDP("AL797512 Corp","DS458")} -> #NAME? | E4: {=_xll.BDP("AL797512 Corp","DS004")} -> #NAME? | F4: {=_xll.BDP("AL797512 Corp","DS035")} -> #NAME? | G4: {=_xll.BDP("AL797512 Corp","DS086")} -> #NAME? | H4: {=_xll.BDP("AL797512 Corp","DS034")} -> #NAME? | I4: {=_xll.BDP("AL797512 Corp","DS033")} -> #NAME? | J4: {=_xll.BDP("AL797512 Corp","YL018")} -> #NAME? | K4: {=_xll.BDP("AL797512 Corp","YL016")} -> #NAME? | L4: {=_xll.BDP("AL797512 Corp","PR004")} -> #NAME? | M4: {=_xll.BDP("AL797512 Corp","PR002")} -> #NAME? | N4: {=_xll.BDP("AL797512 Corp","ID028")} -> #NAME? | O4: {=_xll.BDP("AL797512 Corp","ID005")} -> #NAME? | P4: {=_xll.BDP(A4,"RA007")} -> #NAME? | Q4: {=_xll.BDP(A4,"DS219")} -> #NAME? | R4: {=_xll.BDP(A4,"DS040")} -> #NAME? | S4: =(F4-TODAY())/365.25 -> #NAME? | T4: =S4-ROUNDDOWN(S4,0) -> #NAME? | U4: =DATE(2026,MONTH(TODAY()),DAY(F4))>DATEVALUE(R4) -> #NAME?
A5: AM713129 Corp | B5: {=_xll.BDP("AM713129 Corp","DS520")} -> #NAME? | C5: {=_xll.BDP("AM713129 Corp","DS001")} -> #NAME? | D5: {=_xll.BDP("AM713129 Corp","DS458")} -> #NAME? | E5: {=_xll.BDP("AM713129 Corp","DS004")} -> #NAME? | F5: {=_xll.BDP("AM713129 Corp","DS035")} -> #NAME? | G5: {=_xll.BDP("AM713129 Corp","DS086")} -> #NAME? | H5: {=_xll.BDP("AM713129 Corp","DS034")} -> #NAME? | I5: {=_xll.BDP("AM713129 Corp","DS033")} -> #NAME? | J5: {=_xll.BDP("AM713129 Corp","YL018")} -> #NAME? | K5: {=_xll.BDP("AM713129 Corp","YL016")} -> #NAME? | L5: {=_xll.BDP("AM713129 Corp","PR004")} -> #NAME? | M5: {=_xll.BDP("AM713129 Corp","PR002")} -> #NAME? | N5: {=_xll.BDP("AM713129 Corp","ID028")} -> #NAME? | O5: {=_xll.BDP("AM713129 Corp","ID005")} -> #NAME? | P5: {=_xll.BDP(A5,"RA007")} -> #NAME? | Q5: {=_xll.BDP(A5,"DS219")} -> #NAME? | R5: {=_xll.BDP(A5,"DS040")} -> #NAME? | S5: =(F5-TODAY())/365.25 -> #NAME? | T5: =S5-ROUNDDOWN(S5,0) -> #NAME? | U5: =DATE(2026,MONTH(TODAY()),DAY(F5))>DATEVALUE(R5) -> #NAME?
A6: AM766737 Corp | B6: {=_xll.BDP("AM766737 Corp","DS520")} -> #NAME? | C6: {=_xll.BDP("AM766737 Corp","DS001")} -> #NAME? | D6: {=_xll.BDP("AM766737 Corp","DS458")} -> #NAME? | E6: {=_xll.BDP("AM766737 Corp","DS004")} -> #NAME? | F6: {=_xll.BDP("AM766737 Corp","DS035")} -> #NAME? | G6: {=_xll.BDP("AM766737 Corp","DS086")} -> #NAME? | H6: {=_xll.BDP("AM766737 Corp","DS034")} -> #NAME? | I6: {=_xll.BDP("AM766737 Corp","DS033")} -> #NAME? | J6: {=_xll.BDP("AM766737 Corp","YL018")} -> #NAME? | K6: {=_xll.BDP("AM766737 Corp","YL016")} -> #NAME? | L6: {=_xll.BDP("AM766737 Corp","PR004")} -> #NAME? | M6: {=_xll.BDP("AM766737 Corp","PR002")} -> #NAME? | N6: {=_xll.BDP("AM766737 Corp","ID028")} -> #NAME? | O6: {=_xll.BDP("AM766737 Corp","ID005")} -> #NAME? | P6: {=_xll.BDP(A6,"RA007")} -> #NAME? | Q6: {=_xll.BDP(A6,"DS219")} -> #NAME? | R6: {=_xll.BDP(A6,"DS040")} -> #NAME? | S6: =(F6-TODAY())/365.25 -> #NAME? | T6: =S6-ROUNDDOWN(S6,0) -> #NAME? | U6: =DATE(2026,MONTH(TODAY()),DAY(F6))>DATEVALUE(R6) -> #NAME?
A7: AM850328 Corp | B7: {=_xll.BDP("AM850328 Corp","DS520")} -> #NAME? | C7: {=_xll.BDP("AM850328 Corp","DS001")} -> #NAME? | D7: {=_xll.BDP("AM850328 Corp","DS458")} -> #NAME? | E7: {=_xll.BDP("AM850328 Corp","DS004")} -> #NAME? | F7: {=_xll.BDP("AM850328 Corp","DS035")} -> #NAME? | G7: {=_xll.BDP("AM850328 Corp","DS086")} -> #NAME? | H7: {=_xll.BDP("AM850328 Corp","DS034")} -> #NAME? | I7: {=_xll.BDP("AM850328 Corp","DS033")} -> #NAME? | J7: {=_xll.BDP("AM850328 Corp","YL018")} -> #NAME? | K7: {=_xll.BDP("AM850328 Corp","YL016")} -> #NAME? | L7: {=_xll.BDP("AM850328 Corp","PR004")} -> #NAME? | M7: {=_xll.BDP("AM850328 Corp","PR002")} -> #NAME? | N7: {=_xll.BDP("AM850328 Corp","ID028")} -> #NAME? | O7: {=_xll.BDP("AM850328 Corp","ID005")} -> #NAME? | P7: {=_xll.BDP(A7,"RA007")} -> #NAME? | Q7: {=_xll.BDP(A7,"DS219")} -> #NAME? | R7: {=_xll.BDP(A7,"DS040")} -> #NAME? | S7: =(F7-TODAY())/365.25 -> #NAME? | T7: =S7-ROUNDDOWN(S7,0) -> #NAME? | U7: =DATE(2026,MONTH(TODAY()),DAY(F7))>DATEVALUE(R7) -> #NAME?
A8: AN751153 Corp | B8: {=_xll.BDP("AN751153 Corp","DS520")} -> #NAME? | C8: {=_xll.BDP("AN751153 Corp","DS001")} -> #NAME? | D8: {=_xll.BDP("AN751153 Corp","DS458")} -> #NAME? | E8: {=_xll.BDP("AN751153 Corp","DS004")} -> #NAME? | F8: {=_xll.BDP("AN751153 Corp","DS035")} -> #NAME? | G8: {=_xll.BDP("AN751153 Corp","DS086")} -> #NAME? | H8: {=_xll.BDP("AN751153 Corp","DS034")} -> #NAME? | I8: {=_xll.BDP("AN751153 Corp","DS033")} -> #NAME? | J8: {=_xll.BDP("AN751153 Corp","YL018")} -> #NAME? | K8: {=_xll.BDP("AN751153 Corp","YL016")} -> #NAME? | L8: {=_xll.BDP("AN751153 Corp","PR004")} -> #NAME? | M8: {=_xll.BDP("AN751153 Corp","PR002")} -> #NAME? | N8: {=_xll.BDP("AN751153 Corp","ID028")} -> #NAME? | O8: {=_xll.BDP("AN751153 Corp","ID005")} -> #NAME? | P8: {=_xll.BDP(A8,"RA007")} -> #NAME? | Q8: {=_xll.BDP(A8,"DS219")} -> #NAME? | R8: {=_xll.BDP(A8,"DS040")} -> #NAME? | S8: =(F8-TODAY())/365.25 -> #NAME? | T8: =S8-ROUNDDOWN(S8,0) -> #NAME? | U8: =DATE(2026,MONTH(TODAY()),DAY(F8))>DATEVALUE(R8) -> #NAME?
A9: AN821370 Corp | B9: {=_xll.BDP("AN821370 Corp","DS520")} -> #NAME? | C9: {=_xll.BDP("AN821370 Corp","DS001")} -> #NAME? | D9: {=_xll.BDP("AN821370 Corp","DS458")} -> #NAME? | E9: {=_xll.BDP("AN821370 Corp","DS004")} -> #NAME? | F9: {=_xll.BDP("AN821370 Corp","DS035")} -> #NAME? | G9: {=_xll.BDP("AN821370 Corp","DS086")} -> #NAME? | H9: {=_xll.BDP("AN821370 Corp","DS034")} -> #NAME? | I9: {=_xll.BDP("AN821370 Corp","DS033")} -> #NAME? | J9: {=_xll.BDP("AN821370 Corp","YL018")} -> #NAME? | K9: {=_xll.BDP("AN821370 Corp","YL016")} -> #NAME? | L9: {=_xll.BDP("AN821370 Corp","PR004")} -> #NAME? | M9: {=_xll.BDP("AN821370 Corp","PR002")} -> #NAME? | N9: {=_xll.BDP("AN821370 Corp","ID028")} -> #NAME? | O9: {=_xll.BDP("AN821370 Corp","ID005")} -> #NAME? | P9: {=_xll.BDP(A9,"RA007")} -> #NAME? | Q9: {=_xll.BDP(A9,"DS219")} -> #NAME? | R9: {=_xll.BDP(A9,"DS040")} -> #NAME? | S9: =(F9-TODAY())/365.25 -> #NAME? | T9: =S9-ROUNDDOWN(S9,0) -> #NAME? | U9: =DATE(2026,MONTH(TODAY()),DAY(F9))>DATEVALUE(R9) -> #NAME?
A10: AN861997 Corp | B10: {=_xll.BDP("AN861997 Corp","DS520")} -> #NAME? | C10: {=_xll.BDP("AN861997 Corp","DS001")} -> #NAME? | D10: {=_xll.BDP("AN861997 Corp","DS458")} -> #NAME? | E10: {=_xll.BDP("AN861997 Corp","DS004")} -> #NAME? | F10: {=_xll.BDP("AN861997 Corp","DS035")} -> #NAME? | G10: {=_xll.BDP("AN861997 Corp","DS086")} -> #NAME? | H10: {=_xll.BDP("AN861997 Corp","DS034")} -> #NAME? | I10: {=_xll.BDP("AN861997 Corp","DS033")} -> #NAME? | J10: {=_xll.BDP("AN861997 Corp","YL018")} -> #NAME? | K10: {=_xll.BDP("AN861997 Corp","YL016")} -> #NAME? | L10: {=_xll.BDP("AN861997 Corp","PR004")} -> #NAME? | M10: {=_xll.BDP("AN861997 Corp","PR002")} -> #NAME? | N10: {=_xll.BDP("AN861997 Corp","ID028")} -> #NAME? | O10: {=_xll.BDP("AN861997 Corp","ID005")} -> #NAME? | P10: {=_xll.BDP(A10,"RA007")} -> #NAME? | Q10: {=_xll.BDP(A10,"DS219")} -> #NAME? | R10: {=_xll.BDP(A10,"DS040")} -> #NAME? | S10: =(F10-TODAY())/365.25 -> #NAME? | T10: =S10-ROUNDDOWN(S10,0) -> #NAME? | U10: =DATE(2026,MONTH(TODAY()),DAY(F10))>DATEVALUE(R10) -> #NAME?
A11: AN958432 Corp | B11: {=_xll.BDP("AN958432 Corp","DS520")} -> #NAME? | C11: {=_xll.BDP("AN958432 Corp","DS001")} -> #NAME? | D11: {=_xll.BDP("AN958432 Corp","DS458")} -> #NAME? | E11: {=_xll.BDP("AN958432 Corp","DS004")} -> #NAME? | F11: {=_xll.BDP("AN958432 Corp","DS035")} -> #NAME? | G11: {=_xll.BDP("AN958432 Corp","DS086")} -> #NAME? | H11: {=_xll.BDP("AN958432 Corp","DS034")} -> #NAME? | I11: {=_xll.BDP("AN958432 Corp","DS033")} -> #NAME? | J11: {=_xll.BDP("AN958432 Corp","YL018")} -> #NAME? | K11: {=_xll.BDP("AN958432 Corp","YL016")} -> #NAME? | L11: {=_xll.BDP("AN958432 Corp","PR004")} -> #NAME? | M11: {=_xll.BDP("AN958432 Corp","PR002")} -> #NAME? | N11: {=_xll.BDP("AN958432 Corp","ID028")} -> #NAME? | O11: {=_xll.BDP("AN958432 Corp","ID005")} -> #NAME? | P11: {=_xll.BDP(A11,"RA007")} -> #NAME? | Q11: {=_xll.BDP(A11,"DS219")} -> #NAME? | R11: {=_xll.BDP(A11,"DS040")} -> #NAME? | S11: =(F11-TODAY())/365.25 -> #NAME? | T11: =S11-ROUNDDOWN(S11,0) -> #NAME? | U11: =DATE(2026,MONTH(TODAY()),DAY(F11))>DATEVALUE(R11) -> #NAME?
A12: AP027592 Corp | B12: {=_xll.BDP("AP027592 Corp","DS520")} -> #NAME? | C12: {=_xll.BDP("AP027592 Corp","DS001")} -> #NAME? | D12: {=_xll.BDP("AP027592 Corp","DS458")} -> #NAME? | E12: {=_xll.BDP("AP027592 Corp","DS004")} -> #NAME? | F12: {=_xll.BDP("AP027592 Corp","DS035")} -> #NAME? | G12: {=_xll.BDP("AP027592 Corp","DS086")} -> #NAME? | H12: {=_xll.BDP("AP027592 Corp","DS034")} -> #NAME? | I12: {=_xll.BDP("AP027592 Corp","DS033")} -> #NAME? | J12: {=_xll.BDP("AP027592 Corp","YL018")} -> #NAME? | K12: {=_xll.BDP("AP027592 Corp","YL016")} -> #NAME? | L12: {=_xll.BDP("AP027592 Corp","PR004")} -> #NAME? | M12: {=_xll.BDP("AP027592 Corp","PR002")} -> #NAME? | N12: {=_xll.BDP("AP027592 Corp","ID028")} -> #NAME? | O12: {=_xll.BDP("AP027592 Corp","ID005")} -> #NAME? | P12: {=_xll.BDP(A12,"RA007")} -> #NAME? | Q12: {=_xll.BDP(A12,"DS219")} -> #NAME? | R12: {=_xll.BDP(A12,"DS040")} -> #NAME? | S12: =(F12-TODAY())/365.25 -> #NAME? | T12: =S12-ROUNDDOWN(S12,0) -> #NAME? | U12: =DATE(2026,MONTH(TODAY()),DAY(F12))>DATEVALUE(R12) -> #NAME?
A13: AP059339 Corp | B13: {=_xll.BDP("AP059339 Corp","DS520")} -> #NAME? | C13: {=_xll.BDP("AP059339 Corp","DS001")} -> #NAME? | D13: {=_xll.BDP("AP059339 Corp","DS458")} -> #NAME? | E13: {=_xll.BDP("AP059339 Corp","DS004")} -> #NAME? | F13: {=_xll.BDP("AP059339 Corp","DS035")} -> #NAME? | G13: {=_xll.BDP("AP059339 Corp","DS086")} -> #NAME? | H13: {=_xll.BDP("AP059339 Corp","DS034")} -> #NAME? | I13: {=_xll.BDP("AP059339 Corp","DS033")} -> #NAME? | J13: {=_xll.BDP("AP059339 Corp","YL018")} -> #NAME? | K13: {=_xll.BDP("AP059339 Corp","YL016")} -> #NAME? | L13: {=_xll.BDP("AP059339 Corp","PR004")} -> #NAME? | M13: {=_xll.BDP("AP059339 Corp","PR002")} -> #NAME? | N13: {=_xll.BDP("AP059339 Corp","ID028")} -> #NAME? | O13: {=_xll.BDP("AP059339 Corp","ID005")} -> #NAME? | P13: {=_xll.BDP(A13,"RA007")} -> #NAME? | Q13: {=_xll.BDP(A13,"DS219")} -> #NAME? | R13: {=_xll.BDP(A13,"DS040")} -> #NAME? | S13: =(F13-TODAY())/365.25 -> #NAME? | T13: =S13-ROUNDDOWN(S13,0) -> #NAME? | U13: =DATE(2026,MONTH(TODAY()),DAY(F13))>DATEVALUE(R13) -> #NAME?
A14: AP155275 Corp | B14: {=_xll.BDP("AP155275 Corp","DS520")} -> #NAME? | C14: {=_xll.BDP("AP155275 Corp","DS001")} -> #NAME? | D14: {=_xll.BDP("AP155275 Corp","DS458")} -> #NAME? | E14: {=_xll.BDP("AP155275 Corp","DS004")} -> #NAME? | F14: {=_xll.BDP("AP155275 Corp","DS035")} -> #NAME? | G14: {=_xll.BDP("AP155275 Corp","DS086")} -> #NAME? | H14: {=_xll.BDP("AP155275 Corp","DS034")} -> #NAME? | I14: {=_xll.BDP("AP155275 Corp","DS033")} -> #NAME? | J14: {=_xll.BDP("AP155275 Corp","YL018")} -> #NAME? | K14: {=_xll.BDP("AP155275 Corp","YL016")} -> #NAME? | L14: {=_xll.BDP("AP155275 Corp","PR004")} -> #NAME? | M14: {=_xll.BDP("AP155275 Corp","PR002")} -> #NAME? | N14: {=_xll.BDP("AP155275 Corp","ID028")} -> #NAME? | O14: {=_xll.BDP("AP155275 Corp","ID005")} -> #NAME? | P14: {=_xll.BDP(A14,"RA007")} -> #NAME? | Q14: {=_xll.BDP(A14,"DS219")} -> #NAME? | R14: {=_xll.BDP(A14,"DS040")} -> #NAME? | S14: =(F14-TODAY())/365.25 -> #NAME? | T14: =S14-ROUNDDOWN(S14,0) -> #NAME? | U14: =DATE(2026,MONTH(TODAY()),DAY(F14))>DATEVALUE(R14) -> #NAME?
A15: AQ307103 Corp | B15: {=_xll.BDP("AQ307103 Corp","DS520")} -> #NAME? | C15: {=_xll.BDP("AQ307103 Corp","DS001")} -> #NAME? | D15: {=_xll.BDP("AQ307103 Corp","DS458")} -> #NAME? | E15: {=_xll.BDP("AQ307103 Corp","DS004")} -> #NAME? | F15: {=_xll.BDP("AQ307103 Corp","DS035")} -> #NAME? | G15: {=_xll.BDP("AQ307103 Corp","DS086")} -> #NAME? | H15: {=_xll.BDP("AQ307103 Corp","DS034")} -> #NAME? | I15: {=_xll.BDP("AQ307103 Corp","DS033")} -> #NAME? | J15: {=_xll.BDP("AQ307103 Corp","YL018")} -> #NAME? | K15: {=_xll.BDP("AQ307103 Corp","YL016")} -> #NAME? | L15: {=_xll.BDP("AQ307103 Corp","PR004")} -> #NAME? | M15: {=_xll.BDP("AQ307103 Corp","PR002")} -> #NAME? | N15: {=_xll.BDP("AQ307103 Corp","ID028")} -> #NAME? | O15: {=_xll.BDP("AQ307103 Corp","ID005")} -> #NAME? | P15: {=_xll.BDP(A15,"RA007")} -> #NAME? | Q15: {=_xll.BDP(A15,"DS219")} -> #NAME? | R15: {=_xll.BDP(A15,"DS040")} -> #NAME? | S15: =(F15-TODAY())/365.25 -> #NAME? | T15: =S15-ROUNDDOWN(S15,0) -> #NAME? | U15: =DATE(2026,MONTH(TODAY()),DAY(F15))>DATEVALUE(R15) -> #NAME?
A16: AQ340832 Corp | B16: {=_xll.BDP("AQ340832 Corp","DS520")} -> #NAME? | C16: {=_xll.BDP("AQ340832 Corp","DS001")} -> #NAME? | D16: {=_xll.BDP("AQ340832 Corp","DS458")} -> #NAME? | E16: {=_xll.BDP("AQ340832 Corp","DS004")} -> #NAME? | F16: {=_xll.BDP("AQ340832 Corp","DS035")} -> #NAME? | G16: {=_xll.BDP("AQ340832 Corp","DS086")} -> #NAME? | H16: {=_xll.BDP("AQ340832 Corp","DS034")} -> #NAME? | I16: {=_xll.BDP("AQ340832 Corp","DS033")} -> #NAME? | J16: {=_xll.BDP("AQ340832 Corp","YL018")} -> #NAME? | K16: {=_xll.BDP("AQ340832 Corp","YL016")} -> #NAME? | L16: {=_xll.BDP("AQ340832 Corp","PR004")} -> #NAME? | M16: {=_xll.BDP("AQ340832 Corp","PR002")} -> #NAME? | N16: {=_xll.BDP("AQ340832 Corp","ID028")} -> #NAME? | O16: {=_xll.BDP("AQ340832 Corp","ID005")} -> #NAME? | P16: {=_xll.BDP(A16,"RA007")} -> #NAME? | Q16: {=_xll.BDP(A16,"DS219")} -> #NAME? | R16: {=_xll.BDP(A16,"DS040")} -> #NAME? | S16: =(F16-TODAY())/365.25 -> #NAME? | T16: =S16-ROUNDDOWN(S16,0) -> #NAME? | U16: =DATE(2026,MONTH(TODAY()),DAY(F16))>DATEVALUE(R16) -> #NAME?
A17: AQ417830 Corp | B17: {=_xll.BDP("AQ417830 Corp","DS520")} -> #NAME? | C17: {=_xll.BDP("AQ417830 Corp","DS001")} -> #NAME? | D17: {=_xll.BDP("AQ417830 Corp","DS458")} -> #NAME? | E17: {=_xll.BDP("AQ417830 Corp","DS004")} -> #NAME? | F17: {=_xll.BDP("AQ417830 Corp","DS035")} -> #NAME? | G17: {=_xll.BDP("AQ417830 Corp","DS086")} -> #NAME? | H17: {=_xll.BDP("AQ417830 Corp","DS034")} -> #NAME? | I17: {=_xll.BDP("AQ417830 Corp","DS033")} -> #NAME? | J17: {=_xll.BDP("AQ417830 Corp","YL018")} -> #NAME? | K17: {=_xll.BDP("AQ417830 Corp","YL016")} -> #NAME? | L17: {=_xll.BDP("AQ417830 Corp","PR004")} -> #NAME? | M17: {=_xll.BDP("AQ417830 Corp","PR002")} -> #NAME? | N17: {=_xll.BDP("AQ417830 Corp","ID028")} -> #NAME? | O17: {=_xll.BDP("AQ417830 Corp","ID005")} -> #NAME? | P17: {=_xll.BDP(A17,"RA007")} -> #NAME? | Q17: {=_xll.BDP(A17,"DS219")} -> #NAME? | R17: {=_xll.BDP(A17,"DS040")} -> #NAME? | S17: =(F17-TODAY())/365.25 -> #NAME? | T17: =S17-ROUNDDOWN(S17,0) -> #NAME? | U17: =DATE(2026,MONTH(TODAY()),DAY(F17))>DATEVALUE(R17) -> #NAME?
A18: AR545005 Corp | B18: {=_xll.BDP("AR545005 Corp","DS520")} -> #NAME? | C18: {=_xll.BDP("AR545005 Corp","DS001")} -> #NAME? | D18: {=_xll.BDP("AR545005 Corp","DS458")} -> #NAME? | E18: {=_xll.BDP("AR545005 Corp","DS004")} -> #NAME? | F18: {=_xll.BDP("AR545005 Corp","DS035")} -> #NAME? | G18: {=_xll.BDP("AR545005 Corp","DS086")} -> #NAME? | H18: {=_xll.BDP("AR545005 Corp","DS034")} -> #NAME? | I18: {=_xll.BDP("AR545005 Corp","DS033")} -> #NAME? | J18: {=_xll.BDP("AR545005 Corp","YL018")} -> #NAME? | K18: {=_xll.BDP("AR545005 Corp","YL016")} -> #NAME? | L18: {=_xll.BDP("AR545005 Corp","PR004")} -> #NAME? | M18: {=_xll.BDP("AR545005 Corp","PR002")} -> #NAME? | N18: {=_xll.BDP("AR545005 Corp","ID028")} -> #NAME? | O18: {=_xll.BDP("AR545005 Corp","ID005")} -> #NAME? | P18: {=_xll.BDP(A18,"RA007")} -> #NAME? | Q18: {=_xll.BDP(A18,"DS219")} -> #NAME? | R18: {=_xll.BDP(A18,"DS040")} -> #NAME? | S18: =(F18-TODAY())/365.25 -> #NAME? | T18: =S18-ROUNDDOWN(S18,0) -> #NAME? | U18: =DATE(2026,MONTH(TODAY()),DAY(F18))>DATEVALUE(R18) -> #NAME?
A19: AR620065 Corp | B19: {=_xll.BDP("AR620065 Corp","DS520")} -> #NAME? | C19: {=_xll.BDP("AR620065 Corp","DS001")} -> #NAME? | D19: {=_xll.BDP("AR620065 Corp","DS458")} -> #NAME? | E19: {=_xll.BDP("AR620065 Corp","DS004")} -> #NAME? | F19: {=_xll.BDP("AR620065 Corp","DS035")} -> #NAME? | G19: {=_xll.BDP("AR620065 Corp","DS086")} -> #NAME? | H19: {=_xll.BDP("AR620065 Corp","DS034")} -> #NAME? | I19: {=_xll.BDP("AR620065 Corp","DS033")} -> #NAME? | J19: {=_xll.BDP("AR620065 Corp","YL018")} -> #NAME? | K19: {=_xll.BDP("AR620065 Corp","YL016")} -> #NAME? | L19: {=_xll.BDP("AR620065 Corp","PR004")} -> #NAME? | M19: {=_xll.BDP("AR620065 Corp","PR002")} -> #NAME? | N19: {=_xll.BDP("AR620065 Corp","ID028")} -> #NAME? | O19: {=_xll.BDP("AR620065 Corp","ID005")} -> #NAME? | P19: {=_xll.BDP(A19,"RA007")} -> #NAME? | Q19: {=_xll.BDP(A19,"DS219")} -> #NAME? | R19: {=_xll.BDP(A19,"DS040")} -> #NAME? | S19: =(F19-TODAY())/365.25 -> #NAME? | T19: =S19-ROUNDDOWN(S19,0) -> #NAME? | U19: =DATE(2026,MONTH(TODAY()),DAY(F19))>DATEVALUE(R19) -> #NAME?
A20: AR775109 Corp | B20: {=_xll.BDP("AR775109 Corp","DS520")} -> #NAME? | C20: {=_xll.BDP("AR775109 Corp","DS001")} -> #NAME? | D20: {=_xll.BDP("AR775109 Corp","DS458")} -> #NAME? | E20: {=_xll.BDP("AR775109 Corp","DS004")} -> #NAME? | F20: {=_xll.BDP("AR775109 Corp","DS035")} -> #NAME? | G20: {=_xll.BDP("AR775109 Corp","DS086")} -> #NAME? | H20: {=_xll.BDP("AR775109 Corp","DS034")} -> #NAME? | I20: {=_xll.BDP("AR775109 Corp","DS033")} -> #NAME? | J20: {=_xll.BDP("AR775109 Corp","YL018")} -> #NAME? | K20: {=_xll.BDP("AR775109 Corp","YL016")} -> #NAME? | L20: {=_xll.BDP("AR775109 Corp","PR004")} -> #NAME? | M20: {=_xll.BDP("AR775109 Corp","PR002")} -> #NAME? | N20: {=_xll.BDP("AR775109 Corp","ID028")} -> #NAME? | O20: {=_xll.BDP("AR775109 Corp","ID005")} -> #NAME? | P20: {=_xll.BDP(A20,"RA007")} -> #NAME? | Q20: {=_xll.BDP(A20,"DS219")} -> #NAME? | R20: {=_xll.BDP(A20,"DS040")} -> #NAME? | S20: =(F20-TODAY())/365.25 -> #NAME? | T20: =S20-ROUNDDOWN(S20,0) -> #NAME? | U20: =DATE(2026,MONTH(TODAY()),DAY(F20))>DATEVALUE(R20) -> #NAME?
A21: AS843222 Corp | B21: {=_xll.BDP("AS843222 Corp","DS520")} -> #NAME? | C21: {=_xll.BDP("AS843222 Corp","DS001")} -> #NAME? | D21: {=_xll.BDP("AS843222 Corp","DS458")} -> #NAME? | E21: {=_xll.BDP("AS843222 Corp","DS004")} -> #NAME? | F21: {=_xll.BDP("AS843222 Corp","DS035")} -> #NAME? | G21: {=_xll.BDP("AS843222 Corp","DS086")} -> #NAME? | H21: {=_xll.BDP("AS843222 Corp","DS034")} -> #NAME? | I21: {=_xll.BDP("AS843222 Corp","DS033")} -> #NAME? | J21: {=_xll.BDP("AS843222 Corp","YL018")} -> #NAME? | K21: {=_xll.BDP("AS843222 Corp","YL016")} -> #NAME? | L21: {=_xll.BDP("AS843222 Corp","PR004")} -> #NAME? | M21: {=_xll.BDP("AS843222 Corp","PR002")} -> #NAME? | N21: {=_xll.BDP("AS843222 Corp","ID028")} -> #NAME? | O21: {=_xll.BDP("AS843222 Corp","ID005")} -> #NAME? | P21: {=_xll.BDP(A21,"RA007")} -> #NAME? | Q21: {=_xll.BDP(A21,"DS219")} -> #NAME? | R21: {=_xll.BDP(A21,"DS040")} -> #NAME? | S21: =(F21-TODAY())/365.25 -> #NAME? | T21: =S21-ROUNDDOWN(S21,0) -> #NAME? | U21: =DATE(2026,MONTH(TODAY()),DAY(F21))>DATEVALUE(R21) -> #NAME?
A22: AT427280 Corp | B22: {=_xll.BDP("AT427280 Corp","DS520")} -> #NAME? | C22: {=_xll.BDP("AT427280 Corp","DS001")} -> #NAME? | D22: {=_xll.BDP("AT427280 Corp","DS458")} -> #NAME? | E22: {=_xll.BDP("AT427280 Corp","DS004")} -> #NAME? | F22: {=_xll.BDP("AT427280 Corp","DS035")} -> #NAME? | G22: {=_xll.BDP("AT427280 Corp","DS086")} -> #NAME? | H22: {=_xll.BDP("AT427280 Corp","DS034")} -> #NAME? | I22: {=_xll.BDP("AT427280 Corp","DS033")} -> #NAME? | J22: {=_xll.BDP("AT427280 Corp","YL018")} -> #NAME? | K22: {=_xll.BDP("AT427280 Corp","YL016")} -> #NAME? | L22: {=_xll.BDP("AT427280 Corp","PR004")} -> #NAME? | M22: {=_xll.BDP("AT427280 Corp","PR002")} -> #NAME? | N22: {=_xll.BDP("AT427280 Corp","ID028")} -> #NAME? | O22: {=_xll.BDP("AT427280 Corp","ID005")} -> #NAME? | P22: {=_xll.BDP(A22,"RA007")} -> #NAME? | Q22: {=_xll.BDP(A22,"DS219")} -> #NAME? | R22: {=_xll.BDP(A22,"DS040")} -> #NAME? | S22: =(F22-TODAY())/365.25 -> #NAME? | T22: =S22-ROUNDDOWN(S22,0) -> #NAME? | U22: =DATE(2026,MONTH(TODAY()),DAY(F22))>DATEVALUE(R22) -> #NAME?
A23: AT476518 Corp | B23: {=_xll.BDP("AT476518 Corp","DS520")} -> #NAME? | C23: {=_xll.BDP("AT476518 Corp","DS001")} -> #NAME? | D23: {=_xll.BDP("AT476518 Corp","DS458")} -> #NAME? | E23: {=_xll.BDP("AT476518 Corp","DS004")} -> #NAME? | F23: {=_xll.BDP("AT476518 Corp","DS035")} -> #NAME? | G23: {=_xll.BDP("AT476518 Corp","DS086")} -> #NAME? | H23: {=_xll.BDP("AT476518 Corp","DS034")} -> #NAME? | I23: {=_xll.BDP("AT476518 Corp","DS033")} -> #NAME? | J23: {=_xll.BDP("AT476518 Corp","YL018")} -> #NAME? | K23: {=_xll.BDP("AT476518 Corp","YL016")} -> #NAME? | L23: {=_xll.BDP("AT476518 Corp","PR004")} -> #NAME? | M23: {=_xll.BDP("AT476518 Corp","PR002")} -> #NAME? | N23: {=_xll.BDP("AT476518 Corp","ID028")} -> #NAME? | O23: {=_xll.BDP("AT476518 Corp","ID005")} -> #NAME? | P23: {=_xll.BDP(A23,"RA007")} -> #NAME? | Q23: {=_xll.BDP(A23,"DS219")} -> #NAME? | R23: {=_xll.BDP(A23,"DS040")} -> #NAME? | S23: =(F23-TODAY())/365.25 -> #NAME? | T23: =S23-ROUNDDOWN(S23,0) -> #NAME? | U23: =DATE(2026,MONTH(TODAY()),DAY(F23))>DATEVALUE(R23) -> #NAME?
A24: AT578853 Corp | B24: {=_xll.BDP("AT578853 Corp","DS520")} -> #NAME? | C24: {=_xll.BDP("AT578853 Corp","DS001")} -> #NAME? | D24: {=_xll.BDP("AT578853 Corp","DS458")} -> #NAME? | E24: {=_xll.BDP("AT578853 Corp","DS004")} -> #NAME? | F24: {=_xll.BDP("AT578853 Corp","DS035")} -> #NAME? | G24: {=_xll.BDP("AT578853 Corp","DS086")} -> #NAME? | H24: {=_xll.BDP("AT578853 Corp","DS034")} -> #NAME? | I24: {=_xll.BDP("AT578853 Corp","DS033")} -> #NAME? | J24: {=_xll.BDP("AT578853 Corp","YL018")} -> #NAME? | K24: {=_xll.BDP("AT578853 Corp","YL016")} -> #NAME? | L24: {=_xll.BDP("AT578853 Corp","PR004")} -> #NAME? | M24: {=_xll.BDP("AT578853 Corp","PR002")} -> #NAME? | N24: {=_xll.BDP("AT578853 Corp","ID028")} -> #NAME? | O24: {=_xll.BDP("AT578853 Corp","ID005")} -> #NAME? | P24: {=_xll.BDP(A24,"RA007")} -> #NAME? | Q24: {=_xll.BDP(A24,"DS219")} -> #NAME? | R24: {=_xll.BDP(A24,"DS040")} -> #NAME? | S24: =(F24-TODAY())/365.25 -> #NAME? | T24: =S24-ROUNDDOWN(S24,0) -> #NAME? | U24: =DATE(2026,MONTH(TODAY()),DAY(F24))>DATEVALUE(R24) -> #NAME?
A25: AU788839 Corp | B25: {=_xll.BDP("AU788839 Corp","DS520")} -> #NAME? | C25: {=_xll.BDP("AU788839 Corp","DS001")} -> #NAME? | D25: {=_xll.BDP("AU788839 Corp","DS458")} -> #NAME? | E25: {=_xll.BDP("AU788839 Corp","DS004")} -> #NAME? | F25: {=_xll.BDP("AU788839 Corp","DS035")} -> #NAME? | G25: {=_xll.BDP("AU788839 Corp","DS086")} -> #NAME? | H25: {=_xll.BDP("AU788839 Corp","DS034")} -> #NAME? | I25: {=_xll.BDP("AU788839 Corp","DS033")} -> #NAME? | J25: {=_xll.BDP("AU788839 Corp","YL018")} -> #NAME? | K25: {=_xll.BDP("AU788839 Corp","YL016")} -> #NAME? | L25: {=_xll.BDP("AU788839 Corp","PR004")} -> #NAME? | M25: {=_xll.BDP("AU788839 Corp","PR002")} -> #NAME? | N25: {=_xll.BDP("AU788839 Corp","ID028")} -> #NAME? | O25: {=_xll.BDP("AU788839 Corp","ID005")} -> #NAME? | P25: {=_xll.BDP(A25,"RA007")} -> #NAME? | Q25: {=_xll.BDP(A25,"DS219")} -> #NAME? | R25: {=_xll.BDP(A25,"DS040")} -> #NAME? | S25: =(F25-TODAY())/365.25 -> #NAME? | T25: =S25-ROUNDDOWN(S25,0) -> #NAME? | U25: =DATE(2026,MONTH(TODAY()),DAY(F25))>DATEVALUE(R25) -> #NAME?
A26: AU951286 Corp | B26: {=_xll.BDP("AU951286 Corp","DS520")} -> #NAME? | C26: {=_xll.BDP("AU951286 Corp","DS001")} -> #NAME? | D26: {=_xll.BDP("AU951286 Corp","DS458")} -> #NAME? | E26: {=_xll.BDP("AU951286 Corp","DS004")} -> #NAME? | F26: {=_xll.BDP("AU951286 Corp","DS035")} -> #NAME? | G26: {=_xll.BDP("AU951286 Corp","DS086")} -> #NAME? | H26: {=_xll.BDP("AU951286 Corp","DS034")} -> #NAME? | I26: {=_xll.BDP("AU951286 Corp","DS033")} -> #NAME? | J26: {=_xll.BDP("AU951286 Corp","YL018")} -> #NAME? | K26: {=_xll.BDP("AU951286 Corp","YL016")} -> #NAME? | L26: {=_xll.BDP("AU951286 Corp","PR004")} -> #NAME? | M26: {=_xll.BDP("AU951286 Corp","PR002")} -> #NAME? | N26: {=_xll.BDP("AU951286 Corp","ID028")} -> #NAME? | O26: {=_xll.BDP("AU951286 Corp","ID005")} -> #NAME? | P26: {=_xll.BDP(A26,"RA007")} -> #NAME? | Q26: {=_xll.BDP(A26,"DS219")} -> #NAME? | R26: {=_xll.BDP(A26,"DS040")} -> #NAME? | S26: =(F26-TODAY())/365.25 -> #NAME? | T26: =S26-ROUNDDOWN(S26,0) -> #NAME? | U26: =DATE(2026,MONTH(TODAY()),DAY(F26))>DATEVALUE(R26) -> #NAME?
A27: AV122750 Corp | B27: {=_xll.BDP("AV122750 Corp","DS520")} -> #NAME? | C27: {=_xll.BDP("AV122750 Corp","DS001")} -> #NAME? | D27: {=_xll.BDP("AV122750 Corp","DS458")} -> #NAME? | E27: {=_xll.BDP("AV122750 Corp","DS004")} -> #NAME? | F27: {=_xll.BDP("AV122750 Corp","DS035")} -> #NAME? | G27: {=_xll.BDP("AV122750 Corp","DS086")} -> #NAME? | H27: {=_xll.BDP("AV122750 Corp","DS034")} -> #NAME? | I27: {=_xll.BDP("AV122750 Corp","DS033")} -> #NAME? | J27: {=_xll.BDP("AV122750 Corp","YL018")} -> #NAME? | K27: {=_xll.BDP("AV122750 Corp","YL016")} -> #NAME? | L27: {=_xll.BDP("AV122750 Corp","PR004")} -> #NAME? | M27: {=_xll.BDP("AV122750 Corp","PR002")} -> #NAME? | N27: {=_xll.BDP("AV122750 Corp","ID028")} -> #NAME? | O27: {=_xll.BDP("AV122750 Corp","ID005")} -> #NAME? | P27: {=_xll.BDP(A27,"RA007")} -> #NAME? | Q27: {=_xll.BDP(A27,"DS219")} -> #NAME? | R27: {=_xll.BDP(A27,"DS040")} -> #NAME? | S27: =(F27-TODAY())/365.25 -> #NAME? | T27: =S27-ROUNDDOWN(S27,0) -> #NAME? | U27: =DATE(2026,MONTH(TODAY()),DAY(F27))>DATEVALUE(R27) -> #NAME?
A28: AW566680 Corp | B28: {=_xll.BDP("AW566680 Corp","DS520")} -> #NAME? | C28: {=_xll.BDP("AW566680 Corp","DS001")} -> #NAME? | D28: {=_xll.BDP("AW566680 Corp","DS458")} -> #NAME? | E28: {=_xll.BDP("AW566680 Corp","DS004")} -> #NAME? | F28: {=_xll.BDP("AW566680 Corp","DS035")} -> #NAME? | G28: {=_xll.BDP("AW566680 Corp","DS086")} -> #NAME? | H28: {=_xll.BDP("AW566680 Corp","DS034")} -> #NAME? | I28: {=_xll.BDP("AW566680 Corp","DS033")} -> #NAME? | J28: {=_xll.BDP("AW566680 Corp","YL018")} -> #NAME? | K28: {=_xll.BDP("AW566680 Corp","YL016")} -> #NAME? | L28: {=_xll.BDP("AW566680 Corp","PR004")} -> #NAME? | M28: {=_xll.BDP("AW566680 Corp","PR002")} -> #NAME? | N28: {=_xll.BDP("AW566680 Corp","ID028")} -> #NAME? | O28: {=_xll.BDP("AW566680 Corp","ID005")} -> #NAME? | P28: {=_xll.BDP(A28,"RA007")} -> #NAME? | Q28: {=_xll.BDP(A28,"DS219")} -> #NAME? | R28: {=_xll.BDP(A28,"DS040")} -> #NAME? | S28: =(F28-TODAY())/365.25 -> #NAME? | T28: =S28-ROUNDDOWN(S28,0) -> #NAME? | U28: =DATE(2026,MONTH(TODAY()),DAY(F28))>DATEVALUE(R28) -> #NAME?
A29: AW634174 Corp | B29: {=_xll.BDP("AW634174 Corp","DS520")} -> #NAME? | C29: {=_xll.BDP("AW634174 Corp","DS001")} -> #NAME? | D29: {=_xll.BDP("AW634174 Corp","DS458")} -> #NAME? | E29: {=_xll.BDP("AW634174 Corp","DS004")} -> #NAME? | F29: {=_xll.BDP("AW634174 Corp","DS035")} -> #NAME? | G29: {=_xll.BDP("AW634174 Corp","DS086")} -> #NAME? | H29: {=_xll.BDP("AW634174 Corp","DS034")} -> #NAME? | I29: {=_xll.BDP("AW634174 Corp","DS033")} -> #NAME? | J29: {=_xll.BDP("AW634174 Corp","YL018")} -> #NAME? | K29: {=_xll.BDP("AW634174 Corp","YL016")} -> #NAME? | L29: {=_xll.BDP("AW634174 Corp","PR004")} -> #NAME? | M29: {=_xll.BDP("AW634174 Corp","PR002")} -> #NAME? | N29: {=_xll.BDP("AW634174 Corp","ID028")} -> #NAME? | O29: {=_xll.BDP("AW634174 Corp","ID005")} -> #NAME? | P29: {=_xll.BDP(A29,"RA007")} -> #NAME? | Q29: {=_xll.BDP(A29,"DS219")} -> #NAME? | R29: {=_xll.BDP(A29,"DS040")} -> #NAME? | S29: =(F29-TODAY())/365.25 -> #NAME? | T29: =S29-ROUNDDOWN(S29,0) -> #NAME? | U29: =DATE(2026,MONTH(TODAY()),DAY(F29))>DATEVALUE(R29) -> #NAME?
A30: AW892884 Corp | B30: {=_xll.BDP("AW892884 Corp","DS520")} -> #NAME? | C30: {=_xll.BDP("AW892884 Corp","DS001")} -> #NAME? | D30: {=_xll.BDP("AW892884 Corp","DS458")} -> #NAME? | E30: {=_xll.BDP("AW892884 Corp","DS004")} -> #NAME? | F30: {=_xll.BDP("AW892884 Corp","DS035")} -> #NAME? | G30: {=_xll.BDP("AW892884 Corp","DS086")} -> #NAME? | H30: {=_xll.BDP("AW892884 Corp","DS034")} -> #NAME? | I30: {=_xll.BDP("AW892884 Corp","DS033")} -> #NAME? | J30: {=_xll.BDP("AW892884 Corp","YL018")} -> #NAME? | K30: {=_xll.BDP("AW892884 Corp","YL016")} -> #NAME? | L30: {=_xll.BDP("AW892884 Corp","PR004")} -> #NAME? | M30: {=_xll.BDP("AW892884 Corp","PR002")} -> #NAME? | N30: {=_xll.BDP("AW892884 Corp","ID028")} -> #NAME? | O30: {=_xll.BDP("AW892884 Corp","ID005")} -> #NAME? | P30: {=_xll.BDP(A30,"RA007")} -> #NAME? | Q30: {=_xll.BDP(A30,"DS219")} -> #NAME? | R30: {=_xll.BDP(A30,"DS040")} -> #NAME? | S30: =(F30-TODAY())/365.25 -> #NAME? | T30: =S30-ROUNDDOWN(S30,0) -> #NAME? | U30: =DATE(2026,MONTH(TODAY()),DAY(F30))>DATEVALUE(R30) -> #NAME?
A31: AX991345 Corp | B31: {=_xll.BDP("AX991345 Corp","DS520")} -> #NAME? | C31: {=_xll.BDP("AX991345 Corp","DS001")} -> #NAME? | D31: {=_xll.BDP("AX991345 Corp","DS458")} -> #NAME? | E31: {=_xll.BDP("AX991345 Corp","DS004")} -> #NAME? | F31: {=_xll.BDP("AX991345 Corp","DS035")} -> #NAME? | G31: {=_xll.BDP("AX991345 Corp","DS086")} -> #NAME? | H31: {=_xll.BDP("AX991345 Corp","DS034")} -> #NAME? | I31: {=_xll.BDP("AX991345 Corp","DS033")} -> #NAME? | J31: {=_xll.BDP("AX991345 Corp","YL018")} -> #NAME? | K31: {=_xll.BDP("AX991345 Corp","YL016")} -> #NAME? | L31: {=_xll.BDP("AX991345 Corp","PR004")} -> #NAME? | M31: {=_xll.BDP("AX991345 Corp","PR002")} -> #NAME? | N31: {=_xll.BDP("AX991345 Corp","ID028")} -> #NAME? | O31: {=_xll.BDP("AX991345 Corp","ID005")} -> #NAME? | P31: {=_xll.BDP(A31,"RA007")} -> #NAME? | Q31: {=_xll.BDP(A31,"DS219")} -> #NAME? | R31: {=_xll.BDP(A31,"DS040")} -> #NAME? | S31: =(F31-TODAY())/365.25 -> #NAME? | T31: =S31-ROUNDDOWN(S31,0) -> #NAME? | U31: =DATE(2026,MONTH(TODAY()),DAY(F31))>DATEVALUE(R31) -> #NAME?
A32: AZ459860 Corp | B32: {=_xll.BDP("AZ459860 Corp","DS520")} -> #NAME? | C32: {=_xll.BDP("AZ459860 Corp","DS001")} -> #NAME? | D32: {=_xll.BDP("AZ459860 Corp","DS458")} -> #NAME? | E32: {=_xll.BDP("AZ459860 Corp","DS004")} -> #NAME? | F32: {=_xll.BDP("AZ459860 Corp","DS035")} -> #NAME? | G32: {=_xll.BDP("AZ459860 Corp","DS086")} -> #NAME? | H32: {=_xll.BDP("AZ459860 Corp","DS034")} -> #NAME? | I32: {=_xll.BDP("AZ459860 Corp","DS033")} -> #NAME? | J32: {=_xll.BDP("AZ459860 Corp","YL018")} -> #NAME? | K32: {=_xll.BDP("AZ459860 Corp","YL016")} -> #NAME? | L32: {=_xll.BDP("AZ459860 Corp","PR004")} -> #NAME? | M32: {=_xll.BDP("AZ459860 Corp","PR002")} -> #NAME? | N32: {=_xll.BDP("AZ459860 Corp","ID028")} -> #NAME? | O32: {=_xll.BDP("AZ459860 Corp","ID005")} -> #NAME? | P32: {=_xll.BDP(A32,"RA007")} -> #NAME? | Q32: {=_xll.BDP(A32,"DS219")} -> #NAME? | R32: {=_xll.BDP(A32,"DS040")} -> #NAME? | S32: =(F32-TODAY())/365.25 -> #NAME? | T32: =S32-ROUNDDOWN(S32,0) -> #NAME? | U32: =DATE(2026,MONTH(TODAY()),DAY(F32))>DATEVALUE(R32) -> #NAME?
A33: AZ527231 Corp | B33: {=_xll.BDP("AZ527231 Corp","DS520")} -> #NAME? | C33: {=_xll.BDP("AZ527231 Corp","DS001")} -> #NAME? | D33: {=_xll.BDP("AZ527231 Corp","DS458")} -> #NAME? | E33: {=_xll.BDP("AZ527231 Corp","DS004")} -> #NAME? | F33: {=_xll.BDP("AZ527231 Corp","DS035")} -> #NAME? | G33: {=_xll.BDP("AZ527231 Corp","DS086")} -> #NAME? | H33: {=_xll.BDP("AZ527231 Corp","DS034")} -> #NAME? | I33: {=_xll.BDP("AZ527231 Corp","DS033")} -> #NAME? | J33: {=_xll.BDP("AZ527231 Corp","YL018")} -> #NAME? | K33: {=_xll.BDP("AZ527231 Corp","YL016")} -> #NAME? | L33: {=_xll.BDP("AZ527231 Corp","PR004")} -> #NAME? | M33: {=_xll.BDP("AZ527231 Corp","PR002")} -> #NAME? | N33: {=_xll.BDP("AZ527231 Corp","ID028")} -> #NAME? | O33: {=_xll.BDP("AZ527231 Corp","ID005")} -> #NAME? | P33: {=_xll.BDP(A33,"RA007")} -> #NAME? | Q33: {=_xll.BDP(A33,"DS219")} -> #NAME? | R33: {=_xll.BDP(A33,"DS040")} -> #NAME? | S33: =(F33-TODAY())/365.25 -> #NAME? | T33: =S33-ROUNDDOWN(S33,0) -> #NAME? | U33: =DATE(2026,MONTH(TODAY()),DAY(F33))>DATEVALUE(R33) -> #NAME?
A34: AZ694472 Corp | B34: {=_xll.BDP("AZ694472 Corp","DS520")} -> #NAME? | C34: {=_xll.BDP("AZ694472 Corp","DS001")} -> #NAME? | D34: {=_xll.BDP("AZ694472 Corp","DS458")} -> #NAME? | E34: {=_xll.BDP("AZ694472 Corp","DS004")} -> #NAME? | F34: {=_xll.BDP("AZ694472 Corp","DS035")} -> #NAME? | G34: {=_xll.BDP("AZ694472 Corp","DS086")} -> #NAME? | H34: {=_xll.BDP("AZ694472 Corp","DS034")} -> #NAME? | I34: {=_xll.BDP("AZ694472 Corp","DS033")} -> #NAME? | J34: {=_xll.BDP("AZ694472 Corp","YL018")} -> #NAME? | K34: {=_xll.BDP("AZ694472 Corp","YL016")} -> #NAME? | L34: {=_xll.BDP("AZ694472 Corp","PR004")} -> #NAME? | M34: {=_xll.BDP("AZ694472 Corp","PR002")} -> #NAME? | N34: {=_xll.BDP("AZ694472 Corp","ID028")} -> #NAME? | O34: {=_xll.BDP("AZ694472 Corp","ID005")} -> #NAME? | P34: {=_xll.BDP(A34,"RA007")} -> #NAME? | Q34: {=_xll.BDP(A34,"DS219")} -> #NAME? | R34: {=_xll.BDP(A34,"DS040")} -> #NAME? | S34: =(F34-TODAY())/365.25 -> #NAME? | T34: =S34-ROUNDDOWN(S34,0) -> #NAME? | U34: =DATE(2026,MONTH(TODAY()),DAY(F34))>DATEVALUE(R34) -> #NAME?
A35: BH527948 Corp | B35: {=_xll.BDP("BH527948 Corp","DS520")} -> #NAME? | C35: {=_xll.BDP("BH527948 Corp","DS001")} -> #NAME? | D35: {=_xll.BDP("BH527948 Corp","DS458")} -> #NAME? | E35: {=_xll.BDP("BH527948 Corp","DS004")} -> #NAME? | F35: {=_xll.BDP("BH527948 Corp","DS035")} -> #NAME? | G35: {=_xll.BDP("BH527948 Corp","DS086")} -> #NAME? | H35: {=_xll.BDP("BH527948 Corp","DS034")} -> #NAME? | I35: {=_xll.BDP("BH527948 Corp","DS033")} -> #NAME? | J35: {=_xll.BDP("BH527948 Corp","YL018")} -> #NAME? | K35: {=_xll.BDP("BH527948 Corp","YL016")} -> #NAME? | L35: {=_xll.BDP("BH527948 Corp","PR004")} -> #NAME? | M35: {=_xll.BDP("BH527948 Corp","PR002")} -> #NAME? | N35: {=_xll.BDP("BH527948 Corp","ID028")} -> #NAME? | O35: {=_xll.BDP("BH527948 Corp","ID005")} -> #NAME? | P35: {=_xll.BDP(A35,"RA007")} -> #NAME? | Q35: {=_xll.BDP(A35,"DS219")} -> #NAME? | R35: {=_xll.BDP(A35,"DS040")} -> #NAME? | S35: =(F35-TODAY())/365.25 -> #NAME? | T35: =S35-ROUNDDOWN(S35,0) -> #NAME? | U35: =DATE(2026,MONTH(TODAY()),DAY(F35))>DATEVALUE(R35) -> #NAME?
A36: BH620692 Corp | B36: {=_xll.BDP("BH620692 Corp","DS520")} -> #NAME? | C36: {=_xll.BDP("BH620692 Corp","DS001")} -> #NAME? | D36: {=_xll.BDP("BH620692 Corp","DS458")} -> #NAME? | E36: {=_xll.BDP("BH620692 Corp","DS004")} -> #NAME? | F36: {=_xll.BDP("BH620692 Corp","DS035")} -> #NAME? | G36: {=_xll.BDP("BH620692 Corp","DS086")} -> #NAME? | H36: {=_xll.BDP("BH620692 Corp","DS034")} -> #NAME? | I36: {=_xll.BDP("BH620692 Corp","DS033")} -> #NAME? | J36: {=_xll.BDP("BH620692 Corp","YL018")} -> #NAME? | K36: {=_xll.BDP("BH620692 Corp","YL016")} -> #NAME? | L36: {=_xll.BDP("BH620692 Corp","PR004")} -> #NAME? | M36: {=_xll.BDP("BH620692 Corp","PR002")} -> #NAME? | N36: {=_xll.BDP("BH620692 Corp","ID028")} -> #NAME? | O36: {=_xll.BDP("BH620692 Corp","ID005")} -> #NAME? | P36: {=_xll.BDP(A36,"RA007")} -> #NAME? | Q36: {=_xll.BDP(A36,"DS219")} -> #NAME? | R36: {=_xll.BDP(A36,"DS040")} -> #NAME? | S36: =(F36-TODAY())/365.25 -> #NAME? | T36: =S36-ROUNDDOWN(S36,0) -> #NAME? | U36: =DATE(2026,MONTH(TODAY()),DAY(F36))>DATEVALUE(R36) -> #NAME?
A37: BI018471 Corp | B37: {=_xll.BDP("BI018471 Corp","DS520")} -> #NAME? | C37: {=_xll.BDP("BI018471 Corp","DS001")} -> #NAME? | D37: {=_xll.BDP("BI018471 Corp","DS458")} -> #NAME? | E37: {=_xll.BDP("BI018471 Corp","DS004")} -> #NAME? | F37: {=_xll.BDP("BI018471 Corp","DS035")} -> #NAME? | G37: {=_xll.BDP("BI018471 Corp","DS086")} -> #NAME? | H37: {=_xll.BDP("BI018471 Corp","DS034")} -> #NAME? | I37: {=_xll.BDP("BI018471 Corp","DS033")} -> #NAME? | J37: {=_xll.BDP("BI018471 Corp","YL018")} -> #NAME? | K37: {=_xll.BDP("BI018471 Corp","YL016")} -> #NAME? | L37: {=_xll.BDP("BI018471 Corp","PR004")} -> #NAME? | M37: {=_xll.BDP("BI018471 Corp","PR002")} -> #NAME? | N37: {=_xll.BDP("BI018471 Corp","ID028")} -> #NAME? | O37: {=_xll.BDP("BI018471 Corp","ID005")} -> #NAME? | P37: {=_xll.BDP(A37,"RA007")} -> #NAME? | Q37: {=_xll.BDP(A37,"DS219")} -> #NAME? | R37: {=_xll.BDP(A37,"DS040")} -> #NAME? | S37: =(F37-TODAY())/365.25 -> #NAME? | T37: =S37-ROUNDDOWN(S37,0) -> #NAME? | U37: =DATE(2026,MONTH(TODAY()),DAY(F37))>DATEVALUE(R37) -> #NAME?
A38: BJ706274 Corp | B38: {=_xll.BDP("BJ706274 Corp","DS520")} -> #NAME? | C38: {=_xll.BDP("BJ706274 Corp","DS001")} -> #NAME? | D38: {=_xll.BDP("BJ706274 Corp","DS458")} -> #NAME? | E38: {=_xll.BDP("BJ706274 Corp","DS004")} -> #NAME? | F38: {=_xll.BDP("BJ706274 Corp","DS035")} -> #NAME? | G38: {=_xll.BDP("BJ706274 Corp","DS086")} -> #NAME? | H38: {=_xll.BDP("BJ706274 Corp","DS034")} -> #NAME? | I38: {=_xll.BDP("BJ706274 Corp","DS033")} -> #NAME? | J38: {=_xll.BDP("BJ706274 Corp","YL018")} -> #NAME? | K38: {=_xll.BDP("BJ706274 Corp","YL016")} -> #NAME? | L38: {=_xll.BDP("BJ706274 Corp","PR004")} -> #NAME? | M38: {=_xll.BDP("BJ706274 Corp","PR002")} -> #NAME? | N38: {=_xll.BDP("BJ706274 Corp","ID028")} -> #NAME? | O38: {=_xll.BDP("BJ706274 Corp","ID005")} -> #NAME? | P38: {=_xll.BDP(A38,"RA007")} -> #NAME? | Q38: {=_xll.BDP(A38,"DS219")} -> #NAME? | R38: {=_xll.BDP(A38,"DS040")} -> #NAME? | S38: =(F38-TODAY())/365.25 -> #NAME? | T38: =S38-ROUNDDOWN(S38,0) -> #NAME? | U38: =DATE(2026,MONTH(TODAY()),DAY(F38))>DATEVALUE(R38) -> #NAME?
A39: BK340998 Corp | B39: {=_xll.BDP("BK340998 Corp","DS520")} -> #NAME? | C39: {=_xll.BDP("BK340998 Corp","DS001")} -> #NAME? | D39: {=_xll.BDP("BK340998 Corp","DS458")} -> #NAME? | E39: {=_xll.BDP("BK340998 Corp","DS004")} -> #NAME? | F39: {=_xll.BDP("BK340998 Corp","DS035")} -> #NAME? | G39: {=_xll.BDP("BK340998 Corp","DS086")} -> #NAME? | H39: {=_xll.BDP("BK340998 Corp","DS034")} -> #NAME? | I39: {=_xll.BDP("BK340998 Corp","DS033")} -> #NAME? | J39: {=_xll.BDP("BK340998 Corp","YL018")} -> #NAME? | K39: {=_xll.BDP("BK340998 Corp","YL016")} -> #NAME? | L39: {=_xll.BDP("BK340998 Corp","PR004")} -> #NAME? | M39: {=_xll.BDP("BK340998 Corp","PR002")} -> #NAME? | N39: {=_xll.BDP("BK340998 Corp","ID028")} -> #NAME? | O39: {=_xll.BDP("BK340998 Corp","ID005")} -> #NAME? | P39: {=_xll.BDP(A39,"RA007")} -> #NAME? | Q39: {=_xll.BDP(A39,"DS219")} -> #NAME? | R39: {=_xll.BDP(A39,"DS040")} -> #NAME? | S39: =(F39-TODAY())/365.25 -> #NAME? | T39: =S39-ROUNDDOWN(S39,0) -> #NAME? | U39: =DATE(2026,MONTH(TODAY()),DAY(F39))>DATEVALUE(R39) -> #NAME?
A40: BK411989 Corp | B40: {=_xll.BDP("BK411989 Corp","DS520")} -> #NAME? | C40: {=_xll.BDP("BK411989 Corp","DS001")} -> #NAME? | D40: {=_xll.BDP("BK411989 Corp","DS458")} -> #NAME? | E40: {=_xll.BDP("BK411989 Corp","DS004")} -> #NAME? | F40: {=_xll.BDP("BK411989 Corp","DS035")} -> #NAME? | G40: {=_xll.BDP("BK411989 Corp","DS086")} -> #NAME? | H40: {=_xll.BDP("BK411989 Corp","DS034")} -> #NAME? | I40: {=_xll.BDP("BK411989 Corp","DS033")} -> #NAME? | J40: {=_xll.BDP("BK411989 Corp","YL018")} -> #NAME? | K40: {=_xll.BDP("BK411989 Corp","YL016")} -> #NAME? | L40: {=_xll.BDP("BK411989 Corp","PR004")} -> #NAME? | M40: {=_xll.BDP("BK411989 Corp","PR002")} -> #NAME? | N40: {=_xll.BDP("BK411989 Corp","ID028")} -> #NAME? | O40: {=_xll.BDP("BK411989 Corp","ID005")} -> #NAME? | P40: {=_xll.BDP(A40,"RA007")} -> #NAME? | Q40: {=_xll.BDP(A40,"DS219")} -> #NAME? | R40: {=_xll.BDP(A40,"DS040")} -> #NAME? | S40: =(F40-TODAY())/365.25 -> #NAME? | T40: =S40-ROUNDDOWN(S40,0) -> #NAME? | U40: =DATE(2026,MONTH(TODAY()),DAY(F40))>DATEVALUE(R40) -> #NAME?
A41: BK594564 Corp | B41: {=_xll.BDP("BK594564 Corp","DS520")} -> #NAME? | C41: {=_xll.BDP("BK594564 Corp","DS001")} -> #NAME? | D41: {=_xll.BDP("BK594564 Corp","DS458")} -> #NAME? | E41: {=_xll.BDP("BK594564 Corp","DS004")} -> #NAME? | F41: {=_xll.BDP("BK594564 Corp","DS035")} -> #NAME? | G41: {=_xll.BDP("BK594564 Corp","DS086")} -> #NAME? | H41: {=_xll.BDP("BK594564 Corp","DS034")} -> #NAME? | I41: {=_xll.BDP("BK594564 Corp","DS033")} -> #NAME? | J41: {=_xll.BDP("BK594564 Corp","YL018")} -> #NAME? | K41: {=_xll.BDP("BK594564 Corp","YL016")} -> #NAME? | L41: {=_xll.BDP("BK594564 Corp","PR004")} -> #NAME? | M41: {=_xll.BDP("BK594564 Corp","PR002")} -> #NAME? | N41: {=_xll.BDP("BK594564 Corp","ID028")} -> #NAME? | O41: {=_xll.BDP("BK594564 Corp","ID005")} -> #NAME? | P41: {=_xll.BDP(A41,"RA007")} -> #NAME? | Q41: {=_xll.BDP(A41,"DS219")} -> #NAME? | R41: {=_xll.BDP(A41,"DS040")} -> #NAME? | S41: =(F41-TODAY())/365.25 -> #NAME? | T41: =S41-ROUNDDOWN(S41,0) -> #NAME? | U41: =DATE(2026,MONTH(TODAY()),DAY(F41))>DATEVALUE(R41) -> #NAME?
A42: BM027946 Corp | B42: {=_xll.BDP("BM027946 Corp","DS520")} -> #NAME? | C42: {=_xll.BDP("BM027946 Corp","DS001")} -> #NAME? | D42: {=_xll.BDP("BM027946 Corp","DS458")} -> #NAME? | E42: {=_xll.BDP("BM027946 Corp","DS004")} -> #NAME? | F42: {=_xll.BDP("BM027946 Corp","DS035")} -> #NAME? | G42: {=_xll.BDP("BM027946 Corp","DS086")} -> #NAME? | H42: {=_xll.BDP("BM027946 Corp","DS034")} -> #NAME? | I42: {=_xll.BDP("BM027946 Corp","DS033")} -> #NAME? | J42: {=_xll.BDP("BM027946 Corp","YL018")} -> #NAME? | K42: {=_xll.BDP("BM027946 Corp","YL016")} -> #NAME? | L42: {=_xll.BDP("BM027946 Corp","PR004")} -> #NAME? | M42: {=_xll.BDP("BM027946 Corp","PR002")} -> #NAME? | N42: {=_xll.BDP("BM027946 Corp","ID028")} -> #NAME? | O42: {=_xll.BDP("BM027946 Corp","ID005")} -> #NAME? | P42: {=_xll.BDP(A42,"RA007")} -> #NAME? | Q42: {=_xll.BDP(A42,"DS219")} -> #NAME? | R42: {=_xll.BDP(A42,"DS040")} -> #NAME? | S42: =(F42-TODAY())/365.25 -> #NAME? | T42: =S42-ROUNDDOWN(S42,0) -> #NAME? | U42: =DATE(2026,MONTH(TODAY()),DAY(F42))>DATEVALUE(R42) -> #NAME?
A43: BN361059 Corp | B43: {=_xll.BDP("BN361059 Corp","DS520")} -> #NAME? | C43: {=_xll.BDP("BN361059 Corp","DS001")} -> #NAME? | D43: {=_xll.BDP("BN361059 Corp","DS458")} -> #NAME? | E43: {=_xll.BDP("BN361059 Corp","DS004")} -> #NAME? | F43: {=_xll.BDP("BN361059 Corp","DS035")} -> #NAME? | G43: {=_xll.BDP("BN361059 Corp","DS086")} -> #NAME? | H43: {=_xll.BDP("BN361059 Corp","DS034")} -> #NAME? | I43: {=_xll.BDP("BN361059 Corp","DS033")} -> #NAME? | J43: {=_xll.BDP("BN361059 Corp","YL018")} -> #NAME? | K43: {=_xll.BDP("BN361059 Corp","YL016")} -> #NAME? | L43: {=_xll.BDP("BN361059 Corp","PR004")} -> #NAME? | M43: {=_xll.BDP("BN361059 Corp","PR002")} -> #NAME? | N43: {=_xll.BDP("BN361059 Corp","ID028")} -> #NAME? | O43: {=_xll.BDP("BN361059 Corp","ID005")} -> #NAME? | P43: {=_xll.BDP(A43,"RA007")} -> #NAME? | Q43: {=_xll.BDP(A43,"DS219")} -> #NAME? | R43: {=_xll.BDP(A43,"DS040")} -> #NAME? | S43: =(F43-TODAY())/365.25 -> #NAME? | T43: =S43-ROUNDDOWN(S43,0) -> #NAME? | U43: =DATE(2026,MONTH(TODAY()),DAY(F43))>DATEVALUE(R43) -> #NAME?
A44: BN417655 Corp | B44: {=_xll.BDP("BN417655 Corp","DS520")} -> #NAME? | C44: {=_xll.BDP("BN417655 Corp","DS001")} -> #NAME? | D44: {=_xll.BDP("BN417655 Corp","DS458")} -> #NAME? | E44: {=_xll.BDP("BN417655 Corp","DS004")} -> #NAME? | F44: {=_xll.BDP("BN417655 Corp","DS035")} -> #NAME? | G44: {=_xll.BDP("BN417655 Corp","DS086")} -> #NAME? | H44: {=_xll.BDP("BN417655 Corp","DS034")} -> #NAME? | I44: {=_xll.BDP("BN417655 Corp","DS033")} -> #NAME? | J44: {=_xll.BDP("BN417655 Corp","YL018")} -> #NAME? | K44: {=_xll.BDP("BN417655 Corp","YL016")} -> #NAME? | L44: {=_xll.BDP("BN417655 Corp","PR004")} -> #NAME? | M44: {=_xll.BDP("BN417655 Corp","PR002")} -> #NAME? | N44: {=_xll.BDP("BN417655 Corp","ID028")} -> #NAME? | O44: {=_xll.BDP("BN417655 Corp","ID005")} -> #NAME? | P44: {=_xll.BDP(A44,"RA007")} -> #NAME? | Q44: {=_xll.BDP(A44,"DS219")} -> #NAME? | R44: {=_xll.BDP(A44,"DS040")} -> #NAME? | S44: =(F44-TODAY())/365.25 -> #NAME? | T44: =S44-ROUNDDOWN(S44,0) -> #NAME? | U44: =DATE(2026,MONTH(TODAY()),DAY(F44))>DATEVALUE(R44) -> #NAME?
A45: BN612844 Corp | B45: {=_xll.BDP("BN612844 Corp","DS520")} -> #NAME? | C45: {=_xll.BDP("BN612844 Corp","DS001")} -> #NAME? | D45: {=_xll.BDP("BN612844 Corp","DS458")} -> #NAME? | E45: {=_xll.BDP("BN612844 Corp","DS004")} -> #NAME? | F45: {=_xll.BDP("BN612844 Corp","DS035")} -> #NAME? | G45: {=_xll.BDP("BN612844 Corp","DS086")} -> #NAME? | H45: {=_xll.BDP("BN612844 Corp","DS034")} -> #NAME? | I45: {=_xll.BDP("BN612844 Corp","DS033")} -> #NAME? | J45: {=_xll.BDP("BN612844 Corp","YL018")} -> #NAME? | K45: {=_xll.BDP("BN612844 Corp","YL016")} -> #NAME? | L45: {=_xll.BDP("BN612844 Corp","PR004")} -> #NAME? | M45: {=_xll.BDP("BN612844 Corp","PR002")} -> #NAME? | N45: {=_xll.BDP("BN612844 Corp","ID028")} -> #NAME? | O45: {=_xll.BDP("BN612844 Corp","ID005")} -> #NAME? | P45: {=_xll.BDP(A45,"RA007")} -> #NAME? | Q45: {=_xll.BDP(A45,"DS219")} -> #NAME? | R45: {=_xll.BDP(A45,"DS040")} -> #NAME? | S45: =(F45-TODAY())/365.25 -> #NAME? | T45: =S45-ROUNDDOWN(S45,0) -> #NAME? | U45: =DATE(2026,MONTH(TODAY()),DAY(F45))>DATEVALUE(R45) -> #NAME?
A46: BO911343 Corp | B46: {=_xll.BDP("BO911343 Corp","DS520")} -> #NAME? | C46: {=_xll.BDP("BO911343 Corp","DS001")} -> #NAME? | D46: {=_xll.BDP("BO911343 Corp","DS458")} -> #NAME? | E46: {=_xll.BDP("BO911343 Corp","DS004")} -> #NAME? | F46: {=_xll.BDP("BO911343 Corp","DS035")} -> #NAME? | G46: {=_xll.BDP("BO911343 Corp","DS086")} -> #NAME? | H46: {=_xll.BDP("BO911343 Corp","DS034")} -> #NAME? | I46: {=_xll.BDP("BO911343 Corp","DS033")} -> #NAME? | J46: {=_xll.BDP("BO911343 Corp","YL018")} -> #NAME? | K46: {=_xll.BDP("BO911343 Corp","YL016")} -> #NAME? | L46: {=_xll.BDP("BO911343 Corp","PR004")} -> #NAME? | M46: {=_xll.BDP("BO911343 Corp","PR002")} -> #NAME? | N46: {=_xll.BDP("BO911343 Corp","ID028")} -> #NAME? | O46: {=_xll.BDP("BO911343 Corp","ID005")} -> #NAME? | P46: {=_xll.BDP(A46,"RA007")} -> #NAME? | Q46: {=_xll.BDP(A46,"DS219")} -> #NAME? | R46: {=_xll.BDP(A46,"DS040")} -> #NAME? | S46: =(F46-TODAY())/365.25 -> #NAME? | T46: =S46-ROUNDDOWN(S46,0) -> #NAME? | U46: =DATE(2026,MONTH(TODAY()),DAY(F46))>DATEVALUE(R46) -> #NAME?
A47: BO941870 Corp | B47: {=_xll.BDP("BO941870 Corp","DS520")} -> #NAME? | C47: {=_xll.BDP("BO941870 Corp","DS001")} -> #NAME? | D47: {=_xll.BDP("BO941870 Corp","DS458")} -> #NAME? | E47: {=_xll.BDP("BO941870 Corp","DS004")} -> #NAME? | F47: {=_xll.BDP("BO941870 Corp","DS035")} -> #NAME? | G47: {=_xll.BDP("BO941870 Corp","DS086")} -> #NAME? | H47: {=_xll.BDP("BO941870 Corp","DS034")} -> #NAME? | I47: {=_xll.BDP("BO941870 Corp","DS033")} -> #NAME? | J47: {=_xll.BDP("BO941870 Corp","YL018")} -> #NAME? | K47: {=_xll.BDP("BO941870 Corp","YL016")} -> #NAME? | L47: {=_xll.BDP("BO941870 Corp","PR004")} -> #NAME? | M47: {=_xll.BDP("BO941870 Corp","PR002")} -> #NAME? | N47: {=_xll.BDP("BO941870 Corp","ID028")} -> #NAME? | O47: {=_xll.BDP("BO941870 Corp","ID005")} -> #NAME? | P47: {=_xll.BDP(A47,"RA007")} -> #NAME? | Q47: {=_xll.BDP(A47,"DS219")} -> #NAME? | R47: {=_xll.BDP(A47,"DS040")} -> #NAME? | S47: =(F47-TODAY())/365.25 -> #NAME? | T47: =S47-ROUNDDOWN(S47,0) -> #NAME? | U47: =DATE(2026,MONTH(TODAY()),DAY(F47))>DATEVALUE(R47) -> #NAME?
A48: BO997638 Corp | B48: {=_xll.BDP("BO997638 Corp","DS520")} -> #NAME? | C48: {=_xll.BDP("BO997638 Corp","DS001")} -> #NAME? | D48: {=_xll.BDP("BO997638 Corp","DS458")} -> #NAME? | E48: {=_xll.BDP("BO997638 Corp","DS004")} -> #NAME? | F48: {=_xll.BDP("BO997638 Corp","DS035")} -> #NAME? | G48: {=_xll.BDP("BO997638 Corp","DS086")} -> #NAME? | H48: {=_xll.BDP("BO997638 Corp","DS034")} -> #NAME? | I48: {=_xll.BDP("BO997638 Corp","DS033")} -> #NAME? | J48: {=_xll.BDP("BO997638 Corp","YL018")} -> #NAME? | K48: {=_xll.BDP("BO997638 Corp","YL016")} -> #NAME? | L48: {=_xll.BDP("BO997638 Corp","PR004")} -> #NAME? | M48: {=_xll.BDP("BO997638 Corp","PR002")} -> #NAME? | N48: {=_xll.BDP("BO997638 Corp","ID028")} -> #NAME? | O48: {=_xll.BDP("BO997638 Corp","ID005")} -> #NAME? | P48: {=_xll.BDP(A48,"RA007")} -> #NAME? | Q48: {=_xll.BDP(A48,"DS219")} -> #NAME? | R48: {=_xll.BDP(A48,"DS040")} -> #NAME? | S48: =(F48-TODAY())/365.25 -> #NAME? | T48: =S48-ROUNDDOWN(S48,0) -> #NAME? | U48: =DATE(2026,MONTH(TODAY()),DAY(F48))>DATEVALUE(R48) -> #NAME?
A49: BP172580 Corp | B49: {=_xll.BDP("BP172580 Corp","DS520")} -> #NAME? | C49: {=_xll.BDP("BP172580 Corp","DS001")} -> #NAME? | D49: {=_xll.BDP("BP172580 Corp","DS458")} -> #NAME? | E49: {=_xll.BDP("BP172580 Corp","DS004")} -> #NAME? | F49: {=_xll.BDP("BP172580 Corp","DS035")} -> #NAME? | G49: {=_xll.BDP("BP172580 Corp","DS086")} -> #NAME? | H49: {=_xll.BDP("BP172580 Corp","DS034")} -> #NAME? | I49: {=_xll.BDP("BP172580 Corp","DS033")} -> #NAME? | J49: {=_xll.BDP("BP172580 Corp","YL018")} -> #NAME? | K49: {=_xll.BDP("BP172580 Corp","YL016")} -> #NAME? | L49: {=_xll.BDP("BP172580 Corp","PR004")} -> #NAME? | M49: {=_xll.BDP("BP172580 Corp","PR002")} -> #NAME? | N49: {=_xll.BDP("BP172580 Corp","ID028")} -> #NAME? | O49: {=_xll.BDP("BP172580 Corp","ID005")} -> #NAME? | P49: {=_xll.BDP(A49,"RA007")} -> #NAME? | Q49: {=_xll.BDP(A49,"DS219")} -> #NAME? | R49: {=_xll.BDP(A49,"DS040")} -> #NAME? | S49: =(F49-TODAY())/365.25 -> #NAME? | T49: =S49-ROUNDDOWN(S49,0) -> #NAME? | U49: =DATE(2026,MONTH(TODAY()),DAY(F49))>DATEVALUE(R49) -> #NAME?
A50: BP809355 Corp | B50: {=_xll.BDP("BP809355 Corp","DS520")} -> #NAME? | C50: {=_xll.BDP("BP809355 Corp","DS001")} -> #NAME? | D50: {=_xll.BDP("BP809355 Corp","DS458")} -> #NAME? | E50: {=_xll.BDP("BP809355 Corp","DS004")} -> #NAME? | F50: {=_xll.BDP("BP809355 Corp","DS035")} -> #NAME? | G50: {=_xll.BDP("BP809355 Corp","DS086")} -> #NAME? | H50: {=_xll.BDP("BP809355 Corp","DS034")} -> #NAME? | I50: {=_xll.BDP("BP809355 Corp","DS033")} -> #NAME? | J50: {=_xll.BDP("BP809355 Corp","YL018")} -> #NAME? | K50: {=_xll.BDP("BP809355 Corp","YL016")} -> #NAME? | L50: {=_xll.BDP("BP809355 Corp","PR004")} -> #NAME? | M50: {=_xll.BDP("BP809355 Corp","PR002")} -> #NAME? | N50: {=_xll.BDP("BP809355 Corp","ID028")} -> #NAME? | O50: {=_xll.BDP("BP809355 Corp","ID005")} -> #NAME? | P50: {=_xll.BDP(A50,"RA007")} -> #NAME? | Q50: {=_xll.BDP(A50,"DS219")} -> #NAME? | R50: {=_xll.BDP(A50,"DS040")} -> #NAME? | S50: =(F50-TODAY())/365.25 -> #NAME? | T50: =S50-ROUNDDOWN(S50,0) -> #NAME? | U50: =DATE(2026,MONTH(TODAY()),DAY(F50))>DATEVALUE(R50) -> #NAME?
A51: BQ348089 Corp | B51: {=_xll.BDP("BQ348089 Corp","DS520")} -> #NAME? | C51: {=_xll.BDP("BQ348089 Corp","DS001")} -> #NAME? | D51: {=_xll.BDP("BQ348089 Corp","DS458")} -> #NAME? | E51: {=_xll.BDP("BQ348089 Corp","DS004")} -> #NAME? | F51: {=_xll.BDP("BQ348089 Corp","DS035")} -> #NAME? | G51: {=_xll.BDP("BQ348089 Corp","DS086")} -> #NAME? | H51: {=_xll.BDP("BQ348089 Corp","DS034")} -> #NAME? | I51: {=_xll.BDP("BQ348089 Corp","DS033")} -> #NAME? | J51: {=_xll.BDP("BQ348089 Corp","YL018")} -> #NAME? | K51: {=_xll.BDP("BQ348089 Corp","YL016")} -> #NAME? | L51: {=_xll.BDP("BQ348089 Corp","PR004")} -> #NAME? | M51: {=_xll.BDP("BQ348089 Corp","PR002")} -> #NAME? | N51: {=_xll.BDP("BQ348089 Corp","ID028")} -> #NAME? | O51: {=_xll.BDP("BQ348089 Corp","ID005")} -> #NAME? | P51: {=_xll.BDP(A51,"RA007")} -> #NAME? | Q51: {=_xll.BDP(A51,"DS219")} -> #NAME? | R51: {=_xll.BDP(A51,"DS040")} -> #NAME? | S51: =(F51-TODAY())/365.25 -> #NAME? | T51: =S51-ROUNDDOWN(S51,0) -> #NAME? | U51: =DATE(2026,MONTH(TODAY()),DAY(F51))>DATEVALUE(R51) -> #NAME?
A52: BQ405120 Corp | B52: {=_xll.BDP("BQ405120 Corp","DS520")} -> #NAME? | C52: {=_xll.BDP("BQ405120 Corp","DS001")} -> #NAME? | D52: {=_xll.BDP("BQ405120 Corp","DS458")} -> #NAME? | E52: {=_xll.BDP("BQ405120 Corp","DS004")} -> #NAME? | F52: {=_xll.BDP("BQ405120 Corp","DS035")} -> #NAME? | G52: {=_xll.BDP("BQ405120 Corp","DS086")} -> #NAME? | H52: {=_xll.BDP("BQ405120 Corp","DS034")} -> #NAME? | I52: {=_xll.BDP("BQ405120 Corp","DS033")} -> #NAME? | J52: {=_xll.BDP("BQ405120 Corp","YL018")} -> #NAME? | K52: {=_xll.BDP("BQ405120 Corp","YL016")} -> #NAME? | L52: {=_xll.BDP("BQ405120 Corp","PR004")} -> #NAME? | M52: {=_xll.BDP("BQ405120 Corp","PR002")} -> #NAME? | N52: {=_xll.BDP("BQ405120 Corp","ID028")} -> #NAME? | O52: {=_xll.BDP("BQ405120 Corp","ID005")} -> #NAME? | P52: {=_xll.BDP(A52,"RA007")} -> #NAME? | Q52: {=_xll.BDP(A52,"DS219")} -> #NAME? | R52: {=_xll.BDP(A52,"DS040")} -> #NAME? | S52: =(F52-TODAY())/365.25 -> #NAME? | T52: =S52-ROUNDDOWN(S52,0) -> #NAME? | U52: =DATE(2026,MONTH(TODAY()),DAY(F52))>DATEVALUE(R52) -> #NAME?
A53: BQ447894 Corp | B53: {=_xll.BDP("BQ447894 Corp","DS520")} -> #NAME? | C53: {=_xll.BDP("BQ447894 Corp","DS001")} -> #NAME? | D53: {=_xll.BDP("BQ447894 Corp","DS458")} -> #NAME? | E53: {=_xll.BDP("BQ447894 Corp","DS004")} -> #NAME? | F53: {=_xll.BDP("BQ447894 Corp","DS035")} -> #NAME? | G53: {=_xll.BDP("BQ447894 Corp","DS086")} -> #NAME? | H53: {=_xll.BDP("BQ447894 Corp","DS034")} -> #NAME? | I53: {=_xll.BDP("BQ447894 Corp","DS033")} -> #NAME? | J53: {=_xll.BDP("BQ447894 Corp","YL018")} -> #NAME? | K53: {=_xll.BDP("BQ447894 Corp","YL016")} -> #NAME? | L53: {=_xll.BDP("BQ447894 Corp","PR004")} -> #NAME? | M53: {=_xll.BDP("BQ447894 Corp","PR002")} -> #NAME? | N53: {=_xll.BDP("BQ447894 Corp","ID028")} -> #NAME? | O53: {=_xll.BDP("BQ447894 Corp","ID005")} -> #NAME? | P53: {=_xll.BDP(A53,"RA007")} -> #NAME? | Q53: {=_xll.BDP(A53,"DS219")} -> #NAME? | R53: {=_xll.BDP(A53,"DS040")} -> #NAME? | S53: =(F53-TODAY())/365.25 -> #NAME? | T53: =S53-ROUNDDOWN(S53,0) -> #NAME? | U53: =DATE(2026,MONTH(TODAY()),DAY(F53))>DATEVALUE(R53) -> #NAME?
A54: BQ516777 Corp | B54: {=_xll.BDP("BQ516777 Corp","DS520")} -> #NAME? | C54: {=_xll.BDP("BQ516777 Corp","DS001")} -> #NAME? | D54: {=_xll.BDP("BQ516777 Corp","DS458")} -> #NAME? | E54: {=_xll.BDP("BQ516777 Corp","DS004")} -> #NAME? | F54: {=_xll.BDP("BQ516777 Corp","DS035")} -> #NAME? | G54: {=_xll.BDP("BQ516777 Corp","DS086")} -> #NAME? | H54: {=_xll.BDP("BQ516777 Corp","DS034")} -> #NAME? | I54: {=_xll.BDP("BQ516777 Corp","DS033")} -> #NAME? | J54: {=_xll.BDP("BQ516777 Corp","YL018")} -> #NAME? | K54: {=_xll.BDP("BQ516777 Corp","YL016")} -> #NAME? | L54: {=_xll.BDP("BQ516777 Corp","PR004")} -> #NAME? | M54: {=_xll.BDP("BQ516777 Corp","PR002")} -> #NAME? | N54: {=_xll.BDP("BQ516777 Corp","ID028")} -> #NAME? | O54: {=_xll.BDP("BQ516777 Corp","ID005")} -> #NAME? | P54: {=_xll.BDP(A54,"RA007")} -> #NAME? | Q54: {=_xll.BDP(A54,"DS219")} -> #NAME? | R54: {=_xll.BDP(A54,"DS040")} -> #NAME? | S54: =(F54-TODAY())/365.25 -> #NAME? | T54: =S54-ROUNDDOWN(S54,0) -> #NAME? | U54: =DATE(2026,MONTH(TODAY()),DAY(F54))>DATEVALUE(R54) -> #NAME?
A55: BR788662 Corp | B55: {=_xll.BDP("BR788662 Corp","DS520")} -> #NAME? | C55: {=_xll.BDP("BR788662 Corp","DS001")} -> #NAME? | D55: {=_xll.BDP("BR788662 Corp","DS458")} -> #NAME? | E55: {=_xll.BDP("BR788662 Corp","DS004")} -> #NAME? | F55: {=_xll.BDP("BR788662 Corp","DS035")} -> #NAME? | G55: {=_xll.BDP("BR788662 Corp","DS086")} -> #NAME? | H55: {=_xll.BDP("BR788662 Corp","DS034")} -> #NAME? | I55: {=_xll.BDP("BR788662 Corp","DS033")} -> #NAME? | J55: {=_xll.BDP("BR788662 Corp","YL018")} -> #NAME? | K55: {=_xll.BDP("BR788662 Corp","YL016")} -> #NAME? | L55: {=_xll.BDP("BR788662 Corp","PR004")} -> #NAME? | M55: {=_xll.BDP("BR788662 Corp","PR002")} -> #NAME? | N55: {=_xll.BDP("BR788662 Corp","ID028")} -> #NAME? | O55: {=_xll.BDP("BR788662 Corp","ID005")} -> #NAME? | P55: {=_xll.BDP(A55,"RA007")} -> #NAME? | Q55: {=_xll.BDP(A55,"DS219")} -> #NAME? | R55: {=_xll.BDP(A55,"DS040")} -> #NAME? | S55: =(F55-TODAY())/365.25 -> #NAME? | T55: =S55-ROUNDDOWN(S55,0) -> #NAME? | U55: =DATE(2026,MONTH(TODAY()),DAY(F55))>DATEVALUE(R55) -> #NAME?
A56: BR921605 Corp | B56: {=_xll.BDP("BR921605 Corp","DS520")} -> #NAME? | C56: {=_xll.BDP("BR921605 Corp","DS001")} -> #NAME? | D56: {=_xll.BDP("BR921605 Corp","DS458")} -> #NAME? | E56: {=_xll.BDP("BR921605 Corp","DS004")} -> #NAME? | F56: {=_xll.BDP("BR921605 Corp","DS035")} -> #NAME? | G56: {=_xll.BDP("BR921605 Corp","DS086")} -> #NAME? | H56: {=_xll.BDP("BR921605 Corp","DS034")} -> #NAME? | I56: {=_xll.BDP("BR921605 Corp","DS033")} -> #NAME? | J56: {=_xll.BDP("BR921605 Corp","YL018")} -> #NAME? | K56: {=_xll.BDP("BR921605 Corp","YL016")} -> #NAME? | L56: {=_xll.BDP("BR921605 Corp","PR004")} -> #NAME? | M56: {=_xll.BDP("BR921605 Corp","PR002")} -> #NAME? | N56: {=_xll.BDP("BR921605 Corp","ID028")} -> #NAME? | O56: {=_xll.BDP("BR921605 Corp","ID005")} -> #NAME? | P56: {=_xll.BDP(A56,"RA007")} -> #NAME? | Q56: {=_xll.BDP(A56,"DS219")} -> #NAME? | R56: {=_xll.BDP(A56,"DS040")} -> #NAME? | S56: =(F56-TODAY())/365.25 -> #NAME? | T56: =S56-ROUNDDOWN(S56,0) -> #NAME? | U56: =DATE(2026,MONTH(TODAY()),DAY(F56))>DATEVALUE(R56) -> #NAME?
A57: BR962540 Corp | B57: {=_xll.BDP("BR962540 Corp","DS520")} -> #NAME? | C57: {=_xll.BDP("BR962540 Corp","DS001")} -> #NAME? | D57: {=_xll.BDP("BR962540 Corp","DS458")} -> #NAME? | E57: {=_xll.BDP("BR962540 Corp","DS004")} -> #NAME? | F57: {=_xll.BDP("BR962540 Corp","DS035")} -> #NAME? | G57: {=_xll.BDP("BR962540 Corp","DS086")} -> #NAME? | H57: {=_xll.BDP("BR962540 Corp","DS034")} -> #NAME? | I57: {=_xll.BDP("BR962540 Corp","DS033")} -> #NAME? | J57: {=_xll.BDP("BR962540 Corp","YL018")} -> #NAME? | K57: {=_xll.BDP("BR962540 Corp","YL016")} -> #NAME? | L57: {=_xll.BDP("BR962540 Corp","PR004")} -> #NAME? | M57: {=_xll.BDP("BR962540 Corp","PR002")} -> #NAME? | N57: {=_xll.BDP("BR962540 Corp","ID028")} -> #NAME? | O57: {=_xll.BDP("BR962540 Corp","ID005")} -> #NAME? | P57: {=_xll.BDP(A57,"RA007")} -> #NAME? | Q57: {=_xll.BDP(A57,"DS219")} -> #NAME? | R57: {=_xll.BDP(A57,"DS040")} -> #NAME? | S57: =(F57-TODAY())/365.25 -> #NAME? | T57: =S57-ROUNDDOWN(S57,0) -> #NAME? | U57: =DATE(2026,MONTH(TODAY()),DAY(F57))>DATEVALUE(R57) -> #NAME?
A58: BS028901 Corp | B58: {=_xll.BDP("BS028901 Corp","DS520")} -> #NAME? | C58: {=_xll.BDP("BS028901 Corp","DS001")} -> #NAME? | D58: {=_xll.BDP("BS028901 Corp","DS458")} -> #NAME? | E58: {=_xll.BDP("BS028901 Corp","DS004")} -> #NAME? | F58: {=_xll.BDP("BS028901 Corp","DS035")} -> #NAME? | G58: {=_xll.BDP("BS028901 Corp","DS086")} -> #NAME? | H58: {=_xll.BDP("BS028901 Corp","DS034")} -> #NAME? | I58: {=_xll.BDP("BS028901 Corp","DS033")} -> #NAME? | J58: {=_xll.BDP("BS028901 Corp","YL018")} -> #NAME? | K58: {=_xll.BDP("BS028901 Corp","YL016")} -> #NAME? | L58: {=_xll.BDP("BS028901 Corp","PR004")} -> #NAME? | M58: {=_xll.BDP("BS028901 Corp","PR002")} -> #NAME? | N58: {=_xll.BDP("BS028901 Corp","ID028")} -> #NAME? | O58: {=_xll.BDP("BS028901 Corp","ID005")} -> #NAME? | P58: {=_xll.BDP(A58,"RA007")} -> #NAME? | Q58: {=_xll.BDP(A58,"DS219")} -> #NAME? | R58: {=_xll.BDP(A58,"DS040")} -> #NAME? | S58: =(F58-TODAY())/365.25 -> #NAME? | T58: =S58-ROUNDDOWN(S58,0) -> #NAME? | U58: =DATE(2026,MONTH(TODAY()),DAY(F58))>DATEVALUE(R58) -> #NAME?
A59: BT330618 Corp | B59: {=_xll.BDP("BT330618 Corp","DS520")} -> #NAME? | C59: {=_xll.BDP("BT330618 Corp","DS001")} -> #NAME? | D59: {=_xll.BDP("BT330618 Corp","DS458")} -> #NAME? | E59: {=_xll.BDP("BT330618 Corp","DS004")} -> #NAME? | F59: {=_xll.BDP("BT330618 Corp","DS035")} -> #NAME? | G59: {=_xll.BDP("BT330618 Corp","DS086")} -> #NAME? | H59: {=_xll.BDP("BT330618 Corp","DS034")} -> #NAME? | I59: {=_xll.BDP("BT330618 Corp","DS033")} -> #NAME? | J59: {=_xll.BDP("BT330618 Corp","YL018")} -> #NAME? | K59: {=_xll.BDP("BT330618 Corp","YL016")} -> #NAME? | L59: {=_xll.BDP("BT330618 Corp","PR004")} -> #NAME? | M59: {=_xll.BDP("BT330618 Corp","PR002")} -> #NAME? | N59: {=_xll.BDP("BT330618 Corp","ID028")} -> #NAME? | O59: {=_xll.BDP("BT330618 Corp","ID005")} -> #NAME? | P59: {=_xll.BDP(A59,"RA007")} -> #NAME? | Q59: {=_xll.BDP(A59,"DS219")} -> #NAME? | R59: {=_xll.BDP(A59,"DS040")} -> #NAME? | S59: =(F59-TODAY())/365.25 -> #NAME? | T59: =S59-ROUNDDOWN(S59,0) -> #NAME? | U59: =DATE(2026,MONTH(TODAY()),DAY(F59))>DATEVALUE(R59) -> #NAME?
A60: BT386064 Corp | B60: {=_xll.BDP("BT386064 Corp","DS520")} -> #NAME? | C60: {=_xll.BDP("BT386064 Corp","DS001")} -> #NAME? | D60: {=_xll.BDP("BT386064 Corp","DS458")} -> #NAME? | E60: {=_xll.BDP("BT386064 Corp","DS004")} -> #NAME? | F60: {=_xll.BDP("BT386064 Corp","DS035")} -> #NAME? | G60: {=_xll.BDP("BT386064 Corp","DS086")} -> #NAME? | H60: {=_xll.BDP("BT386064 Corp","DS034")} -> #NAME? | I60: {=_xll.BDP("BT386064 Corp","DS033")} -> #NAME? | J60: {=_xll.BDP("BT386064 Corp","YL018")} -> #NAME? | K60: {=_xll.BDP("BT386064 Corp","YL016")} -> #NAME? | L60: {=_xll.BDP("BT386064 Corp","PR004")} -> #NAME? | M60: {=_xll.BDP("BT386064 Corp","PR002")} -> #NAME? | N60: {=_xll.BDP("BT386064 Corp","ID028")} -> #NAME? | O60: {=_xll.BDP("BT386064 Corp","ID005")} -> #NAME? | P60: {=_xll.BDP(A60,"RA007")} -> #NAME? | Q60: {=_xll.BDP(A60,"DS219")} -> #NAME? | R60: {=_xll.BDP(A60,"DS040")} -> #NAME? | S60: =(F60-TODAY())/365.25 -> #NAME? | T60: =S60-ROUNDDOWN(S60,0) -> #NAME? | U60: =DATE(2026,MONTH(TODAY()),DAY(F60))>DATEVALUE(R60) -> #NAME?
A61: BT484763 Corp | B61: {=_xll.BDP("BT484763 Corp","DS520")} -> #NAME? | C61: {=_xll.BDP("BT484763 Corp","DS001")} -> #NAME? | D61: {=_xll.BDP("BT484763 Corp","DS458")} -> #NAME? | E61: {=_xll.BDP("BT484763 Corp","DS004")} -> #NAME? | F61: {=_xll.BDP("BT484763 Corp","DS035")} -> #NAME? | G61: {=_xll.BDP("BT484763 Corp","DS086")} -> #NAME? | H61: {=_xll.BDP("BT484763 Corp","DS034")} -> #NAME? | I61: {=_xll.BDP("BT484763 Corp","DS033")} -> #NAME? | J61: {=_xll.BDP("BT484763 Corp","YL018")} -> #NAME? | K61: {=_xll.BDP("BT484763 Corp","YL016")} -> #NAME? | L61: {=_xll.BDP("BT484763 Corp","PR004")} -> #NAME? | M61: {=_xll.BDP("BT484763 Corp","PR002")} -> #NAME? | N61: {=_xll.BDP("BT484763 Corp","ID028")} -> #NAME? | O61: {=_xll.BDP("BT484763 Corp","ID005")} -> #NAME? | P61: {=_xll.BDP(A61,"RA007")} -> #NAME? | Q61: {=_xll.BDP(A61,"DS219")} -> #NAME? | R61: {=_xll.BDP(A61,"DS040")} -> #NAME? | S61: =(F61-TODAY())/365.25 -> #NAME? | T61: =S61-ROUNDDOWN(S61,0) -> #NAME? | U61: =DATE(2026,MONTH(TODAY()),DAY(F61))>DATEVALUE(R61) -> #NAME?
A62: BT530456 Corp | B62: {=_xll.BDP("BT530456 Corp","DS520")} -> #NAME? | C62: {=_xll.BDP("BT530456 Corp","DS001")} -> #NAME? | D62: {=_xll.BDP("BT530456 Corp","DS458")} -> #NAME? | E62: {=_xll.BDP("BT530456 Corp","DS004")} -> #NAME? | F62: {=_xll.BDP("BT530456 Corp","DS035")} -> #NAME? | G62: {=_xll.BDP("BT530456 Corp","DS086")} -> #NAME? | H62: {=_xll.BDP("BT530456 Corp","DS034")} -> #NAME? | I62: {=_xll.BDP("BT530456 Corp","DS033")} -> #NAME? | J62: {=_xll.BDP("BT530456 Corp","YL018")} -> #NAME? | K62: {=_xll.BDP("BT530456 Corp","YL016")} -> #NAME? | L62: {=_xll.BDP("BT530456 Corp","PR004")} -> #NAME? | M62: {=_xll.BDP("BT530456 Corp","PR002")} -> #NAME? | N62: {=_xll.BDP("BT530456 Corp","ID028")} -> #NAME? | O62: {=_xll.BDP("BT530456 Corp","ID005")} -> #NAME? | P62: {=_xll.BDP(A62,"RA007")} -> #NAME? | Q62: {=_xll.BDP(A62,"DS219")} -> #NAME? | R62: {=_xll.BDP(A62,"DS040")} -> #NAME? | S62: =(F62-TODAY())/365.25 -> #NAME? | T62: =S62-ROUNDDOWN(S62,0) -> #NAME? | U62: =DATE(2026,MONTH(TODAY()),DAY(F62))>DATEVALUE(R62) -> #NAME?
A63: BV737650 Corp | B63: {=_xll.BDP("BV737650 Corp","DS520")} -> #NAME? | C63: {=_xll.BDP("BV737650 Corp","DS001")} -> #NAME? | D63: {=_xll.BDP("BV737650 Corp","DS458")} -> #NAME? | E63: {=_xll.BDP("BV737650 Corp","DS004")} -> #NAME? | F63: {=_xll.BDP("BV737650 Corp","DS035")} -> #NAME? | G63: {=_xll.BDP("BV737650 Corp","DS086")} -> #NAME? | H63: {=_xll.BDP("BV737650 Corp","DS034")} -> #NAME? | I63: {=_xll.BDP("BV737650 Corp","DS033")} -> #NAME? | J63: {=_xll.BDP("BV737650 Corp","YL018")} -> #NAME? | K63: {=_xll.BDP("BV737650 Corp","YL016")} -> #NAME? | L63: {=_xll.BDP("BV737650 Corp","PR004")} -> #NAME? | M63: {=_xll.BDP("BV737650 Corp","PR002")} -> #NAME? | N63: {=_xll.BDP("BV737650 Corp","ID028")} -> #NAME? | O63: {=_xll.BDP("BV737650 Corp","ID005")} -> #NAME? | P63: {=_xll.BDP(A63,"RA007")} -> #NAME? | Q63: {=_xll.BDP(A63,"DS219")} -> #NAME? | R63: {=_xll.BDP(A63,"DS040")} -> #NAME? | S63: =(F63-TODAY())/365.25 -> #NAME? | T63: =S63-ROUNDDOWN(S63,0) -> #NAME? | U63: =DATE(2026,MONTH(TODAY()),DAY(F63))>DATEVALUE(R63) -> #NAME?
A64: BV801821 Corp | B64: {=_xll.BDP("BV801821 Corp","DS520")} -> #NAME? | C64: {=_xll.BDP("BV801821 Corp","DS001")} -> #NAME? | D64: {=_xll.BDP("BV801821 Corp","DS458")} -> #NAME? | E64: {=_xll.BDP("BV801821 Corp","DS004")} -> #NAME? | F64: {=_xll.BDP("BV801821 Corp","DS035")} -> #NAME? | G64: {=_xll.BDP("BV801821 Corp","DS086")} -> #NAME? | H64: {=_xll.BDP("BV801821 Corp","DS034")} -> #NAME? | I64: {=_xll.BDP("BV801821 Corp","DS033")} -> #NAME? | J64: {=_xll.BDP("BV801821 Corp","YL018")} -> #NAME? | K64: {=_xll.BDP("BV801821 Corp","YL016")} -> #NAME? | L64: {=_xll.BDP("BV801821 Corp","PR004")} -> #NAME? | M64: {=_xll.BDP("BV801821 Corp","PR002")} -> #NAME? | N64: {=_xll.BDP("BV801821 Corp","ID028")} -> #NAME? | O64: {=_xll.BDP("BV801821 Corp","ID005")} -> #NAME? | P64: {=_xll.BDP(A64,"RA007")} -> #NAME? | Q64: {=_xll.BDP(A64,"DS219")} -> #NAME? | R64: {=_xll.BDP(A64,"DS040")} -> #NAME? | S64: =(F64-TODAY())/365.25 -> #NAME? | T64: =S64-ROUNDDOWN(S64,0) -> #NAME? | U64: =DATE(2026,MONTH(TODAY()),DAY(F64))>DATEVALUE(R64) -> #NAME?
A65: BV894033 Corp | B65: {=_xll.BDP("BV894033 Corp","DS520")} -> #NAME? | C65: {=_xll.BDP("BV894033 Corp","DS001")} -> #NAME? | D65: {=_xll.BDP("BV894033 Corp","DS458")} -> #NAME? | E65: {=_xll.BDP("BV894033 Corp","DS004")} -> #NAME? | F65: {=_xll.BDP("BV894033 Corp","DS035")} -> #NAME? | G65: {=_xll.BDP("BV894033 Corp","DS086")} -> #NAME? | H65: {=_xll.BDP("BV894033 Corp","DS034")} -> #NAME? | I65: {=_xll.BDP("BV894033 Corp","DS033")} -> #NAME? | J65: {=_xll.BDP("BV894033 Corp","YL018")} -> #NAME? | K65: {=_xll.BDP("BV894033 Corp","YL016")} -> #NAME? | L65: {=_xll.BDP("BV894033 Corp","PR004")} -> #NAME? | M65: {=_xll.BDP("BV894033 Corp","PR002")} -> #NAME? | N65: {=_xll.BDP("BV894033 Corp","ID028")} -> #NAME? | O65: {=_xll.BDP("BV894033 Corp","ID005")} -> #NAME? | P65: {=_xll.BDP(A65,"RA007")} -> #NAME? | Q65: {=_xll.BDP(A65,"DS219")} -> #NAME? | R65: {=_xll.BDP(A65,"DS040")} -> #NAME? | S65: =(F65-TODAY())/365.25 -> #NAME? | T65: =S65-ROUNDDOWN(S65,0) -> #NAME? | U65: =DATE(2026,MONTH(TODAY()),DAY(F65))>DATEVALUE(R65) -> #NAME?
A66: BV949862 Corp | B66: {=_xll.BDP("BV949862 Corp","DS520")} -> #NAME? | C66: {=_xll.BDP("BV949862 Corp","DS001")} -> #NAME? | D66: {=_xll.BDP("BV949862 Corp","DS458")} -> #NAME? | E66: {=_xll.BDP("BV949862 Corp","DS004")} -> #NAME? | F66: {=_xll.BDP("BV949862 Corp","DS035")} -> #NAME? | G66: {=_xll.BDP("BV949862 Corp","DS086")} -> #NAME? | H66: {=_xll.BDP("BV949862 Corp","DS034")} -> #NAME? | I66: {=_xll.BDP("BV949862 Corp","DS033")} -> #NAME? | J66: {=_xll.BDP("BV949862 Corp","YL018")} -> #NAME? | K66: {=_xll.BDP("BV949862 Corp","YL016")} -> #NAME? | L66: {=_xll.BDP("BV949862 Corp","PR004")} -> #NAME? | M66: {=_xll.BDP("BV949862 Corp","PR002")} -> #NAME? | N66: {=_xll.BDP("BV949862 Corp","ID028")} -> #NAME? | O66: {=_xll.BDP("BV949862 Corp","ID005")} -> #NAME? | P66: {=_xll.BDP(A66,"RA007")} -> #NAME? | Q66: {=_xll.BDP(A66,"DS219")} -> #NAME? | R66: {=_xll.BDP(A66,"DS040")} -> #NAME? | S66: =(F66-TODAY())/365.25 -> #NAME? | T66: =S66-ROUNDDOWN(S66,0) -> #NAME? | U66: =DATE(2026,MONTH(TODAY()),DAY(F66))>DATEVALUE(R66) -> #NAME?
A67: BW843591 Corp | B67: {=_xll.BDP("BW843591 Corp","DS520")} -> #NAME? | C67: {=_xll.BDP("BW843591 Corp","DS001")} -> #NAME? | D67: {=_xll.BDP("BW843591 Corp","DS458")} -> #NAME? | E67: {=_xll.BDP("BW843591 Corp","DS004")} -> #NAME? | F67: {=_xll.BDP("BW843591 Corp","DS035")} -> #NAME? | G67: {=_xll.BDP("BW843591 Corp","DS086")} -> #NAME? | H67: {=_xll.BDP("BW843591 Corp","DS034")} -> #NAME? | I67: {=_xll.BDP("BW843591 Corp","DS033")} -> #NAME? | J67: {=_xll.BDP("BW843591 Corp","YL018")} -> #NAME? | K67: {=_xll.BDP("BW843591 Corp","YL016")} -> #NAME? | L67: {=_xll.BDP("BW843591 Corp","PR004")} -> #NAME? | M67: {=_xll.BDP("BW843591 Corp","PR002")} -> #NAME? | N67: {=_xll.BDP("BW843591 Corp","ID028")} -> #NAME? | O67: {=_xll.BDP("BW843591 Corp","ID005")} -> #NAME? | P67: {=_xll.BDP(A67,"RA007")} -> #NAME? | Q67: {=_xll.BDP(A67,"DS219")} -> #NAME? | R67: {=_xll.BDP(A67,"DS040")} -> #NAME? | S67: =(F67-TODAY())/365.25 -> #NAME? | T67: =S67-ROUNDDOWN(S67,0) -> #NAME? | U67: =DATE(2026,MONTH(TODAY()),DAY(F67))>DATEVALUE(R67) -> #NAME?
A68: BX331425 Corp | B68: {=_xll.BDP("BX331425 Corp","DS520")} -> #NAME? | C68: {=_xll.BDP("BX331425 Corp","DS001")} -> #NAME? | D68: {=_xll.BDP("BX331425 Corp","DS458")} -> #NAME? | E68: {=_xll.BDP("BX331425 Corp","DS004")} -> #NAME? | F68: {=_xll.BDP("BX331425 Corp","DS035")} -> #NAME? | G68: {=_xll.BDP("BX331425 Corp","DS086")} -> #NAME? | H68: {=_xll.BDP("BX331425 Corp","DS034")} -> #NAME? | I68: {=_xll.BDP("BX331425 Corp","DS033")} -> #NAME? | J68: {=_xll.BDP("BX331425 Corp","YL018")} -> #NAME? | K68: {=_xll.BDP("BX331425 Corp","YL016")} -> #NAME? | L68: {=_xll.BDP("BX331425 Corp","PR004")} -> #NAME? | M68: {=_xll.BDP("BX331425 Corp","PR002")} -> #NAME? | N68: {=_xll.BDP("BX331425 Corp","ID028")} -> #NAME? | O68: {=_xll.BDP("BX331425 Corp","ID005")} -> #NAME? | P68: {=_xll.BDP(A68,"RA007")} -> #NAME? | Q68: {=_xll.BDP(A68,"DS219")} -> #NAME? | R68: {=_xll.BDP(A68,"DS040")} -> #NAME? | S68: =(F68-TODAY())/365.25 -> #NAME? | T68: =S68-ROUNDDOWN(S68,0) -> #NAME? | U68: =DATE(2026,MONTH(TODAY()),DAY(F68))>DATEVALUE(R68) -> #NAME?
A69: BX625748 Corp | B69: {=_xll.BDP("BX625748 Corp","DS520")} -> #NAME? | C69: {=_xll.BDP("BX625748 Corp","DS001")} -> #NAME? | D69: {=_xll.BDP("BX625748 Corp","DS458")} -> #NAME? | E69: {=_xll.BDP("BX625748 Corp","DS004")} -> #NAME? | F69: {=_xll.BDP("BX625748 Corp","DS035")} -> #NAME? | G69: {=_xll.BDP("BX625748 Corp","DS086")} -> #NAME? | H69: {=_xll.BDP("BX625748 Corp","DS034")} -> #NAME? | I69: {=_xll.BDP("BX625748 Corp","DS033")} -> #NAME? | J69: {=_xll.BDP("BX625748 Corp","YL018")} -> #NAME? | K69: {=_xll.BDP("BX625748 Corp","YL016")} -> #NAME? | L69: {=_xll.BDP("BX625748 Corp","PR004")} -> #NAME? | M69: {=_xll.BDP("BX625748 Corp","PR002")} -> #NAME? | N69: {=_xll.BDP("BX625748 Corp","ID028")} -> #NAME? | O69: {=_xll.BDP("BX625748 Corp","ID005")} -> #NAME? | P69: {=_xll.BDP(A69,"RA007")} -> #NAME? | Q69: {=_xll.BDP(A69,"DS219")} -> #NAME? | R69: {=_xll.BDP(A69,"DS040")} -> #NAME? | S69: =(F69-TODAY())/365.25 -> #NAME? | T69: =S69-ROUNDDOWN(S69,0) -> #NAME? | U69: =DATE(2026,MONTH(TODAY()),DAY(F69))>DATEVALUE(R69) -> #NAME?
A70: BX715025 Corp | B70: {=_xll.BDP("BX715025 Corp","DS520")} -> #NAME? | C70: {=_xll.BDP("BX715025 Corp","DS001")} -> #NAME? | D70: {=_xll.BDP("BX715025 Corp","DS458")} -> #NAME? | E70: {=_xll.BDP("BX715025 Corp","DS004")} -> #NAME? | F70: {=_xll.BDP("BX715025 Corp","DS035")} -> #NAME? | G70: {=_xll.BDP("BX715025 Corp","DS086")} -> #NAME? | H70: {=_xll.BDP("BX715025 Corp","DS034")} -> #NAME? | I70: {=_xll.BDP("BX715025 Corp","DS033")} -> #NAME? | J70: {=_xll.BDP("BX715025 Corp","YL018")} -> #NAME? | K70: {=_xll.BDP("BX715025 Corp","YL016")} -> #NAME? | L70: {=_xll.BDP("BX715025 Corp","PR004")} -> #NAME? | M70: {=_xll.BDP("BX715025 Corp","PR002")} -> #NAME? | N70: {=_xll.BDP("BX715025 Corp","ID028")} -> #NAME? | O70: {=_xll.BDP("BX715025 Corp","ID005")} -> #NAME? | P70: {=_xll.BDP(A70,"RA007")} -> #NAME? | Q70: {=_xll.BDP(A70,"DS219")} -> #NAME? | R70: {=_xll.BDP(A70,"DS040")} -> #NAME? | S70: =(F70-TODAY())/365.25 -> #NAME? | T70: =S70-ROUNDDOWN(S70,0) -> #NAME? | U70: =DATE(2026,MONTH(TODAY()),DAY(F70))>DATEVALUE(R70) -> #NAME?
A71: BX810244 Corp | B71: {=_xll.BDP("BX810244 Corp","DS520")} -> #NAME? | C71: {=_xll.BDP("BX810244 Corp","DS001")} -> #NAME? | D71: {=_xll.BDP("BX810244 Corp","DS458")} -> #NAME? | E71: {=_xll.BDP("BX810244 Corp","DS004")} -> #NAME? | F71: {=_xll.BDP("BX810244 Corp","DS035")} -> #NAME? | G71: {=_xll.BDP("BX810244 Corp","DS086")} -> #NAME? | H71: {=_xll.BDP("BX810244 Corp","DS034")} -> #NAME? | I71: {=_xll.BDP("BX810244 Corp","DS033")} -> #NAME? | J71: {=_xll.BDP("BX810244 Corp","YL018")} -> #NAME? | K71: {=_xll.BDP("BX810244 Corp","YL016")} -> #NAME? | L71: {=_xll.BDP("BX810244 Corp","PR004")} -> #NAME? | M71: {=_xll.BDP("BX810244 Corp","PR002")} -> #NAME? | N71: {=_xll.BDP("BX810244 Corp","ID028")} -> #NAME? | O71: {=_xll.BDP("BX810244 Corp","ID005")} -> #NAME? | P71: {=_xll.BDP(A71,"RA007")} -> #NAME? | Q71: {=_xll.BDP(A71,"DS219")} -> #NAME? | R71: {=_xll.BDP(A71,"DS040")} -> #NAME? | S71: =(F71-TODAY())/365.25 -> #NAME? | T71: =S71-ROUNDDOWN(S71,0) -> #NAME? | U71: =DATE(2026,MONTH(TODAY()),DAY(F71))>DATEVALUE(R71) -> #NAME?
A72: BX863121 Corp | B72: {=_xll.BDP("BX863121 Corp","DS520")} -> #NAME? | C72: {=_xll.BDP("BX863121 Corp","DS001")} -> #NAME? | D72: {=_xll.BDP("BX863121 Corp","DS458")} -> #NAME? | E72: {=_xll.BDP("BX863121 Corp","DS004")} -> #NAME? | F72: {=_xll.BDP("BX863121 Corp","DS035")} -> #NAME? | G72: {=_xll.BDP("BX863121 Corp","DS086")} -> #NAME? | H72: {=_xll.BDP("BX863121 Corp","DS034")} -> #NAME? | I72: {=_xll.BDP("BX863121 Corp","DS033")} -> #NAME? | J72: {=_xll.BDP("BX863121 Corp","YL018")} -> #NAME? | K72: {=_xll.BDP("BX863121 Corp","YL016")} -> #NAME? | L72: {=_xll.BDP("BX863121 Corp","PR004")} -> #NAME? | M72: {=_xll.BDP("BX863121 Corp","PR002")} -> #NAME? | N72: {=_xll.BDP("BX863121 Corp","ID028")} -> #NAME? | O72: {=_xll.BDP("BX863121 Corp","ID005")} -> #NAME? | P72: {=_xll.BDP(A72,"RA007")} -> #NAME? | Q72: {=_xll.BDP(A72,"DS219")} -> #NAME? | R72: {=_xll.BDP(A72,"DS040")} -> #NAME? | S72: =(F72-TODAY())/365.25 -> #NAME? | T72: =S72-ROUNDDOWN(S72,0) -> #NAME? | U72: =DATE(2026,MONTH(TODAY()),DAY(F72))>DATEVALUE(R72) -> #NAME?
A73: BZ503564 Corp | B73: {=_xll.BDP("BZ503564 Corp","DS520")} -> #NAME? | C73: {=_xll.BDP("BZ503564 Corp","DS001")} -> #NAME? | D73: {=_xll.BDP("BZ503564 Corp","DS458")} -> #NAME? | E73: {=_xll.BDP("BZ503564 Corp","DS004")} -> #NAME? | F73: {=_xll.BDP("BZ503564 Corp","DS035")} -> #NAME? | G73: {=_xll.BDP("BZ503564 Corp","DS086")} -> #NAME? | H73: {=_xll.BDP("BZ503564 Corp","DS034")} -> #NAME? | I73: {=_xll.BDP("BZ503564 Corp","DS033")} -> #NAME? | J73: {=_xll.BDP("BZ503564 Corp","YL018")} -> #NAME? | K73: {=_xll.BDP("BZ503564 Corp","YL016")} -> #NAME? | L73: {=_xll.BDP("BZ503564 Corp","PR004")} -> #NAME? | M73: {=_xll.BDP("BZ503564 Corp","PR002")} -> #NAME? | N73: {=_xll.BDP("BZ503564 Corp","ID028")} -> #NAME? | O73: {=_xll.BDP("BZ503564 Corp","ID005")} -> #NAME? | P73: {=_xll.BDP(A73,"RA007")} -> #NAME? | Q73: {=_xll.BDP(A73,"DS219")} -> #NAME? | R73: {=_xll.BDP(A73,"DS040")} -> #NAME? | S73: =(F73-TODAY())/365.25 -> #NAME? | T73: =S73-ROUNDDOWN(S73,0) -> #NAME? | U73: =DATE(2026,MONTH(TODAY()),DAY(F73))>DATEVALUE(R73) -> #NAME?
A74: BZ687913 Corp | B74: {=_xll.BDP("BZ687913 Corp","DS520")} -> #NAME? | C74: {=_xll.BDP("BZ687913 Corp","DS001")} -> #NAME? | D74: {=_xll.BDP("BZ687913 Corp","DS458")} -> #NAME? | E74: {=_xll.BDP("BZ687913 Corp","DS004")} -> #NAME? | F74: {=_xll.BDP("BZ687913 Corp","DS035")} -> #NAME? | G74: {=_xll.BDP("BZ687913 Corp","DS086")} -> #NAME? | H74: {=_xll.BDP("BZ687913 Corp","DS034")} -> #NAME? | I74: {=_xll.BDP("BZ687913 Corp","DS033")} -> #NAME? | J74: {=_xll.BDP("BZ687913 Corp","YL018")} -> #NAME? | K74: {=_xll.BDP("BZ687913 Corp","YL016")} -> #NAME? | L74: {=_xll.BDP("BZ687913 Corp","PR004")} -> #NAME? | M74: {=_xll.BDP("BZ687913 Corp","PR002")} -> #NAME? | N74: {=_xll.BDP("BZ687913 Corp","ID028")} -> #NAME? | O74: {=_xll.BDP("BZ687913 Corp","ID005")} -> #NAME? | P74: {=_xll.BDP(A74,"RA007")} -> #NAME? | Q74: {=_xll.BDP(A74,"DS219")} -> #NAME? | R74: {=_xll.BDP(A74,"DS040")} -> #NAME? | S74: =(F74-TODAY())/365.25 -> #NAME? | T74: =S74-ROUNDDOWN(S74,0) -> #NAME? | U74: =DATE(2026,MONTH(TODAY()),DAY(F74))>DATEVALUE(R74) -> #NAME?
A75: BZ743105 Corp | B75: {=_xll.BDP("BZ743105 Corp","DS520")} -> #NAME? | C75: {=_xll.BDP("BZ743105 Corp","DS001")} -> #NAME? | D75: {=_xll.BDP("BZ743105 Corp","DS458")} -> #NAME? | E75: {=_xll.BDP("BZ743105 Corp","DS004")} -> #NAME? | F75: {=_xll.BDP("BZ743105 Corp","DS035")} -> #NAME? | G75: {=_xll.BDP("BZ743105 Corp","DS086")} -> #NAME? | H75: {=_xll.BDP("BZ743105 Corp","DS034")} -> #NAME? | I75: {=_xll.BDP("BZ743105 Corp","DS033")} -> #NAME? | J75: {=_xll.BDP("BZ743105 Corp","YL018")} -> #NAME? | K75: {=_xll.BDP("BZ743105 Corp","YL016")} -> #NAME? | L75: {=_xll.BDP("BZ743105 Corp","PR004")} -> #NAME? | M75: {=_xll.BDP("BZ743105 Corp","PR002")} -> #NAME? | N75: {=_xll.BDP("BZ743105 Corp","ID028")} -> #NAME? | O75: {=_xll.BDP("BZ743105 Corp","ID005")} -> #NAME? | P75: {=_xll.BDP(A75,"RA007")} -> #NAME? | Q75: {=_xll.BDP(A75,"DS219")} -> #NAME? | R75: {=_xll.BDP(A75,"DS040")} -> #NAME? | S75: =(F75-TODAY())/365.25 -> #NAME? | T75: =S75-ROUNDDOWN(S75,0) -> #NAME? | U75: =DATE(2026,MONTH(TODAY()),DAY(F75))>DATEVALUE(R75) -> #NAME?
A76: BZ802616 Corp | B76: {=_xll.BDP("BZ802616 Corp","DS520")} -> #NAME? | C76: {=_xll.BDP("BZ802616 Corp","DS001")} -> #NAME? | D76: {=_xll.BDP("BZ802616 Corp","DS458")} -> #NAME? | E76: {=_xll.BDP("BZ802616 Corp","DS004")} -> #NAME? | F76: {=_xll.BDP("BZ802616 Corp","DS035")} -> #NAME? | G76: {=_xll.BDP("BZ802616 Corp","DS086")} -> #NAME? | H76: {=_xll.BDP("BZ802616 Corp","DS034")} -> #NAME? | I76: {=_xll.BDP("BZ802616 Corp","DS033")} -> #NAME? | J76: {=_xll.BDP("BZ802616 Corp","YL018")} -> #NAME? | K76: {=_xll.BDP("BZ802616 Corp","YL016")} -> #NAME? | L76: {=_xll.BDP("BZ802616 Corp","PR004")} -> #NAME? | M76: {=_xll.BDP("BZ802616 Corp","PR002")} -> #NAME? | N76: {=_xll.BDP("BZ802616 Corp","ID028")} -> #NAME? | O76: {=_xll.BDP("BZ802616 Corp","ID005")} -> #NAME? | P76: {=_xll.BDP(A76,"RA007")} -> #NAME? | Q76: {=_xll.BDP(A76,"DS219")} -> #NAME? | R76: {=_xll.BDP(A76,"DS040")} -> #NAME? | S76: =(F76-TODAY())/365.25 -> #NAME? | T76: =S76-ROUNDDOWN(S76,0) -> #NAME? | U76: =DATE(2026,MONTH(TODAY()),DAY(F76))>DATEVALUE(R76) -> #NAME?
A77: DA962213 Corp | B77: {=_xll.BDP("DA962213 Corp","DS520")} -> #NAME? | C77: {=_xll.BDP("DA962213 Corp","DS001")} -> #NAME? | D77: {=_xll.BDP("DA962213 Corp","DS458")} -> #NAME? | E77: {=_xll.BDP("DA962213 Corp","DS004")} -> #NAME? | F77: {=_xll.BDP("DA962213 Corp","DS035")} -> #NAME? | G77: {=_xll.BDP("DA962213 Corp","DS086")} -> #NAME? | H77: {=_xll.BDP("DA962213 Corp","DS034")} -> #NAME? | I77: {=_xll.BDP("DA962213 Corp","DS033")} -> #NAME? | J77: {=_xll.BDP("DA962213 Corp","YL018")} -> #NAME? | K77: {=_xll.BDP("DA962213 Corp","YL016")} -> #NAME? | L77: {=_xll.BDP("DA962213 Corp","PR004")} -> #NAME? | M77: {=_xll.BDP("DA962213 Corp","PR002")} -> #NAME? | N77: {=_xll.BDP("DA962213 Corp","ID028")} -> #NAME? | O77: {=_xll.BDP("DA962213 Corp","ID005")} -> #NAME? | P77: {=_xll.BDP(A77,"RA007")} -> #NAME? | Q77: {=_xll.BDP(A77,"DS219")} -> #NAME? | R77: {=_xll.BDP(A77,"DS040")} -> #NAME? | S77: =(F77-TODAY())/365.25 -> #NAME? | T77: =S77-ROUNDDOWN(S77,0) -> #NAME? | U77: =DATE(2026,MONTH(TODAY()),DAY(F77))>DATEVALUE(R77) -> #NAME?
A78: DC209344 Corp | B78: {=_xll.BDP("DC209344 Corp","DS520")} -> #NAME? | C78: {=_xll.BDP("DC209344 Corp","DS001")} -> #NAME? | D78: {=_xll.BDP("DC209344 Corp","DS458")} -> #NAME? | E78: {=_xll.BDP("DC209344 Corp","DS004")} -> #NAME? | F78: {=_xll.BDP("DC209344 Corp","DS035")} -> #NAME? | G78: {=_xll.BDP("DC209344 Corp","DS086")} -> #NAME? | H78: {=_xll.BDP("DC209344 Corp","DS034")} -> #NAME? | I78: {=_xll.BDP("DC209344 Corp","DS033")} -> #NAME? | J78: {=_xll.BDP("DC209344 Corp","YL018")} -> #NAME? | K78: {=_xll.BDP("DC209344 Corp","YL016")} -> #NAME? | L78: {=_xll.BDP("DC209344 Corp","PR004")} -> #NAME? | M78: {=_xll.BDP("DC209344 Corp","PR002")} -> #NAME? | N78: {=_xll.BDP("DC209344 Corp","ID028")} -> #NAME? | O78: {=_xll.BDP("DC209344 Corp","ID005")} -> #NAME? | P78: {=_xll.BDP(A78,"RA007")} -> #NAME? | Q78: {=_xll.BDP(A78,"DS219")} -> #NAME? | R78: {=_xll.BDP(A78,"DS040")} -> #NAME? | S78: =(F78-TODAY())/365.25 -> #NAME? | T78: =S78-ROUNDDOWN(S78,0) -> #NAME? | U78: =DATE(2026,MONTH(TODAY()),DAY(F78))>DATEVALUE(R78) -> #NAME?
A79: DC578379 Corp | B79: {=_xll.BDP("DC578379 Corp","DS520")} -> #NAME? | C79: {=_xll.BDP("DC578379 Corp","DS001")} -> #NAME? | D79: {=_xll.BDP("DC578379 Corp","DS458")} -> #NAME? | E79: {=_xll.BDP("DC578379 Corp","DS004")} -> #NAME? | F79: {=_xll.BDP("DC578379 Corp","DS035")} -> #NAME? | G79: {=_xll.BDP("DC578379 Corp","DS086")} -> #NAME? | H79: {=_xll.BDP("DC578379 Corp","DS034")} -> #NAME? | I79: {=_xll.BDP("DC578379 Corp","DS033")} -> #NAME? | J79: {=_xll.BDP("DC578379 Corp","YL018")} -> #NAME? | K79: {=_xll.BDP("DC578379 Corp","YL016")} -> #NAME? | L79: {=_xll.BDP("DC578379 Corp","PR004")} -> #NAME? | M79: {=_xll.BDP("DC578379 Corp","PR002")} -> #NAME? | N79: {=_xll.BDP("DC578379 Corp","ID028")} -> #NAME? | O79: {=_xll.BDP("DC578379 Corp","ID005")} -> #NAME? | P79: {=_xll.BDP(A79,"RA007")} -> #NAME? | Q79: {=_xll.BDP(A79,"DS219")} -> #NAME? | R79: {=_xll.BDP(A79,"DS040")} -> #NAME? | S79: =(F79-TODAY())/365.25 -> #NAME? | T79: =S79-ROUNDDOWN(S79,0) -> #NAME? | U79: =DATE(2026,MONTH(TODAY()),DAY(F79))>DATEVALUE(R79) -> #NAME?
A80: DC746693 Corp | B80: {=_xll.BDP("DC746693 Corp","DS520")} -> #NAME? | C80: {=_xll.BDP("DC746693 Corp","DS001")} -> #NAME? | D80: {=_xll.BDP("DC746693 Corp","DS458")} -> #NAME? | E80: {=_xll.BDP("DC746693 Corp","DS004")} -> #NAME? | F80: {=_xll.BDP("DC746693 Corp","DS035")} -> #NAME? | G80: {=_xll.BDP("DC746693 Corp","DS086")} -> #NAME? | H80: {=_xll.BDP("DC746693 Corp","DS034")} -> #NAME? | I80: {=_xll.BDP("DC746693 Corp","DS033")} -> #NAME? | J80: {=_xll.BDP("DC746693 Corp","YL018")} -> #NAME? | K80: {=_xll.BDP("DC746693 Corp","YL016")} -> #NAME? | L80: {=_xll.BDP("DC746693 Corp","PR004")} -> #NAME? | M80: {=_xll.BDP("DC746693 Corp","PR002")} -> #NAME? | N80: {=_xll.BDP("DC746693 Corp","ID028")} -> #NAME? | O80: {=_xll.BDP("DC746693 Corp","ID005")} -> #NAME? | P80: {=_xll.BDP(A80,"RA007")} -> #NAME? | Q80: {=_xll.BDP(A80,"DS219")} -> #NAME? | R80: {=_xll.BDP(A80,"DS040")} -> #NAME? | S80: =(F80-TODAY())/365.25 -> #NAME? | T80: =S80-ROUNDDOWN(S80,0) -> #NAME? | U80: =DATE(2026,MONTH(TODAY()),DAY(F80))>DATEVALUE(R80) -> #NAME?
A81: DC841111 Corp | B81: {=_xll.BDP("DC841111 Corp","DS520")} -> #NAME? | C81: {=_xll.BDP("DC841111 Corp","DS001")} -> #NAME? | D81: {=_xll.BDP("DC841111 Corp","DS458")} -> #NAME? | E81: {=_xll.BDP("DC841111 Corp","DS004")} -> #NAME? | F81: {=_xll.BDP("DC841111 Corp","DS035")} -> #NAME? | G81: {=_xll.BDP("DC841111 Corp","DS086")} -> #NAME? | H81: {=_xll.BDP("DC841111 Corp","DS034")} -> #NAME? | I81: {=_xll.BDP("DC841111 Corp","DS033")} -> #NAME? | J81: {=_xll.BDP("DC841111 Corp","YL018")} -> #NAME? | K81: {=_xll.BDP("DC841111 Corp","YL016")} -> #NAME? | L81: {=_xll.BDP("DC841111 Corp","PR004")} -> #NAME? | M81: {=_xll.BDP("DC841111 Corp","PR002")} -> #NAME? | N81: {=_xll.BDP("DC841111 Corp","ID028")} -> #NAME? | O81: {=_xll.BDP("DC841111 Corp","ID005")} -> #NAME? | P81: {=_xll.BDP(A81,"RA007")} -> #NAME? | Q81: {=_xll.BDP(A81,"DS219")} -> #NAME? | R81: {=_xll.BDP(A81,"DS040")} -> #NAME? | S81: =(F81-TODAY())/365.25 -> #NAME? | T81: =S81-ROUNDDOWN(S81,0) -> #NAME? | U81: =DATE(2026,MONTH(TODAY()),DAY(F81))>DATEVALUE(R81) -> #NAME?
A82: DF972719 Corp | B82: {=_xll.BDP("DF972719 Corp","DS520")} -> #NAME? | C82: {=_xll.BDP("DF972719 Corp","DS001")} -> #NAME? | D82: {=_xll.BDP("DF972719 Corp","DS458")} -> #NAME? | E82: {=_xll.BDP("DF972719 Corp","DS004")} -> #NAME? | F82: {=_xll.BDP("DF972719 Corp","DS035")} -> #NAME? | G82: {=_xll.BDP("DF972719 Corp","DS086")} -> #NAME? | H82: {=_xll.BDP("DF972719 Corp","DS034")} -> #NAME? | I82: {=_xll.BDP("DF972719 Corp","DS033")} -> #NAME? | J82: {=_xll.BDP("DF972719 Corp","YL018")} -> #NAME? | K82: {=_xll.BDP("DF972719 Corp","YL016")} -> #NAME? | L82: {=_xll.BDP("DF972719 Corp","PR004")} -> #NAME? | M82: {=_xll.BDP("DF972719 Corp","PR002")} -> #NAME? | N82: {=_xll.BDP("DF972719 Corp","ID028")} -> #NAME? | O82: {=_xll.BDP("DF972719 Corp","ID005")} -> #NAME? | P82: {=_xll.BDP(A82,"RA007")} -> #NAME? | Q82: {=_xll.BDP(A82,"DS219")} -> #NAME? | R82: {=_xll.BDP(A82,"DS040")} -> #NAME? | S82: =(F82-TODAY())/365.25 -> #NAME? | T82: =S82-ROUNDDOWN(S82,0) -> #NAME? | U82: =DATE(2026,MONTH(TODAY()),DAY(F82))>DATEVALUE(R82) -> #NAME?
A83: EC174534 Corp | B83: {=_xll.BDP("EC174534 Corp","DS520")} -> #NAME? | C83: {=_xll.BDP("EC174534 Corp","DS001")} -> #NAME? | D83: {=_xll.BDP("EC174534 Corp","DS458")} -> #NAME? | E83: {=_xll.BDP("EC174534 Corp","DS004")} -> #NAME? | F83: {=_xll.BDP("EC174534 Corp","DS035")} -> #NAME? | G83: {=_xll.BDP("EC174534 Corp","DS086")} -> #NAME? | H83: {=_xll.BDP("EC174534 Corp","DS034")} -> #NAME? | I83: {=_xll.BDP("EC174534 Corp","DS033")} -> #NAME? | J83: {=_xll.BDP("EC174534 Corp","YL018")} -> #NAME? | K83: {=_xll.BDP("EC174534 Corp","YL016")} -> #NAME? | L83: {=_xll.BDP("EC174534 Corp","PR004")} -> #NAME? | M83: {=_xll.BDP("EC174534 Corp","PR002")} -> #NAME? | N83: {=_xll.BDP("EC174534 Corp","ID028")} -> #NAME? | O83: {=_xll.BDP("EC174534 Corp","ID005")} -> #NAME? | P83: {=_xll.BDP(A83,"RA007")} -> #NAME? | Q83: {=_xll.BDP(A83,"DS219")} -> #NAME? | R83: {=_xll.BDP(A83,"DS040")} -> #NAME? | S83: =(F83-TODAY())/365.25 -> #NAME? | T83: =S83-ROUNDDOWN(S83,0) -> #NAME? | U83: =DATE(2026,MONTH(TODAY()),DAY(F83))>DATEVALUE(R83) -> #NAME?
A84: EC222031 Corp | B84: {=_xll.BDP("EC222031 Corp","DS520")} -> #NAME? | C84: {=_xll.BDP("EC222031 Corp","DS001")} -> #NAME? | D84: {=_xll.BDP("EC222031 Corp","DS458")} -> #NAME? | E84: {=_xll.BDP("EC222031 Corp","DS004")} -> #NAME? | F84: {=_xll.BDP("EC222031 Corp","DS035")} -> #NAME? | G84: {=_xll.BDP("EC222031 Corp","DS086")} -> #NAME? | H84: {=_xll.BDP("EC222031 Corp","DS034")} -> #NAME? | I84: {=_xll.BDP("EC222031 Corp","DS033")} -> #NAME? | J84: {=_xll.BDP("EC222031 Corp","YL018")} -> #NAME? | K84: {=_xll.BDP("EC222031 Corp","YL016")} -> #NAME? | L84: {=_xll.BDP("EC222031 Corp","PR004")} -> #NAME? | M84: {=_xll.BDP("EC222031 Corp","PR002")} -> #NAME? | N84: {=_xll.BDP("EC222031 Corp","ID028")} -> #NAME? | O84: {=_xll.BDP("EC222031 Corp","ID005")} -> #NAME? | P84: {=_xll.BDP(A84,"RA007")} -> #NAME? | Q84: {=_xll.BDP(A84,"DS219")} -> #NAME? | R84: {=_xll.BDP(A84,"DS040")} -> #NAME? | S84: =(F84-TODAY())/365.25 -> #NAME? | T84: =S84-ROUNDDOWN(S84,0) -> #NAME? | U84: =DATE(2026,MONTH(TODAY()),DAY(F84))>DATEVALUE(R84) -> #NAME?
A85: EC256531 Corp | B85: {=_xll.BDP("EC256531 Corp","DS520")} -> #NAME? | C85: {=_xll.BDP("EC256531 Corp","DS001")} -> #NAME? | D85: {=_xll.BDP("EC256531 Corp","DS458")} -> #NAME? | E85: {=_xll.BDP("EC256531 Corp","DS004")} -> #NAME? | F85: {=_xll.BDP("EC256531 Corp","DS035")} -> #NAME? | G85: {=_xll.BDP("EC256531 Corp","DS086")} -> #NAME? | H85: {=_xll.BDP("EC256531 Corp","DS034")} -> #NAME? | I85: {=_xll.BDP("EC256531 Corp","DS033")} -> #NAME? | J85: {=_xll.BDP("EC256531 Corp","YL018")} -> #NAME? | K85: {=_xll.BDP("EC256531 Corp","YL016")} -> #NAME? | L85: {=_xll.BDP("EC256531 Corp","PR004")} -> #NAME? | M85: {=_xll.BDP("EC256531 Corp","PR002")} -> #NAME? | N85: {=_xll.BDP("EC256531 Corp","ID028")} -> #NAME? | O85: {=_xll.BDP("EC256531 Corp","ID005")} -> #NAME? | P85: {=_xll.BDP(A85,"RA007")} -> #NAME? | Q85: {=_xll.BDP(A85,"DS219")} -> #NAME? | R85: {=_xll.BDP(A85,"DS040")} -> #NAME? | S85: =(F85-TODAY())/365.25 -> #NAME? | T85: =S85-ROUNDDOWN(S85,0) -> #NAME? | U85: =DATE(2026,MONTH(TODAY()),DAY(F85))>DATEVALUE(R85) -> #NAME?
A86: EC306656 Corp | B86: {=_xll.BDP("EC306656 Corp","DS520")} -> #NAME? | C86: {=_xll.BDP("EC306656 Corp","DS001")} -> #NAME? | D86: {=_xll.BDP("EC306656 Corp","DS458")} -> #NAME? | E86: {=_xll.BDP("EC306656 Corp","DS004")} -> #NAME? | F86: {=_xll.BDP("EC306656 Corp","DS035")} -> #NAME? | G86: {=_xll.BDP("EC306656 Corp","DS086")} -> #NAME? | H86: {=_xll.BDP("EC306656 Corp","DS034")} -> #NAME? | I86: {=_xll.BDP("EC306656 Corp","DS033")} -> #NAME? | J86: {=_xll.BDP("EC306656 Corp","YL018")} -> #NAME? | K86: {=_xll.BDP("EC306656 Corp","YL016")} -> #NAME? | L86: {=_xll.BDP("EC306656 Corp","PR004")} -> #NAME? | M86: {=_xll.BDP("EC306656 Corp","PR002")} -> #NAME? | N86: {=_xll.BDP("EC306656 Corp","ID028")} -> #NAME? | O86: {=_xll.BDP("EC306656 Corp","ID005")} -> #NAME? | P86: {=_xll.BDP(A86,"RA007")} -> #NAME? | Q86: {=_xll.BDP(A86,"DS219")} -> #NAME? | R86: {=_xll.BDP(A86,"DS040")} -> #NAME? | S86: =(F86-TODAY())/365.25 -> #NAME? | T86: =S86-ROUNDDOWN(S86,0) -> #NAME? | U86: =DATE(2026,MONTH(TODAY()),DAY(F86))>DATEVALUE(R86) -> #NAME?
A87: EC387594 Corp | B87: {=_xll.BDP("EC387594 Corp","DS520")} -> #NAME? | C87: {=_xll.BDP("EC387594 Corp","DS001")} -> #NAME? | D87: {=_xll.BDP("EC387594 Corp","DS458")} -> #NAME? | E87: {=_xll.BDP("EC387594 Corp","DS004")} -> #NAME? | F87: {=_xll.BDP("EC387594 Corp","DS035")} -> #NAME? | G87: {=_xll.BDP("EC387594 Corp","DS086")} -> #NAME? | H87: {=_xll.BDP("EC387594 Corp","DS034")} -> #NAME? | I87: {=_xll.BDP("EC387594 Corp","DS033")} -> #NAME? | J87: {=_xll.BDP("EC387594 Corp","YL018")} -> #NAME? | K87: {=_xll.BDP("EC387594 Corp","YL016")} -> #NAME? | L87: {=_xll.BDP("EC387594 Corp","PR004")} -> #NAME? | M87: {=_xll.BDP("EC387594 Corp","PR002")} -> #NAME? | N87: {=_xll.BDP("EC387594 Corp","ID028")} -> #NAME? | O87: {=_xll.BDP("EC387594 Corp","ID005")} -> #NAME? | P87: {=_xll.BDP(A87,"RA007")} -> #NAME? | Q87: {=_xll.BDP(A87,"DS219")} -> #NAME? | R87: {=_xll.BDP(A87,"DS040")} -> #NAME? | S87: =(F87-TODAY())/365.25 -> #NAME? | T87: =S87-ROUNDDOWN(S87,0) -> #NAME? | U87: =DATE(2026,MONTH(TODAY()),DAY(F87))>DATEVALUE(R87) -> #NAME?
A88: EC474539 Corp | B88: {=_xll.BDP("EC474539 Corp","DS520")} -> #NAME? | C88: {=_xll.BDP("EC474539 Corp","DS001")} -> #NAME? | D88: {=_xll.BDP("EC474539 Corp","DS458")} -> #NAME? | E88: {=_xll.BDP("EC474539 Corp","DS004")} -> #NAME? | F88: {=_xll.BDP("EC474539 Corp","DS035")} -> #NAME? | G88: {=_xll.BDP("EC474539 Corp","DS086")} -> #NAME? | H88: {=_xll.BDP("EC474539 Corp","DS034")} -> #NAME? | I88: {=_xll.BDP("EC474539 Corp","DS033")} -> #NAME? | J88: {=_xll.BDP("EC474539 Corp","YL018")} -> #NAME? | K88: {=_xll.BDP("EC474539 Corp","YL016")} -> #NAME? | L88: {=_xll.BDP("EC474539 Corp","PR004")} -> #NAME? | M88: {=_xll.BDP("EC474539 Corp","PR002")} -> #NAME? | N88: {=_xll.BDP("EC474539 Corp","ID028")} -> #NAME? | O88: {=_xll.BDP("EC474539 Corp","ID005")} -> #NAME? | P88: {=_xll.BDP(A88,"RA007")} -> #NAME? | Q88: {=_xll.BDP(A88,"DS219")} -> #NAME? | R88: {=_xll.BDP(A88,"DS040")} -> #NAME? | S88: =(F88-TODAY())/365.25 -> #NAME? | T88: =S88-ROUNDDOWN(S88,0) -> #NAME? | U88: =DATE(2026,MONTH(TODAY()),DAY(F88))>DATEVALUE(R88) -> #NAME?
A89: EC565086 Corp | B89: {=_xll.BDP("EC565086 Corp","DS520")} -> #NAME? | C89: {=_xll.BDP("EC565086 Corp","DS001")} -> #NAME? | D89: {=_xll.BDP("EC565086 Corp","DS458")} -> #NAME? | E89: {=_xll.BDP("EC565086 Corp","DS004")} -> #NAME? | F89: {=_xll.BDP("EC565086 Corp","DS035")} -> #NAME? | G89: {=_xll.BDP("EC565086 Corp","DS086")} -> #NAME? | H89: {=_xll.BDP("EC565086 Corp","DS034")} -> #NAME? | I89: {=_xll.BDP("EC565086 Corp","DS033")} -> #NAME? | J89: {=_xll.BDP("EC565086 Corp","YL018")} -> #NAME? | K89: {=_xll.BDP("EC565086 Corp","YL016")} -> #NAME? | L89: {=_xll.BDP("EC565086 Corp","PR004")} -> #NAME? | M89: {=_xll.BDP("EC565086 Corp","PR002")} -> #NAME? | N89: {=_xll.BDP("EC565086 Corp","ID028")} -> #NAME? | O89: {=_xll.BDP("EC565086 Corp","ID005")} -> #NAME? | P89: {=_xll.BDP(A89,"RA007")} -> #NAME? | Q89: {=_xll.BDP(A89,"DS219")} -> #NAME? | R89: {=_xll.BDP(A89,"DS040")} -> #NAME? | S89: =(F89-TODAY())/365.25 -> #NAME? | T89: =S89-ROUNDDOWN(S89,0) -> #NAME? | U89: =DATE(2026,MONTH(TODAY()),DAY(F89))>DATEVALUE(R89) -> #NAME?
A90: EC748607 Corp | B90: {=_xll.BDP("EC748607 Corp","DS520")} -> #NAME? | C90: {=_xll.BDP("EC748607 Corp","DS001")} -> #NAME? | D90: {=_xll.BDP("EC748607 Corp","DS458")} -> #NAME? | E90: {=_xll.BDP("EC748607 Corp","DS004")} -> #NAME? | F90: {=_xll.BDP("EC748607 Corp","DS035")} -> #NAME? | G90: {=_xll.BDP("EC748607 Corp","DS086")} -> #NAME? | H90: {=_xll.BDP("EC748607 Corp","DS034")} -> #NAME? | I90: {=_xll.BDP("EC748607 Corp","DS033")} -> #NAME? | J90: {=_xll.BDP("EC748607 Corp","YL018")} -> #NAME? | K90: {=_xll.BDP("EC748607 Corp","YL016")} -> #NAME? | L90: {=_xll.BDP("EC748607 Corp","PR004")} -> #NAME? | M90: {=_xll.BDP("EC748607 Corp","PR002")} -> #NAME? | N90: {=_xll.BDP("EC748607 Corp","ID028")} -> #NAME? | O90: {=_xll.BDP("EC748607 Corp","ID005")} -> #NAME? | P90: {=_xll.BDP(A90,"RA007")} -> #NAME? | Q90: {=_xll.BDP(A90,"DS219")} -> #NAME? | R90: {=_xll.BDP(A90,"DS040")} -> #NAME? | S90: =(F90-TODAY())/365.25 -> #NAME? | T90: =S90-ROUNDDOWN(S90,0) -> #NAME? | U90: =DATE(2026,MONTH(TODAY()),DAY(F90))>DATEVALUE(R90) -> #NAME?
A91: EC820426 Corp | B91: {=_xll.BDP("EC820426 Corp","DS520")} -> #NAME? | C91: {=_xll.BDP("EC820426 Corp","DS001")} -> #NAME? | D91: {=_xll.BDP("EC820426 Corp","DS458")} -> #NAME? | E91: {=_xll.BDP("EC820426 Corp","DS004")} -> #NAME? | F91: {=_xll.BDP("EC820426 Corp","DS035")} -> #NAME? | G91: {=_xll.BDP("EC820426 Corp","DS086")} -> #NAME? | H91: {=_xll.BDP("EC820426 Corp","DS034")} -> #NAME? | I91: {=_xll.BDP("EC820426 Corp","DS033")} -> #NAME? | J91: {=_xll.BDP("EC820426 Corp","YL018")} -> #NAME? | K91: {=_xll.BDP("EC820426 Corp","YL016")} -> #NAME? | L91: {=_xll.BDP("EC820426 Corp","PR004")} -> #NAME? | M91: {=_xll.BDP("EC820426 Corp","PR002")} -> #NAME? | N91: {=_xll.BDP("EC820426 Corp","ID028")} -> #NAME? | O91: {=_xll.BDP("EC820426 Corp","ID005")} -> #NAME? | P91: {=_xll.BDP(A91,"RA007")} -> #NAME? | Q91: {=_xll.BDP(A91,"DS219")} -> #NAME? | R91: {=_xll.BDP(A91,"DS040")} -> #NAME? | S91: =(F91-TODAY())/365.25 -> #NAME? | T91: =S91-ROUNDDOWN(S91,0) -> #NAME? | U91: =DATE(2026,MONTH(TODAY()),DAY(F91))>DATEVALUE(R91) -> #NAME?
A92: EC974778 Corp | B92: {=_xll.BDP("EC974778 Corp","DS520")} -> #NAME? | C92: {=_xll.BDP("EC974778 Corp","DS001")} -> #NAME? | D92: {=_xll.BDP("EC974778 Corp","DS458")} -> #NAME? | E92: {=_xll.BDP("EC974778 Corp","DS004")} -> #NAME? | F92: {=_xll.BDP("EC974778 Corp","DS035")} -> #NAME? | G92: {=_xll.BDP("EC974778 Corp","DS086")} -> #NAME? | H92: {=_xll.BDP("EC974778 Corp","DS034")} -> #NAME? | I92: {=_xll.BDP("EC974778 Corp","DS033")} -> #NAME? | J92: {=_xll.BDP("EC974778 Corp","YL018")} -> #NAME? | K92: {=_xll.BDP("EC974778 Corp","YL016")} -> #NAME? | L92: {=_xll.BDP("EC974778 Corp","PR004")} -> #NAME? | M92: {=_xll.BDP("EC974778 Corp","PR002")} -> #NAME? | N92: {=_xll.BDP("EC974778 Corp","ID028")} -> #NAME? | O92: {=_xll.BDP("EC974778 Corp","ID005")} -> #NAME? | P92: {=_xll.BDP(A92,"RA007")} -> #NAME? | Q92: {=_xll.BDP(A92,"DS219")} -> #NAME? | R92: {=_xll.BDP(A92,"DS040")} -> #NAME? | S92: =(F92-TODAY())/365.25 -> #NAME? | T92: =S92-ROUNDDOWN(S92,0) -> #NAME? | U92: =DATE(2026,MONTH(TODAY()),DAY(F92))>DATEVALUE(R92) -> #NAME?
A93: ED067043 Corp | B93: {=_xll.BDP("ED067043 Corp","DS520")} -> #NAME? | C93: {=_xll.BDP("ED067043 Corp","DS001")} -> #NAME? | D93: {=_xll.BDP("ED067043 Corp","DS458")} -> #NAME? | E93: {=_xll.BDP("ED067043 Corp","DS004")} -> #NAME? | F93: {=_xll.BDP("ED067043 Corp","DS035")} -> #NAME? | G93: {=_xll.BDP("ED067043 Corp","DS086")} -> #NAME? | H93: {=_xll.BDP("ED067043 Corp","DS034")} -> #NAME? | I93: {=_xll.BDP("ED067043 Corp","DS033")} -> #NAME? | J93: {=_xll.BDP("ED067043 Corp","YL018")} -> #NAME? | K93: {=_xll.BDP("ED067043 Corp","YL016")} -> #NAME? | L93: {=_xll.BDP("ED067043 Corp","PR004")} -> #NAME? | M93: {=_xll.BDP("ED067043 Corp","PR002")} -> #NAME? | N93: {=_xll.BDP("ED067043 Corp","ID028")} -> #NAME? | O93: {=_xll.BDP("ED067043 Corp","ID005")} -> #NAME? | P93: {=_xll.BDP(A93,"RA007")} -> #NAME? | Q93: {=_xll.BDP(A93,"DS219")} -> #NAME? | R93: {=_xll.BDP(A93,"DS040")} -> #NAME? | S93: =(F93-TODAY())/365.25 -> #NAME? | T93: =S93-ROUNDDOWN(S93,0) -> #NAME? | U93: =DATE(2026,MONTH(TODAY()),DAY(F93))>DATEVALUE(R93) -> #NAME?
A94: ED216135 Corp | B94: {=_xll.BDP("ED216135 Corp","DS520")} -> #NAME? | C94: {=_xll.BDP("ED216135 Corp","DS001")} -> #NAME? | D94: {=_xll.BDP("ED216135 Corp","DS458")} -> #NAME? | E94: {=_xll.BDP("ED216135 Corp","DS004")} -> #NAME? | F94: {=_xll.BDP("ED216135 Corp","DS035")} -> #NAME? | G94: {=_xll.BDP("ED216135 Corp","DS086")} -> #NAME? | H94: {=_xll.BDP("ED216135 Corp","DS034")} -> #NAME? | I94: {=_xll.BDP("ED216135 Corp","DS033")} -> #NAME? | J94: {=_xll.BDP("ED216135 Corp","YL018")} -> #NAME? | K94: {=_xll.BDP("ED216135 Corp","YL016")} -> #NAME? | L94: {=_xll.BDP("ED216135 Corp","PR004")} -> #NAME? | M94: {=_xll.BDP("ED216135 Corp","PR002")} -> #NAME? | N94: {=_xll.BDP("ED216135 Corp","ID028")} -> #NAME? | O94: {=_xll.BDP("ED216135 Corp","ID005")} -> #NAME? | P94: {=_xll.BDP(A94,"RA007")} -> #NAME? | Q94: {=_xll.BDP(A94,"DS219")} -> #NAME? | R94: {=_xll.BDP(A94,"DS040")} -> #NAME? | S94: =(F94-TODAY())/365.25 -> #NAME? | T94: =S94-ROUNDDOWN(S94,0) -> #NAME? | U94: =DATE(2026,MONTH(TODAY()),DAY(F94))>DATEVALUE(R94) -> #NAME?
A95: ED335706 Corp | B95: {=_xll.BDP("ED335706 Corp","DS520")} -> #NAME? | C95: {=_xll.BDP("ED335706 Corp","DS001")} -> #NAME? | D95: {=_xll.BDP("ED335706 Corp","DS458")} -> #NAME? | E95: {=_xll.BDP("ED335706 Corp","DS004")} -> #NAME? | F95: {=_xll.BDP("ED335706 Corp","DS035")} -> #NAME? | G95: {=_xll.BDP("ED335706 Corp","DS086")} -> #NAME? | H95: {=_xll.BDP("ED335706 Corp","DS034")} -> #NAME? | I95: {=_xll.BDP("ED335706 Corp","DS033")} -> #NAME? | J95: {=_xll.BDP("ED335706 Corp","YL018")} -> #NAME? | K95: {=_xll.BDP("ED335706 Corp","YL016")} -> #NAME? | L95: {=_xll.BDP("ED335706 Corp","PR004")} -> #NAME? | M95: {=_xll.BDP("ED335706 Corp","PR002")} -> #NAME? | N95: {=_xll.BDP("ED335706 Corp","ID028")} -> #NAME? | O95: {=_xll.BDP("ED335706 Corp","ID005")} -> #NAME? | P95: {=_xll.BDP(A95,"RA007")} -> #NAME? | Q95: {=_xll.BDP(A95,"DS219")} -> #NAME? | R95: {=_xll.BDP(A95,"DS040")} -> #NAME? | S95: =(F95-TODAY())/365.25 -> #NAME? | T95: =S95-ROUNDDOWN(S95,0) -> #NAME? | U95: =DATE(2026,MONTH(TODAY()),DAY(F95))>DATEVALUE(R95) -> #NAME?
A96: ED424001 Corp | B96: {=_xll.BDP("ED424001 Corp","DS520")} -> #NAME? | C96: {=_xll.BDP("ED424001 Corp","DS001")} -> #NAME? | D96: {=_xll.BDP("ED424001 Corp","DS458")} -> #NAME? | E96: {=_xll.BDP("ED424001 Corp","DS004")} -> #NAME? | F96: {=_xll.BDP("ED424001 Corp","DS035")} -> #NAME? | G96: {=_xll.BDP("ED424001 Corp","DS086")} -> #NAME? | H96: {=_xll.BDP("ED424001 Corp","DS034")} -> #NAME? | I96: {=_xll.BDP("ED424001 Corp","DS033")} -> #NAME? | J96: {=_xll.BDP("ED424001 Corp","YL018")} -> #NAME? | K96: {=_xll.BDP("ED424001 Corp","YL016")} -> #NAME? | L96: {=_xll.BDP("ED424001 Corp","PR004")} -> #NAME? | M96: {=_xll.BDP("ED424001 Corp","PR002")} -> #NAME? | N96: {=_xll.BDP("ED424001 Corp","ID028")} -> #NAME? | O96: {=_xll.BDP("ED424001 Corp","ID005")} -> #NAME? | P96: {=_xll.BDP(A96,"RA007")} -> #NAME? | Q96: {=_xll.BDP(A96,"DS219")} -> #NAME? | R96: {=_xll.BDP(A96,"DS040")} -> #NAME? | S96: =(F96-TODAY())/365.25 -> #NAME? | T96: =S96-ROUNDDOWN(S96,0) -> #NAME? | U96: =DATE(2026,MONTH(TODAY()),DAY(F96))>DATEVALUE(R96) -> #NAME?
A97: ED580618 Corp | B97: {=_xll.BDP("ED580618 Corp","DS520")} -> #NAME? | C97: {=_xll.BDP("ED580618 Corp","DS001")} -> #NAME? | D97: {=_xll.BDP("ED580618 Corp","DS458")} -> #NAME? | E97: {=_xll.BDP("ED580618 Corp","DS004")} -> #NAME? | F97: {=_xll.BDP("ED580618 Corp","DS035")} -> #NAME? | G97: {=_xll.BDP("ED580618 Corp","DS086")} -> #NAME? | H97: {=_xll.BDP("ED580618 Corp","DS034")} -> #NAME? | I97: {=_xll.BDP("ED580618 Corp","DS033")} -> #NAME? | J97: {=_xll.BDP("ED580618 Corp","YL018")} -> #NAME? | K97: {=_xll.BDP("ED580618 Corp","YL016")} -> #NAME? | L97: {=_xll.BDP("ED580618 Corp","PR004")} -> #NAME? | M97: {=_xll.BDP("ED580618 Corp","PR002")} -> #NAME? | N97: {=_xll.BDP("ED580618 Corp","ID028")} -> #NAME? | O97: {=_xll.BDP("ED580618 Corp","ID005")} -> #NAME? | P97: {=_xll.BDP(A97,"RA007")} -> #NAME? | Q97: {=_xll.BDP(A97,"DS219")} -> #NAME? | R97: {=_xll.BDP(A97,"DS040")} -> #NAME? | S97: =(F97-TODAY())/365.25 -> #NAME? | T97: =S97-ROUNDDOWN(S97,0) -> #NAME? | U97: =DATE(2026,MONTH(TODAY()),DAY(F97))>DATEVALUE(R97) -> #NAME?
A98: ED659106 Corp | B98: {=_xll.BDP("ED659106 Corp","DS520")} -> #NAME? | C98: {=_xll.BDP("ED659106 Corp","DS001")} -> #NAME? | D98: {=_xll.BDP("ED659106 Corp","DS458")} -> #NAME? | E98: {=_xll.BDP("ED659106 Corp","DS004")} -> #NAME? | F98: {=_xll.BDP("ED659106 Corp","DS035")} -> #NAME? | G98: {=_xll.BDP("ED659106 Corp","DS086")} -> #NAME? | H98: {=_xll.BDP("ED659106 Corp","DS034")} -> #NAME? | I98: {=_xll.BDP("ED659106 Corp","DS033")} -> #NAME? | J98: {=_xll.BDP("ED659106 Corp","YL018")} -> #NAME? | K98: {=_xll.BDP("ED659106 Corp","YL016")} -> #NAME? | L98: {=_xll.BDP("ED659106 Corp","PR004")} -> #NAME? | M98: {=_xll.BDP("ED659106 Corp","PR002")} -> #NAME? | N98: {=_xll.BDP("ED659106 Corp","ID028")} -> #NAME? | O98: {=_xll.BDP("ED659106 Corp","ID005")} -> #NAME? | P98: {=_xll.BDP(A98,"RA007")} -> #NAME? | Q98: {=_xll.BDP(A98,"DS219")} -> #NAME? | R98: {=_xll.BDP(A98,"DS040")} -> #NAME? | S98: =(F98-TODAY())/365.25 -> #NAME? | T98: =S98-ROUNDDOWN(S98,0) -> #NAME? | U98: =DATE(2026,MONTH(TODAY()),DAY(F98))>DATEVALUE(R98) -> #NAME?
A99: ED819390 Corp | B99: {=_xll.BDP("ED819390 Corp","DS520")} -> #NAME? | C99: {=_xll.BDP("ED819390 Corp","DS001")} -> #NAME? | D99: {=_xll.BDP("ED819390 Corp","DS458")} -> #NAME? | E99: {=_xll.BDP("ED819390 Corp","DS004")} -> #NAME? | F99: {=_xll.BDP("ED819390 Corp","DS035")} -> #NAME? | G99: {=_xll.BDP("ED819390 Corp","DS086")} -> #NAME? | H99: {=_xll.BDP("ED819390 Corp","DS034")} -> #NAME? | I99: {=_xll.BDP("ED819390 Corp","DS033")} -> #NAME? | J99: {=_xll.BDP("ED819390 Corp","YL018")} -> #NAME? | K99: {=_xll.BDP("ED819390 Corp","YL016")} -> #NAME? | L99: {=_xll.BDP("ED819390 Corp","PR004")} -> #NAME? | M99: {=_xll.BDP("ED819390 Corp","PR002")} -> #NAME? | N99: {=_xll.BDP("ED819390 Corp","ID028")} -> #NAME? | O99: {=_xll.BDP("ED819390 Corp","ID005")} -> #NAME? | P99: {=_xll.BDP(A99,"RA007")} -> #NAME? | Q99: {=_xll.BDP(A99,"DS219")} -> #NAME? | R99: {=_xll.BDP(A99,"DS040")} -> #NAME? | S99: =(F99-TODAY())/365.25 -> #NAME? | T99: =S99-ROUNDDOWN(S99,0) -> #NAME? | U99: =DATE(2026,MONTH(TODAY()),DAY(F99))>DATEVALUE(R99) -> #NAME?
A100: ED903474 Corp | B100: {=_xll.BDP("ED903474 Corp","DS520")} -> #NAME? | C100: {=_xll.BDP("ED903474 Corp","DS001")} -> #NAME? | D100: {=_xll.BDP("ED903474 Corp","DS458")} -> #NAME? | E100: {=_xll.BDP("ED903474 Corp","DS004")} -> #NAME? | F100: {=_xll.BDP("ED903474 Corp","DS035")} -> #NAME? | G100: {=_xll.BDP("ED903474 Corp","DS086")} -> #NAME? | H100: {=_xll.BDP("ED903474 Corp","DS034")} -> #NAME? | I100: {=_xll.BDP("ED903474 Corp","DS033")} -> #NAME? | J100: {=_xll.BDP("ED903474 Corp","YL018")} -> #NAME? | K100: {=_xll.BDP("ED903474 Corp","YL016")} -> #NAME? | L100: {=_xll.BDP("ED903474 Corp","PR004")} -> #NAME? | M100: {=_xll.BDP("ED903474 Corp","PR002")} -> #NAME? | N100: {=_xll.BDP("ED903474 Corp","ID028")} -> #NAME? | O100: {=_xll.BDP("ED903474 Corp","ID005")} -> #NAME? | P100: {=_xll.BDP(A100,"RA007")} -> #NAME? | Q100: {=_xll.BDP(A100,"DS219")} -> #NAME? | R100: {=_xll.BDP(A100,"DS040")} -> #NAME? | S100: =(F100-TODAY())/365.25 -> #NAME? | T100: =S100-ROUNDDOWN(S100,0) -> #NAME? | U100: =DATE(2026,MONTH(TODAY()),DAY(F100))>DATEVALUE(R100) -> #NAME?
...

Sheet Offline
A1: Instrument | B1: Name | C1: Ticker | D1: Country/Region | E1: Currency | F1: Maturity | G1: Coupon Type | H1: Coupon Frequency | I1: Coupon | J1: Ask Yield to Maturity | K1: Bid Yield to Maturity | L1: Ask Price | M1: Bid Price | N1: Identifier | O1: ISIN | P1: Bloomberg Composite Rating | Q1: Announce | R1: Next Coupon Settle Date | S1: Time | T1: AVG price | U1: id | V1: TIMEish | W1: years ago | X1: Accrued Interest | Y1: Clean price | Z1: AVG yield
A2: AL516835 Corp | B2: Japan Government Ten Year Bond | C2: JGB | D2: JP | E2: JPY | F2: 20/12/2026 | G2: FIXED | H2: 2 | I2: 0.1 | J2: 0.957 | K2: 0.979 | L2: 99.34 | M2: 99.323 | N2: AL5168359 | O2: JP1103451GC0 | P2: A+ | Q2: 42705 | R2: 46193 | S2: =(F2-TODAY())/365.25 -> 0.72553046 | T2: =AVERAGE(L2:M2) -> 99.3315 | U2: {=_xlfn.SEQUENCE(COUNTA(A2:A327))} -> 1 | V2: =ROUNDDOWN(S2,0)+IF(S2-ROUNDDOWN(S2,0)>0.5,0.5,0) -> 0.5 | W2: =YEAR(TODAY())-YEAR(Q2) -> 10 | X2: =(TODAY()-DATE(YEAR(R2),MONTH(R2)-6,DAY(R2)))/182*(I2) -> 0.054945055 | Y2: =T2-X2 -> 99.276555 | Z2: =AVERAGE(J2:K2) -> 0.968
A3: AL662876 Corp | B3: Japan Government Thirty Year Bond | C3: JGB | D3: JP | E3: JPY | F3: 20/12/2046 | G3: FIXED | H3: 2 | I3: 0.6 | J3: 3.94 | K3: 3.975 | L3: 61.843 | M3: 61.597 | N3: AL6628765 | O3: JP1300531GC0 | P3: A+ | Q3: 42712 | R3: 46193 | S3: =(F3-TODAY())/365.25 -> 20.72553 | T3: =AVERAGE(L3:M3) -> 61.72 | U3: 2 | V3: =ROUNDDOWN(S3,0)+IF(S3-ROUNDDOWN(S3,0)>0.5,0.5,0) -> 20.5 | W3: =YEAR(TODAY())-YEAR(Q3) -> 10 | X3: =(TODAY()-DATE(YEAR(R3),MONTH(R3)-6,DAY(R3)))/182*(I3) -> 0.32967033 | Y3: =T3-X3 -> 61.39033 | Z3: =AVERAGE(J3:K3) -> 3.9575
A4: AL797512 Corp | B4: Japan Government Twenty Year Bond | C4: JGB | D4: JP | E4: JPY | F4: 20/12/2036 | G4: FIXED | H4: 2 | I4: 0.6 | J4: 2.469 | K4: 2.493 | L4: 84.092 | M4: 83.921 | N4: AL7975124 | O4: JP1201591GC4 | P4: A+ | Q4: 42719 | R4: 46193 | S4: =(F4-TODAY())/365.25 -> 10.726899 | T4: =AVERAGE(L4:M4) -> 84.0065 | U4: 3 | V4: =ROUNDDOWN(S4,0)+IF(S4-ROUNDDOWN(S4,0)>0.5,0.5,0) -> 10.5 | W4: =YEAR(TODAY())-YEAR(Q4) -> 10 | X4: =(TODAY()-DATE(YEAR(R4),MONTH(R4)-6,DAY(R4)))/182*(I4) -> 0.32967033 | Y4: =T4-X4 -> 83.67683 | Z4: =AVERAGE(J4:K4) -> 2.481
A5: AM713129 Corp | B5: Japan Government Ten Year Bond | C5: JGB | D5: JP | E5: JPY | F5: 20/03/2027 | G5: FIXED | H5: 2 | I5: 0.1 | J5: 1 | K5: 1.021 | L5: 99.089 | M5: 99.068 | N5: AM7131296 | O5: JP1103461H35 | P5: A+ | Q5: 42796 | R5: 46101 | S5: =(F5-TODAY())/365.25 -> 0.97193703 | T5: =AVERAGE(L5:M5) -> 99.0785 | U5: 4 | V5: =ROUNDDOWN(S5,0)+IF(S5-ROUNDDOWN(S5,0)>0.5,0.5,0) -> 0.5 | W5: =YEAR(TODAY())-YEAR(Q5) -> 9 | X5: =(TODAY()-DATE(YEAR(R5),MONTH(R5)-6,DAY(R5)))/182*(I5) -> 0.10494505 | Y5: =T5-X5 -> 98.973555 | Z5: =AVERAGE(J5:K5) -> 1.0105
A6: AM766737 Corp | B6: Japan Government Thirty Year Bond | C6: JGB | D6: JP | E6: JPY | F6: 20/03/2047 | G6: FIXED | H6: 2 | I6: 0.8 | J6: 3.862 | K6: 3.901 | L6: 64.473 | M6: 64.183 | N6: AM7667372 | O6: JP1300541H31 | P6: A+ | Q6: 42801 | R6: 46101 | S6: =(F6-TODAY())/365.25 -> 20.971937 | T6: =AVERAGE(L6:M6) -> 64.328 | U6: 5 | V6: =ROUNDDOWN(S6,0)+IF(S6-ROUNDDOWN(S6,0)>0.5,0.5,0) -> 20.5 | W6: =YEAR(TODAY())-YEAR(Q6) -> 9 | X6: =(TODAY()-DATE(YEAR(R6),MONTH(R6)-6,DAY(R6)))/182*(I6) -> 0.83956044 | Y6: =T6-X6 -> 63.48844 | Z6: =AVERAGE(J6:K6) -> 3.8815
A7: AM850328 Corp | B7: Japan Government Twenty Year Bond | C7: JGB | D7: JP | E7: JPY | F7: 20/03/2037 | G7: FIXED | H7: 2 | I7: 0.7 | J7: 2.49 | K7: 2.516 | L7: 84.519 | M7: 84.329 | N7: AM8503287 | O7: JP1201601H38 | P7: A+ | Q7: 42808 | R7: 46101 | S7: =(F7-TODAY())/365.25 -> 10.973306 | T7: =AVERAGE(L7:M7) -> 84.424 | U7: 6 | V7: =ROUNDDOWN(S7,0)+IF(S7-ROUNDDOWN(S7,0)>0.5,0.5,0) -> 10.5 | W7: =YEAR(TODAY())-YEAR(Q7) -> 9 | X7: =(TODAY()-DATE(YEAR(R7),MONTH(R7)-6,DAY(R7)))/182*(I7) -> 0.73461538 | Y7: =T7-X7 -> 83.689385 | Z7: =AVERAGE(J7:K7) -> 2.503
A8: AN751153 Corp | B8: Japan Government Forty Year Bond | C8: JGB | D8: JP | E8: JPY | F8: 20/03/2057 | G8: FIXED | H8: 2 | I8: 0.9 | J8: 4.63 | K8: 4.69 | L8: 52.505 | M8: 52.107 | N8: AN7511537 | O8: JP1400101H56 | P8: A+ | Q8: 42880 | R8: 46101 | S8: =(F8-TODAY())/365.25 -> 30.973306 | T8: =AVERAGE(L8:M8) -> 52.306 | U8: 7 | V8: =ROUNDDOWN(S8,0)+IF(S8-ROUNDDOWN(S8,0)>0.5,0.5,0) -> 30.5 | W8: =YEAR(TODAY())-YEAR(Q8) -> 9 | X8: =(TODAY()-DATE(YEAR(R8),MONTH(R8)-6,DAY(R8)))/182*(I8) -> 0.94450549 | Y8: =T8-X8 -> 51.361495 | Z8: =AVERAGE(J8:K8) -> 4.66
A9: AN821370 Corp | B9: Japan Government Ten Year Bond | C9: JGB | D9: JP | E9: JPY | F9: 20/06/2027 | G9: FIXED | H9: 2 | I9: 0.1 | J9: 1.062 | K9: 1.085 | L9: 98.79 | M9: 98.762 | N9: AN8213703 | O9: JP1103471H66 | P9: A+ | Q9: 42887 | R9: 46193 | S9: =(F9-TODAY())/365.25 -> 1.2238193 | T9: =AVERAGE(L9:M9) -> 98.776 | U9: 8 | V9: =ROUNDDOWN(S9,0)+IF(S9-ROUNDDOWN(S9,0)>0.5,0.5,0) -> 1 | W9: =YEAR(TODAY())-YEAR(Q9) -> 9 | X9: =(TODAY()-DATE(YEAR(R9),MONTH(R9)-6,DAY(R9)))/182*(I9) -> 0.054945055 | Y9: =T9-X9 -> 98.721055 | Z9: =AVERAGE(J9:K9) -> 1.0735
A10: AN861997 Corp | B10: Japan Government Thirty Year Bond | C10: JGB | D10: JP | E10: JPY | F10: 20/06/2047 | G10: FIXED | H10: 2 | I10: 0.8 | J10: 3.895 | K10: 3.934 | L10: 63.993 | M10: 63.704 | N10: AN8619974 | O10: JP1300551H61 | P10: A+ | Q10: 42892 | R10: 46193 | S10: =(F10-TODAY())/365.25 -> 21.223819 | T10: =AVERAGE(L10:M10) -> 63.8485 | U10: 9 | V10: =ROUNDDOWN(S10,0)+IF(S10-ROUNDDOWN(S10,0)>0.5,0.5,0) -> 21 | W10: =YEAR(TODAY())-YEAR(Q10) -> 9 | X10: =(TODAY()-DATE(YEAR(R10),MONTH(R10)-6,DAY(R10)))/182*(I10) -> 0.43956044 | Y10: =T10-X10 -> 63.40894 | Z10: =AVERAGE(J10:K10) -> 3.9145
A11: AN958432 Corp | B11: Japan Government Twenty Year Bond | C11: JGB | D11: JP | E11: JPY | F11: 20/06/2037 | G11: FIXED | H11: 2 | I11: 0.6 | J11: 2.551 | K11: 2.576 | L11: 82.917 | M11: 82.736 | N11: AN9584326 | O11: JP1201611H69 | P11: A+ | Q11: 42899 | R11: 46193 | S11: =(F11-TODAY())/365.25 -> 11.225188 | T11: =AVERAGE(L11:M11) -> 82.8265 | U11: 10 | V11: =ROUNDDOWN(S11,0)+IF(S11-ROUNDDOWN(S11,0)>0.5,0.5,0) -> 11 | W11: =YEAR(TODAY())-YEAR(Q11) -> 9 | X11: =(TODAY()-DATE(YEAR(R11),MONTH(R11)-6,DAY(R11)))/182*(I11) -> 0.32967033 | Y11: =T11-X11 -> 82.49683 | Z11: =AVERAGE(J11:K11) -> 2.5635
A12: AP027592 Corp | B12: Japan Government Ten Year Bond | C12: JGB | D12: JP | E12: JPY | F12: 20/09/2027 | G12: FIXED | H12: 2 | I12: 0.1 | J12: 1.138 | K12: 1.161 | L12: 98.443 | M12: 98.409 | N12: AP0275929 | O12: JP1103481H98 | P12: A+ | Q12: 42983 | R12: 46101 | S12: =(F12-TODAY())/365.25 -> 1.4757016 | T12: =AVERAGE(L12:M12) -> 98.426 | U12: 11 | V12: =ROUNDDOWN(S12,0)+IF(S12-ROUNDDOWN(S12,0)>0.5,0.5,0) -> 1 | W12: =YEAR(TODAY())-YEAR(Q12) -> 9 | X12: =(TODAY()-DATE(YEAR(R12),MONTH(R12)-6,DAY(R12)))/182*(I12) -> 0.10494505 | Y12: =T12-X12 -> 98.321055 | Z12: =AVERAGE(J12:K12) -> 1.1495
A13: AP059339 Corp | B13: Japan Government Thirty Year Bond | C13: JGB | D13: JP | E13: JPY | F13: 20/09/2047 | G13: FIXED | H13: 2 | I13: 0.8 | J13: 3.927 | K13: 3.964 | L13: 63.523 | M13: 63.25 | N13: AP0593396 | O13: JP1300561H93 | P13: A+ | Q13: 42985 | R13: 46101 | S13: =(F13-TODAY())/365.25 -> 21.475702 | T13: =AVERAGE(L13:M13) -> 63.3865 | U13: 12 | V13: =ROUNDDOWN(S13,0)+IF(S13-ROUNDDOWN(S13,0)>0.5,0.5,0) -> 21 | W13: =YEAR(TODAY())-YEAR(Q13) -> 9 | X13: =(TODAY()-DATE(YEAR(R13),MONTH(R13)-6,DAY(R13)))/182*(I13) -> 0.83956044 | Y13: =T13-X13 -> 62.54694 | Z13: =AVERAGE(J13:K13) -> 3.9455
A14: AP155275 Corp | B14: Japan Government Twenty Year Bond | C14: JGB | D14: JP | E14: JPY | F14: 20/09/2037 | G14: FIXED | H14: 2 | I14: 0.6 | J14: 2.584 | K14: 2.61 | L14: 82.38 | M14: 82.19 | N14: AP1552755 | O14: JP1201621H91 | P14: A+ | Q14: 42992 | R14: 46101 | S14: =(F14-TODAY())/365.25 -> 11.47707 | T14: =AVERAGE(L14:M14) -> 82.285 | U14: 13 | V14: =ROUNDDOWN(S14,0)+IF(S14-ROUNDDOWN(S14,0)>0.5,0.5,0) -> 11 | W14: =YEAR(TODAY())-YEAR(Q14) -> 9 | X14: =(TODAY()-DATE(YEAR(R14),MONTH(R14)-6,DAY(R14)))/182*(I14) -> 0.62967033 | Y14: =T14-X14 -> 81.65533 | Z14: =AVERAGE(J14:K14) -> 2.597
... A327: ZS877644 Corp | B327: Japan Government Forty Year Bond | C327: JGB | D327: JP | E327: JPY | F327: 20/03/2059 | G327: FIXED | H327: 2 | I327: 0.5 | J327: 5.212 | K327: 5.281 | L327: 42.817 | M327: 42.462 | N327: ZS8776446 | O327: JP1400121K57 | P327: A+ | Q327: 43613 | R327: 46101 | S327: =(F327-TODAY())/365.25 -> 32.971937 | T327: =AVERAGE(L327:M327) -> 42.6395 | U327: 326 | V327: =ROUNDDOWN(S327,0)+IF(S327-ROUNDDOWN(S327,0)>0.5,0.5,0) -> 32.5 | W327: =YEAR(TODAY())-YEAR(Q327) -> 7 | X327: =(TODAY()-DATE(YEAR(R327),MONTH(R327)-6,DAY(R327)))/182*(I327) -> 0.52472527 | Y327: =T327-X327 -> 42.114775 | Z327: =AVERAGE(J327:K327) -> 5.2465

Sheet SORT
A1: {=+OFFSET(Offline!A1,,,1,COUNTA(Offline!1:1))} -> Instrument | B1: Name | C1: Ticker | D1: Country/Region | E1: Currency | F1: Maturity | G1: Coupon Type | H1: Coupon Frequency | I1: Coupon | J1: Ask Yield to Maturity | K1: Bid Yield to Maturity | L1: Ask Price | M1: Bid Price | N1: Identifier | O1: ISIN | P1: Bloomberg Composite Rating | Q1: Announce | R1: Next Coupon Settle Date | S1: Time | T1: AVG price | U1: id | V1: TIMEish | W1: years ago | X1: Accrued Interest | Y1: Clean price | Z1: AVG yield
A2: {=_xlfn._xlws.SORT(OFFSET(Offline!A2,,,COUNTA(Offline!A:A)-1,COUNTA(Offline!1:1)),COLUMN(Offline!S1))} -> BO997638 Corp | B2: Japan Government Five Year Bond | C2: JGB | D2: JP | E2: JPY | F2: 20/03/2026 | G2: FIXED | H2: 2 | I2: 0.005 | J2: 0.74800001 | K2: 0.76600001 | L2: 99.983 | M2: 99.983 | N2: BO9976388 | O2: JP1051471M45 | P2: A+ | Q2: 44287 | R2: 46101 | S2: -0.027378508 | T2: 99.983 | U2: 47 | V2: 0 | W2: 5 | X2: 0.0052472527 | Y2: 99.977753 | Z2: 0.75700001
A3: EF329501 Corp | B3: Japan Government Twenty Year Bond | C3: JGB | D3: JP | E3: JPY | F3: 20/03/2026 | G3: FIXED | H3: 2 | I3: 2.1 | J3: 0.748 | K3: 0.771 | L3: 100.029 | M3: 100.029 | N3: EF3295013 | O3: JP1200851630 | P3: A+ | Q3: 38792 | R3: 46101 | S3: -0.027378508 | T3: 100.029 | U3: 103 | V3: 0 | W3: 20 | X3: 2.2038462 | Y3: 97.825154 | Z3: 0.7595
A4: EF381218 Corp | B4: Japan Government Twenty Year Bond | C4: JGB | D4: JP | E4: JPY | F4: 20/03/2026 | G4: FIXED | H4: 2 | I4: 2.3 | J4: 0.736 | K4: 0.768 | L4: 100.034 | M4: 100.033 | N4: EF3812189 | O4: JP1200861647 | P4: A+ | Q4: 38832 | R4: 46101 | S4: -0.027378508 | T4: 100.0335 | U4: 105 | V4: 0 | W4: 20 | X4: 2.4137363 | Y4: 97.619764 | Z4: 0.752
A5: EF452796 Corp | B5: Japan Government Twenty Year Bond | C5: JGB | D5: JP | E5: JPY | F5: 20/03/2026 | G5: FIXED | H5: 2 | I5: 2.2 | J5: 0.737 | K5: 0.762 | L5: 100.032 | M5: 100.031 | N5: EF4527968 | O5: JP1200871653 | P5: A+ | Q5: 38862 | R5: 46101 | S5: -0.027378508 | T5: 100.0315 | U5: 106 | V5: 0 | W5: 20 | X5: 2.3087912 | Y5: 97.722709 | Z5: 0.7495
A6: JK298261 Corp | B6: Japan Government Ten Year Bond | C6: JGB | D6: JP | E6: JPY | F6: 20/03/2026 | G6: FIXED | H6: 2 | I6: 0.1 | J6: 0.74 | K6: 0.763 | L6: 99.985 | M6: 99.985 | N6: JK2982615 | O6: JP1103421G35 | P6: A+ | Q6: 42430 | R6: 46101 | S6: -0.027378508 | T6: 99.985 | U6: 206 | V6: 0 | W6: 10 | X6: 0.10494505 | Y6: 99.880055 | Z6: 0.7515
A7: ZB137529 Corp | B7: Japan Government Two Year Bond | C7: JGB | D7: JP | E7: JPY | F7: 01/04/2026 | G7: FIXED | H7: 2 | I7: 0.2 | J7: 0.735 | K7: 0.75800001 | L7: 99.97 | M7: 99.969 | N7: ZB1375292 | O7: JP1024591Q43 | P7: A+ | Q7: 45373 | R7: 46113 | S7: 0.0054757016 | T7: 99.9695 | U7: 280 | V7: 0 | W7: 2 | X7: 0.1978022 | Y7: 99.771698 | Z7: 0.7465
A8: ZB651229 Corp | B8: Japan Government Two Year Bond | C8: JGB | D8: JP | E8: JPY | F8: 01/05/2026 | G8: FIXED | H8: 2 | I8: 0.3 | J8: 0.75 | K8: 0.773 | L8: 99.938 | M8: 99.935 | N8: ZB6512295 | O8: JP1024601Q58 | P8: A+ | Q8: 45398 | R8: 46143 | S8: 0.087611225 | T8: 99.9365 | U8: 285 | V8: 0 | W8: 2 | X8: 0.2456044 | Y8: 99.690896 | Z8: 0.7615
A9: YX440521 Corp | B9: Japan Government Two Year Bond | C9: JGB | D9: JP | E9: JPY | F9: 01/06/2026 | G9: FIXED | H9: 2 | I9: 0.4 | J9: 0.763 | K9: 0.785 | L9: 99.919 | M9: 99.914 | N9: YX4405214 | O9: JP1024611Q64 | P9: A+ | Q9: 45435 | R9: 46174 | S9: 0.1724846 | T9: 99.9165 | U9: 278 | V9: 0 | W9: 2 | X9: 0.26153846 | Y9: 99.654962 | Z9: 0.774
A10: BQ447894 Corp | B10: Japan Government Five Year Bond | C10: JGB | D10: JP | E10: JPY | F10: 20/06/2026 | G10: FIXED | H10: 2 | I10: 0.005 | J10: 0.78 | K10: 0.803 | L10: 99.788 | M10: 99.781 | N10: BQ4478948 | O10: JP1051481M76 | P10: NR | Q10: 44378 | R10: 46193 | S10: 0.22450376 | T10: 99.7845 | U10: 52 | V10: 0 | W10: 5 | X10: 0.0027472527 | Y10: 99.781753 | Z10: 0.7915
A11: EF500367 Corp | B11: Japan Government Twenty Year Bond | C11: JGB | D11: JP | E11: JPY | F11: 20/06/2026 | G11: FIXED | H11: 2 | I11: 2.3 | J11: 0.786 | K11: 0.81 | L11: 100.413 | M11: 100.407 | N11: EF5003670 | O11: JP1200881660 | P11: A+ | Q11: 38888 | R11: 46193 | S11: 0.22450376 | T11: 100.41 | U11: 107 | V11: 0 | W11: 20 | X11: 1.2637363 | Y11: 99.146264 | Z11: 0.798
A12: EF659299 Corp | B12: Japan Government Twenty Year Bond | C12: JGB | D12: JP | E12: JPY | F12: 20/06/2026 | G12: FIXED | H12: 2 | I12: 2.2 | J12: 0.78 | K12: 0.81 | L12: 100.388 | M12: 100.379 | N12: EF6592994 | O12: JP1200891685 | P12: A+ | Q12: 38953 | R12: 46193 | S12: 0.22450376 | T12: 100.3835 | U12: 109 | V12: 0 | W12: 20 | X12: 1.2087912 | Y12: 99.174709 | Z12: 0.795
A13: LW316486 Corp | B13: Japan Government Ten Year Bond | C13: JGB | D13: JP | E13: JPY | F13: 20/06/2026 | G13: FIXED | H13: 2 | I13: 0.1 | J13: 0.772 | K13: 0.794 | L13: 99.816 | M13: 99.81 | N13: LW3164867 | O13: JP1103431G66 | P13: A+ | Q13: 42523 | R13: 46193 | S13: 0.22450376 | T13: 99.813 | U13: 212 | V13: 0 | W13: 10 | X13: 0.054945055 | Y13: 99.758055 | Z13: 0.783
A14: YW041715 Corp | B14: Japan Government Two Year Bond | C14: JGB | D14: JP | E14: JPY | F14: 01/07/2026 | G14: FIXED | H14: 2 | I14: 0.4 | J14: 0.79 | K14: 0.813 | L14: 99.881 | M14: 99.874 | N14: YW0417157 | O14: JP1024621Q70 | P14: A+ | Q14: 45463 | R14: 46204 | S14: 0.25462012 | T14: 99.8775 | U14: 268 | V14: 0 | W14: 2 | X14: 0.19340659 | Y14: 99.684093 | Z14: 0.8015
... A327: YO939740 Corp | B327: Japan Government Forty Year Bond | C327: JGB | D327: JP | E327: JPY | F327: 20/03/2065 | G327: FIXED | H327: 2 | I327: 3.1 | J327: 3.611 | K327: 3.669 | L327: 91.722 | M327: 90.869 | N327: YO9397408 | O327: JP1400181R57 | P327: A+ | Q327: 45798 | R327: 46101 | S327: 38.973306 | T327: 91.2955 | U327: 241 | V327: 38.5 | W327: 1 | X327: 3.2532967 | Y327: 88.042203 | Z327: 3.64

Sheet ID filter
A1: ID | B1: {=_xlfn.ANCHORARRAY(SORT!A1)} -> Instrument | C1: Name | D1: Ticker | E1: Country/Region | F1: Currency | G1: Maturity | H1: Coupon Type | I1: Coupon Frequency | J1: Coupon | K1: Ask Yield to Maturity | L1: Bid Yield to Maturity | M1: Ask Price | N1: Bid Price | O1: Identifier | P1: ISIN | Q1: Bloomberg Composite Rating | R1: Announce | S1: Next Coupon Settle Date | T1: Time | U1: AVG price | V1: id | W1: TIMEish | X1: years ago | Y1: Accrued Interest | Z1: Clean price | AA1: AVG yield
A2: 251 | B2: {=_xlfn.XLOOKUP(A2,SORT!$U$2:$U$327,_xlfn.ANCHORARRAY(SORT!$A$2),,0)} -> YR907955 Corp | C2: Japan Government Two Year Bond | D2: JGB | E2: JP | F2: JPY | G2: 01/03/2027 | H2: FIXED | I2: 2 | J2: 0.8 | K2: 0.976 | L2: 0.999 | M2: 99.83 | N2: 99.808 | O2: YR9079553 | P2: JP1024701R31 | Q2: A+ | R2: 45708 | S2: 46266 | T2: 0.91991786 | U2: 99.819 | V2: 251 | W2: 0.5 | X2: 1 | Y2: 0.12747253 | Z2: 99.691527 | AA2: 0.9875
A3: 232 | B3: {=_xlfn.XLOOKUP(A3,SORT!$U$2:$U$327,_xlfn.ANCHORARRAY(SORT!$A$2),,0)} -> YL701515 Corp | C3: Japan Government Two Year Bond | D3: JGB | E3: JP | F3: JPY | G3: 01/09/2027 | H3: FIXED | I3: 2 | J3: 0.9 | K3: 1.132 | L3: 1.151 | M3: 99.663 | N3: 99.636 | O3: YL7015156 | P3: JP1024761R95 | Q3: A+ | R3: 45890 | S3: 46266 | T3: 1.4236824 | U3: 99.6495 | V3: 232 | W3: 1 | X3: 1 | Y3: 0.14340659 | Z3: 99.506093 | AA3: 1.1415
A4: 17 | B4: {=_xlfn.XLOOKUP(A4,SORT!$U$2:$U$327,_xlfn.ANCHORARRAY(SORT!$A$2),,0)} -> AR545005 Corp | C4: Japan Government Ten Year Bond | D4: JGB | E4: JP | F4: JPY | G4: 20/03/2028 | H4: FIXED | I4: 2 | J4: 0.1 | K4: 1.213 | L4: 1.236 | M4: 97.803 | N4: 97.759 | O4: AR5450051 | P4: JP1103501J35 | Q4: A+ | R4: 43160 | S4: 46101 | T4: 1.9739904 | U4: 97.781 | V4: 17 | W4: 1.5 | X4: 8 | Y4: 0.10494505 | Z4: 97.676055 | AA4: 1.2245
A5: 21 | B5: {=_xlfn.XLOOKUP(A5,SORT!$U$2:$U$327,_xlfn.ANCHORARRAY(SORT!$A$2),,0)} -> AT427280 Corp | C5: Japan Government Ten Year Bond | D5: JGB | E5: JP | F5: JPY | G5: 20/06/2028 | H5: FIXED | I5: 2 | J5: 0.1 | K5: 1.241 | L5: 1.262 | M5: 97.476 | N5: 97.431 | O5: AT4272809 | P5: JP1103511J74 | Q5: A+ | R5: 43284 | S5: 46193 | T5: 2.2258727 | U5: 97.4535 | V5: 21 | W5: 2 | X5: 8 | Y5: 0.054945055 | Z5: 97.398555 | AA5: 1.2515
A6: 27 | B6: {=_xlfn.XLOOKUP(A6,SORT!$U$2:$U$327,_xlfn.ANCHORARRAY(SORT!$A$2),,0)} -> AW566680 Corp | C6: Japan Government Ten Year Bond | D6: JGB | E6: JP | F6: JPY | G6: 20/12/2028 | H6: FIXED | I6: 2 | J6: 0.1 | K6: 1.322 | L6: 1.344 | M6: 96.728 | N6: 96.671 | O6: AW5666804 | P6: JP1103531K10 | Q6: A+ | R6: 43473 | S6: 46193 | T6: 2.7268994 | U6: 96.6995 | V6: 27 | W6: 2.5 | X6: 7 | Y6: 0.054945055 | Z6: 96.644555 | AA6: 1.333
A7: 31 | B7: {=_xlfn.XLOOKUP(A7,SORT!$U$2:$U$327,_xlfn.ANCHORARRAY(SORT!$A$2),,0)} -> AZ459860 Corp | C7: Japan Government Ten Year Bond | D7: JGB | E7: JP | F7: JPY | G7: 20/06/2029 | H7: FIXED | I7: 2 | J7: 0.1 | K7: 1.416 | L7: 1.44 | M7: 95.882 | N7: 95.81 | O7: AZ4598605 | P7: JP1103551K72 | Q7: A+ | R7: 43648 | S7: 46193 | T7: 3.2251882 | U7: 95.846 | V7: 31 | W7: 3 | X7: 7 | Y7: 0.054945055 | Z7: 95.791055 | AA7: 1.428
A8: 323 | B8: {=_xlfn.XLOOKUP(A8,SORT!$U$2:$U$327,_xlfn.ANCHORARRAY(SORT!$A$2),,0)} -> ZR885925 Corp | C8: Japan Government Ten Year Bond | D8: JGB | E8: JP | F8: JPY | G8: 20/09/2029 | H8: FIXED | I8: 2 | J8: 0.1 | K8: 1.46 | L8: 1.482 | M8: 95.439 | N8: 95.369 | O8: ZR8859251 | P8: JP1103561KA2 | Q8: A+ | R8: 43739 | S8: 46101 | T8: 3.4770705 | U8: 95.404 | V8: 323 | W8: 3 | X8: 7 | Y8: 0.10494505 | Z8: 95.299055 | AA8: 1.471
A9: 38 | B9: {=_xlfn.XLOOKUP(A9,SORT!$U$2:$U$327,_xlfn.ANCHORARRAY(SORT!$A$2),,0)} -> BK340998 Corp | C9: Japan Government Ten Year Bond | D9: JGB | E9: JP | F9: JPY | G9: 20/06/2030 | H9: FIXED | I9: 2 | J9: 0.1 | K9: 1.58 | L9: 1.603 | M9: 94.074 | N9: 93.988 | O9: BK3409988 | P9: JP1103591L73 | Q9: A+ | R9: 44007 | S9: 46193 | T9: 4.2245038 | U9: 94.031 | V9: 38 | W9: 4 | X9: 6 | Y9: 0.054945055 | Z9: 93.976055 | AA9: 1.5915
A10: 42 | B10: {=_xlfn.XLOOKUP(A10,SORT!$U$2:$U$327,_xlfn.ANCHORARRAY(SORT!$A$2),,0)} -> BN361059 Corp | C10: Japan Government Ten Year Bond | D10: JGB | E10: JP | F10: JPY | G10: 20/12/2030 | H10: FIXED | I10: 2 | J10: 0.1 | K10: 1.644 | L10: 1.665 | M10: 93.163 | N10: 93.077 | O10: BN3610597 | P10: JP1103611M11 | Q10: NR | R10: 44193 | S10: 46193 | T10: 4.7255305 | U10: 93.12 | V10: 42 | W10: 4.5 | X10: 6 | Y10: 0.054945055 | Z10: 93.065055 | AA10: 1.6545
A11: 50 | B11: {=_xlfn.XLOOKUP(A11,SORT!$U$2:$U$327,_xlfn.ANCHORARRAY(SORT!$A$2),,0)} -> BQ348089 Corp | C11: Japan Government Ten Year Bond | D11: JGB | E11: JP | F11: JPY | G11: 20/06/2031 | H11: FIXED | I11: 2 | J11: 0.1 | K11: 1.71 | L11: 1.727 | M11: 92.211 | N11: 92.135 | O11: BQ3480895 | P11: JP1103631M74 | Q11: NR | R11: 44371 | S11: 46193 | T11: 5.2238193 | U11: 92.173 | V11: 50 | W11: 5 | X11: 5 | Y11: 0.054945055 | Z11: 92.118055 | AA11: 1.7185
A12: 58 | B12: {=_xlfn.XLOOKUP(A12,SORT!$U$2:$U$327,_xlfn.ANCHORARRAY(SORT!$A$2),,0)} -> BT330618 Corp | C12: Japan Government Ten Year Bond | D12: JGB | E12: JP | F12: JPY | G12: 20/12/2031 | H12: FIXED | I12: 2 | J12: 0.1 | K12: 1.775 | L12: 1.792 | M12: 91.225 | N12: 91.144 | O12: BT3306185 | P12: JP1103651N11 | Q12: NR | R12: 44558 | S12: 46193 | T12: 5.724846 | U12: 91.1845 | V12: 58 | W12: 5.5 | X12: 5 | Y12: 0.054945055 | Z12: 91.129555 | AA12: 1.7835
A13: 68 | B13: {=_xlfn.XLOOKUP(A13,SORT!$U$2:$U$327,_xlfn.ANCHORARRAY(SORT!$A$2),,0)} -> BX625748 Corp | C13: Japan Government Ten Year Bond | D13: JGB | E13: JP | F13: JPY | G13: 20/06/2032 | H13: FIXED | I13: 2 | J13: 0.2 | K13: 1.835 | L13: 1.852 | M13: 90.801 | N13: 90.714 | O13: BX6257485 | P13: JP1103671N74 | Q13: A+ | R13: 44740 | S13: 46193 | T13: 6.2258727 | U13: 90.7575 | V13: 68 | W13: 6 | X13: 4 | Y13: 0.10989011 | Z13: 90.64761 | AA13: 1.8435
... A69: 276 | B69: {=_xlfn.XLOOKUP(A69,SORT!$U$2:$U$327,_xlfn.ANCHORARRAY(SORT!$A$2),,0)} -> YX270525 Corp | C69: Japan Government Forty Year Bond | D69: JGB | E69: JP | F69: JPY | G69: 20/03/2064 | H69: FIXED | I69: 2 | J69: 2.2 | K69: 4.021 | L69: 4.072 | M69: 72.62 | N69: 72.068 | O69: YX2705250 | P69: JP1400171Q50 | Q69: A+ | R69: 45427 | S69: 46101 | T69: 37.97399 | U69: 72.344 | V69: 276 | W69: 37.5 | X69: 2 | Y69: 2.3087912 | Z69: 70.035209 | AA69: 4.0465

Sheet F date<=1
A1: ID | B1: {=_xlfn.ANCHORARRAY(SORT!A1)} -> Instrument | C1: Name | D1: Ticker | E1: Country/Region | F1: Currency | G1: Maturity | H1: Coupon Type | I1: Coupon Frequency | J1: Coupon | K1: Ask Yield to Maturity | L1: Bid Yield to Maturity | M1: Ask Price | N1: Bid Price | O1: Identifier | P1: ISIN | Q1: Bloomberg Composite Rating | R1: Announce | S1: Next Coupon Settle Date | T1: Time | U1: AVG price | V1: id | W1: TIMEish | X1: years ago | Y1: Accrued Interest | Z1: Clean price | AA1: AVG yield | AD1: {=_xlfn.ANCHORARRAY(B1)} -> Instrument | AE1: Name | AF1: Ticker | AG1: Country/Region | AH1: Currency | AI1: Maturity | AJ1: Coupon Type | AK1: Coupon Frequency | AL1: Coupon | AM1: Ask Yield to Maturity | AN1: Bid Yield to Maturity | AO1: Ask Price | AP1: Bid Price | AQ1: Identifier | AR1: ISIN | AS1: Bloomberg Composite Rating | AT1: Announce | AU1: Next Coupon Settle Date | AV1: Time | AW1: AVG price | AX1: id | AY1: TIMEish | AZ1: years ago | BA1: Accrued Interest | BB1: Clean price | BC1: AVG yield
B2: {=_xlfn._xlws.FILTER(_xlfn.ANCHORARRAY(AD2),OFFSET(AY1,1,,COUNT(AY:AY))>0)} -> YR145899 Corp | C2: Japan Government Two Year Bond | D2: JGB | E2: JP | F2: JPY | G2: 01/02/2027 | H2: FIXED | I2: 2 | J2: 0.7 | K2: 0.972 | L2: 0.994 | M2: 99.759 | N2: 99.739 | O2: YR1458995 | P2: JP1024691R25 | Q2: A+ | R2: 45681 | S2: 46235 | T2: 0.84325804 | U2: 99.749 | V2: 249 | W2: 0.5 | X2: 1 | Y2: 0.21923077 | Z2: 99.529769 | AA2: 0.983 | AD2: {=_xlfn._xlws.FILTER(_xlfn.ANCHORARRAY(SORT!A2),SORT!W2:W327<=1)} -> YR145899 Corp | AE2: Japan Government Two Year Bond | AF2: JGB | AG2: JP | AH2: JPY | AI2: 01/02/2027 | AJ2: FIXED | AK2: 2 | AL2: 0.7 | AM2: 0.972 | AN2: 0.994 | AO2: 99.759 | AP2: 99.739 | AQ2: YR1458995 | AR2: JP1024691R25 | AS2: A+ | AT2: 45681 | AU2: 46235 | AV2: 0.84325804 | AW2: 99.749 | AX2: 249 | AY2: 0.5 | AZ2: 1 | BA2: 0.21923077 | BB2: 99.529769 | BC2: 0.983
B3: YR907955 Corp | C3: Japan Government Two Year Bond | D3: JGB | E3: JP | F3: JPY | G3: 01/03/2027 | H3: FIXED | I3: 2 | J3: 0.8 | K3: 0.976 | L3: 0.999 | M3: 99.83 | N3: 99.808 | O3: YR9079553 | P3: JP1024701R31 | Q3: A+ | R3: 45708 | S3: 46266 | T3: 0.91991786 | U3: 99.819 | V3: 251 | W3: 0.5 | X3: 1 | Y3: 0.12747253 | Z3: 99.691527 | AA3: 0.9875 | AD3: YR907955 Corp | AE3: Japan Government Two Year Bond | AF3: JGB | AG3: JP | AH3: JPY | AI3: 01/03/2027 | AJ3: FIXED | AK3: 2 | AL3: 0.8 | AM3: 0.976 | AN3: 0.999 | AO3: 99.83 | AP3: 99.808 | AQ3: YR9079553 | AR3: JP1024701R31 | AS3: A+ | AT3: 45708 | AU3: 46266 | AV3: 0.91991786 | AW3: 99.819 | AX3: 251 | AY3: 0.5 | AZ3: 1 | BA3: 0.12747253 | BB3: 99.691527 | BC3: 0.9875
B4: YQ865312 Corp | C4: Japan Government Two Year Bond | D4: JGB | E4: JP | F4: JPY | G4: 01/04/2027 | H4: FIXED | I4: 2 | J4: 0.9 | K4: 0.991 | L4: 1.014 | M4: 99.905 | N4: 99.881 | O4: YQ8653129 | P4: JP1024711R47 | Q4: A+ | R4: 45740 | S4: 46113 | T4: 1.0047912 | U4: 99.893 | V4: 247 | W4: 1 | X4: 1 | Y4: 0.89010989 | Z4: 99.00289 | AA4: 1.0025 | AD4: YQ865312 Corp | AE4: Japan Government Two Year Bond | AF4: JGB | AG4: JP | AH4: JPY | AI4: 01/04/2027 | AJ4: FIXED | AK4: 2 | AL4: 0.9 | AM4: 0.991 | AN4: 1.014 | AO4: 99.905 | AP4: 99.881 | AQ4: YQ8653129 | AR4: JP1024711R47 | AS4: A+ | AT4: 45740 | AU4: 46113 | AV4: 1.0047912 | AW4: 99.893 | AX4: 247 | AY4: 1 | AZ4: 1 | BA4: 0.89010989 | BB4: 99.00289 | BC4: 1.0025
B5: YP920263 Corp | C5: Japan Government Two Year Bond | D5: JGB | E5: JP | F5: JPY | G5: 01/05/2027 | H5: FIXED | I5: 2 | J5: 0.7 | K5: 1.013 | L5: 1.036 | M5: 99.648 | N5: 99.622 | O5: YP9202639 | P5: JP1024721R52 | Q5: A+ | R5: 45764 | S5: 46143 | T5: 1.0869268 | U5: 99.635 | V5: 245 | W5: 1 | X5: 1 | Y5: 0.57307692 | Z5: 99.061923 | AA5: 1.0245 | AD5: YP920263 Corp | AE5: Japan Government Two Year Bond | AF5: JGB | AG5: JP | AH5: JPY | AI5: 01/05/2027 | AJ5: FIXED | AK5: 2 | AL5: 0.7 | AM5: 1.013 | AN5: 1.036 | AO5: 99.648 | AP5: 99.622 | AQ5: YP9202639 | AR5: JP1024721R52 | AS5: A+ | AT5: 45764 | AU5: 46143 | AV5: 1.0869268 | AW5: 99.635 | AX5: 245 | AY5: 1 | AZ5: 1 | BA5: 0.57307692 | BB5: 99.061923 | BC5: 1.0245
B6: YN009853 Corp | C6: Japan Government Two Year Bond | D6: JGB | E6: JP | F6: JPY | G6: 01/06/2027 | H6: FIXED | I6: 2 | J6: 0.8 | K6: 1.056 | L6: 1.076 | M6: 99.691 | N6: 99.667 | O6: YN0098536 | P6: JP1024731R68 | Q6: A+ | R6: 45800 | S6: 46174 | T6: 1.1718001 | U6: 99.679 | V6: 237 | W6: 1 | X6: 1 | Y6: 0.52307692 | Z6: 99.155923 | AA6: 1.066 | AD6: YN009853 Corp | AE6: Japan Government Two Year Bond | AF6: JGB | AG6: JP | AH6: JPY | AI6: 01/06/2027 | AJ6: FIXED | AK6: 2 | AL6: 0.8 | AM6: 1.056 | AN6: 1.076 | AO6: 99.691 | AP6: 99.667 | AQ6: YN0098536 | AR6: JP1024731R68 | AS6: A+ | AT6: 45800 | AU6: 46174 | AV6: 1.1718001 | AW6: 99.679 | AX6: 237 | AY6: 1 | AZ6: 1 | BA6: 0.52307692 | BB6: 99.155923 | BC6: 1.066
B7: YN766681 Corp | C7: Japan Government Two Year Bond | D7: JGB | E7: JP | F7: JPY | G7: 01/07/2027 | H7: FIXED | I7: 2 | J7: 0.7 | K7: 1.084 | L7: 1.104 | M7: 99.506 | N7: 99.48 | O7: YN7666814 | P7: JP1024741R74 | Q7: A+ | R7: 45827 | S7: 46204 | T7: 1.2539357 | U7: 99.493 | V7: 238 | W7: 1 | X7: 1 | Y7: 0.33846154 | Z7: 99.154538 | AA7: 1.094 | AD7: YN766681 Corp | AE7: Japan Government Two Year Bond | AF7: JGB | AG7: JP | AH7: JPY | AI7: 01/07/2027 | AJ7: FIXED | AK7: 2 | AL7: 0.7 | AM7: 1.084 | AN7: 1.104 | AO7: 99.506 | AP7: 99.48 | AQ7: YN7666814 | AR7: JP1024741R74 | AS7: A+ | AT7: 45827 | AU7: 46204 | AV7: 1.2539357 | AW7: 99.493 | AX7: 238 | AY7: 1 | AZ7: 1 | BA7: 0.33846154 | BB7: 99.154538 | BC7: 1.094
B8: YM801404 Corp | C8: Japan Government Two Year Bond | D8: JGB | E8: JP | F8: JPY | G8: 01/08/2027 | H8: FIXED | I8: 2 | J8: 0.9 | K8: 1.108 | L8: 1.13 | M8: 99.715 | N8: 99.685 | O8: YM8014040 | P8: JP1024751R89 | Q8: A+ | R8: 45860 | S8: 46235 | T8: 1.338809 | U8: 99.7 | V8: 236 | W8: 1 | X8: 1 | Y8: 0.28186813 | Z8: 99.418132 | AA8: 1.119 | AD8: YM801404 Corp | AE8: Japan Government Two Year Bond | AF8: JGB | AG8: JP | AH8: JPY | AI8: 01/08/2027 | AJ8: FIXED | AK8: 2 | AL8: 0.9 | AM8: 1.108 | AN8: 1.13 | AO8: 99.715 | AP8: 99.685 | AQ8: YM8014040 | AR8: JP1024751R89 | AS8: A+ | AT8: 45860 | AU8: 46235 | AV8: 1.338809 | AW8: 99.7 | AX8: 236 | AY8: 1 | AZ8: 1 | BA8: 0.28186813 | BB8: 99.418132 | BC8: 1.119
B9: YL701515 Corp | C9: Japan Government Two Year Bond | D9: JGB | E9: JP | F9: JPY | G9: 01/09/2027 | H9: FIXED | I9: 2 | J9: 0.9 | K9: 1.132 | L9: 1.151 | M9: 99.663 | N9: 99.636 | O9: YL7015156 | P9: JP1024761R95 | Q9: A+ | R9: 45890 | S9: 46266 | T9: 1.4236824 | U9: 99.6495 | V9: 232 | W9: 1 | X9: 1 | Y9: 0.14340659 | Z9: 99.506093 | AA9: 1.1415 | AD9: YL701515 Corp | AE9: Japan Government Two Year Bond | AF9: JGB | AG9: JP | AH9: JPY | AI9: 01/09/2027 | AJ9: FIXED | AK9: 2 | AL9: 0.9 | AM9: 1.132 | AN9: 1.151 | AO9: 99.663 | AP9: 99.636 | AQ9: YL7015156 | AR9: JP1024761R95 | AS9: A+ | AT9: 45890 | AU9: 46266 | AV9: 1.4236824 | AW9: 99.6495 | AX9: 232 | AY9: 1 | AZ9: 1 | BA9: 0.14340659 | BB9: 99.506093 | BC9: 1.1415
B10: YK553774 Corp | C10: Japan Government Two Year Bond | D10: JGB | E10: JP | F10: JPY | G10: 01/10/2027 | H10: FIXED | I10: 2 | J10: 1 | K10: 1.151 | L10: 1.171 | M10: 99.769 | N10: 99.738 | O10: YK5537740 | P10: JP1024771RA8 | Q10: A+ | R10: 45922 | S10: 46113 | T10: 1.5058179 | U10: 99.7535 | V10: 228 | W10: 1.5 | X10: 1 | Y10: 0.98901099 | Z10: 98.764489 | AA10: 1.161 | AD10: YK553774 Corp | AE10: Japan Government Two Year Bond | AF10: JGB | AG10: JP | AH10: JPY | AI10: 01/10/2027 | AJ10: FIXED | AK10: 2 | AL10: 1 | AM10: 1.151 | AN10: 1.171 | AO10: 99.769 | AP10: 99.738 | AQ10: YK5537740 | AR10: JP1024771RA8 | AS10: A+ | AT10: 45922 | AU10: 46113 | AV10: 1.5058179 | AW10: 99.7535 | AX10: 228 | AY10: 1.5 | AZ10: 1 | BA10: 0.98901099 | BB10: 98.764489 | BC10: 1.161
B11: YJ827109 Corp | C11: Japan Government Two Year Bond | D11: JGB | E11: JP | F11: JPY | G11: 01/11/2027 | H11: FIXED | I11: 2 | J11: 1 | K11: 1.168 | L11: 1.187 | M11: 99.729 | N11: 99.698 | O11: YJ8271092 | P11: JP1024781RB5 | Q11: A+ | R11: 45954 | S11: 46143 | T11: 1.5906913 | U11: 99.7135 | V11: 226 | W11: 1.5 | X11: 1 | Y11: 0.81868132 | Z11: 98.894819 | AA11: 1.1775 | AD11: YJ827109 Corp | AE11: Japan Government Two Year Bond | AF11: JGB | AG11: JP | AH11: JPY | AI11: 01/11/2027 | AJ11: FIXED | AK11: 2 | AL11: 1 | AM11: 1.168 | AN11: 1.187 | AO11: 99.729 | AP11: 99.698 | AQ11: YJ8271092 | AR11: JP1024781RB5 | AS11: A+ | AT11: 45954 | AU11: 46143 | AV11: 1.5906913 | AW11: 99.7135 | AX11: 226 | AY11: 1.5 | AZ11: 1 | BA11: 0.81868132 | BB11: 98.894819 | BC11: 1.1775
B12: DA962213 Corp | C12: Japan Government Two Year Bond | D12: JGB | E12: JP | F12: JPY | G12: 01/12/2027 | H12: FIXED | I12: 2 | J12: 1 | K12: 1.181 | L12: 1.201 | M12: 99.694 | N12: 99.66 | O12: DA9622139 | P12: JP1024791RC2 | Q12: A+ | R12: 45982 | S12: 46174 | T12: 1.6728268 | U12: 99.677 | V12: 76 | W12: 1.5 | X12: 1 | Y12: 0.65384615 | Z12: 99.023154 | AA12: 1.191 | AD12: DA962213 Corp | AE12: Japan Government Two Year Bond | AF12: JGB | AG12: JP | AH12: JPY | AI12: 01/12/2027 | AJ12: FIXED | AK12: 2 | AL12: 1 | AM12: 1.181 | AN12: 1.201 | AO12: 99.694 | AP12: 99.66 | AQ12: DA9622139 | AR12: JP1024791RC2 | AS12: A+ | AT12: 45982 | AU12: 46174 | AV12: 1.6728268 | AW12: 99.677 | AX12: 76 | AY12: 1.5 | AZ12: 1 | BA12: 0.65384615 | BB12: 99.023154 | BC12: 1.191
B13: DC578379 Corp | C13: Japan Government Two Year Bond | D13: JGB | E13: JP | F13: JPY | G13: 01/01/2028 | H13: FIXED | I13: 2 | J13: 1.1 | K13: 1.198 | L13: 1.22 | M13: 99.826 | N13: 99.787 | O13: DC5783790 | P13: JP1024801S13 | Q13: A+ | R13: 46009 | S13: 46204 | T13: 1.7577002 | U13: 99.8065 | V13: 78 | W13: 1.5 | X13: 1 | Y13: 0.53186813 | Z13: 99.274632 | AA13: 1.209 | AD13: DC578379 Corp | AE13: Japan Government Two Year Bond | AF13: JGB | AG13: JP | AH13: JPY | AI13: 01/01/2028 | AJ13: FIXED | AK13: 2 | AL13: 1.1 | AM13: 1.198 | AN13: 1.22 | AO13: 99.826 | AP13: 99.787 | AQ13: DC5783790 | AR13: JP1024801S13 | AS13: A+ | AT13: 46009 | AU13: 46204 | AV13: 1.7577002 | AW13: 99.8065 | AX13: 78 | AY13: 1.5 | AZ13: 1 | BA13: 0.53186813 | BB13: 99.274632 | BC13: 1.209
B14: YI570831 Corp | C14: Japan Government Two Year Bond | D14: JGB | E14: JP | F14: JPY | G14: 01/02/2028 | H14: FIXED | I14: 2 | J14: 1.3 | K14: 1.218 | L14: 1.241 | M14: 100.151 | N14: 100.109 | O14: YI5708312 | P14: JP1024811S29 | Q14: A+ | R14: 46045 | S14: 46235 | T14: 1.8425736 | U14: 100.13 | V14: 223 | W14: 1.5 | X14: 0 | Y14: 0.40714286 | Z14: 99.722857 | AA14: 1.2295 | AD14: YI570831 Corp | AE14: Japan Government Two Year Bond | AF14: JGB | AG14: JP | AH14: JPY | AI14: 01/02/2028 | AJ14: FIXED | AK14: 2 | AL14: 1.3 | AM14: 1.218 | AN14: 1.241 | AO14: 100.151 | AP14: 100.109 | AQ14: YI5708312 | AR14: JP1024811S29 | AS14: A+ | AT14: 46045 | AU14: 46235 | AV14: 1.8425736 | AW14: 100.13 | AX14: 223 | AY14: 1.5 | AZ14: 0 | BA14: 0.40714286 | BB14: 99.722857 | BC14: 1.2295
... B41: YO939740 Corp | C41: Japan Government Forty Year Bond | D41: JGB | E41: JP | F41: JPY | G41: 20/03/2065 | H41: FIXED | I41: 2 | J41: 3.1 | K41: 3.611 | L41: 3.669 | M41: 91.722 | N41: 90.869 | O41: YO9397408 | P41: JP1400181R57 | Q41: A+ | R41: 45798 | S41: 46101 | T41: 38.973306 | U41: 91.2955 | V41: 241 | W41: 38.5 | X41: 1 | Y41: 3.2532967 | Z41: 88.042203 | AA41: 3.64 | AD41: YO939740 Corp | AE41: Japan Government Forty Year Bond | AF41: JGB | AG41: JP | AH41: JPY | AI41: 20/03/2065 | AJ41: FIXED | AK41: 2 | AL41: 3.1 | AM41: 3.611 | AN41: 3.669 | AO41: 91.722 | AP41: 90.869 | AQ41: YO9397408 | AR41: JP1400181R57 | AS41: A+ | AT41: 45798 | AU41: 46101 | AV41: 38.973306 | AW41: 91.2955 | AX41: 241 | AY41: 38.5 | AZ41: 1 | BA41: 3.2532967 | BB41: 88.042203 | BC41: 3.64

Sheet F coupon<0.5
A1: ID | B1: {=_xlfn.ANCHORARRAY(SORT!A1)} -> Instrument | C1: Name | D1: Ticker | E1: Country/Region | F1: Currency | G1: Maturity | H1: Coupon Type | I1: Coupon Frequency | J1: Coupon | K1: Ask Yield to Maturity | L1: Bid Yield to Maturity | M1: Ask Price | N1: Bid Price | O1: Identifier | P1: ISIN | Q1: Bloomberg Composite Rating | R1: Announce | S1: Next Coupon Settle Date | T1: Time | U1: AVG price | V1: id | W1: TIMEish | X1: years ago | Y1: Accrued Interest | Z1: Clean price | AA1: AVG yield | AE1: {=_xlfn.ANCHORARRAY(B1)} -> Instrument | AF1: Name | AG1: Ticker | AH1: Country/Region | AI1: Currency | AJ1: Maturity | AK1: Coupon Type | AL1: Coupon Frequency | AM1: Coupon | AN1: Ask Yield to Maturity | AO1: Bid Yield to Maturity | AP1: Ask Price | AQ1: Bid Price | AR1: Identifier | AS1: ISIN | AT1: Bloomberg Composite Rating | AU1: Announce | AV1: Next Coupon Settle Date | AW1: Time | AX1: AVG price | AY1: id | AZ1: TIMEish | BA1: years ago | BB1: Accrued Interest | BC1: Clean price | BD1: AVG yield
B2: {=_xlfn._xlws.FILTER(_xlfn.ANCHORARRAY(AE2),OFFSET(AZ1,1,,COUNT(AZ:AZ))>0)} -> YU173621 Corp | C2: Japan Government Two Year Bond | D2: JGB | E2: JP | F2: JPY | G2: 01/10/2026 | H2: FIXED | I2: 2 | J2: 0.4 | K2: 0.876 | L2: 0.9 | M2: 99.736 | N2: 99.723 | O2: YU1736211 | P2: JP1024651QA4 | Q2: A+ | R2: 45555 | S2: 46113 | T2: 0.5065024 | U2: 99.7295 | V2: 259 | W2: 0.5 | X2: 2 | Y2: 0.3956044 | Z2: 99.333896 | AA2: 0.888 | AE2: {=_xlfn._xlws.FILTER(_xlfn.ANCHORARRAY(SORT!A2),SORT!I2:I327<0.5)} -> BO997638 Corp | AF2: Japan Government Five Year Bond | AG2: JGB | AH2: JP | AI2: JPY | AJ2: 20/03/2026 | AK2: FIXED | AL2: 2 | AM2: 0.005 | AN2: 0.74800001 | AO2: 0.76600001 | AP2: 99.983 | AQ2: 99.983 | AR2: BO9976388 | AS2: JP1051471M45 | AT2: A+ | AU2: 44287 | AV2: 46101 | AW2: -0.027378508 | AX2: 99.983 | AY2: 47 | AZ2: 0 | BA2: 5 | BB2: 0.0052472527 | BC2: 99.977753 | BD2: 0.75700001
B3: AL516835 Corp | C3: Japan Government Ten Year Bond | D3: JGB | E3: JP | F3: JPY | G3: 20/12/2026 | H3: FIXED | I3: 2 | J3: 0.1 | K3: 0.957 | L3: 0.979 | M3: 99.34 | N3: 99.323 | O3: AL5168359 | P3: JP1103451GC0 | Q3: A+ | R3: 42705 | S3: 46193 | T3: 0.72553046 | U3: 99.3315 | V3: 1 | W3: 0.5 | X3: 10 | Y3: 0.054945055 | Z3: 99.276555 | AA3: 0.968 | AE3: JK298261 Corp | AF3: Japan Government Ten Year Bond | AG3: JGB | AH3: JP | AI3: JPY | AJ3: 20/03/2026 | AK3: FIXED | AL3: 2 | AM3: 0.1 | AN3: 0.74 | AO3: 0.763 | AP3: 99.985 | AQ3: 99.985 | AR3: JK2982615 | AS3: JP1103421G35 | AT3: A+ | AU3: 42430 | AV3: 46101 | AW3: -0.027378508 | AX3: 99.985 | AY3: 206 | AZ3: 0 | BA3: 10 | BB3: 0.10494505 | BC3: 99.880055 | BD3: 0.7515
B4: BT484763 Corp | C4: Japan Government Five Year Bond | D4: JGB | E4: JP | F4: JPY | G4: 20/12/2026 | H4: FIXED | I4: 2 | J4: 0.005 | K4: 0.951 | L4: 0.973 | M4: 99.271 | N4: 99.255 | O4: BT4847633 | P4: JP1051501N14 | Q4: NR | R4: 44566 | S4: 46193 | T4: 0.72553046 | U4: 99.263 | V4: 60 | W4: 0.5 | X4: 4 | Y4: 0.0027472527 | Z4: 99.260253 | AA4: 0.962 | AE4: ZB137529 Corp | AF4: Japan Government Two Year Bond | AG4: JGB | AH4: JP | AI4: JPY | AJ4: 01/04/2026 | AK4: FIXED | AL4: 2 | AM4: 0.2 | AN4: 0.735 | AO4: 0.75800001 | AP4: 99.97 | AQ4: 99.969 | AR4: ZB1375292 | AS4: JP1024591Q43 | AT4: A+ | AU4: 45373 | AV4: 46113 | AW4: 0.0054757016 | AX4: 99.9695 | AY4: 280 | AZ4: 0 | BA4: 2 | BB4: 0.1978022 | BC4: 99.771698 | BD4: 0.7465
B5: AM713129 Corp | C5: Japan Government Ten Year Bond | D5: JGB | E5: JP | F5: JPY | G5: 20/03/2027 | H5: FIXED | I5: 2 | J5: 0.1 | K5: 1 | L5: 1.021 | M5: 99.089 | N5: 99.068 | O5: AM7131296 | P5: JP1103461H35 | Q5: A+ | R5: 42796 | S5: 46101 | T5: 0.97193703 | U5: 99.0785 | V5: 4 | W5: 0.5 | X5: 9 | Y5: 0.10494505 | Z5: 98.973555 | AA5: 1.0105 | AE5: ZB651229 Corp | AF5: Japan Government Two Year Bond | AG5: JGB | AH5: JP | AI5: JPY | AJ5: 01/05/2026 | AK5: FIXED | AL5: 2 | AM5: 0.3 | AN5: 0.75 | AO5: 0.773 | AP5: 99.938 | AQ5: 99.935 | AR5: ZB6512295 | AS5: JP1024601Q58 | AT5: A+ | AU5: 45398 | AV5: 46143 | AW5: 0.087611225 | AX5: 99.9365 | AY5: 285 | AZ5: 0 | BA5: 2 | BB5: 0.2456044 | BC5: 99.690896 | BD5: 0.7615
B6: BV894033 Corp | C6: Japan Government Five Year Bond | D6: JGB | E6: JP | F6: JPY | G6: 20/03/2027 | H6: FIXED | I6: 2 | J6: 0.005 | K6: 0.991 | L6: 1.016 | M6: 99.002 | N6: 98.977 | O6: BV8940330 | P6: JP1051511N46 | Q6: A+ | R6: 44656 | S6: 46101 | T6: 0.97193703 | U6: 98.9895 | V6: 64 | W6: 0.5 | X6: 4 | Y6: 0.0052472527 | Z6: 98.984253 | AA6: 1.0035 | AE6: YX440521 Corp | AF6: Japan Government Two Year Bond | AG6: JGB | AH6: JP | AI6: JPY | AJ6: 01/06/2026 | AK6: FIXED | AL6: 2 | AM6: 0.4 | AN6: 0.763 | AO6: 0.785 | AP6: 99.919 | AQ6: 99.914 | AR6: YX4405214 | AS6: JP1024611Q64 | AT6: A+ | AU6: 45435 | AV6: 46174 | AW6: 0.1724846 | AX6: 99.9165 | AY6: 278 | AZ6: 0 | BA6: 2 | BB6: 0.26153846 | BC6: 99.654962 | BD6: 0.774
B7: BX331425 Corp | C7: Japan Government Five Year Bond | D7: JGB | E7: JP | F7: JPY | G7: 20/03/2027 | H7: FIXED | I7: 2 | J7: 0.1 | K7: 0.992 | L7: 1.016 | M7: 99.097 | N7: 99.073 | O7: BX3314255 | P7: JP1051521N69 | Q7: A+ | R7: 44726 | S7: 46101 | T7: 0.97193703 | U7: 99.085 | V7: 67 | W7: 0.5 | X7: 4 | Y7: 0.10494505 | Z7: 98.980055 | AA7: 1.004 | AE7: BQ447894 Corp | AF7: Japan Government Five Year Bond | AG7: JGB | AH7: JP | AI7: JPY | AJ7: 20/06/2026 | AK7: FIXED | AL7: 2 | AM7: 0.005 | AN7: 0.78 | AO7: 0.803 | AP7: 99.788 | AQ7: 99.781 | AR7: BQ4478948 | AS7: JP1051481M76 | AT7: NR | AU7: 44378 | AV7: 46193 | AW7: 0.22450376 | AX7: 99.7845 | AY7: 52 | AZ7: 0 | BA7: 5 | BB7: 0.0027472527 | BC7: 99.781753 | BD7: 0.7915
B8: AN821370 Corp | C8: Japan Government Ten Year Bond | D8: JGB | E8: JP | F8: JPY | G8: 20/06/2027 | H8: FIXED | I8: 2 | J8: 0.1 | K8: 1.062 | L8: 1.085 | M8: 98.79 | N8: 98.762 | O8: AN8213703 | P8: JP1103471H66 | Q8: A+ | R8: 42887 | S8: 46193 | T8: 1.2238193 | U8: 98.776 | V8: 8 | W8: 1 | X8: 9 | Y8: 0.054945055 | Z8: 98.721055 | AA8: 1.0735 | AE8: LW316486 Corp | AF8: Japan Government Ten Year Bond | AG8: JGB | AH8: JP | AI8: JPY | AJ8: 20/06/2026 | AK8: FIXED | AL8: 2 | AM8: 0.1 | AN8: 0.772 | AO8: 0.794 | AP8: 99.816 | AQ8: 99.81 | AR8: LW3164867 | AS8: JP1103431G66 | AT8: A+ | AU8: 42523 | AV8: 46193 | AW8: 0.22450376 | AX8: 99.813 | AY8: 212 | AZ8: 0 | BA8: 10 | BB8: 0.054945055 | BC8: 99.758055 | BD8: 0.783
B9: BX810244 Corp | C9: Japan Government Five Year Bond | D9: JGB | E9: JP | F9: JPY | G9: 20/06/2027 | H9: FIXED | I9: 2 | J9: 0.005 | K9: 1.06 | L9: 1.085 | M9: 98.673 | N9: 98.642 | O9: BX8102440 | P9: JP1051531N75 | Q9: A+ | R9: 44747 | S9: 46193 | T9: 1.2238193 | U9: 98.6575 | V9: 70 | W9: 1 | X9: 4 | Y9: 0.0027472527 | Z9: 98.654753 | AA9: 1.0725 | AE9: YW041715 Corp | AF9: Japan Government Two Year Bond | AG9: JGB | AH9: JP | AI9: JPY | AJ9: 01/07/2026 | AK9: FIXED | AL9: 2 | AM9: 0.4 | AN9: 0.79 | AO9: 0.813 | AP9: 99.881 | AQ9: 99.874 | AR9: YW0417157 | AS9: JP1024621Q70 | AT9: A+ | AU9: 45463 | AV9: 46204 | AW9: 0.25462012 | AX9: 99.8775 | AY9: 268 | AZ9: 0 | BA9: 2 | BB9: 0.19340659 | BC9: 99.684093 | BD9: 0.8015
B10: AP027592 Corp | C10: Japan Government Ten Year Bond | D10: JGB | E10: JP | F10: JPY | G10: 20/09/2027 | H10: FIXED | I10: 2 | J10: 0.1 | K10: 1.138 | L10: 1.161 | M10: 98.443 | N10: 98.409 | O10: AP0275929 | P10: JP1103481H98 | Q10: A+ | R10: 42983 | S10: 46101 | T10: 1.4757016 | U10: 98.426 | V10: 11 | W10: 1 | X10: 9 | Y10: 0.10494505 | Z10: 98.321055 | AA10: 1.1495 | AE10: YW691926 Corp | AF10: Japan Government Two Year Bond | AG10: JGB | AH10: JP | AI10: JPY | AJ10: 01/08/2026 | AK10: FIXED | AL10: 2 | AM10: 0.4 | AN10: 0.824 | AO10: 0.847 | AP10: 99.835 | AQ10: 99.826 | AR10: YW6919263 | AS10: JP1024631Q86 | AT10: A+ | AU10: 45492 | AV10: 46235 | AW10: 0.3394935 | AX10: 99.8305 | AY10: 274 | AZ10: 0 | BA10: 2 | BB10: 0.12527473 | BC10: 99.705225 | BD10: 0.8355
B11: BZ743105 Corp | C11: Japan Government Five Year Bond | D11: JGB | E11: JP | F11: JPY | G11: 20/09/2027 | H11: FIXED | I11: 2 | J11: 0.1 | K11: 1.144 | L11: 1.167 | M11: 98.434 | N11: 98.4 | O11: BZ7431050 | P11: JP1051541NA0 | Q11: A+ | R11: 44841 | S11: 46101 | T11: 1.4757016 | U11: 98.417 | V11: 74 | W11: 1 | X11: 4 | Y11: 0.10494505 | Z11: 98.312055 | AA11: 1.1555 | AE11: YV477187 Corp | AF11: Japan Government Two Year Bond | AG11: JGB | AH11: JP | AI11: JPY | AJ11: 01/09/2026 | AK11: FIXED | AL11: 2 | AM11: 0.4 | AN11: 0.853 | AO11: 0.876 | AP11: 99.786 | AQ11: 99.775 | AR11: YV4771874 | AS11: JP1024641Q92 | AT11: A+ | AU11: 45526 | AV11: 46266 | AW11: 0.42436687 | AX11: 99.7805 | AY11: 266 | AZ11: 0 | BA11: 2 | BB11: 0.063736264 | BC11: 99.716764 | BD11: 0.8645
B12: AQ307103 Corp | C12: Japan Government Ten Year Bond | D12: JGB | E12: JP | F12: JPY | G12: 20/12/2027 | H12: FIXED | I12: 2 | J12: 0.1 | K12: 1.178 | L12: 1.202 | M12: 98.125 | N12: 98.084 | O12: AQ3071034 | P12: JP1103491HC4 | Q12: A+ | R12: 43074 | S12: 46193 | T12: 1.724846 | U12: 98.1045 | V12: 14 | W12: 1.5 | X12: 9 | Y12: 0.054945055 | Z12: 98.049555 | AA12: 1.19 | AE12: BR962540 Corp | AF12: Japan Government Five Year Bond | AG12: JGB | AH12: JP | AI12: JPY | AJ12: 20/09/2026 | AK12: FIXED | AL12: 2 | AM12: 0.005 | AN12: 0.873 | AO12: 0.896 | AP12: 99.545 | AQ12: 99.533 | AR12: BR9625400 | AS12: JP1051491MA0 | AT12: A+ | AU12: 44476 | AV12: 46101 | AW12: 0.47638604 | AX12: 99.539 | AY12: 56 | AZ12: 0 | BA12: 5 | BB12: 0.0052472527 | BC12: 99.533753 | BD12: 0.8845
B13: ZL113533 Corp | C13: Japan Government Five Year Bond | D13: JGB | E13: JP | F13: JPY | G13: 20/12/2027 | H13: FIXED | I13: 2 | J13: 0.2 | K13: 1.179 | L13: 1.204 | M13: 98.297 | N13: 98.254 | O13: ZL1135330 | P13: JP1051561P27 | Q13: A+ | R13: 44966 | S13: 46193 | T13: 1.724846 | U13: 98.2755 | V13: 311 | W13: 1.5 | X13: 3 | Y13: 0.10989011 | Z13: 98.16561 | AA13: 1.1915 | AE13: QZ413850 Corp | AF13: Japan Government Ten Year Bond | AG13: JGB | AH13: JP | AI13: JPY | AJ13: 20/09/2026 | AK13: FIXED | AL13: 2 | AM13: 0.1 | AN13: 0.867 | AO13: 0.889 | AP13: 99.598 | AQ13: 99.586 | AR13: QZ4138504 | AS13: JP1103441G98 | AT13: A+ | AU13: 42614 | AV13: 46101 | AW13: 0.47638604 | AX13: 99.592 | AY13: 215 | AZ13: 0 | BA13: 10 | BB13: 0.10494505 | BC13: 99.487055 | BD13: 0.878
B14: ZM445143 Corp | C14: Japan Government Five Year Bond | D14: JGB | E14: JP | F14: JPY | G14: 20/12/2027 | H14: FIXED | I14: 2 | J14: 0.3 | K14: 1.182 | L14: 1.206 | M14: 98.466 | N14: 98.425 | O14: ZM4451435 | P14: JP1051551P11 | Q14: A+ | R14: 44932 | S14: 46193 | T14: 1.724846 | U14: 98.4455 | V14: 314 | W14: 1.5 | X14: 3 | Y14: 0.16483516 | Z14: 98.280665 | AA14: 1.194 | AE14: YU173621 Corp | AF14: Japan Government Two Year Bond | AG14: JGB | AH14: JP | AI14: JPY | AJ14: 01/10/2026 | AK14: FIXED | AL14: 2 | AM14: 0.4 | AN14: 0.876 | AO14: 0.9 | AP14: 99.736 | AQ14: 99.723 | AR14: YU1736211 | AS14: JP1024651QA4 | AT14: A+ | AU14: 45555 | AV14: 46113 | AW14: 0.5065024 | AX14: 99.7295 | AY14: 259 | AZ14: 0.5 | BA14: 2 | BB14: 0.3956044 | BC14: 99.333896 | BD14: 0.888
... B63: LW239433 Corp | C63: Japan Government Forty Year Bond | D63: JGB | E63: JP | F63: JPY | G63: 20/03/2056 | H63: FIXED | I63: 2 | J63: 0.4 | K63: 5.153 | L63: 5.212 | M63: 43.976 | N63: 43.672 | O63: LW2394333 | P63: JP1400091G59 | Q63: A+ | R63: 42516 | S63: 46101 | T63: 29.97399 | U63: 43.824 | V63: 211 | W63: 29.5 | X63: 10 | Y63: 0.41978022 | Z63: 43.40422 | AA63: 5.1825 | AE63: AZ694472 Corp | AF63: Japan Government Twenty Year Bond | AG63: JGB | AH63: JP | AI63: JPY | AJ63: 20/06/2039 | AK63: FIXED | AL63: 2 | AM63: 0.3 | AN63: 2.941 | AO63: 2.966 | AP63: 74.786 | AQ63: 74.608 | AR63: AZ6944724 | AS63: JP1201691K75 | AT63: A+ | AU63: 43663 | AV63: 46193 | AW63: 13.223819 | AX63: 74.697 | AY63: 33 | AZ63: 13 | BA63: 7 | BB63: 0.16483516 | BC63: 74.532165 | BD63: 2.9535
AE64: ZQ278992 Corp | AF64: Japan Government Twenty Year Bond | AG64: JGB | AH64: JP | AI64: JPY | AJ64: 20/09/2039 | AK64: FIXED | AL64: 2 | AM64: 0.3 | AN64: 2.985 | AO64: 3.011 | AP64: 74.128 | AQ64: 73.943 | AR64: ZQ2789928 | AS64: JP1201701KA5 | AT64: A+ | AU64: 43762 | AV64: 46101 | AW64: 13.475702 | AX64: 74.0355 | AY64: 322 | AZ64: 13 | BA64: 7 | BB64: 0.31483516 | BC64: 73.720665 | BD64: 2.998
AE65: ZP562354 Corp | AF65: Japan Government Twenty Year Bond | AG65: JGB | AH65: JP | AI65: JPY | AJ65: 20/12/2039 | AK65: FIXED | AL65: 2 | AM65: 0.3 | AN65: 3.027 | AO65: 3.053 | AP65: 73.489 | AQ65: 73.303 | AR65: ZP5623548 | AS65: JP1201711L13 | AT65: A+ | AU65: 43840 | AV65: 46193 | AW65: 13.724846 | AX65: 73.396 | AY65: 320 | AZ65: 13.5 | BA65: 6 | BB65: 0.16483516 | BC65: 73.231165 | BD65: 3.04
AE66: BI018471 Corp | AF66: Japan Government Twenty Year Bond | AG66: JGB | AH66: JP | AI66: JPY | AJ66: 20/03/2040 | AK66: FIXED | AL66: 2 | AM66: 0.4 | AN66: 3.045 | AO66: 3.071 | AP66: 74.009 | AQ66: 73.82 | AR66: BI0184712 | AS66: JP1201721L45 | AT66: A+ | AU66: 43935 | AV66: 46101 | AW66: 13.97399 | AX66: 73.9145 | AY66: 36 | AZ66: 13.5 | BA66: 6 | BB66: 0.41978022 | BC66: 73.49472 | BD66: 3.058
AE67: BK594564 Corp | AF67: Japan Government Twenty Year Bond | AG67: JGB | AH67: JP | AI67: JPY | AJ67: 20/06/2040 | AK67: FIXED | AL67: 2 | AM67: 0.4 | AN67: 3.081 | AO67: 3.105 | AP67: 73.42 | AQ67: 73.246 | AR67: BK5945641 | AS67: JP1201731L76 | AT67: A+ | AU67: 44026 | AV67: 46193 | AW67: 14.225873 | AX67: 73.333 | AY67: 40 | AZ67: 14 | BA67: 6 | BB67: 0.21978022 | BC67: 73.11322 | BD67: 3.093
AE68: BM027946 Corp | AF68: Japan Government Twenty Year Bond | AG68: JGB | AH68: JP | AI68: JPY | AJ68: 20/09/2040 | AK68: FIXED | AL68: 2 | AM68: 0.4 | AN68: 3.118 | AO68: 3.144 | AP68: 72.825 | AQ68: 72.637 | AR68: BM0279463 | AS68: JP1201741LA9 | AT68: NR | AU68: 44117 | AV68: 46101 | AW68: 14.477755 | AX68: 72.731 | AY68: 41 | AZ68: 14 | BA68: 6 | BB68: 0.41978022 | BC68: 72.31122 | BD68: 3.131
AE69: BQ516777 Corp | AF69: Japan Government Twenty Year Bond | AG69: JGB | AH69: JP | AI69: JPY | AJ69: 20/06/2041 | AK69: FIXED | AL69: 2 | AM69: 0.4 | AN69: 3.245 | AO69: 3.269 | AP69: 70.945 | AQ69: 70.772 | AR69: BQ5167771 | AS69: JP1201771M76 | AT69: NR | AU69: 44383 | AV69: 46193 | AW69: 15.225188 | AX69: 70.8585 | AY69: 53 | AZ69: 15 | BA69: 5 | BB69: 0.21978022 | BC69: 70.63872 | BD69: 3.257
AE70: LW361469 Corp | AF70: Japan Government Thirty Year Bond | AG70: JGB | AH70: JP | AI70: JPY | AJ70: 20/06/2046 | AK70: FIXED | AL70: 2 | AM70: 0.3 | AN70: 4.034 | AO70: 4.072 | AP70: 58.355 | AQ70: 58.109 | AR70: LW3614697 | AS70: JP1300511G61 | AT70: A+ | AU70: 42528 | AV70: 46193 | AW70: 20.224504 | AX70: 58.232 | AY70: 213 | AZ70: 20 | BA70: 10 | BB70: 0.16483516 | BC70: 58.067165 | BD70: 4.053
AE71: AZ527231 Corp | AF71: Japan Government Thirty Year Bond | AG71: JGB | AH71: JP | AI71: JPY | AJ71: 20/06/2049 | AK71: FIXED | AL71: 2 | AM71: 0.4 | AN71: 4.431 | AO71: 4.469 | AP71: 53.813 | AQ71: 53.58 | AR71: AZ5272317 | AS71: JP1300631K78 | AT71: A+ | AU71: 43650 | AV71: 46193 | AW71: 23.225188 | AX71: 53.6965 | AY71: 32 | AZ71: 23 | BA71: 7 | BB71: 0.21978022 | BC71: 53.47672 | BD71: 4.45
AE72: ZQ061592 Corp | AF72: Japan Government Thirty Year Bond | AG72: JGB | AH72: JP | AI72: JPY | AJ72: 20/09/2049 | AK72: FIXED | AL72: 2 | AM72: 0.4 | AN72: 4.476 | AO72: 4.515 | AP72: 53.292 | AQ72: 53.055 | AR72: ZQ0615927 | AS72: JP1300641KA3 | AT72: A+ | AU72: 43748 | AV72: 46101 | AW72: 23.47707 | AX72: 53.1735 | AY72: 321 | AZ72: 23 | BA72: 7 | BB72: 0.41978022 | BC72: 52.75372 | BD72: 4.4955
AE73: ZP387400 Corp | AF73: Japan Government Thirty Year Bond | AG73: JGB | AH73: JP | AI73: JPY | AJ73: 20/12/2049 | AK73: FIXED | AL73: 2 | AM73: 0.4 | AN73: 4.523 | AO73: 4.559 | AP73: 52.766 | AQ73: 52.55 | AR73: ZP3874002 | AS73: JP1300651L15 | AT73: A+ | AU73: 43826 | AV73: 46193 | AW73: 23.726215 | AX73: 52.658 | AY73: 319 | AZ73: 23.5 | BA73: 7 | BB73: 0.21978022 | BC73: 52.43822 | BD73: 4.541
AE74: BH620692 Corp | AF74: Japan Government Thirty Year Bond | AG74: JGB | AH74: JP | AI74: JPY | AJ74: 20/03/2050 | AK74: FIXED | AL74: 2 | AM74: 0.4 | AN74: 4.559 | AO74: 4.598 | AP74: 52.315 | AQ74: 52.082 | AR74: BH6206925 | AS74: JP1300661L47 | AT74: A+ | AU74: 43921 | AV74: 46101 | AW74: 23.972621 | AX74: 52.1985 | AY74: 35 | AZ74: 23.5 | BA74: 6 | BB74: 0.41978022 | BC74: 51.77872 | BD74: 4.5785
AE75: LW239433 Corp | AF75: Japan Government Forty Year Bond | AG75: JGB | AH75: JP | AI75: JPY | AJ75: 20/03/2056 | AK75: FIXED | AL75: 2 | AM75: 0.4 | AN75: 5.153 | AO75: 5.212 | AP75: 43.976 | AQ75: 43.672 | AR75: LW2394333 | AS75: JP1400091G59 | AT75: A+ | AU75: 42516 | AV75: 46101 | AW75: 29.97399 | AX75: 43.824 | AY75: 211 | AZ75: 29.5 | BA75: 10 | BB75: 0.41978022 | BC75: 43.40422 | BD75: 5.1825

Sheet NSS
A1: F coupon<0.5 | C1: Price | E1: =IF(COUNT(H:H)>=COUNT(INDIRECT("'"&A1&"'!W:W")),"YAY ENOUGH ROWS","NEEDS MORE ROWS") -> YAY ENOUGH ROWS | K1: Cash flows | CN1: FITTED VISUALISATION | EC1: AVG yield | ED1: ask yield | EE1: bid yield
A2: Maturity | B2: Coupon | C2: Market | D2: Model | E2: Error | F2: Abs Error | G2: Yield | H2: Yield Model | I2: Yield Error | J2: - prices | K2: {=_xlfn.SEQUENCE(1,79,0,0.5)} -> 0 | L2: 0.5 | M2: 1 | N2: 1.5 | O2: 2 | P2: 2.5 | Q2: 3 | R2: 3.5 | S2: 4 | T2: 4.5 | U2: 5 | V2: 5.5 | W2: 6 | X2: 6.5 | Y2: 7 | Z2: 7.5 | AA2: 8 | AB2: 8.5 | AC2: 9 | AD2: 9.5 | AE2: 10 | AF2: 10.5 | AG2: 11 | AH2: 11.5 | AI2: 12 | AJ2: 12.5 | AK2: 13 | AL2: 13.5 | AM2: 14 | AN2: 14.5 | AO2: 15 | AP2: 15.5 | AQ2: 16 | AR2: 16.5 | AS2: 17 | AT2: 17.5 | AU2: 18 | AV2: 18.5 | AW2: 19 | AX2: 19.5 | AY2: 20 | AZ2: 20.5 | BA2: 21 | BB2: 21.5 | BC2: 22 | BD2: 22.5 | BE2: 23 | BF2: 23.5 | BG2: 24 | BH2: 24.5 | BI2: 25 | BJ2: 25.5 | BK2: 26 | BL2: 26.5 | BM2: 27 | BN2: 27.5 | BO2: 28 | BP2: 28.5 | BQ2: 29 | BR2: 29.5 | BS2: 30 | BT2: 30.5 | BU2: 31 | BV2: 31.5 | BW2: 32 | BX2: 32.5 | BY2: 33 | BZ2: 33.5 | CA2: 34 | CB2: 34.5 | CC2: 35 | CD2: 35.5 | CE2: 36 | CF2: 36.5 | CG2: 37 | CH2: 37.5 | CI2: 38 | CJ2: 38.5 | CK2: 39 | CN2: Time discretization | CO2: Long term spot | CP2: Time decay | CQ2: First hump | CR2: Second hump | CS2: Total | EC2: {=OFFSET(INDIRECT(ADDRESS(1,27,,,A1)),1,,COUNT(INDIRECT("'"&A1&"'!U:U")))/100} -> 0.00888 | ED2: {=OFFSET(INDIRECT(ADDRESS(1,11,,,A1)),1,,COUNT(INDIRECT("'"&A1&"'!U:U")))/100} -> 0.00876 | EE2: {=OFFSET(INDIRECT(ADDRESS(1,12,,,A1)),1,,COUNT(INDIRECT("'"&A1&"'!U:U")))/100} -> 0.009
A3: {=OFFSET(INDIRECT(ADDRESS(1,23,,,A1)),1,,COUNT(INDIRECT("'"&A1&"'!W:W")))} -> 0.5 | B3: {=OFFSET(INDIRECT(ADDRESS(1,10,,,A1)),1,,COUNT(INDIRECT("'"&A1&"'!J:J")))/100} -> 0.004 | C3: {=OFFSET(INDIRECT(ADDRESS(1,21,,,A1)),1,,COUNT(INDIRECT("'"&A1&"'!U:U")))} -> 99.7295 | D3: =SUMPRODUCT(L3:CK3,$L$249:$CK$249) -> 99.629386 | E3: =+D3-C3 -> -0.10011433 | F3: =ABS(C3-D3) -> 0.10011433 | G3: =+IFERROR(IRR(K3:CK3,0),0) -> 0.0067231862 | H3: =IFERROR(IRR((J3,L3:CK3),0),0) -> 0.0077348096 | I3: =IFERROR(H3-G3,0) -> 0.0010116234 | J3: =-D3 -> -99.629386 | K3: =-C3 -> -99.7295 | L3: =$B3*100*(L$2<$A3)+100*(1+$B3)*(L$2=$A3) -> 100.4 | M3: =$B3*100*(M$2<$A3)+100*(1+$B3)*(M$2=$A3) -> 0 | N3: =$B3*100*(N$2<$A3)+100*(1+$B3)*(N$2=$A3) -> 0 | O3: =$B3*100*(O$2<$A3)+100*(1+$B3)*(O$2=$A3) -> 0 | P3: =$B3*100*(P$2<$A3)+100*(1+$B3)*(P$2=$A3) -> 0 | Q3: =$B3*100*(Q$2<$A3)+100*(1+$B3)*(Q$2=$A3) -> 0 | R3: =$B3*100*(R$2<$A3)+100*(1+$B3)*(R$2=$A3) -> 0 | S3: =$B3*100*(S$2<$A3)+100*(1+$B3)*(S$2=$A3) -> 0 | ... CK3: =$B3*100*(CK$2<$A3)+100*(1+$B3)*(CK$2=$A3) -> 0 | CN3: 1e-06 | CO3: =$B$248 -> 0.05 | CP3: =b1_*(1-EXP(-CN3/tau1_))/(CN3/tau1_) -> -0.040658777 | CQ3: =b2_*((1-EXP(-CN3/tau1_))/(CN3/tau1_)-EXP(-CN3/tau1_)) -> -5.3576813e-09 | CR3: =+b3_*((1-EXP(-CN3/tau2_))/(CN3/tau2_)-EXP(-CN3/tau2_)) -> 2.5003682e-09 | CS3: =SUM(CO3:CR3) -> 0.0093412201 | EC3: 0.00968 | ED3: 0.00957 | EE3: 0.00979
A4: 0.5 | B4: 0.001 | C4: 99.3315 | D4: =SUMPRODUCT(L4:CK4,$L$249:$CK$249) -> 99.331688 | E4: =+D4-C4 -> 0.00018830187 | F4: =ABS(C4-D4) -> 0.00018830187 | G4: =+IFERROR(IRR(K4:CK4,0),0) -> 0.00773672 | H4: =IFERROR(IRR((J4,L4:CK4),0),0) -> 0.0077348096 | I4: =IFERROR(H4-G4,0) -> -1.9103542e-06 | J4: =-D4 -> -99.331688 | K4: =-C4 -> -99.3315 | L4: =$B4*100*(L$2<$A4)+100*(1+$B4)*(L$2=$A4) -> 100.1 | M4: =$B4*100*(M$2<$A4)+100*(1+$B4)*(M$2=$A4) -> 0 | N4: =$B4*100*(N$2<$A4)+100*(1+$B4)*(N$2=$A4) -> 0 | O4: =$B4*100*(O$2<$A4)+100*(1+$B4)*(O$2=$A4) -> 0 | P4: =$B4*100*(P$2<$A4)+100*(1+$B4)*(P$2=$A4) -> 0 | Q4: =$B4*100*(Q$2<$A4)+100*(1+$B4)*(Q$2=$A4) -> 0 | R4: =$B4*100*(R$2<$A4)+100*(1+$B4)*(R$2=$A4) -> 0 | S4: =$B4*100*(S$2<$A4)+100*(1+$B4)*(S$2=$A4) -> 0 | ... CK4: =$B4*100*(CK$2<$A4)+100*(1+$B4)*(CK$2=$A4) -> 0 | CN4: {=_xlfn.SEQUENCE(500,,0.5,0.5)} -> 0.5 | CO4: {=_xlfn.ANCHORARRAY(CN4)-_xlfn.ANCHORARRAY(CN4)+$B$248} -> 0.05 | CP4: {=b1_*(1-EXP(-_xlfn.ANCHORARRAY(CN4)/tau1_))/(_xlfn.ANCHORARRAY(CN4)/tau1_)} -> -0.038388015 | CQ4: {=b2_*((1-EXP(-_xlfn.ANCHORARRAY(CN4)/tau1_))/(_xlfn.ANCHORARRAY(CN4)/tau1_)-EXP(-_xlfn.ANCHORARRAY(CN4)/tau1_))} -> -0.002479083 | CR4: {=+b3_*((1-EXP(-_xlfn.ANCHORARRAY(CN4)/tau2_))/(_xlfn.ANCHORARRAY(CN4)/tau2_)-EXP(-_xlfn.ANCHORARRAY(CN4)/tau2_))} -> 0.00079159629 | CS4: =SUM(CO4:CR4) -> 0.0099244979 | EC4: 0.00962 | ED4: 0.00951 | EE4: 0.00973
A5: 0.5 | B5: 5e-05 | C5: 99.263 | D5: =SUMPRODUCT(L5:CK5,$L$249:$CK$249) -> 99.237417 | E5: =+D5-C5 -> -0.025582531 | F5: =ABS(C5-D5) -> 0.025582531 | G5: =+IFERROR(IRR(K5:CK5,0),0) -> 0.0074750914 | H5: =IFERROR(IRR((J5,L5:CK5),0),0) -> 0.0077348096 | I5: =IFERROR(H5-G5,0) -> 0.0002597182 | J5: =-D5 -> -99.237417 | K5: =-C5 -> -99.263 | L5: =$B5*100*(L$2<$A5)+100*(1+$B5)*(L$2=$A5) -> 100.005 | M5: =$B5*100*(M$2<$A5)+100*(1+$B5)*(M$2=$A5) -> 0 | N5: =$B5*100*(N$2<$A5)+100*(1+$B5)*(N$2=$A5) -> 0 | O5: =$B5*100*(O$2<$A5)+100*(1+$B5)*(O$2=$A5) -> 0 | P5: =$B5*100*(P$2<$A5)+100*(1+$B5)*(P$2=$A5) -> 0 | Q5: =$B5*100*(Q$2<$A5)+100*(1+$B5)*(Q$2=$A5) -> 0 | R5: =$B5*100*(R$2<$A5)+100*(1+$B5)*(R$2=$A5) -> 0 | S5: =$B5*100*(S$2<$A5)+100*(1+$B5)*(S$2=$A5) -> 0 | ... CK5: =$B5*100*(CK$2<$A5)+100*(1+$B5)*(CK$2=$A5) -> 0 | CN5: 1 | CO5: 0.05 | CP5: -0.036284745 | CQ5: -0.0045942128 | CR5: 0.0010330657 | CS5: =SUM(CO5:CR5) -> 0.010154107 | EC5: 0.010105 | ED5: 0.01 | EE5: 0.01021
A6: 0.5 | B6: 0.001 | C6: 99.0785 | D6: =SUMPRODUCT(L6:CK6,$L$249:$CK$249) -> 99.331688 | E6: =+D6-C6 -> 0.2531883 | F6: =ABS(C6-D6) -> 0.2531883 | G6: =+IFERROR(IRR(K6:CK6,0),0) -> 0.010310007 | H6: =IFERROR(IRR((J6,L6:CK6),0),0) -> 0.0077348096 | I6: =IFERROR(H6-G6,0) -> -0.0025751971 | J6: =-D6 -> -99.331688 | K6: =-C6 -> -99.0785 | L6: =$B6*100*(L$2<$A6)+100*(1+$B6)*(L$2=$A6) -> 100.1 | M6: =$B6*100*(M$2<$A6)+100*(1+$B6)*(M$2=$A6) -> 0 | N6: =$B6*100*(N$2<$A6)+100*(1+$B6)*(N$2=$A6) -> 0 | O6: =$B6*100*(O$2<$A6)+100*(1+$B6)*(O$2=$A6) -> 0 | P6: =$B6*100*(P$2<$A6)+100*(1+$B6)*(P$2=$A6) -> 0 | Q6: =$B6*100*(Q$2<$A6)+100*(1+$B6)*(Q$2=$A6) -> 0 | R6: =$B6*100*(R$2<$A6)+100*(1+$B6)*(R$2=$A6) -> 0 | S6: =$B6*100*(S$2<$A6)+100*(1+$B6)*(S$2=$A6) -> 0 | ... CK6: =$B6*100*(CK$2<$A6)+100*(1+$B6)*(CK$2=$A6) -> 0 | CN6: 1.5 | CO6: 0.05 | CP6: -0.034335126 | CQ6: -0.0063903867 | CR6: 0.0010435906 | CS6: =SUM(CO6:CR6) -> 0.010318078 | EC6: 0.010035 | ED6: 0.00991 | EE6: 0.01016
A7: 0.5 | B7: 5e-05 | C7: 98.9895 | D7: =SUMPRODUCT(L7:CK7,$L$249:$CK$249) -> 99.237417 | E7: =+D7-C7 -> 0.24791747 | F7: =ABS(C7-D7) -> 0.24791747 | G7: =+IFERROR(IRR(K7:CK7,0),0) -> 0.010258664 | H7: =IFERROR(IRR((J7,L7:CK7),0),0) -> 0.0077348096 | I7: =IFERROR(H7-G7,0) -> -0.0025238542 | J7: =-D7 -> -99.237417 | K7: =-C7 -> -98.9895 | L7: =$B7*100*(L$2<$A7)+100*(1+$B7)*(L$2=$A7) -> 100.005 | M7: =$B7*100*(M$2<$A7)+100*(1+$B7)*(M$2=$A7) -> 0 | N7: =$B7*100*(N$2<$A7)+100*(1+$B7)*(N$2=$A7) -> 0 | O7: =$B7*100*(O$2<$A7)+100*(1+$B7)*(O$2=$A7) -> 0 | P7: =$B7*100*(P$2<$A7)+100*(1+$B7)*(P$2=$A7) -> 0 | Q7: =$B7*100*(Q$2<$A7)+100*(1+$B7)*(Q$2=$A7) -> 0 | R7: =$B7*100*(R$2<$A7)+100*(1+$B7)*(R$2=$A7) -> 0 | S7: =$B7*100*(S$2<$A7)+100*(1+$B7)*(S$2=$A7) -> 0 | ... CK7: =$B7*100*(CK$2<$A7)+100*(1+$B7)*(CK$2=$A7) -> 0 | CN7: 2 | CO7: 0.05 | CP7: -0.032526528 | CQ7: -0.0079073324 | CR7: 0.00096772586 | CS7: =SUM(CO7:CR7) -> 0.010533865 | EC7: 0.01004 | ED7: 0.00992 | EE7: 0.01016
A8: 0.5 | B8: 0.001 | C8: 99.085 | D8: =SUMPRODUCT(L8:CK8,$L$249:$CK$249) -> 99.331688 | E8: =+D8-C8 -> 0.2466883 | F8: =ABS(C8-D8) -> 0.2466883 | G8: =+IFERROR(IRR(K8:CK8,0),0) -> 0.01024373 | H8: =IFERROR(IRR((J8,L8:CK8),0),0) -> 0.0077348096 | I8: =IFERROR(H8-G8,0) -> -0.0025089205 | J8: =-D8 -> -99.331688 | K8: =-C8 -> -99.085 | L8: =$B8*100*(L$2<$A8)+100*(1+$B8)*(L$2=$A8) -> 100.1 | M8: =$B8*100*(M$2<$A8)+100*(1+$B8)*(M$2=$A8) -> 0 | N8: =$B8*100*(N$2<$A8)+100*(1+$B8)*(N$2=$A8) -> 0 | O8: =$B8*100*(O$2<$A8)+100*(1+$B8)*(O$2=$A8) -> 0 | P8: =$B8*100*(P$2<$A8)+100*(1+$B8)*(P$2=$A8) -> 0 | Q8: =$B8*100*(Q$2<$A8)+100*(1+$B8)*(Q$2=$A8) -> 0 | R8: =$B8*100*(R$2<$A8)+100*(1+$B8)*(R$2=$A8) -> 0 | S8: =$B8*100*(S$2<$A8)+100*(1+$B8)*(S$2=$A8) -> 0 | ... CK8: =$B8*100*(CK$2<$A8)+100*(1+$B8)*(CK$2=$A8) -> 0 | CN8: 2.5 | CO8: 0.05 | CP8: -0.030847433 | CQ8: -0.0091801102 | CR8: 0.0008683995 | CS8: =SUM(CO8:CR8) -> 0.010840856 | EC8: 0.010735 | ED8: 0.01062 | EE8: 0.01085
A9: 1 | B9: 0.001 | C9: 98.776 | D9: =SUMPRODUCT(L9:CK9,$L$249:$CK$249) -> 98.746553 | E9: =+D9-C9 -> -0.029447039 | F9: =ABS(C9-D9) -> 0.029447039 | G9: =+IFERROR(IRR(K9:CK9,0),0) -> 0.0071860466 | H9: =IFERROR(IRR((J9,L9:CK9),0),0) -> 0.0073362866 | I9: =IFERROR(H9-G9,0) -> 0.00015023993 | J9: =-D9 -> -98.746553 | K9: =-C9 -> -98.776 | L9: =$B9*100*(L$2<$A9)+100*(1+$B9)*(L$2=$A9) -> 0.1 | M9: =$B9*100*(M$2<$A9)+100*(1+$B9)*(M$2=$A9) -> 100.1 | N9: =$B9*100*(N$2<$A9)+100*(1+$B9)*(N$2=$A9) -> 0 | O9: =$B9*100*(O$2<$A9)+100*(1+$B9)*(O$2=$A9) -> 0 | P9: =$B9*100*(P$2<$A9)+100*(1+$B9)*(P$2=$A9) -> 0 | Q9: =$B9*100*(Q$2<$A9)+100*(1+$B9)*(Q$2=$A9) -> 0 | R9: =$B9*100*(R$2<$A9)+100*(1+$B9)*(R$2=$A9) -> 0 | S9: =$B9*100*(S$2<$A9)+100*(1+$B9)*(S$2=$A9) -> 0 | ... CK9: =$B9*100*(CK$2<$A9)+100*(1+$B9)*(CK$2=$A9) -> 0 | CN9: 3 | CO9: 0.05 | CP9: -0.029287325 | CQ9: -0.010239647 | CR9: 0.00077110825 | CS9: =SUM(CO9:CR9) -> 0.011244136 | EC9: 0.010725 | ED9: 0.0106 | EE9: 0.01085
A10: 1 | B10: 5e-05 | C10: 98.6575 | D10: =SUMPRODUCT(L10:CK10,$L$249:$CK$249) -> 98.558661 | E10: =+D10-C10 -> -0.098839205 | F10: =ABS(C10-D10) -> 0.098839205 | G10: =+IFERROR(IRR(K10:CK10,0),0) -> 0.0068313613 | H10: =IFERROR(IRR((J10,L10:CK10),0),0) -> 0.0073360962 | I10: =IFERROR(H10-G10,0) -> 0.00050473484 | J10: =-D10 -> -98.558661 | K10: =-C10 -> -98.6575 | L10: =$B10*100*(L$2<$A10)+100*(1+$B10)*(L$2=$A10) -> 0.005 | M10: =$B10*100*(M$2<$A10)+100*(1+$B10)*(M$2=$A10) -> 100.005 | N10: =$B10*100*(N$2<$A10)+100*(1+$B10)*(N$2=$A10) -> 0 | O10: =$B10*100*(O$2<$A10)+100*(1+$B10)*(O$2=$A10) -> 0 | P10: =$B10*100*(P$2<$A10)+100*(1+$B10)*(P$2=$A10) -> 0 | Q10: =$B10*100*(Q$2<$A10)+100*(1+$B10)*(Q$2=$A10) -> 0 | R10: =$B10*100*(R$2<$A10)+100*(1+$B10)*(R$2=$A10) -> 0 | S10: =$B10*100*(S$2<$A10)+100*(1+$B10)*(S$2=$A10) -> 0 | ... CK10: =$B10*100*(CK$2<$A10)+100*(1+$B10)*(CK$2=$A10) -> 0 | CN10: 3.5 | CO10: 0.05 | CP10: -0.027836603 | CQ10: -0.011113212 | CR10: 0.00068469113 | CS10: =SUM(CO10:CR10) -> 0.011734876 | EC10: 0.011495 | ED10: 0.01138 | EE10: 0.01161
A11: 1 | B11: 0.001 | C11: 98.426 | D11: =SUMPRODUCT(L11:CK11,$L$249:$CK$249) -> 98.746553 | E11: =+D11-C11 -> 0.32055296 | F11: =ABS(C11-D11) -> 0.32055296 | G11: =+IFERROR(IRR(K11:CK11,0),0) -> 0.0089761209 | H11: =IFERROR(IRR((J11,L11:CK11),0),0) -> 0.0073362866 | I11: =IFERROR(H11-G11,0) -> -0.0016398344 | J11: =-D11 -> -98.746553 | K11: =-C11 -> -98.426 | L11: =$B11*100*(L$2<$A11)+100*(1+$B11)*(L$2=$A11) -> 0.1 | M11: =$B11*100*(M$2<$A11)+100*(1+$B11)*(M$2=$A11) -> 100.1 | N11: =$B11*100*(N$2<$A11)+100*(1+$B11)*(N$2=$A11) -> 0 | O11: =$B11*100*(O$2<$A11)+100*(1+$B11)*(O$2=$A11) -> 0 | P11: =$B11*100*(P$2<$A11)+100*(1+$B11)*(P$2=$A11) -> 0 | Q11: =$B11*100*(Q$2<$A11)+100*(1+$B11)*(Q$2=$A11) -> 0 | R11: =$B11*100*(R$2<$A11)+100*(1+$B11)*(R$2=$A11) -> 0 | S11: =$B11*100*(S$2<$A11)+100*(1+$B11)*(S$2=$A11) -> 0 | ... CK11: =$B11*100*(CK$2<$A11)+100*(1+$B11)*(CK$2=$A11) -> 0 | CN11: 4 | CO11: 0.05 | CP11: -0.026486498 | CQ11: -0.011824834 | CR11: 0.00061094067 | CS11: =SUM(CO11:CR11) -> 0.012299608 | EC11: 0.011555 | ED11: 0.01144 | EE11: 0.01167
A12: 1 | B12: 0.001 | C12: 98.417 | D12: =SUMPRODUCT(L12:CK12,$L$249:$CK$249) -> 98.746553 | E12: =+D12-C12 -> 0.32955296 | F12: =ABS(C12-D12) -> 0.32955296 | G12: =+IFERROR(IRR(K12:CK12,0),0) -> 0.0090222773 | H12: =IFERROR(IRR((J12,L12:CK12),0),0) -> 0.0073362866 | I12: =IFERROR(H12-G12,0) -> -0.0016859908 | J12: =-D12 -> -98.746553 | K12: =-C12 -> -98.417 | L12: =$B12*100*(L$2<$A12)+100*(1+$B12)*(L$2=$A12) -> 0.1 | M12: =$B12*100*(M$2<$A12)+100*(1+$B12)*(M$2=$A12) -> 100.1 | N12: =$B12*100*(N$2<$A12)+100*(1+$B12)*(N$2=$A12) -> 0 | O12: =$B12*100*(O$2<$A12)+100*(1+$B12)*(O$2=$A12) -> 0 | P12: =$B12*100*(P$2<$A12)+100*(1+$B12)*(P$2=$A12) -> 0 | Q12: =$B12*100*(Q$2<$A12)+100*(1+$B12)*(Q$2=$A12) -> 0 | R12: =$B12*100*(R$2<$A12)+100*(1+$B12)*(R$2=$A12) -> 0 | S12: =$B12*100*(S$2<$A12)+100*(1+$B12)*(S$2=$A12) -> 0 | ... CK12: =$B12*100*(CK$2<$A12)+100*(1+$B12)*(CK$2=$A12) -> 0 | CN12: 4.5 | CO12: 0.05 | CP12: -0.025228998 | CQ12: -0.012395678 | CR12: 0.00054894447 | CS12: =SUM(CO12:CR12) -> 0.012924269 | EC12: 0.0119 | ED12: 0.01178 | EE12: 0.01202
A13: 1.5 | B13: 0.001 | C13: 98.1045 | D13: =SUMPRODUCT(L13:CK13,$L$249:$CK$249) -> 98.104478 | E13: =+D13-C13 -> -2.2018722e-05 | F13: =ABS(C13-D13) -> 2.2018722e-05 | G13: =+IFERROR(IRR(K13:CK13,0),0) -> 0.0074122298 | H13: =IFERROR(IRR((J13,L13:CK13),0),0) -> 0.0074123052 | I13: =IFERROR(H13-G13,0) -> 7.5444533e-08 | J13: =-D13 -> -98.104478 | K13: =-C13 -> -98.1045 | L13: =$B13*100*(L$2<$A13)+100*(1+$B13)*(L$2=$A13) -> 0.1 | M13: =$B13*100*(M$2<$A13)+100*(1+$B13)*(M$2=$A13) -> 0.1 | N13: =$B13*100*(N$2<$A13)+100*(1+$B13)*(N$2=$A13) -> 100.1 | O13: =$B13*100*(O$2<$A13)+100*(1+$B13)*(O$2=$A13) -> 0 | P13: =$B13*100*(P$2<$A13)+100*(1+$B13)*(P$2=$A13) -> 0 | Q13: =$B13*100*(Q$2<$A13)+100*(1+$B13)*(Q$2=$A13) -> 0 | R13: =$B13*100*(R$2<$A13)+100*(1+$B13)*(R$2=$A13) -> 0 | S13: =$B13*100*(S$2<$A13)+100*(1+$B13)*(S$2=$A13) -> 0 | ... CK13: =$B13*100*(CK$2<$A13)+100*(1+$B13)*(CK$2=$A13) -> 0 | CN13: 5 | CO13: 0.05 | CP13: -0.024056777 | CQ13: -0.012844372 | CR13: 0.00049697223 | CS13: =SUM(CO13:CR13) -> 0.013595823 | EC13: 0.011915 | ED13: 0.01179 | EE13: 0.01204
A14: 1.5 | B14: 0.002 | C14: 98.2755 | D14: =SUMPRODUCT(L14:CK14,$L$249:$CK$249) -> 98.400068 | E14: =+D14-C14 -> 0.1245681 | F14: =ABS(C14-D14) -> 0.1245681 | G14: =+IFERROR(IRR(K14:CK14,0),0) -> 0.0078386867 | H14: =IFERROR(IRR((J14,L14:CK14),0),0) -> 0.0074123628 | I14: =IFERROR(H14-G14,0) -> -0.00042632385 | J14: =-D14 -> -98.400068 | K14: =-C14 -> -98.2755 | L14: =$B14*100*(L$2<$A14)+100*(1+$B14)*(L$2=$A14) -> 0.2 | M14: =$B14*100*(M$2<$A14)+100*(1+$B14)*(M$2=$A14) -> 0.2 | N14: =$B14*100*(N$2<$A14)+100*(1+$B14)*(N$2=$A14) -> 100.2 | O14: =$B14*100*(O$2<$A14)+100*(1+$B14)*(O$2=$A14) -> 0 | P14: =$B14*100*(P$2<$A14)+100*(1+$B14)*(P$2=$A14) -> 0 | Q14: =$B14*100*(Q$2<$A14)+100*(1+$B14)*(Q$2=$A14) -> 0 | R14: =$B14*100*(R$2<$A14)+100*(1+$B14)*(R$2=$A14) -> 0 | S14: =$B14*100*(S$2<$A14)+100*(1+$B14)*(S$2=$A14) -> 0 | ... CK14: =$B14*100*(CK$2<$A14)+100*(1+$B14)*(CK$2=$A14) -> 0 | CN14: 5.5 | CO14: 0.05 | CP14: -0.022963135 | CQ14: -0.013187305 | CR14: 0.0004532419 | CS14: =SUM(CO14:CR14) -> 0.014302802 | EC14: 0.01194 | ED14: 0.01182 | EE14: 0.01206
A15: 1.5 | B15: 0.003 | C15: 98.4455 | D15: =SUMPRODUCT(L15:CK15,$L$249:$CK$249) -> 98.695658 | E15: =+D15-C15 -> 0.25015821 | F15: =ABS(C15-D15) -> 0.25015821 | G15: =+IFERROR(IRR(K15:CK15,0),0) -> 0.0082675815 | H15: =IFERROR(IRR((J15,L15:CK15),0),0) -> 0.0074124202 | I15: =IFERROR(H15-G15,0) -> -0.00085516136 | J15: =-D15 -> -98.695658 | K15: =-C15 -> -98.4455 | L15: =$B15*100*(L$2<$A15)+100*(1+$B15)*(L$2=$A15) -> 0.3 | M15: =$B15*100*(M$2<$A15)+100*(1+$B15)*(M$2=$A15) -> 0.3 | N15: =$B15*100*(N$2<$A15)+100*(1+$B15)*(N$2=$A15) -> 100.3 | O15: =$B15*100*(O$2<$A15)+100*(1+$B15)*(O$2=$A15) -> 0 | P15: =$B15*100*(P$2<$A15)+100*(1+$B15)*(P$2=$A15) -> 0 | Q15: =$B15*100*(Q$2<$A15)+100*(1+$B15)*(Q$2=$A15) -> 0 | R15: =$B15*100*(R$2<$A15)+100*(1+$B15)*(R$2=$A15) -> 0 | S15: =$B15*100*(S$2<$A15)+100*(1+$B15)*(S$2=$A15) -> 0 | ... CK15: =$B15*100*(CK$2<$A15)+100*(1+$B15)*(CK$2=$A15) -> 0 | CN15: 6 | CO15: 0.05 | CP15: -0.021941943 | CQ15: -0.01343888 | CR15: 0.00041618955 | CS15: =SUM(CO15:CR15) -> 0.015035366 | EC15: 0.012245 | ED15: 0.01213 | EE15: 0.01236
A16: 1.5 | B16: 0.001 | C16: 97.781 | D16: =SUMPRODUCT(L16:CK16,$L$249:$CK$249) -> 98.104478 | E16: =+D16-C16 -> 0.32347798 | F16: =ABS(C16-D16) -> 0.32347798 | G16: =+IFERROR(IRR(K16:CK16,0),0) -> 0.0085231085 | H16: =IFERROR(IRR((J16,L16:CK16),0),0) -> 0.0074123052 | I16: =IFERROR(H16-G16,0) -> -0.0011108033 | J16: =-D16 -> -98.104478 | K16: =-C16 -> -97.781 | L16: =$B16*100*(L$2<$A16)+100*(1+$B16)*(L$2=$A16) -> 0.1 | M16: =$B16*100*(M$2<$A16)+100*(1+$B16)*(M$2=$A16) -> 0.1 | N16: =$B16*100*(N$2<$A16)+100*(1+$B16)*(N$2=$A16) -> 100.1 | O16: =$B16*100*(O$2<$A16)+100*(1+$B16)*(O$2=$A16) -> 0 | P16: =$B16*100*(P$2<$A16)+100*(1+$B16)*(P$2=$A16) -> 0 | Q16: =$B16*100*(Q$2<$A16)+100*(1+$B16)*(Q$2=$A16) -> 0 | R16: =$B16*100*(R$2<$A16)+100*(1+$B16)*(R$2=$A16) -> 0 | S16: =$B16*100*(S$2<$A16)+100*(1+$B16)*(S$2=$A16) -> 0 | ... CK16: =$B16*100*(CK$2<$A16)+100*(1+$B16)*(CK$2=$A16) -> 0 | CN16: 6.5 | CO16: 0.05 | CP16: -0.020987591 | CQ16: -0.013611751 | CR16: 0.00038453032 | CS16: =SUM(CO16:CR16) -> 0.015785188 | EC16: 0.01227 | ED16: 0.01215 | EE16: 0.01239
... A63: 23.5 | B63: 0.004 | C63: 52.1985 | D63: =SUMPRODUCT(L63:CK63,$L$249:$CK$249) -> 53.092735 | E63: =+D63-C63 -> 0.89423534 | F63: =ABS(C63-D63) -> 0.89423534 | G63: =+IFERROR(IRR(K63:CK63,0),0) -> 0.019683184 | H63: =IFERROR(IRR((J63,L63:CK63),0),0) -> 0.019259125 | I63: =IFERROR(H63-G63,0) -> -0.00042405953 | J63: =-D63 -> -53.092735 | K63: =-C63 -> -52.1985 | L63: =$B63*100*(L$2<$A63)+100*(1+$B63)*(L$2=$A63) -> 0.4 | M63: =$B63*100*(M$2<$A63)+100*(1+$B63)*(M$2=$A63) -> 0.4 | N63: =$B63*100*(N$2<$A63)+100*(1+$B63)*(N$2=$A63) -> 0.4 | O63: =$B63*100*(O$2<$A63)+100*(1+$B63)*(O$2=$A63) -> 0.4 | P63: =$B63*100*(P$2<$A63)+100*(1+$B63)*(P$2=$A63) -> 0.4 | Q63: =$B63*100*(Q$2<$A63)+100*(1+$B63)*(Q$2=$A63) -> 0.4 | R63: =$B63*100*(R$2<$A63)+100*(1+$B63)*(R$2=$A63) -> 0.4 | S63: =$B63*100*(S$2<$A63)+100*(1+$B63)*(S$2=$A63) -> 0.4 | ... CK63: =$B63*100*(CK$2<$A63)+100*(1+$B63)*(CK$2=$A63) -> 0 | CN63: 30 | CO63: 0.05 | CP63: -0.0058331641 | CQ63: -0.0065758331 | CR63: 8.340171e-05 | CS63: =SUM(CO63:CR63) -> 0.037674404 | EC63: 0.051825 | ED63: 0.05153 | EE63: 0.05212
A64: 29.5 | B64: 0.004 | C64: 43.824 | D64: =SUMPRODUCT(L64:CK64,$L$249:$CK$249) -> 43.772111 | E64: =+D64-C64 -> -0.05188922 | F64: =ABS(C64-D64) -> 0.05188922 | G64: =+IFERROR(IRR(K64:CK64,0),0) -> 0.020498522 | H64: =IFERROR(IRR((J64,L64:CK64),0),0) -> 0.020523608 | I64: =IFERROR(H64-G64,0) -> 2.5085535e-05 | J64: =-D64 -> -43.772111 | K64: =-C64 -> -43.824 | L64: =$B64*100*(L$2<$A64)+100*(1+$B64)*(L$2=$A64) -> 0.4 | M64: =$B64*100*(M$2<$A64)+100*(1+$B64)*(M$2=$A64) -> 0.4 | N64: =$B64*100*(N$2<$A64)+100*(1+$B64)*(N$2=$A64) -> 0.4 | O64: =$B64*100*(O$2<$A64)+100*(1+$B64)*(O$2=$A64) -> 0.4 | P64: =$B64*100*(P$2<$A64)+100*(1+$B64)*(P$2=$A64) -> 0.4 | Q64: =$B64*100*(Q$2<$A64)+100*(1+$B64)*(Q$2=$A64) -> 0.4 | R64: =$B64*100*(R$2<$A64)+100*(1+$B64)*(R$2=$A64) -> 0.4 | S64: =$B64*100*(S$2<$A64)+100*(1+$B64)*(S$2=$A64) -> 0.4 | ... CK64: =$B64*100*(CK$2<$A64)+100*(1+$B64)*(CK$2=$A64) -> 0 | CN64: 30.5 | CO64: 0.05 | CP64: -0.0057381335 | CQ64: -0.0064727736 | CR64: 8.2034469e-05 | CS64: =SUM(CO64:CR64) -> 0.037871127
D65: =SUMPRODUCT(L65:CK65,$L$249:$CK$249) -> 0 | E65: =+D65-C65 -> 0 | F65: =ABS(C65-D65) -> 0 | G65: =+IFERROR(IRR(K65:CK65,0),0) -> 0 | H65: =IFERROR(IRR((J65,L65:CK65),0),0) -> 0 | I65: =IFERROR(H65-G65,0) -> 0 | J65: =-D65 -> 0 | K65: =-C65 -> 0 | L65: =$B65*100*(L$2<$A65)+100*(1+$B65)*(L$2=$A65) -> 0 | M65: =$B65*100*(M$2<$A65)+100*(1+$B65)*(M$2=$A65) -> 0 | N65: =$B65*100*(N$2<$A65)+100*(1+$B65)*(N$2=$A65) -> 0 | O65: =$B65*100*(O$2<$A65)+100*(1+$B65)*(O$2=$A65) -> 0 | P65: =$B65*100*(P$2<$A65)+100*(1+$B65)*(P$2=$A65) -> 0 | Q65: =$B65*100*(Q$2<$A65)+100*(1+$B65)*(Q$2=$A65) -> 0 | R65: =$B65*100*(R$2<$A65)+100*(1+$B65)*(R$2=$A65) -> 0 | S65: =$B65*100*(S$2<$A65)+100*(1+$B65)*(S$2=$A65) -> 0 | ... CK65: =$B65*100*(CK$2<$A65)+100*(1+$B65)*(CK$2=$A65) -> 0 | CN65: 31 | CO65: 0.05 | CP65: -0.0056461043 | CQ65: -0.006372596 | CR65: 8.0711332e-05 | CS65: =SUM(CO65:CR65) -> 0.038062011
D66: =SUMPRODUCT(L66:CK66,$L$249:$CK$249) -> 0 | E66: =+D66-C66 -> 0 | F66: =ABS(C66-D66) -> 0 | G66: =+IFERROR(IRR(K66:CK66,0),0) -> 0 | H66: =IFERROR(IRR((J66,L66:CK66),0),0) -> 0 | I66: =IFERROR(H66-G66,0) -> 0 | J66: =-D66 -> 0 | K66: =-C66 -> 0 | L66: =$B66*100*(L$2<$A66)+100*(1+$B66)*(L$2=$A66) -> 0 | M66: =$B66*100*(M$2<$A66)+100*(1+$B66)*(M$2=$A66) -> 0 | N66: =$B66*100*(N$2<$A66)+100*(1+$B66)*(N$2=$A66) -> 0 | O66: =$B66*100*(O$2<$A66)+100*(1+$B66)*(O$2=$A66) -> 0 | P66: =$B66*100*(P$2<$A66)+100*(1+$B66)*(P$2=$A66) -> 0 | Q66: =$B66*100*(Q$2<$A66)+100*(1+$B66)*(Q$2=$A66) -> 0 | R66: =$B66*100*(R$2<$A66)+100*(1+$B66)*(R$2=$A66) -> 0 | S66: =$B66*100*(S$2<$A66)+100*(1+$B66)*(S$2=$A66) -> 0 | ... CK66: =$B66*100*(CK$2<$A66)+100*(1+$B66)*(CK$2=$A66) -> 0 | CN66: 31.5 | CO66: 0.05 | CP66: -0.0055569404 | CQ66: -0.0062752036 | CR66: 7.94302e-05 | CS66: =SUM(CO66:CR66) -> 0.038247286
CN67: 32 | CO67: 0.05 | CP67: -0.0054705137 | CQ67: -0.0061805018 | CR67: 7.8189103e-05 | CS67: =SUM(CO67:CR67) -> 0.038427174
CN68: 32.5 | CO68: 0.05 | CP68: -0.005386703 | CQ68: -0.0060883989 | CR68: 7.6986194e-05 | CS68: =SUM(CO68:CR68) -> 0.038601884
CN69: 33 | CO69: 0.05 | CP69: -0.0053053941 | CQ69: -0.0059988058 | CR69: 7.5819736e-05 | CS69: =SUM(CO69:CR69) -> 0.03877162
CN70: 33.5 | CO70: 0.05 | CP70: -0.0052264791 | CQ70: -0.005911636 | CR70: 7.4688098e-05 | CS70: =SUM(CO70:CR70) -> 0.038936573
CN71: 34 | CO71: 0.05 | CP71: -0.005149856 | CQ71: -0.005826806 | CR71: 7.3589744e-05 | CS71: =SUM(CO71:CR71) -> 0.039096928
CN72: 34.5 | CO72: 0.05 | CP72: -0.0050754283 | CQ72: -0.0057442347 | CR72: 7.2523226e-05 | CS72: =SUM(CO72:CR72) -> 0.03925286
CN73: 35 | CO73: 0.05 | CP73: -0.0050031047 | CQ73: -0.0056638441 | CR73: 7.148718e-05 | CS73: =SUM(CO73:CR73) -> 0.039404538
CN74: 35.5 | CO74: 0.05 | CP74: -0.0049327986 | CQ74: -0.0055855588 | CR74: 7.0480318e-05 | CS74: =SUM(CO74:CR74) -> 0.039552123
CN75: 36 | CO75: 0.05 | CP75: -0.0048644281 | CQ75: -0.0055093058 | CR75: 6.9501425e-05 | CS75: =SUM(CO75:CR75) -> 0.039695767
CN76: 36.5 | CO76: 0.05 | CP76: -0.0047979156 | CQ76: -0.0054350151 | CR76: 6.8549351e-05 | CS76: =SUM(CO76:CR76) -> 0.039835619
CN77: 37 | CO77: 0.05 | CP77: -0.0047331874 | CQ77: -0.0053626191 | CR77: 6.7623008e-05 | CS77: =SUM(CO77:CR77) -> 0.039971816
CN78: 37.5 | CO78: 0.05 | CP78: -0.0046701736 | CQ78: -0.0052920527 | CR78: 6.6721368e-05 | CS78: =SUM(CO78:CR78) -> 0.040104495
... CN241: 119 | CO241: 0.05 | CP241: -0.0014719374 | CQ241: -0.0016703516 | CR241: 2.1025641e-05 | CS241: =SUM(CO241:CR241) -> 0.046878737
E242: =_xlfn.CONCAT("Value = c(",ROUND(C248,5),",",ROUND(C249,5),",",ROUND(C250,5),",",ROUND(C251,5),",",ROUND(C252,5),",",ROUND(C253,5),"),") -> Value = c(0.0556,-0.04066,-0.04614,0.00354,4.30806,0.70736), | CN242: 119.5 | CO242: 0.05 | CP242: -0.0014657787 | CQ242: -0.0016633627 | CR242: 2.0937668e-05 | CS242: =SUM(CO242:CR242) -> 0.046891796
E243: =_xlfn.CONCAT("Value = c(""",ROUND(E249,2),""",""",ROUND(E255,0),""",""",ROUND(E251,2),""",""",ROUND(E253,0),"""),") -> Value = c("0.44","709","0.58","966"), | CN243: 120 | CO243: 0.05 | CP243: -0.0014596713 | CQ243: -0.001656432 | CR243: 2.0850427e-05 | CS243: =SUM(CO243:CR243) -> 0.046904747
CN244: 120.5 | CO244: 0.05 | CP244: -0.0014536146 | CQ244: -0.0016495589 | CR244: 2.0763911e-05 | CS244: =SUM(CO244:CR244) -> 0.04691759
CN245: 121 | CO245: 0.05 | CP245: -0.0014476079 | CQ245: -0.0016427425 | CR245: 2.067811e-05 | CS245: =SUM(CO245:CR245) -> 0.046930328
CN246: 121.5 | CO246: 0.05 | CP246: -0.0014416507 | CQ246: -0.0016359822 | CR246: 2.0593015e-05 | CS246: =SUM(CO246:CR246) -> 0.04694296
B247: INITIAL VALUES | C247: SOLVER VALUES | D247: INITIAL RESULTS | E247: SOLVER RESULTS | CN247: 122 | CO247: 0.05 | CP247: -0.0014357423 | CQ247: -0.0016292774 | CR247: 2.0508617e-05 | CS247: =SUM(CO247:CR247) -> 0.046955489
A248: b0 | B248: 0.05 | C248: 0.055604949 | D248: Mean abs error | E248: MAE (Price) | I248: r(t) | J248: FITTED | K248: Spot | L248: =+b0+b1_*((1-EXP(-L2/tau1_))*tau1_/L2)+b2_*((1-EXP(-L2/tau1_))*tau1_/L2-EXP(-L2/tau1_))+b3_*((1-EXP(-L2/tau2_))*tau2_/L2-EXP(-L2/tau2_)) -> 0.015529447 | M248: =+b0+b1_*((1-EXP(-M2/tau1_))*tau1_/M2)+b2_*((1-EXP(-M2/tau1_))*tau1_/M2-EXP(-M2/tau1_)) -> 0.01472599 | N248: =+b0+b1_*((1-EXP(-N2/tau1_))*tau1_/N2)+b2_*((1-EXP(-N2/tau1_))*tau1_/N2-EXP(-N2/tau1_)) -> 0.014879436 | O248: =+b0+b1_*((1-EXP(-O2/tau1_))*tau1_/O2)+b2_*((1-EXP(-O2/tau1_))*tau1_/O2-EXP(-O2/tau1_)) -> 0.015171088 | P248: =+b0+b1_*((1-EXP(-P2/tau1_))*tau1_/P2)+b2_*((1-EXP(-P2/tau1_))*tau1_/P2-EXP(-P2/tau1_)) -> 0.015577405 | Q248: =+b0+b1_*((1-EXP(-Q2/tau1_))*tau1_/Q2)+b2_*((1-EXP(-Q2/tau1_))*tau1_/Q2-EXP(-Q2/tau1_)) -> 0.016077977 | R248: =+b0+b1_*((1-EXP(-R2/tau1_))*tau1_/R2)+b2_*((1-EXP(-R2/tau1_))*tau1_/R2-EXP(-R2/tau1_)) -> 0.016655134 | S248: =+b0+b1_*((1-EXP(-S2/tau1_))*tau1_/S2)+b2_*((1-EXP(-S2/tau1_))*tau1_/S2-EXP(-S2/tau1_)) -> 0.017293616 | T248: =+b0+b1_*((1-EXP(-T2/tau1_))*tau1_/T2)+b2_*((1-EXP(-T2/tau1_))*tau1_/T2-EXP(-T2/tau1_)) -> 0.017980273 | ... CK248: =+b0+b1_*((1-EXP(-CK2/tau1_))*tau1_/CK2)+b2_*((1-EXP(-CK2/tau1_))*tau1_/CK2-EXP(-CK2/tau1_)) -> 0.046023462 | CN248: 122.5 | CO248: 0.05 | CP248: -0.0014298821 | CQ248: -0.0016226273 | CR248: 2.0424909e-05 | CS248: =SUM(CO248:CR248) -> 0.046967916
A249: b1 | B249: -0.04 | C249: -0.040658782 | D249: 6.6983366 | E249: =AVERAGE(F3:F231) -> 0.43541404 | I249: d(t) | J249: Discount factor | L249: =+(1+L248)^(-L2) -> 0.99232456 | M249: =+(1+M248)^(-M2) -> 0.98548772 | N249: =+(1+N248)^(-N2) -> 0.97808888 | O249: =+(1+O248)^(-O2) -> 0.9703346 | P249: =+(1+P248)^(-P2) -> 0.96209382 | Q249: =+(1+Q248)^(-Q2) -> 0.9532765 | R249: =+(1+R248)^(-R2) -> 0.94382656 | S249: =+(1+S248)^(-S2) -> 0.93371583 | ... CK249: =+(1+CK248)^(-CK2) -> 0.1729356 | CN249: 123 | CO249: 0.05 | CP249: -0.0014240696 | CQ249: -0.0016160312 | CR249: 2.034188e-05 | CS249: =SUM(CO249:CR249) -> 0.046980241
A250: b2 | B250: 0.05 | C250: -0.046139503 | D250: RMSE (Price) | E250: RMSE (Price) | I250: f(t) | J250: Forward | N250: =L249/N249-1 -> 0.014554587 | O250: =M249/O249-1 -> 0.01561638 | P250: =N249/P249-1 -> 0.016625259 | Q250: =O249/Q249-1 -> 0.017894186 | R250: =P249/R249-1 -> 0.019354461 | S250: =Q249/S249-1 -> 0.020949268 | T250: =R249/T249-1 -> 0.022631875 | U250: =S249/U249-1 -> 0.024364109 | ... CK250: =CI249/CK249-1 -> 0.055589908 | CN250: 123.5 | CO250: 0.05 | CP250: -0.0014183041 | CQ250: -0.0016094886 | CR250: 2.0259525e-05 | CS250: =SUM(CO250:CR250) -> 0.046992467
A251: b3 | B251: -0.05 | C251: 0.0035371483 | D251: 8.3914837 | E251: =SQRT(SUMSQ(E3:E231)/COUNT(E3:E231)) -> 0.58249182 | J251: Forward credit spread | N251: =[2]NSS!N250-N250 -> 0.0038507626 | O251: =[2]NSS!O250-O250 -> 0.0050934519 | P251: =[2]NSS!P250-P250 -> 0.0058554488 | Q251: =[2]NSS!Q250-Q250 -> 0.006272059 | R251: =[2]NSS!R250-R250 -> 0.0064152642 | S251: =[2]NSS!S250-S250 -> 0.0063450579 | T251: =[2]NSS!T250-T250 -> 0.0061112423 | U251: =[2]NSS!U250-U250 -> 0.0057549624 | ... CK251: =[2]NSS!CK250-CK250 -> -0.0082685261 | CN251: 124 | CO251: 0.05 | CP251: -0.0014125851 | CQ251: -0.0016029987 | CR251: 2.0177833e-05 | CS251: =SUM(CO251:CR251) -> 0.047004594
A252: t1 | B252: 5 | C252: 4.3080621 | D252: RMSE (Yield) | E252: RMSE (Yield) | J252: full forward formula | N252: =(((1+N248)^N2)/((1+L248)^L2))^(1/(N2-L2))-1 -> 0.014554587 | O252: =(((1+O248)^O2)/((1+M248)^M2))^(1/(O2-M2))-1 -> 0.01561638 | P252: =(((1+P248)^P2)/((1+N248)^N2))^(1/(P2-N2))-1 -> 0.016625259 | Q252: =(((1+Q248)^Q2)/((1+O248)^O2))^(1/(Q2-O2))-1 -> 0.017894186 | R252: =(((1+R248)^R2)/((1+P248)^P2))^(1/(R2-P2))-1 -> 0.019354461 | S252: =(((1+S248)^S2)/((1+Q248)^Q2))^(1/(S2-Q2))-1 -> 0.020949268 | T252: =(((1+T248)^T2)/((1+R248)^R2))^(1/(T2-R2))-1 -> 0.022631875 | U252: =(((1+U248)^U2)/((1+S248)^S2))^(1/(U2-S2))-1 -> 0.024364109 | ... CK252: =(((1+CK248)^CK2)/((1+CI248)^CI2))^(1/(CK2-CI2))-1 -> 0.055589908 | CN252: 124.5 | CO252: 0.05 | CP252: -0.0014069121 | CQ252: -0.001596561 | CR252: 2.0096798e-05 | CS252: =SUM(CO252:CR252) -> 0.047016624
A253: t2 | B253: 10 | C253: 0.70736397 | D253: 6334.9423 | E253: =SQRT(SUMSQ(I3:I236)/COUNT(I3:I236))*1000000 -> 965.577 | CN253: 125 | CO253: 0.05 | CP253: -0.0014012844 | CQ253: -0.0015901747 | CR253: 2.001641e-05 | CS253: =SUM(CO253:CR253) -> 0.047028557
E254: MAE (Yield) | CN254: 125.5 | CO254: 0.05 | CP254: -0.0013957016 | CQ254: -0.0015838394 | CR254: 1.9936664e-05 | CS254: =SUM(CO254:CR254) -> 0.047040396
E255: {=AVERAGE(ABS(G3:G66-H3:H66))*1000000} -> 709.05419 | CN255: 126 | CO255: 0.05 | CP255: -0.0013901631 | CQ255: -0.0015775543 | CR255: 1.985755e-05 | CS255: =SUM(CO255:CR255) -> 0.04705214
CN256: 126.5 | CO256: 0.05 | CP256: -0.0013846684 | CQ256: -0.0015713189 | CR256: 1.9779062e-05 | CS256: =SUM(CO256:CR256) -> 0.047063792
CN257: 127 | CO257: 0.05 | CP257: -0.001379217 | CQ257: -0.0015651326 | CR257: 1.9701191e-05 | CS257: =SUM(CO257:CR257) -> 0.047075352
CN258: 127.5 | CO258: 0.05 | CP258: -0.0013738083 | CQ258: -0.0015589948 | CR258: 1.9623932e-05 | CS258: =SUM(CO258:CR258) -> 0.047086821
CN259: 128 | CO259: 0.05 | CP259: -0.0013684418 | CQ259: -0.001552905 | CR259: 1.9547276e-05 | CS259: =SUM(CO259:CR259) -> 0.0470982
CN260: 128.5 | CO260: 0.05 | CP260: -0.0013631172 | CQ260: -0.0015468626 | CR260: 1.9471216e-05 | CS260: =SUM(CO260:CR260) -> 0.047109491
CN261: 129 | CO261: 0.05 | CP261: -0.0013578338 | CQ261: -0.001540867 | CR261: 1.9395746e-05 | CS261: =SUM(CO261:CR261) -> 0.047120695
CN262: 129.5 | CO262: 0.05 | CP262: -0.0013525912 | CQ262: -0.0015349177 | CR262: 1.9320859e-05 | CS262: =SUM(CO262:CR262) -> 0.047131812
CN263: 130 | CO263: 0.05 | CP263: -0.0013473889 | CQ263: -0.0015290142 | CR263: 1.9246548e-05 | CS263: =SUM(CO263:CR263) -> 0.047142843
CN264: 130.5 | CO264: 0.05 | CP264: -0.0013422265 | CQ264: -0.0015231559 | CR264: 1.9172807e-05 | CS264: =SUM(CO264:CR264) -> 0.04715379
CN265: 131 | CO265: 0.05 | CP265: -0.0013371035 | CQ265: -0.0015173423 | CR265: 1.9099628e-05 | CS265: =SUM(CO265:CR265) -> 0.047164654
CN266: 131.5 | CO266: 0.05 | CP266: -0.0013320194 | CQ266: -0.0015115729 | CR266: 1.9027006e-05 | CS266: =SUM(CO266:CR266) -> 0.047175435
CN267: 132 | CO267: 0.05 | CP267: -0.0013269739 | CQ267: -0.0015058473 | CR267: 1.8954934e-05 | CS267: =SUM(CO267:CR267) -> 0.047186134
... CN503: 250 | CO503: 0.05 | CP503: -0.00070064222 | CQ503: -0.00079508737 | CR503: 1.0008205e-05 | CS503: =SUM(CO503:CR503) -> 0.048514279

Sheet MANUAL FILTER
A1: min | B1: 9.5 | G1: {=_xlfn.ANCHORARRAY(SORT!A1)} -> Instrument | H1: Name | I1: Ticker | J1: Country/Region | K1: Currency | L1: Maturity | M1: Coupon Type | N1: Coupon Frequency | O1: Coupon | P1: Ask Yield to Maturity | Q1: Bid Yield to Maturity | R1: Ask Price | S1: Bid Price | T1: Identifier | U1: ISIN | V1: Bloomberg Composite Rating | W1: Announce | X1: Next Coupon Settle Date | Y1: Time | Z1: AVG price | AA1: id | AB1: TIMEish | AC1: years ago | AD1: Accrued Interest | AE1: Clean price | AF1: AVG yield
A2: max | B2: =B1+0.6 -> 10.1 | C2: {=(SORT!S2:S327>'MANUAL FILTER'!B1)} -> FALSE | D2: {=(SORT!S2:S327<'MANUAL FILTER'!B2)} -> TRUE | E2: =AND(C2:D2) -> FALSE | G2: {=_xlfn._xlws.FILTER(_xlfn.ANCHORARRAY(SORT!A2),E2:E327)} -> DC746693 Corp | H2: Japan Government Ten Year Bond | I2: JGB | J2: JP | K2: JPY | L2: 20/12/2035 | M2: FIXED | N2: 2 | O2: 2.1 | P2: 2.161 | Q2: 2.18 | R2: 99.507 | S2: 99.355 | T2: DC7466931 | U2: JP1103811S13 | V2: A+ | W2: 46017 | X2: 46193 | Y2: 9.724846 | Z2: 99.431 | AA2: 79 | AB2: 9.5 | AC2: 1 | AD2: 1.1538462 | AE2: 98.277154 | AF2: 2.1705
C3: FALSE | D3: TRUE | E3: =AND(C3:D3) -> FALSE | G3: EF250218 Corp | H3: Japan Government Thirty Year Bond | I3: JGB | J3: JP | K3: JPY | L3: 20/12/2035 | M3: FIXED | N3: 2 | O3: 2.3 | P3: 2.147 | Q3: 2.167 | R3: 101.236 | S3: 101.072 | T3: EF2502187 | U3: JP1300211610 | V3: A+ | W3: 38736 | X3: 46193 | Y3: 9.724846 | Z3: 101.154 | AA3: 102 | AB3: 9.5 | AC3: 20 | AD3: 1.2637363 | AE3: 99.890264 | AF3: 2.157
C4: FALSE | D4: TRUE | E4: =AND(C4:D4) -> FALSE | G4: JV336866 Corp | H4: Japan Government Twenty Year Bond | I4: JGB | J4: JP | K4: JPY | L4: 20/12/2035 | M4: FIXED | N4: 2 | O4: 1 | P4: 2.266 | Q4: 2.286 | R4: 89.868 | S4: 89.725 | T4: JV3368661 | U4: JP1201551FC0 | V4: A+ | W4: 42355 | X4: 46193 | Y4: 9.724846 | Z4: 89.7965 | AA4: 210 | AB4: 9.5 | AC4: 11 | AD4: 0.54945055 | AE4: 89.247049 | AF4: 2.276
C5: FALSE | D5: TRUE | E5: =AND(C5:D5) -> FALSE | G5: EF371144 Corp | H5: Japan Government Thirty Year Bond | I5: JGB | J5: JP | K5: JPY | L5: 20/03/2036 | M5: FIXED | N5: 2 | O5: 2.5 | P5: 2.153 | Q5: 2.177 | R5: 102.86 | S5: 102.657 | T5: EF3711449 | U5: JP1300221643 | V5: A+ | W5: 38825 | X5: 46101 | Y5: 9.9739904 | Z5: 102.7585 | AA5: 104 | AB5: 9.5 | AC5: 20 | AD5: 2.6236264 | AE5: 100.13487 | AF5: 2.165
C6: FALSE | D6: TRUE | E6: =AND(C6:D6) -> FALSE | G6: JK501604 Corp | H6: Japan Government Twenty Year Bond | I6: JGB | J6: JP | K6: JPY | L6: 20/03/2036 | M6: FIXED | N6: 2 | O6: 0.4 | P6: 2.374 | Q6: 2.398 | R6: 84.018 | S6: 83.856 | T6: JK5016049 | U6: JP1201561G37 | V6: A+ | W6: 42446 | X6: 46101 | Y6: 9.9739904 | Z6: 83.937 | AA6: 208 | AB6: 9.5 | AC6: 10 | AD6: 0.41978022 | AE6: 83.51722 | AF6: 2.386
C7: FALSE | D7: TRUE | E7: =AND(C7:D7) -> FALSE
C8: FALSE | D8: TRUE | E8: =AND(C8:D8) -> FALSE
C9: FALSE | D9: TRUE | E9: =AND(C9:D9) -> FALSE
C10: FALSE | D10: TRUE | E10: =AND(C10:D10) -> FALSE
C11: FALSE | D11: TRUE | E11: =AND(C11:D11) -> FALSE
C12: FALSE | D12: TRUE | E12: =AND(C12:D12) -> FALSE
C13: FALSE | D13: TRUE | E13: =AND(C13:D13) -> FALSE
C14: FALSE | D14: TRUE | E14: =AND(C14:D14) -> FALSE
C15: FALSE | D15: TRUE | E15: =AND(C15:D15) -> FALSE
C16: FALSE | D16: TRUE | E16: =AND(C16:D16) -> FALSE
C17: FALSE | D17: TRUE | E17: =AND(C17:D17) -> FALSE
C18: FALSE | D18: TRUE | E18: =AND(C18:D18) -> FALSE
... C327: TRUE | D327: FALSE | E327: =AND(C327:D327) -> FALSE
